Workbook

Sheet W&M-DS.M-QS
A1: DS | B1: Décembre | D1: Novembre
B2: Magasin FO | C2: Magasin BO | D2: Magasin FO | E2: Magasin BO
A3: Appels comptabilisés | B3: ='Daily-DS.M-QS'!BJ3+'Daily-DS.M-QS'!BH3+'Daily-DS.M-QS'!BF3+'Daily-DS.M-QS'!BD3+'Daily-DS.M-QS'!BB3+'Daily-DS.M-QS'!AZ3+'Daily-DS.M-QS'!AX3+'Daily-DS.M-QS'!AV3+'Daily-DS.M-QS'!AT3+'Daily-DS.M-QS'!AR3+'Daily-DS.M-QS'!AP3+'Daily-DS.M-QS'!AN3+'Daily-DS.M-QS'!AL3+'Daily-DS.M-QS'!AJ3+'Daily-DS.M-QS'!AH3+'Daily-DS.M-QS'!AF3+'Daily-DS.M-QS'!AD3+'Daily-DS.M-QS'!AB3+'Daily-DS.M-QS'!Z3+'Daily-DS.M-QS'!X3+'Daily-DS.M-QS'!V3+'Daily-DS.M-QS'!T3+'Daily-DS.M-QS'!R3+'Daily-DS.M-QS'!P3+'Daily-DS.M-QS'!N3+'Daily-DS.M-QS'!L3+'Daily-DS.M-QS'!J3+'Daily-DS.M-QS'!H3+'Daily-DS.M-QS'!F3+'Daily-DS.M-QS'!D3+'Daily-DS.M-QS'!B3 -> 1574 | C3: ='Daily-DS.M-QS'!BK3+'Daily-DS.M-QS'!BI3+'Daily-DS.M-QS'!BG3+'Daily-DS.M-QS'!BE3+'Daily-DS.M-QS'!BC3+'Daily-DS.M-QS'!BA3+'Daily-DS.M-QS'!AY3+'Daily-DS.M-QS'!AW3+'Daily-DS.M-QS'!AU3+'Daily-DS.M-QS'!AS3+'Daily-DS.M-QS'!AQ3+'Daily-DS.M-QS'!AO3+'Daily-DS.M-QS'!AM3+'Daily-DS.M-QS'!AK3+'Daily-DS.M-QS'!AI3+'Daily-DS.M-QS'!AG3+'Daily-DS.M-QS'!AE3+'Daily-DS.M-QS'!AC3+'Daily-DS.M-QS'!AA3+'Daily-DS.M-QS'!Y3+'Daily-DS.M-QS'!W3+'Daily-DS.M-QS'!U3+'Daily-DS.M-QS'!S3+'Daily-DS.M-QS'!Q3+'Daily-DS.M-QS'!O3+'Daily-DS.M-QS'!M3+'Daily-DS.M-QS'!K3+'Daily-DS.M-QS'!I3+'Daily-DS.M-QS'!G3+'Daily-DS.M-QS'!E3+'Daily-DS.M-QS'!C3 -> 1219 | D3: ='Daily-DS.M-QS'!DR3+'Daily-DS.M-QS'!DP3+'Daily-DS.M-QS'!DN3+'Daily-DS.M-QS'!DL3+'Daily-DS.M-QS'!DJ3+'Daily-DS.M-QS'!DH3+'Daily-DS.M-QS'!DF3+'Daily-DS.M-QS'!DD3+'Daily-DS.M-QS'!DB3+'Daily-DS.M-QS'!CZ3+'Daily-DS.M-QS'!CX3+'Daily-DS.M-QS'!CV3+'Daily-DS.M-QS'!CT3+'Daily-DS.M-QS'!CR3+'Daily-DS.M-QS'!CP3+'Daily-DS.M-QS'!CN3+'Daily-DS.M-QS'!CL3+'Daily-DS.M-QS'!CJ3+'Daily-DS.M-QS'!CH3+'Daily-DS.M-QS'!CF3+'Daily-DS.M-QS'!CD3+'Daily-DS.M-QS'!CB3+'Daily-DS.M-QS'!BZ3+'Daily-DS.M-QS'!BX3+'Daily-DS.M-QS'!BV3+'Daily-DS.M-QS'!BT3+'Daily-DS.M-QS'!BR3+'Daily-DS.M-QS'!BP3+'Daily-DS.M-QS'!BN3+'Daily-DS.M-QS'!BL3 -> 3097 | E3: ='Daily-DS.M-QS'!DS3+'Daily-DS.M-QS'!DQ3+'Daily-DS.M-QS'!DO3+'Daily-DS.M-QS'!DM3+'Daily-DS.M-QS'!DK3+'Daily-DS.M-QS'!DI3+'Daily-DS.M-QS'!DG3+'Daily-DS.M-QS'!DE3+'Daily-DS.M-QS'!DC3+'Daily-DS.M-QS'!DA3+'Daily-DS.M-QS'!CY3+'Daily-DS.M-QS'!CW3+'Daily-DS.M-QS'!CU3+'Daily-DS.M-QS'!CS3+'Daily-DS.M-QS'!CQ3+'Daily-DS.M-QS'!CO3+'Daily-DS.M-QS'!CM3+'Daily-DS.M-QS'!CK3+'Daily-DS.M-QS'!CI3+'Daily-DS.M-QS'!CG3+'Daily-DS.M-QS'!CE3+'Daily-DS.M-QS'!CC3+'Daily-DS.M-QS'!CA3+'Daily-DS.M-QS'!BY3+'Daily-DS.M-QS'!BW3+'Daily-DS.M-QS'!BU3+'Daily-DS.M-QS'!BS3+'Daily-DS.M-QS'!BQ3+'Daily-DS.M-QS'!BO3+'Daily-DS.M-QS'!BM3 -> 1767
A4: Appels Répondus | B4: ='Daily-DS.M-QS'!BJ4+'Daily-DS.M-QS'!BH4+'Daily-DS.M-QS'!BF4+'Daily-DS.M-QS'!BD4+'Daily-DS.M-QS'!BB4+'Daily-DS.M-QS'!AZ4+'Daily-DS.M-QS'!AX4+'Daily-DS.M-QS'!AV4+'Daily-DS.M-QS'!AT4+'Daily-DS.M-QS'!AR4+'Daily-DS.M-QS'!AP4+'Daily-DS.M-QS'!AN4+'Daily-DS.M-QS'!AL4+'Daily-DS.M-QS'!AJ4+'Daily-DS.M-QS'!AH4+'Daily-DS.M-QS'!AF4+'Daily-DS.M-QS'!AD4+'Daily-DS.M-QS'!AB4+'Daily-DS.M-QS'!Z4+'Daily-DS.M-QS'!X4+'Daily-DS.M-QS'!V4+'Daily-DS.M-QS'!T4+'Daily-DS.M-QS'!R4+'Daily-DS.M-QS'!P4+'Daily-DS.M-QS'!N4+'Daily-DS.M-QS'!L4+'Daily-DS.M-QS'!J4+'Daily-DS.M-QS'!H4+'Daily-DS.M-QS'!F4+'Daily-DS.M-QS'!D4+'Daily-DS.M-QS'!B4 -> 1535 | C4: ='Daily-DS.M-QS'!BK4+'Daily-DS.M-QS'!BI4+'Daily-DS.M-QS'!BG4+'Daily-DS.M-QS'!BE4+'Daily-DS.M-QS'!BC4+'Daily-DS.M-QS'!BA4+'Daily-DS.M-QS'!AY4+'Daily-DS.M-QS'!AW4+'Daily-DS.M-QS'!AU4+'Daily-DS.M-QS'!AS4+'Daily-DS.M-QS'!AQ4+'Daily-DS.M-QS'!AO4+'Daily-DS.M-QS'!AM4+'Daily-DS.M-QS'!AK4+'Daily-DS.M-QS'!AI4+'Daily-DS.M-QS'!AG4+'Daily-DS.M-QS'!AE4+'Daily-DS.M-QS'!AC4+'Daily-DS.M-QS'!AA4+'Daily-DS.M-QS'!Y4+'Daily-DS.M-QS'!W4+'Daily-DS.M-QS'!U4+'Daily-DS.M-QS'!S4+'Daily-DS.M-QS'!Q4+'Daily-DS.M-QS'!O4+'Daily-DS.M-QS'!M4+'Daily-DS.M-QS'!K4+'Daily-DS.M-QS'!I4+'Daily-DS.M-QS'!G4+'Daily-DS.M-QS'!E4+'Daily-DS.M-QS'!C4 -> 1187 | D4: ='Daily-DS.M-QS'!DR4+'Daily-DS.M-QS'!DP4+'Daily-DS.M-QS'!DN4+'Daily-DS.M-QS'!DL4+'Daily-DS.M-QS'!DJ4+'Daily-DS.M-QS'!DH4+'Daily-DS.M-QS'!DF4+'Daily-DS.M-QS'!DD4+'Daily-DS.M-QS'!DB4+'Daily-DS.M-QS'!CZ4+'Daily-DS.M-QS'!CX4+'Daily-DS.M-QS'!CV4+'Daily-DS.M-QS'!CT4+'Daily-DS.M-QS'!CR4+'Daily-DS.M-QS'!CP4+'Daily-DS.M-QS'!CN4+'Daily-DS.M-QS'!CL4+'Daily-DS.M-QS'!CJ4+'Daily-DS.M-QS'!CH4+'Daily-DS.M-QS'!CF4+'Daily-DS.M-QS'!CD4+'Daily-DS.M-QS'!CB4+'Daily-DS.M-QS'!BZ4+'Daily-DS.M-QS'!BX4+'Daily-DS.M-QS'!BV4+'Daily-DS.M-QS'!BT4+'Daily-DS.M-QS'!BR4+'Daily-DS.M-QS'!BP4+'Daily-DS.M-QS'!BN4+'Daily-DS.M-QS'!BL4 -> 2897 | E4: ='Daily-DS.M-QS'!DS4+'Daily-DS.M-QS'!DQ4+'Daily-DS.M-QS'!DO4+'Daily-DS.M-QS'!DM4+'Daily-DS.M-QS'!DK4+'Daily-DS.M-QS'!DI4+'Daily-DS.M-QS'!DG4+'Daily-DS.M-QS'!DE4+'Daily-DS.M-QS'!DC4+'Daily-DS.M-QS'!DA4+'Daily-DS.M-QS'!CY4+'Daily-DS.M-QS'!CW4+'Daily-DS.M-QS'!CU4+'Daily-DS.M-QS'!CS4+'Daily-DS.M-QS'!CQ4+'Daily-DS.M-QS'!CO4+'Daily-DS.M-QS'!CM4+'Daily-DS.M-QS'!CK4+'Daily-DS.M-QS'!CI4+'Daily-DS.M-QS'!CG4+'Daily-DS.M-QS'!CE4+'Daily-DS.M-QS'!CC4+'Daily-DS.M-QS'!CA4+'Daily-DS.M-QS'!BY4+'Daily-DS.M-QS'!BW4+'Daily-DS.M-QS'!BU4+'Daily-DS.M-QS'!BS4+'Daily-DS.M-QS'!BQ4+'Daily-DS.M-QS'!BO4+'Daily-DS.M-QS'!BM4 -> 1737
A5: Appels Perdus | B5: ='Daily-DS.M-QS'!BJ5+'Daily-DS.M-QS'!BH5+'Daily-DS.M-QS'!BF5+'Daily-DS.M-QS'!BD5+'Daily-DS.M-QS'!BB5+'Daily-DS.M-QS'!AZ5+'Daily-DS.M-QS'!AX5+'Daily-DS.M-QS'!AV5+'Daily-DS.M-QS'!AT5+'Daily-DS.M-QS'!AR5+'Daily-DS.M-QS'!AP5+'Daily-DS.M-QS'!AN5+'Daily-DS.M-QS'!AL5+'Daily-DS.M-QS'!AJ5+'Daily-DS.M-QS'!AH5+'Daily-DS.M-QS'!AF5+'Daily-DS.M-QS'!AD5+'Daily-DS.M-QS'!AB5+'Daily-DS.M-QS'!Z5+'Daily-DS.M-QS'!X5+'Daily-DS.M-QS'!V5+'Daily-DS.M-QS'!T5+'Daily-DS.M-QS'!R5+'Daily-DS.M-QS'!P5+'Daily-DS.M-QS'!N5+'Daily-DS.M-QS'!L5+'Daily-DS.M-QS'!J5+'Daily-DS.M-QS'!H5+'Daily-DS.M-QS'!F5+'Daily-DS.M-QS'!D5+'Daily-DS.M-QS'!B5 -> 39 | C5: ='Daily-DS.M-QS'!BK5+'Daily-DS.M-QS'!BI5+'Daily-DS.M-QS'!BG5+'Daily-DS.M-QS'!BE5+'Daily-DS.M-QS'!BC5+'Daily-DS.M-QS'!BA5+'Daily-DS.M-QS'!AY5+'Daily-DS.M-QS'!AW5+'Daily-DS.M-QS'!AU5+'Daily-DS.M-QS'!AS5+'Daily-DS.M-QS'!AQ5+'Daily-DS.M-QS'!AO5+'Daily-DS.M-QS'!AM5+'Daily-DS.M-QS'!AK5+'Daily-DS.M-QS'!AI5+'Daily-DS.M-QS'!AG5+'Daily-DS.M-QS'!AE5+'Daily-DS.M-QS'!AC5+'Daily-DS.M-QS'!AA5+'Daily-DS.M-QS'!Y5+'Daily-DS.M-QS'!W5+'Daily-DS.M-QS'!U5+'Daily-DS.M-QS'!S5+'Daily-DS.M-QS'!Q5+'Daily-DS.M-QS'!O5+'Daily-DS.M-QS'!M5+'Daily-DS.M-QS'!K5+'Daily-DS.M-QS'!I5+'Daily-DS.M-QS'!G5+'Daily-DS.M-QS'!E5+'Daily-DS.M-QS'!C5 -> 32 | D5: ='Daily-DS.M-QS'!DR5+'Daily-DS.M-QS'!DP5+'Daily-DS.M-QS'!DN5+'Daily-DS.M-QS'!DL5+'Daily-DS.M-QS'!DJ5+'Daily-DS.M-QS'!DH5+'Daily-DS.M-QS'!DF5+'Daily-DS.M-QS'!DD5+'Daily-DS.M-QS'!DB5+'Daily-DS.M-QS'!CZ5+'Daily-DS.M-QS'!CX5+'Daily-DS.M-QS'!CV5+'Daily-DS.M-QS'!CT5+'Daily-DS.M-QS'!CR5+'Daily-DS.M-QS'!CP5+'Daily-DS.M-QS'!CN5+'Daily-DS.M-QS'!CL5+'Daily-DS.M-QS'!CJ5+'Daily-DS.M-QS'!CH5+'Daily-DS.M-QS'!CF5+'Daily-DS.M-QS'!CD5+'Daily-DS.M-QS'!CB5+'Daily-DS.M-QS'!BZ5+'Daily-DS.M-QS'!BX5+'Daily-DS.M-QS'!BV5+'Daily-DS.M-QS'!BT5+'Daily-DS.M-QS'!BR5+'Daily-DS.M-QS'!BP5+'Daily-DS.M-QS'!BN5+'Daily-DS.M-QS'!BL5 -> 200 | E5: ='Daily-DS.M-QS'!DS5+'Daily-DS.M-QS'!DQ5+'Daily-DS.M-QS'!DO5+'Daily-DS.M-QS'!DM5+'Daily-DS.M-QS'!DK5+'Daily-DS.M-QS'!DI5+'Daily-DS.M-QS'!DG5+'Daily-DS.M-QS'!DE5+'Daily-DS.M-QS'!DC5+'Daily-DS.M-QS'!DA5+'Daily-DS.M-QS'!CY5+'Daily-DS.M-QS'!CW5+'Daily-DS.M-QS'!CU5+'Daily-DS.M-QS'!CS5+'Daily-DS.M-QS'!CQ5+'Daily-DS.M-QS'!CO5+'Daily-DS.M-QS'!CM5+'Daily-DS.M-QS'!CK5+'Daily-DS.M-QS'!CI5+'Daily-DS.M-QS'!CG5+'Daily-DS.M-QS'!CE5+'Daily-DS.M-QS'!CC5+'Daily-DS.M-QS'!CA5+'Daily-DS.M-QS'!BY5+'Daily-DS.M-QS'!BW5+'Daily-DS.M-QS'!BU5+'Daily-DS.M-QS'!BS5+'Daily-DS.M-QS'!BQ5+'Daily-DS.M-QS'!BO5+'Daily-DS.M-QS'!BM5 -> 30
A6: Appels Abandonnés | B6: ='Daily-DS.M-QS'!BJ6+'Daily-DS.M-QS'!BH6+'Daily-DS.M-QS'!BF6+'Daily-DS.M-QS'!BD6+'Daily-DS.M-QS'!BB6+'Daily-DS.M-QS'!AZ6+'Daily-DS.M-QS'!AX6+'Daily-DS.M-QS'!AV6+'Daily-DS.M-QS'!AT6+'Daily-DS.M-QS'!AR6+'Daily-DS.M-QS'!AP6+'Daily-DS.M-QS'!AN6+'Daily-DS.M-QS'!AL6+'Daily-DS.M-QS'!AJ6+'Daily-DS.M-QS'!AH6+'Daily-DS.M-QS'!AF6+'Daily-DS.M-QS'!AD6+'Daily-DS.M-QS'!AB6+'Daily-DS.M-QS'!Z6+'Daily-DS.M-QS'!X6+'Daily-DS.M-QS'!V6+'Daily-DS.M-QS'!T6+'Daily-DS.M-QS'!R6+'Daily-DS.M-QS'!P6+'Daily-DS.M-QS'!N6+'Daily-DS.M-QS'!L6+'Daily-DS.M-QS'!J6+'Daily-DS.M-QS'!H6+'Daily-DS.M-QS'!F6+'Daily-DS.M-QS'!D6+'Daily-DS.M-QS'!B6 -> 16 | C6: ='Daily-DS.M-QS'!BK6+'Daily-DS.M-QS'!BI6+'Daily-DS.M-QS'!BG6+'Daily-DS.M-QS'!BE6+'Daily-DS.M-QS'!BC6+'Daily-DS.M-QS'!BA6+'Daily-DS.M-QS'!AY6+'Daily-DS.M-QS'!AW6+'Daily-DS.M-QS'!AU6+'Daily-DS.M-QS'!AS6+'Daily-DS.M-QS'!AQ6+'Daily-DS.M-QS'!AO6+'Daily-DS.M-QS'!AM6+'Daily-DS.M-QS'!AK6+'Daily-DS.M-QS'!AI6+'Daily-DS.M-QS'!AG6+'Daily-DS.M-QS'!AE6+'Daily-DS.M-QS'!AC6+'Daily-DS.M-QS'!AA6+'Daily-DS.M-QS'!Y6+'Daily-DS.M-QS'!W6+'Daily-DS.M-QS'!U6+'Daily-DS.M-QS'!S6+'Daily-DS.M-QS'!Q6+'Daily-DS.M-QS'!O6+'Daily-DS.M-QS'!M6+'Daily-DS.M-QS'!K6+'Daily-DS.M-QS'!I6+'Daily-DS.M-QS'!G6+'Daily-DS.M-QS'!E6+'Daily-DS.M-QS'!C6 -> 14 | D6: ='Daily-DS.M-QS'!DR6+'Daily-DS.M-QS'!DP6+'Daily-DS.M-QS'!DN6+'Daily-DS.M-QS'!DL6+'Daily-DS.M-QS'!DJ6+'Daily-DS.M-QS'!DH6+'Daily-DS.M-QS'!DF6+'Daily-DS.M-QS'!DD6+'Daily-DS.M-QS'!DB6+'Daily-DS.M-QS'!CZ6+'Daily-DS.M-QS'!CX6+'Daily-DS.M-QS'!CV6+'Daily-DS.M-QS'!CT6+'Daily-DS.M-QS'!CR6+'Daily-DS.M-QS'!CP6+'Daily-DS.M-QS'!CN6+'Daily-DS.M-QS'!CL6+'Daily-DS.M-QS'!CJ6+'Daily-DS.M-QS'!CH6+'Daily-DS.M-QS'!CF6+'Daily-DS.M-QS'!CD6+'Daily-DS.M-QS'!CB6+'Daily-DS.M-QS'!BZ6+'Daily-DS.M-QS'!BX6+'Daily-DS.M-QS'!BV6+'Daily-DS.M-QS'!BT6+'Daily-DS.M-QS'!BR6+'Daily-DS.M-QS'!BP6+'Daily-DS.M-QS'!BN6+'Daily-DS.M-QS'!BL6 -> 99 | E6: ='Daily-DS.M-QS'!DS6+'Daily-DS.M-QS'!DQ6+'Daily-DS.M-QS'!DO6+'Daily-DS.M-QS'!DM6+'Daily-DS.M-QS'!DK6+'Daily-DS.M-QS'!DI6+'Daily-DS.M-QS'!DG6+'Daily-DS.M-QS'!DE6+'Daily-DS.M-QS'!DC6+'Daily-DS.M-QS'!DA6+'Daily-DS.M-QS'!CY6+'Daily-DS.M-QS'!CW6+'Daily-DS.M-QS'!CU6+'Daily-DS.M-QS'!CS6+'Daily-DS.M-QS'!CQ6+'Daily-DS.M-QS'!CO6+'Daily-DS.M-QS'!CM6+'Daily-DS.M-QS'!CK6+'Daily-DS.M-QS'!CI6+'Daily-DS.M-QS'!CG6+'Daily-DS.M-QS'!CE6+'Daily-DS.M-QS'!CC6+'Daily-DS.M-QS'!CA6+'Daily-DS.M-QS'!BY6+'Daily-DS.M-QS'!BW6+'Daily-DS.M-QS'!BU6+'Daily-DS.M-QS'!BS6+'Daily-DS.M-QS'!BQ6+'Daily-DS.M-QS'!BO6+'Daily-DS.M-QS'!BM6 -> 25
A7: QS | B7: =B4/B3 -> 0.97522236 | C7: =C4/C3 -> 0.97374897 | D7: =D4/D3 -> 0.93542138 | E7: =E4/E3 -> 0.98302207
A8: Taux des perdus | B8: =B5/B3 -> 0.024777637 | C8: =C5/C3 -> 0.026251025 | D8: =D5/D3 -> 0.064578624 | E8: =E5/E3 -> 0.016977929
A9: Taux des abandonnés | B9: =B6/B3 -> 0.010165184 | C9: =C6/C3 -> 0.011484824 | D9: =D6/D3 -> 0.031966419 | E9: =E6/E3 -> 0.014148274
A11: Durée Moy. d'attente | B11: =AVERAGE('Daily-DS.M-QS'!BJ11,'Daily-DS.M-QS'!BH11,'Daily-DS.M-QS'!BF11,'Daily-DS.M-QS'!BD11,'Daily-DS.M-QS'!BB11,'Daily-DS.M-QS'!AZ11,'Daily-DS.M-QS'!AX11,'Daily-DS.M-QS'!AV11,'Daily-DS.M-QS'!AT11,'Daily-DS.M-QS'!AR11,'Daily-DS.M-QS'!AP11,'Daily-DS.M-QS'!AN11,'Daily-DS.M-QS'!AL11,'Daily-DS.M-QS'!AJ11,'Daily-DS.M-QS'!AH11,'Daily-DS.M-QS'!AF11,'Daily-DS.M-QS'!AD11,'Daily-DS.M-QS'!AB11,'Daily-DS.M-QS'!Z11,'Daily-DS.M-QS'!X11,'Daily-DS.M-QS'!V11,'Daily-DS.M-QS'!T11,'Daily-DS.M-QS'!R11,'Daily-DS.M-QS'!P11,'Daily-DS.M-QS'!N11,'Daily-DS.M-QS'!L11,'Daily-DS.M-QS'!J11,'Daily-DS.M-QS'!H11,'Daily-DS.M-QS'!F11,'Daily-DS.M-QS'!D11+'Daily-DS.M-QS'!B11) -> 0.020261438 | C11: =AVERAGE('Daily-DS.M-QS'!BK11,'Daily-DS.M-QS'!BI11,'Daily-DS.M-QS'!BG11,'Daily-DS.M-QS'!BE11,'Daily-DS.M-QS'!BC11,'Daily-DS.M-QS'!BA11,'Daily-DS.M-QS'!AY11,'Daily-DS.M-QS'!AW11,'Daily-DS.M-QS'!AU11,'Daily-DS.M-QS'!AS11,'Daily-DS.M-QS'!AQ11,'Daily-DS.M-QS'!AO11,'Daily-DS.M-QS'!AM11,'Daily-DS.M-QS'!AK11,'Daily-DS.M-QS'!AI11,'Daily-DS.M-QS'!AG11,'Daily-DS.M-QS'!AE11,'Daily-DS.M-QS'!AC11,'Daily-DS.M-QS'!AA11,'Daily-DS.M-QS'!Y11,'Daily-DS.M-QS'!W11,'Daily-DS.M-QS'!U11,'Daily-DS.M-QS'!S11,'Daily-DS.M-QS'!Q11,'Daily-DS.M-QS'!O11,'Daily-DS.M-QS'!M11,'Daily-DS.M-QS'!K11,'Daily-DS.M-QS'!I11,'Daily-DS.M-QS'!G11,'Daily-DS.M-QS'!E11+'Daily-DS.M-QS'!C11) -> 0.020179739 | D11: =AVERAGE('Daily-DS.M-QS'!DR11,'Daily-DS.M-QS'!DP11,'Daily-DS.M-QS'!DN11,'Daily-DS.M-QS'!DL11,'Daily-DS.M-QS'!DJ11,'Daily-DS.M-QS'!DH11,'Daily-DS.M-QS'!DF11,'Daily-DS.M-QS'!DD11,'Daily-DS.M-QS'!DB11,'Daily-DS.M-QS'!CZ11,'Daily-DS.M-QS'!CX11,'Daily-DS.M-QS'!CV11,'Daily-DS.M-QS'!CT11,'Daily-DS.M-QS'!CR11,'Daily-DS.M-QS'!CP11,'Daily-DS.M-QS'!CN11,'Daily-DS.M-QS'!CL11,'Daily-DS.M-QS'!CJ11,'Daily-DS.M-QS'!CH11,'Daily-DS.M-QS'!CF11,'Daily-DS.M-QS'!CD11,'Daily-DS.M-QS'!CB11,'Daily-DS.M-QS'!BZ11,'Daily-DS.M-QS'!BX11,'Daily-DS.M-QS'!BV11,'Daily-DS.M-QS'!BT11,'Daily-DS.M-QS'!BR11,'Daily-DS.M-QS'!BP11,'Daily-DS.M-QS'!BN11,'Daily-DS.M-QS'!BL11) -> 0.030717593 | E11: =AVERAGE('Daily-DS.M-QS'!DS11,'Daily-DS.M-QS'!DQ11,'Daily-DS.M-QS'!DO11,'Daily-DS.M-QS'!DM11,'Daily-DS.M-QS'!DK11,'Daily-DS.M-QS'!DI11,'Daily-DS.M-QS'!DG11,'Daily-DS.M-QS'!DE11,'Daily-DS.M-QS'!DC11,'Daily-DS.M-QS'!DA11,'Daily-DS.M-QS'!CY11,'Daily-DS.M-QS'!CW11,'Daily-DS.M-QS'!CU11,'Daily-DS.M-QS'!CS11,'Daily-DS.M-QS'!CQ11,'Daily-DS.M-QS'!CO11,'Daily-DS.M-QS'!CM11,'Daily-DS.M-QS'!CK11,'Daily-DS.M-QS'!CI11,'Daily-DS.M-QS'!CG11,'Daily-DS.M-QS'!CE11,'Daily-DS.M-QS'!CC11,'Daily-DS.M-QS'!CA11,'Daily-DS.M-QS'!BY11,'Daily-DS.M-QS'!BW11,'Daily-DS.M-QS'!BU11,'Daily-DS.M-QS'!BS11,'Daily-DS.M-QS'!BQ11,'Daily-DS.M-QS'!BO11,'Daily-DS.M-QS'!BM11) -> 0.015925926
A12: Durée Moy. de communication | B12: =AVERAGE('Daily-DS.M-QS'!BJ12,'Daily-DS.M-QS'!BH12,'Daily-DS.M-QS'!BF12,'Daily-DS.M-QS'!BD12,'Daily-DS.M-QS'!BB12,'Daily-DS.M-QS'!AZ12,'Daily-DS.M-QS'!AX12,'Daily-DS.M-QS'!AV12,'Daily-DS.M-QS'!AT12,'Daily-DS.M-QS'!AR12,'Daily-DS.M-QS'!AP12,'Daily-DS.M-QS'!AN12,'Daily-DS.M-QS'!AL12,'Daily-DS.M-QS'!AJ12,'Daily-DS.M-QS'!AH12,'Daily-DS.M-QS'!AF12,'Daily-DS.M-QS'!AD12,'Daily-DS.M-QS'!AB12,'Daily-DS.M-QS'!Z12,'Daily-DS.M-QS'!X12,'Daily-DS.M-QS'!V12,'Daily-DS.M-QS'!T12,'Daily-DS.M-QS'!R12,'Daily-DS.M-QS'!P12,'Daily-DS.M-QS'!N12,'Daily-DS.M-QS'!L12,'Daily-DS.M-QS'!J12,'Daily-DS.M-QS'!H12,'Daily-DS.M-QS'!F12,'Daily-DS.M-QS'!D12+'Daily-DS.M-QS'!B12) -> 0.26789216 | C12: =AVERAGE('Daily-DS.M-QS'!BK12,'Daily-DS.M-QS'!BI12,'Daily-DS.M-QS'!BG12,'Daily-DS.M-QS'!BE12,'Daily-DS.M-QS'!BC12,'Daily-DS.M-QS'!BA12,'Daily-DS.M-QS'!AY12,'Daily-DS.M-QS'!AW12,'Daily-DS.M-QS'!AU12,'Daily-DS.M-QS'!AS12,'Daily-DS.M-QS'!AQ12,'Daily-DS.M-QS'!AO12,'Daily-DS.M-QS'!AM12,'Daily-DS.M-QS'!AK12,'Daily-DS.M-QS'!AI12,'Daily-DS.M-QS'!AG12,'Daily-DS.M-QS'!AE12,'Daily-DS.M-QS'!AC12,'Daily-DS.M-QS'!AA12,'Daily-DS.M-QS'!Y12,'Daily-DS.M-QS'!W12,'Daily-DS.M-QS'!U12,'Daily-DS.M-QS'!S12,'Daily-DS.M-QS'!Q12,'Daily-DS.M-QS'!O12,'Daily-DS.M-QS'!M12,'Daily-DS.M-QS'!K12,'Daily-DS.M-QS'!I12,'Daily-DS.M-QS'!G12,'Daily-DS.M-QS'!E12+'Daily-DS.M-QS'!C12) -> 0.18541667 | D12: =AVERAGE('Daily-DS.M-QS'!DR12,'Daily-DS.M-QS'!DP12,'Daily-DS.M-QS'!DN12,'Daily-DS.M-QS'!DL12,'Daily-DS.M-QS'!DJ12,'Daily-DS.M-QS'!DH12,'Daily-DS.M-QS'!DF12,'Daily-DS.M-QS'!DD12,'Daily-DS.M-QS'!DB12,'Daily-DS.M-QS'!CZ12,'Daily-DS.M-QS'!CX12,'Daily-DS.M-QS'!CV12,'Daily-DS.M-QS'!CT12,'Daily-DS.M-QS'!CR12,'Daily-DS.M-QS'!CP12,'Daily-DS.M-QS'!CN12,'Daily-DS.M-QS'!CL12,'Daily-DS.M-QS'!CJ12,'Daily-DS.M-QS'!CH12,'Daily-DS.M-QS'!CF12,'Daily-DS.M-QS'!CD12,'Daily-DS.M-QS'!CB12,'Daily-DS.M-QS'!BZ12,'Daily-DS.M-QS'!BX12,'Daily-DS.M-QS'!BV12,'Daily-DS.M-QS'!BT12,'Daily-DS.M-QS'!BR12,'Daily-DS.M-QS'!BP12,'Daily-DS.M-QS'!BN12,'Daily-DS.M-QS'!BL12) -> 0.2919213 | E12: =AVERAGE('Daily-DS.M-QS'!DS12,'Daily-DS.M-QS'!DQ12,'Daily-DS.M-QS'!DO12,'Daily-DS.M-QS'!DM12,'Daily-DS.M-QS'!DK12,'Daily-DS.M-QS'!DI12,'Daily-DS.M-QS'!DG12,'Daily-DS.M-QS'!DE12,'Daily-DS.M-QS'!DC12,'Daily-DS.M-QS'!DA12,'Daily-DS.M-QS'!CY12,'Daily-DS.M-QS'!CW12,'Daily-DS.M-QS'!CU12,'Daily-DS.M-QS'!CS12,'Daily-DS.M-QS'!CQ12,'Daily-DS.M-QS'!CO12,'Daily-DS.M-QS'!CM12,'Daily-DS.M-QS'!CK12,'Daily-DS.M-QS'!CI12,'Daily-DS.M-QS'!CG12,'Daily-DS.M-QS'!CE12,'Daily-DS.M-QS'!CC12,'Daily-DS.M-QS'!CA12,'Daily-DS.M-QS'!BY12,'Daily-DS.M-QS'!BW12,'Daily-DS.M-QS'!BU12,'Daily-DS.M-QS'!BS12,'Daily-DS.M-QS'!BQ12,'Daily-DS.M-QS'!BO12,'Daily-DS.M-QS'!BM12) -> 0.22900463
A14: Appels courts < 15s | B14: ='Daily-DS.M-QS'!BJ14+'Daily-DS.M-QS'!BH14+'Daily-DS.M-QS'!BF14+'Daily-DS.M-QS'!BD14+'Daily-DS.M-QS'!BB14+'Daily-DS.M-QS'!AZ14+'Daily-DS.M-QS'!AX14+'Daily-DS.M-QS'!AV14+'Daily-DS.M-QS'!AT14+'Daily-DS.M-QS'!AR14+'Daily-DS.M-QS'!AP14+'Daily-DS.M-QS'!AN14+'Daily-DS.M-QS'!AL14+'Daily-DS.M-QS'!AJ14+'Daily-DS.M-QS'!AH14+'Daily-DS.M-QS'!AF14+'Daily-DS.M-QS'!AD14+'Daily-DS.M-QS'!AB14+'Daily-DS.M-QS'!Z14+'Daily-DS.M-QS'!X14+'Daily-DS.M-QS'!V14+'Daily-DS.M-QS'!T14+'Daily-DS.M-QS'!R14+'Daily-DS.M-QS'!P14+'Daily-DS.M-QS'!N14+'Daily-DS.M-QS'!L14+'Daily-DS.M-QS'!J14+'Daily-DS.M-QS'!H14+'Daily-DS.M-QS'!F14+'Daily-DS.M-QS'!D14+'Daily-DS.M-QS'!B14 -> 97 | C14: ='Daily-DS.M-QS'!BK14+'Daily-DS.M-QS'!BI14+'Daily-DS.M-QS'!BG14+'Daily-DS.M-QS'!BE14+'Daily-DS.M-QS'!BC14+'Daily-DS.M-QS'!BA14+'Daily-DS.M-QS'!AY14+'Daily-DS.M-QS'!AW14+'Daily-DS.M-QS'!AU14+'Daily-DS.M-QS'!AS14+'Daily-DS.M-QS'!AQ14+'Daily-DS.M-QS'!AO14+'Daily-DS.M-QS'!AM14+'Daily-DS.M-QS'!AK14+'Daily-DS.M-QS'!AI14+'Daily-DS.M-QS'!AG14+'Daily-DS.M-QS'!AE14+'Daily-DS.M-QS'!AC14+'Daily-DS.M-QS'!AA14+'Daily-DS.M-QS'!Y14+'Daily-DS.M-QS'!W14+'Daily-DS.M-QS'!U14+'Daily-DS.M-QS'!S14+'Daily-DS.M-QS'!Q14+'Daily-DS.M-QS'!O14+'Daily-DS.M-QS'!M14+'Daily-DS.M-QS'!K14+'Daily-DS.M-QS'!I14+'Daily-DS.M-QS'!G14+'Daily-DS.M-QS'!E14+'Daily-DS.M-QS'!C14 -> 90 | D14: ='Daily-DS.M-QS'!DR14+'Daily-DS.M-QS'!DP14+'Daily-DS.M-QS'!DN14+'Daily-DS.M-QS'!DL14+'Daily-DS.M-QS'!DJ14+'Daily-DS.M-QS'!DH14+'Daily-DS.M-QS'!DF14+'Daily-DS.M-QS'!DD14+'Daily-DS.M-QS'!DB14+'Daily-DS.M-QS'!CZ14+'Daily-DS.M-QS'!CX14+'Daily-DS.M-QS'!CV14+'Daily-DS.M-QS'!CT14+'Daily-DS.M-QS'!CR14+'Daily-DS.M-QS'!CP14+'Daily-DS.M-QS'!CN14+'Daily-DS.M-QS'!CL14+'Daily-DS.M-QS'!CJ14+'Daily-DS.M-QS'!CH14+'Daily-DS.M-QS'!CF14+'Daily-DS.M-QS'!CD14+'Daily-DS.M-QS'!CB14+'Daily-DS.M-QS'!BZ14+'Daily-DS.M-QS'!BX14+'Daily-DS.M-QS'!BV14+'Daily-DS.M-QS'!BT14+'Daily-DS.M-QS'!BR14+'Daily-DS.M-QS'!BP14+'Daily-DS.M-QS'!BN14+'Daily-DS.M-QS'!BL14 -> 193 | E14: ='Daily-DS.M-QS'!DS14+'Daily-DS.M-QS'!DQ14+'Daily-DS.M-QS'!DO14+'Daily-DS.M-QS'!DM14+'Daily-DS.M-QS'!DK14+'Daily-DS.M-QS'!DI14+'Daily-DS.M-QS'!DG14+'Daily-DS.M-QS'!DE14+'Daily-DS.M-QS'!DC14+'Daily-DS.M-QS'!DA14+'Daily-DS.M-QS'!CY14+'Daily-DS.M-QS'!CW14+'Daily-DS.M-QS'!CU14+'Daily-DS.M-QS'!CS14+'Daily-DS.M-QS'!CQ14+'Daily-DS.M-QS'!CO14+'Daily-DS.M-QS'!CM14+'Daily-DS.M-QS'!CK14+'Daily-DS.M-QS'!CI14+'Daily-DS.M-QS'!CG14+'Daily-DS.M-QS'!CE14+'Daily-DS.M-QS'!CC14+'Daily-DS.M-QS'!CA14+'Daily-DS.M-QS'!BY14+'Daily-DS.M-QS'!BW14+'Daily-DS.M-QS'!BU14+'Daily-DS.M-QS'!BS14+'Daily-DS.M-QS'!BQ14+'Daily-DS.M-QS'!BO14+'Daily-DS.M-QS'!BM14 -> 115
A15: Taux de conformité | B15: =B14/B4 -> 0.063192182 | C15: =C14/C4 -> 0.075821398 | D15: =D14/D4 -> 0.066620642 | E15: =E14/E4 -> 0.066206102
A17: Appels Répondus <30s | B17: ='Daily-DS.M-QS'!BJ17+'Daily-DS.M-QS'!BH17+'Daily-DS.M-QS'!BF17+'Daily-DS.M-QS'!BD17+'Daily-DS.M-QS'!BB17+'Daily-DS.M-QS'!AZ17+'Daily-DS.M-QS'!AX17+'Daily-DS.M-QS'!AV17+'Daily-DS.M-QS'!AT17+'Daily-DS.M-QS'!AR17+'Daily-DS.M-QS'!AP17+'Daily-DS.M-QS'!AN17+'Daily-DS.M-QS'!AL17+'Daily-DS.M-QS'!AJ17+'Daily-DS.M-QS'!AH17+'Daily-DS.M-QS'!AF17+'Daily-DS.M-QS'!AD17+'Daily-DS.M-QS'!AB17+'Daily-DS.M-QS'!Z17+'Daily-DS.M-QS'!X17+'Daily-DS.M-QS'!V17+'Daily-DS.M-QS'!T17+'Daily-DS.M-QS'!R17+'Daily-DS.M-QS'!P17+'Daily-DS.M-QS'!N17+'Daily-DS.M-QS'!L17+'Daily-DS.M-QS'!J17+'Daily-DS.M-QS'!H17+'Daily-DS.M-QS'!F17+'Daily-DS.M-QS'!D17+'Daily-DS.M-QS'!B17 -> 1259 | C17: ='Daily-DS.M-QS'!BK17+'Daily-DS.M-QS'!BI17+'Daily-DS.M-QS'!BG17+'Daily-DS.M-QS'!BE17+'Daily-DS.M-QS'!BC17+'Daily-DS.M-QS'!BA17+'Daily-DS.M-QS'!AY17+'Daily-DS.M-QS'!AW17+'Daily-DS.M-QS'!AU17+'Daily-DS.M-QS'!AS17+'Daily-DS.M-QS'!AQ17+'Daily-DS.M-QS'!AO17+'Daily-DS.M-QS'!AM17+'Daily-DS.M-QS'!AK17+'Daily-DS.M-QS'!AI17+'Daily-DS.M-QS'!AG17+'Daily-DS.M-QS'!AE17+'Daily-DS.M-QS'!AC17+'Daily-DS.M-QS'!AA17+'Daily-DS.M-QS'!Y17+'Daily-DS.M-QS'!W17+'Daily-DS.M-QS'!U17+'Daily-DS.M-QS'!S17+'Daily-DS.M-QS'!Q17+'Daily-DS.M-QS'!O17+'Daily-DS.M-QS'!M17+'Daily-DS.M-QS'!K17+'Daily-DS.M-QS'!I17+'Daily-DS.M-QS'!G17+'Daily-DS.M-QS'!E17+'Daily-DS.M-QS'!C17 -> 983 | D17: ='Daily-DS.M-QS'!DR17+'Daily-DS.M-QS'!DP17+'Daily-DS.M-QS'!DN17+'Daily-DS.M-QS'!DL17+'Daily-DS.M-QS'!DJ17+'Daily-DS.M-QS'!DH17+'Daily-DS.M-QS'!DF17+'Daily-DS.M-QS'!DD17+'Daily-DS.M-QS'!DB17+'Daily-DS.M-QS'!CZ17+'Daily-DS.M-QS'!CX17+'Daily-DS.M-QS'!CV17+'Daily-DS.M-QS'!CT17+'Daily-DS.M-QS'!CR17+'Daily-DS.M-QS'!CP17+'Daily-DS.M-QS'!CN17+'Daily-DS.M-QS'!CL17+'Daily-DS.M-QS'!CJ17+'Daily-DS.M-QS'!CH17+'Daily-DS.M-QS'!CF17+'Daily-DS.M-QS'!CD17+'Daily-DS.M-QS'!CB17+'Daily-DS.M-QS'!BZ17+'Daily-DS.M-QS'!BX17+'Daily-DS.M-QS'!BV17+'Daily-DS.M-QS'!BT17+'Daily-DS.M-QS'!BR17+'Daily-DS.M-QS'!BP17+'Daily-DS.M-QS'!BN17+'Daily-DS.M-QS'!BL17 -> 2236 | E17: ='Daily-DS.M-QS'!DS17+'Daily-DS.M-QS'!DQ17+'Daily-DS.M-QS'!DO17+'Daily-DS.M-QS'!DM17+'Daily-DS.M-QS'!DK17+'Daily-DS.M-QS'!DI17+'Daily-DS.M-QS'!DG17+'Daily-DS.M-QS'!DE17+'Daily-DS.M-QS'!DC17+'Daily-DS.M-QS'!DA17+'Daily-DS.M-QS'!CY17+'Daily-DS.M-QS'!CW17+'Daily-DS.M-QS'!CU17+'Daily-DS.M-QS'!CS17+'Daily-DS.M-QS'!CQ17+'Daily-DS.M-QS'!CO17+'Daily-DS.M-QS'!CM17+'Daily-DS.M-QS'!CK17+'Daily-DS.M-QS'!CI17+'Daily-DS.M-QS'!CG17+'Daily-DS.M-QS'!CE17+'Daily-DS.M-QS'!CC17+'Daily-DS.M-QS'!CA17+'Daily-DS.M-QS'!BY17+'Daily-DS.M-QS'!BW17+'Daily-DS.M-QS'!BU17+'Daily-DS.M-QS'!BS17+'Daily-DS.M-QS'!BQ17+'Daily-DS.M-QS'!BO17+'Daily-DS.M-QS'!BM17 -> 1516
A18: SLA (30s) | B18: =B17/B4 -> 0.82019544 | C18: =C17/C4 -> 0.82813816 | D18: =D17/D4 -> 0.77183293 | E18: =E17/E4 -> 0.87276914
A21: DS | B21: S50 | D21: S49 | F21: S48 | H21: S47 | J21: S46 | L21: S45 | N21: S44 | P21: S43
B22: Magasin FO | C22: Magasin BO | D22: Magasin FO | E22: Magasin BO | F22: Magasin FO | G22: Magasin BO | H22: Magasin FO | I22: Magasin BO | J22: Magasin FO | K22: Magasin BO | L22: Magasin FO | M22: Magasin BO | N22: Magasin FO | O22: Magasin BO | P22: Magasin FO | Q22: Magasin BO
A23: Appels comptabilisés | B23: ='Daily-DS.M-QS'!AJ3+'Daily-DS.M-QS'!AL3+'Daily-DS.M-QS'!AN3+'Daily-DS.M-QS'!AP3+'Daily-DS.M-QS'!AR3+'Daily-DS.M-QS'!AT3+'Daily-DS.M-QS'!AV3 -> 669 | C23: ='Daily-DS.M-QS'!AK3+'Daily-DS.M-QS'!AM3+'Daily-DS.M-QS'!AO3+'Daily-DS.M-QS'!AQ3+'Daily-DS.M-QS'!AS3+'Daily-DS.M-QS'!AU3+'Daily-DS.M-QS'!AW3 -> 457 | D23: ='Daily-DS.M-QS'!AX3+'Daily-DS.M-QS'!AZ3+'Daily-DS.M-QS'!BB3+'Daily-DS.M-QS'!BD3+'Daily-DS.M-QS'!BF3+'Daily-DS.M-QS'!BH3+'Daily-DS.M-QS'!BJ3 -> 650 | E23: ='Daily-DS.M-QS'!AY3+'Daily-DS.M-QS'!BA3+'Daily-DS.M-QS'!BC3+'Daily-DS.M-QS'!BE3+'Daily-DS.M-QS'!BG3+'Daily-DS.M-QS'!BI3+'Daily-DS.M-QS'!BK3 -> 583 | F23: ='Daily-DS.M-QS'!BL3+'Daily-DS.M-QS'!BN3+'Daily-DS.M-QS'!BP3+'Daily-DS.M-QS'!BR3+'Daily-DS.M-QS'!BT3+'Daily-DS.M-QS'!BV3+'Daily-DS.M-QS'!BX3 -> 799 | G23: ='Daily-DS.M-QS'!BM3+'Daily-DS.M-QS'!BO3+'Daily-DS.M-QS'!BQ3+'Daily-DS.M-QS'!BS3+'Daily-DS.M-QS'!BU3+'Daily-DS.M-QS'!BW3+'Daily-DS.M-QS'!BY3 -> 410 | H23: ='Daily-DS.M-QS'!BZ3+'Daily-DS.M-QS'!CB3+'Daily-DS.M-QS'!CD3+'Daily-DS.M-QS'!CF3+'Daily-DS.M-QS'!CH3+'Daily-DS.M-QS'!CJ3+'Daily-DS.M-QS'!CL3 -> 623 | I23: ='Daily-DS.M-QS'!CA3+'Daily-DS.M-QS'!CC3+'Daily-DS.M-QS'!CE3+'Daily-DS.M-QS'!CG3+'Daily-DS.M-QS'!CI3+'Daily-DS.M-QS'!CK3+'Daily-DS.M-QS'!CM3 -> 456 | J23: ='Daily-DS.M-QS'!CN3+'Daily-DS.M-QS'!CP3+'Daily-DS.M-QS'!CR3+'Daily-DS.M-QS'!CT3+'Daily-DS.M-QS'!CV3+'Daily-DS.M-QS'!CX3+'Daily-DS.M-QS'!CZ3 -> 762 | K23: ='Daily-DS.M-QS'!CO3+'Daily-DS.M-QS'!CQ3+'Daily-DS.M-QS'!CS3+'Daily-DS.M-QS'!CU3+'Daily-DS.M-QS'!CW3+'Daily-DS.M-QS'!CY3+'Daily-DS.M-QS'!DA3 -> 351 | L23: ='Daily-DS.M-QS'!DB3+'Daily-DS.M-QS'!DD3+'Daily-DS.M-QS'!DF3+'Daily-DS.M-QS'!DH3+'Daily-DS.M-QS'!DJ3+'Daily-DS.M-QS'!DL3+'Daily-DS.M-QS'!DN3 -> 757 | M23: ='Daily-DS.M-QS'!DC3+'Daily-DS.M-QS'!DE3+'Daily-DS.M-QS'!DG3+'Daily-DS.M-QS'!DI3+'Daily-DS.M-QS'!DK3+'Daily-DS.M-QS'!DM3+'Daily-DS.M-QS'!DO3 -> 496 | N23: 812 | O23: 642 | P23: 613 | Q23: 481
A24: Appels Répondus | B24: ='Daily-DS.M-QS'!AJ4+'Daily-DS.M-QS'!AL4+'Daily-DS.M-QS'!AN4+'Daily-DS.M-QS'!AP4+'Daily-DS.M-QS'!AR4+'Daily-DS.M-QS'!AT4+'Daily-DS.M-QS'!AV4 -> 648 | C24: ='Daily-DS.M-QS'!AK4+'Daily-DS.M-QS'!AM4+'Daily-DS.M-QS'!AO4+'Daily-DS.M-QS'!AQ4+'Daily-DS.M-QS'!AS4+'Daily-DS.M-QS'!AU4+'Daily-DS.M-QS'!AW4 -> 446 | D24: ='Daily-DS.M-QS'!AX4+'Daily-DS.M-QS'!AZ4+'Daily-DS.M-QS'!BB4+'Daily-DS.M-QS'!BD4+'Daily-DS.M-QS'!BF4+'Daily-DS.M-QS'!BH4+'Daily-DS.M-QS'!BJ4 -> 640 | E24: ='Daily-DS.M-QS'!AY4+'Daily-DS.M-QS'!BA4+'Daily-DS.M-QS'!BC4+'Daily-DS.M-QS'!BE4+'Daily-DS.M-QS'!BG4+'Daily-DS.M-QS'!BI4+'Daily-DS.M-QS'!BK4 -> 569 | F24: ='Daily-DS.M-QS'!BL4+'Daily-DS.M-QS'!BN4+'Daily-DS.M-QS'!BP4+'Daily-DS.M-QS'!BR4+'Daily-DS.M-QS'!BT4+'Daily-DS.M-QS'!BV4+'Daily-DS.M-QS'!BX4 -> 778 | G24: ='Daily-DS.M-QS'!BM4+'Daily-DS.M-QS'!BO4+'Daily-DS.M-QS'!BQ4+'Daily-DS.M-QS'!BS4+'Daily-DS.M-QS'!BU4+'Daily-DS.M-QS'!BW4+'Daily-DS.M-QS'!BY4 -> 395 | H24: ='Daily-DS.M-QS'!BZ4+'Daily-DS.M-QS'!CB4+'Daily-DS.M-QS'!CD4+'Daily-DS.M-QS'!CF4+'Daily-DS.M-QS'!CH4+'Daily-DS.M-QS'!CJ4+'Daily-DS.M-QS'!CL4 -> 607 | I24: ='Daily-DS.M-QS'!CA4+'Daily-DS.M-QS'!CC4+'Daily-DS.M-QS'!CE4+'Daily-DS.M-QS'!CG4+'Daily-DS.M-QS'!CI4+'Daily-DS.M-QS'!CK4+'Daily-DS.M-QS'!CM4 -> 451 | J24: ='Daily-DS.M-QS'!CN4+'Daily-DS.M-QS'!CP4+'Daily-DS.M-QS'!CR4+'Daily-DS.M-QS'!CT4+'Daily-DS.M-QS'!CV4+'Daily-DS.M-QS'!CX4+'Daily-DS.M-QS'!CZ4 -> 690 | K24: ='Daily-DS.M-QS'!CO4+'Daily-DS.M-QS'!CQ4+'Daily-DS.M-QS'!CS4+'Daily-DS.M-QS'!CU4+'Daily-DS.M-QS'!CW4+'Daily-DS.M-QS'!CY4+'Daily-DS.M-QS'!DA4 -> 351 | L24: ='Daily-DS.M-QS'!DB4+'Daily-DS.M-QS'!DD4+'Daily-DS.M-QS'!DF4+'Daily-DS.M-QS'!DH4+'Daily-DS.M-QS'!DJ4+'Daily-DS.M-QS'!DL4+'Daily-DS.M-QS'!DN4 -> 720 | M24: ='Daily-DS.M-QS'!DC4+'Daily-DS.M-QS'!DE4+'Daily-DS.M-QS'!DG4+'Daily-DS.M-QS'!DI4+'Daily-DS.M-QS'!DK4+'Daily-DS.M-QS'!DM4+'Daily-DS.M-QS'!DO4 -> 487 | N24: 704 | O24: 570 | P24: 579 | Q24: 473
A25: Appels Perdus | B25: ='Daily-DS.M-QS'!AJ5+'Daily-DS.M-QS'!AL5+'Daily-DS.M-QS'!AN5+'Daily-DS.M-QS'!AP5+'Daily-DS.M-QS'!AR5+'Daily-DS.M-QS'!AT5+'Daily-DS.M-QS'!AV5 -> 21 | C25: ='Daily-DS.M-QS'!AK5+'Daily-DS.M-QS'!AM5+'Daily-DS.M-QS'!AO5+'Daily-DS.M-QS'!AQ5+'Daily-DS.M-QS'!AS5+'Daily-DS.M-QS'!AU5+'Daily-DS.M-QS'!AW5 -> 11 | D25: ='Daily-DS.M-QS'!AX5+'Daily-DS.M-QS'!AZ5+'Daily-DS.M-QS'!BB5+'Daily-DS.M-QS'!BD5+'Daily-DS.M-QS'!BF5+'Daily-DS.M-QS'!BH5+'Daily-DS.M-QS'!BJ5 -> 10 | E25: ='Daily-DS.M-QS'!AY5+'Daily-DS.M-QS'!BA5+'Daily-DS.M-QS'!BC5+'Daily-DS.M-QS'!BE5+'Daily-DS.M-QS'!BG5+'Daily-DS.M-QS'!BI5+'Daily-DS.M-QS'!BK5 -> 14 | F25: ='Daily-DS.M-QS'!BL5+'Daily-DS.M-QS'!BN5+'Daily-DS.M-QS'!BP5+'Daily-DS.M-QS'!BR5+'Daily-DS.M-QS'!BT5+'Daily-DS.M-QS'!BV5+'Daily-DS.M-QS'!BX5 -> 21 | G25: ='Daily-DS.M-QS'!BM5+'Daily-DS.M-QS'!BO5+'Daily-DS.M-QS'!BQ5+'Daily-DS.M-QS'!BS5+'Daily-DS.M-QS'!BU5+'Daily-DS.M-QS'!BW5+'Daily-DS.M-QS'!BY5 -> 15 | H25: ='Daily-DS.M-QS'!BZ5+'Daily-DS.M-QS'!CB5+'Daily-DS.M-QS'!CD5+'Daily-DS.M-QS'!CF5+'Daily-DS.M-QS'!CH5+'Daily-DS.M-QS'!CJ5+'Daily-DS.M-QS'!CL5 -> 16 | I25: ='Daily-DS.M-QS'!CA5+'Daily-DS.M-QS'!CC5+'Daily-DS.M-QS'!CE5+'Daily-DS.M-QS'!CG5+'Daily-DS.M-QS'!CI5+'Daily-DS.M-QS'!CK5+'Daily-DS.M-QS'!CM5 -> 5 | J25: ='Daily-DS.M-QS'!CN5+'Daily-DS.M-QS'!CP5+'Daily-DS.M-QS'!CR5+'Daily-DS.M-QS'!CT5+'Daily-DS.M-QS'!CV5+'Daily-DS.M-QS'!CX5+'Daily-DS.M-QS'!CZ5 -> 72 | K25: ='Daily-DS.M-QS'!CO5+'Daily-DS.M-QS'!CQ5+'Daily-DS.M-QS'!CS5+'Daily-DS.M-QS'!CU5+'Daily-DS.M-QS'!CW5+'Daily-DS.M-QS'!CY5+'Daily-DS.M-QS'!DA5 -> 0 | L25: ='Daily-DS.M-QS'!DB5+'Daily-DS.M-QS'!DD5+'Daily-DS.M-QS'!DF5+'Daily-DS.M-QS'!DH5+'Daily-DS.M-QS'!DJ5+'Daily-DS.M-QS'!DL5+'Daily-DS.M-QS'!DN5 -> 37 | M25: ='Daily-DS.M-QS'!DC5+'Daily-DS.M-QS'!DE5+'Daily-DS.M-QS'!DG5+'Daily-DS.M-QS'!DI5+'Daily-DS.M-QS'!DK5+'Daily-DS.M-QS'!DM5+'Daily-DS.M-QS'!DO5 -> 9 | N25: 108 | O25: 72 | P25: 34 | Q25: 8
A26: Appels Abandonnés | B26: ='Daily-DS.M-QS'!AJ6+'Daily-DS.M-QS'!AL6+'Daily-DS.M-QS'!AN6+'Daily-DS.M-QS'!AP6+'Daily-DS.M-QS'!AR6+'Daily-DS.M-QS'!AT6+'Daily-DS.M-QS'!AV6 -> 10 | C26: ='Daily-DS.M-QS'!AK6+'Daily-DS.M-QS'!AM6+'Daily-DS.M-QS'!AO6+'Daily-DS.M-QS'!AQ6+'Daily-DS.M-QS'!AS6+'Daily-DS.M-QS'!AU6+'Daily-DS.M-QS'!AW6 -> 7 | D26: ='Daily-DS.M-QS'!AX6+'Daily-DS.M-QS'!AZ6+'Daily-DS.M-QS'!BB6+'Daily-DS.M-QS'!BD6+'Daily-DS.M-QS'!BF6+'Daily-DS.M-QS'!BH6+'Daily-DS.M-QS'!BJ6 -> 3 | E26: ='Daily-DS.M-QS'!AY6+'Daily-DS.M-QS'!BA6+'Daily-DS.M-QS'!BC6+'Daily-DS.M-QS'!BE6+'Daily-DS.M-QS'!BG6+'Daily-DS.M-QS'!BI6+'Daily-DS.M-QS'!BK6 -> 2 | F26: ='Daily-DS.M-QS'!BL6+'Daily-DS.M-QS'!BN6+'Daily-DS.M-QS'!BP6+'Daily-DS.M-QS'!BR6+'Daily-DS.M-QS'!BT6+'Daily-DS.M-QS'!BV6+'Daily-DS.M-QS'!BX6 -> 7 | G26: ='Daily-DS.M-QS'!BM6+'Daily-DS.M-QS'!BO6+'Daily-DS.M-QS'!BQ6+'Daily-DS.M-QS'!BS6+'Daily-DS.M-QS'!BU6+'Daily-DS.M-QS'!BW6+'Daily-DS.M-QS'!BY6 -> 7 | H26: ='Daily-DS.M-QS'!BZ6+'Daily-DS.M-QS'!CB6+'Daily-DS.M-QS'!CD6+'Daily-DS.M-QS'!CF6+'Daily-DS.M-QS'!CH6+'Daily-DS.M-QS'!CJ6+'Daily-DS.M-QS'!CL6 -> 2 | I26: ='Daily-DS.M-QS'!CA6+'Daily-DS.M-QS'!CC6+'Daily-DS.M-QS'!CE6+'Daily-DS.M-QS'!CG6+'Daily-DS.M-QS'!CI6+'Daily-DS.M-QS'!CK6+'Daily-DS.M-QS'!CM6 -> 8 | J26: ='Daily-DS.M-QS'!CN6+'Daily-DS.M-QS'!CP6+'Daily-DS.M-QS'!CR6+'Daily-DS.M-QS'!CT6+'Daily-DS.M-QS'!CV6+'Daily-DS.M-QS'!CX6+'Daily-DS.M-QS'!CZ6 -> 57 | K26: ='Daily-DS.M-QS'!CO6+'Daily-DS.M-QS'!CQ6+'Daily-DS.M-QS'!CS6+'Daily-DS.M-QS'!CU6+'Daily-DS.M-QS'!CW6+'Daily-DS.M-QS'!CY6+'Daily-DS.M-QS'!DA6 -> 2 | L26: ='Daily-DS.M-QS'!DB6+'Daily-DS.M-QS'!DD6+'Daily-DS.M-QS'!DF6+'Daily-DS.M-QS'!DH6+'Daily-DS.M-QS'!DJ6+'Daily-DS.M-QS'!DL6+'Daily-DS.M-QS'!DN6 -> 26 | M26: ='Daily-DS.M-QS'!DC6+'Daily-DS.M-QS'!DE6+'Daily-DS.M-QS'!DG6+'Daily-DS.M-QS'!DI6+'Daily-DS.M-QS'!DK6+'Daily-DS.M-QS'!DM6+'Daily-DS.M-QS'!DO6 -> 7 | N26: 15 | O26: 16 | P26: 11 | Q26: 8
A27: QS | B27: =B24/B23 -> 0.96860987 | C27: =C24/C23 -> 0.97592998 | D27: =D24/D23 -> 0.98461538 | E27: =E24/E23 -> 0.97598628 | F27: =F24/F23 -> 0.97371715 | G27: =G24/G23 -> 0.96341463 | H27: =H24/H23 -> 0.97431782 | I27: =I24/I23 -> 0.98903509 | ... K27: =K24/K23 -> 1 | L27: 0.95 | M27: 0.98 | N27: 0.867 | O27: 0.8879 | P27: 0.9445 | Q27: 0.9834
A28: Taux des perdus | B28: =B25/B23 -> 0.031390135 | C28: =C26/C23 -> 0.015317287 | D28: =D25/D23 -> 0.015384615 | E28: =E26/E23 -> 0.0034305317 | F28: =F25/F23 -> 0.026282854 | G28: =G26/G23 -> 0.017073171 | H28: =H25/H23 -> 0.025682183 | I28: =I26/I23 -> 0.01754386 | J28: =J25/J23 -> 0.094488189 | K28: =K26/K23 -> 0.0056980057 | L28: 0.05 | M28: 0.02 | N28: 0.133 | O28: 0.1121 | P28: 0.0555 | Q28: 0.0166
A29: Taux des abandonnés | B29: =B26/B23 -> 0.014947683 | C29: =C26/C23 -> 0.015317287 | D29: =D26/D23 -> 0.0046153846 | E29: =E26/E23 -> 0.0034305317 | F29: =F26/F23 -> 0.0087609512 | G29: =G26/G23 -> 0.017073171 | H29: =H26/H23 -> 0.0032102729 | I29: =I26/I23 -> 0.01754386 | ... M29: =M26/M23 -> 0.014112903 | N29: 1,85% | O29: 2,49% | P29: 1,79% | Q29: 1,66%
A31: Durée Moy. d'attente | B31: =AVERAGE('Daily-DS.M-QS'!AJ11,'Daily-DS.M-QS'!AL11,'Daily-DS.M-QS'!AN11,'Daily-DS.M-QS'!AP11,'Daily-DS.M-QS'!AR11,'Daily-DS.M-QS'!AT11,'Daily-DS.M-QS'!AV11) -> 0.021130952 | C31: =AVERAGE('Daily-DS.M-QS'!AK11,'Daily-DS.M-QS'!AM11,'Daily-DS.M-QS'!AO11,'Daily-DS.M-QS'!AQ11,'Daily-DS.M-QS'!AS11,'Daily-DS.M-QS'!AU11,'Daily-DS.M-QS'!AW11) -> 0.025992063 | D31: =AVERAGE('Daily-DS.M-QS'!AX11,'Daily-DS.M-QS'!AZ11,'Daily-DS.M-QS'!BB11,'Daily-DS.M-QS'!BD11,'Daily-DS.M-QS'!BF11,'Daily-DS.M-QS'!BH11,'Daily-DS.M-QS'!BJ11) -> 0.016666667 | E31: =AVERAGE('Daily-DS.M-QS'!AY11,'Daily-DS.M-QS'!BA11,'Daily-DS.M-QS'!BC11,'Daily-DS.M-QS'!BE11,'Daily-DS.M-QS'!BG11,'Daily-DS.M-QS'!BI11,'Daily-DS.M-QS'!BK11) -> 0.015674603 | F31: =AVERAGE('Daily-DS.M-QS'!BL11,'Daily-DS.M-QS'!BN11,'Daily-DS.M-QS'!BP11,'Daily-DS.M-QS'!BR11,'Daily-DS.M-QS'!BT11,'Daily-DS.M-QS'!BV11,'Daily-DS.M-QS'!BX11) -> 0.022619048 | G31: =AVERAGE('Daily-DS.M-QS'!BM11,'Daily-DS.M-QS'!BO11,'Daily-DS.M-QS'!BQ11,'Daily-DS.M-QS'!BS11,'Daily-DS.M-QS'!BU11,'Daily-DS.M-QS'!BW11,'Daily-DS.M-QS'!BY11) -> 0.018551587 | H31: =AVERAGE('Daily-DS.M-QS'!BZ11,'Daily-DS.M-QS'!CB11,'Daily-DS.M-QS'!CD11,'Daily-DS.M-QS'!CF11,'Daily-DS.M-QS'!CH11,'Daily-DS.M-QS'!CJ11,'Daily-DS.M-QS'!CL11) -> 0.022718254 | I31: =AVERAGE('Daily-DS.M-QS'!CA11,'Daily-DS.M-QS'!CC11,'Daily-DS.M-QS'!CE11,'Daily-DS.M-QS'!CG11,'Daily-DS.M-QS'!CI11,'Daily-DS.M-QS'!CK11,'Daily-DS.M-QS'!CM11) -> 0.014583333 | J31: =AVERAGE('Daily-DS.M-QS'!CN11,'Daily-DS.M-QS'!CP11,'Daily-DS.M-QS'!CR11,'Daily-DS.M-QS'!CT11,'Daily-DS.M-QS'!CV11,'Daily-DS.M-QS'!CX11,'Daily-DS.M-QS'!CZ11) -> 0.022420635 | K31: =AVERAGE('Daily-DS.M-QS'!CO11,'Daily-DS.M-QS'!CQ11,'Daily-DS.M-QS'!CS11,'Daily-DS.M-QS'!CU11,'Daily-DS.M-QS'!CW11,'Daily-DS.M-QS'!CY11,'Daily-DS.M-QS'!DA11) -> 0.012301587 | L31: =AVERAGE('Daily-DS.M-QS'!DB11,'Daily-DS.M-QS'!DD11,'Daily-DS.M-QS'!DF11,'Daily-DS.M-QS'!DH11,'Daily-DS.M-QS'!DJ11,'Daily-DS.M-QS'!DL11,'Daily-DS.M-QS'!DN11) -> 0.034126984 | M31: =AVERAGE('Daily-DS.M-QS'!DC11,'Daily-DS.M-QS'!DE11,'Daily-DS.M-QS'!DG11,'Daily-DS.M-QS'!DI11,'Daily-DS.M-QS'!DK11,'Daily-DS.M-QS'!DM11,'Daily-DS.M-QS'!DO11) -> 0.019742063 | N31: 0.063888889 | O31: 0.013194444 | P31: 0.035416667 | Q31: 0.01875
A32: Durée Moy. de communication | B32: =AVERAGE('Daily-DS.M-QS'!AJ12,'Daily-DS.M-QS'!AL12,'Daily-DS.M-QS'!AN12,'Daily-DS.M-QS'!AP12,'Daily-DS.M-QS'!AR12,'Daily-DS.M-QS'!AT12,'Daily-DS.M-QS'!AV12) -> 0.28025794 | C32: =AVERAGE('Daily-DS.M-QS'!AK12,'Daily-DS.M-QS'!AM12,'Daily-DS.M-QS'!AO12,'Daily-DS.M-QS'!AQ12,'Daily-DS.M-QS'!AS12,'Daily-DS.M-QS'!AU12,'Daily-DS.M-QS'!AW12) -> 0.1781746 | D32: =AVERAGE('Daily-DS.M-QS'!AX12,'Daily-DS.M-QS'!AZ12,'Daily-DS.M-QS'!BB12,'Daily-DS.M-QS'!BD12,'Daily-DS.M-QS'!BF12,'Daily-DS.M-QS'!BH12,'Daily-DS.M-QS'!BJ12) -> 0.30486111 | E32: =AVERAGE('Daily-DS.M-QS'!AY12,'Daily-DS.M-QS'!BA12,'Daily-DS.M-QS'!BC12,'Daily-DS.M-QS'!BE12,'Daily-DS.M-QS'!BG12,'Daily-DS.M-QS'!BI12,'Daily-DS.M-QS'!BK12) -> 0.20168651 | F32: =AVERAGE('Daily-DS.M-QS'!BL12,'Daily-DS.M-QS'!BN12,'Daily-DS.M-QS'!BP12,'Daily-DS.M-QS'!BR12,'Daily-DS.M-QS'!BT12,'Daily-DS.M-QS'!BV12,'Daily-DS.M-QS'!BX12) -> 0.26458333 | G32: =AVERAGE('Daily-DS.M-QS'!BM12,'Daily-DS.M-QS'!BO12,'Daily-DS.M-QS'!BQ12,'Daily-DS.M-QS'!BS12,'Daily-DS.M-QS'!BU12,'Daily-DS.M-QS'!BW12,'Daily-DS.M-QS'!BY12) -> 0.17797619 | H32: =AVERAGE('Daily-DS.M-QS'!BZ12,'Daily-DS.M-QS'!CB12,'Daily-DS.M-QS'!CD12,'Daily-DS.M-QS'!CF12,'Daily-DS.M-QS'!CH12,'Daily-DS.M-QS'!CJ12,'Daily-DS.M-QS'!CL12) -> 0.2860119 | I32: =AVERAGE('Daily-DS.M-QS'!CA12,'Daily-DS.M-QS'!CC12,'Daily-DS.M-QS'!CE12,'Daily-DS.M-QS'!CG12,'Daily-DS.M-QS'!CI12,'Daily-DS.M-QS'!CK12,'Daily-DS.M-QS'!CM12) -> 0.23392857 | J32: =AVERAGE('Daily-DS.M-QS'!CN12,'Daily-DS.M-QS'!CP12,'Daily-DS.M-QS'!CR12,'Daily-DS.M-QS'!CT12,'Daily-DS.M-QS'!CV12,'Daily-DS.M-QS'!CX12,'Daily-DS.M-QS'!CZ12) -> 0.29206349 | K32: =AVERAGE('Daily-DS.M-QS'!CO12,'Daily-DS.M-QS'!CQ12,'Daily-DS.M-QS'!CS12,'Daily-DS.M-QS'!CU12,'Daily-DS.M-QS'!CW12,'Daily-DS.M-QS'!CY12,'Daily-DS.M-QS'!DA12) -> 0.26765873 | L32: =AVERAGE('Daily-DS.M-QS'!DB12,'Daily-DS.M-QS'!DD12,'Daily-DS.M-QS'!DF12,'Daily-DS.M-QS'!DH12,'Daily-DS.M-QS'!DJ12,'Daily-DS.M-QS'!DL12,'Daily-DS.M-QS'!DN12) -> 0.32202381 | M32: =AVERAGE('Daily-DS.M-QS'!DC12,'Daily-DS.M-QS'!DE12,'Daily-DS.M-QS'!DG12,'Daily-DS.M-QS'!DI12,'Daily-DS.M-QS'!DK12,'Daily-DS.M-QS'!DM12,'Daily-DS.M-QS'!DO12) -> 0.21418651 | N32: 0.30277778 | O32: 0.22222222 | P32: 0.32152778 | Q32: 0.18680556
A34: Appels courts < 15s | B34: ='Daily-DS.M-QS'!AJ14+'Daily-DS.M-QS'!AL14+'Daily-DS.M-QS'!AN14+'Daily-DS.M-QS'!AP14+'Daily-DS.M-QS'!AR14+'Daily-DS.M-QS'!AT14+'Daily-DS.M-QS'!AV14 -> 42 | C34: ='Daily-DS.M-QS'!AK14+'Daily-DS.M-QS'!AM14+'Daily-DS.M-QS'!AO14+'Daily-DS.M-QS'!AQ14+'Daily-DS.M-QS'!AS14+'Daily-DS.M-QS'!AU14+'Daily-DS.M-QS'!AW14 -> 26 | D34: ='Daily-DS.M-QS'!AX14+'Daily-DS.M-QS'!AZ14+'Daily-DS.M-QS'!BB14+'Daily-DS.M-QS'!BD14+'Daily-DS.M-QS'!BF14+'Daily-DS.M-QS'!BH14+'Daily-DS.M-QS'!BJ14 -> 34 | E34: ='Daily-DS.M-QS'!AY14+'Daily-DS.M-QS'!BA14+'Daily-DS.M-QS'!BC14+'Daily-DS.M-QS'!BE14+'Daily-DS.M-QS'!BG14+'Daily-DS.M-QS'!BI14+'Daily-DS.M-QS'!BK14 -> 46 | F34: ='Daily-DS.M-QS'!BL14+'Daily-DS.M-QS'!BN14+'Daily-DS.M-QS'!BP14+'Daily-DS.M-QS'!BR14+'Daily-DS.M-QS'!BT14+'Daily-DS.M-QS'!BV14+'Daily-DS.M-QS'!BX14 -> 59 | G34: ='Daily-DS.M-QS'!BM14+'Daily-DS.M-QS'!BO14+'Daily-DS.M-QS'!BQ14+'Daily-DS.M-QS'!BS14+'Daily-DS.M-QS'!BU14+'Daily-DS.M-QS'!BW14+'Daily-DS.M-QS'!BY14 -> 38 | H34: ='Daily-DS.M-QS'!BZ14+'Daily-DS.M-QS'!CB14+'Daily-DS.M-QS'!CD14+'Daily-DS.M-QS'!CF14+'Daily-DS.M-QS'!CH14+'Daily-DS.M-QS'!CJ14+'Daily-DS.M-QS'!CL14 -> 51 | I34: ='Daily-DS.M-QS'!CA14+'Daily-DS.M-QS'!CC14+'Daily-DS.M-QS'!CE14+'Daily-DS.M-QS'!CG14+'Daily-DS.M-QS'!CI14+'Daily-DS.M-QS'!CK14+'Daily-DS.M-QS'!CM14 -> 21 | J34: ='Daily-DS.M-QS'!CN14+'Daily-DS.M-QS'!CP14+'Daily-DS.M-QS'!CR14+'Daily-DS.M-QS'!CT14+'Daily-DS.M-QS'!CV14+'Daily-DS.M-QS'!CX14+'Daily-DS.M-QS'!CZ14 -> 47 | K34: ='Daily-DS.M-QS'!CO14+'Daily-DS.M-QS'!CQ14+'Daily-DS.M-QS'!CS14+'Daily-DS.M-QS'!CU14+'Daily-DS.M-QS'!CW14+'Daily-DS.M-QS'!CY14+'Daily-DS.M-QS'!DA14 -> 20 | L34: ='Daily-DS.M-QS'!DB14+'Daily-DS.M-QS'!DD14+'Daily-DS.M-QS'!DF14+'Daily-DS.M-QS'!DH14+'Daily-DS.M-QS'!DJ14+'Daily-DS.M-QS'!DL14+'Daily-DS.M-QS'!DN14 -> 32 | M34: ='Daily-DS.M-QS'!DC14+'Daily-DS.M-QS'!DE14+'Daily-DS.M-QS'!DG14+'Daily-DS.M-QS'!DI14+'Daily-DS.M-QS'!DK14+'Daily-DS.M-QS'!DM14+'Daily-DS.M-QS'!DO14 -> 33 | N34: 24 | O34: 29 | P34: 26 | Q34: 28
A35: Taux de conformité | B35: =B34/B24 -> 0.064814815 | C35: =C34/C24 -> 0.058295964 | D35: =D34/D24 -> 0.053125 | E35: =E34/E24 -> 0.080843585 | F35: =F34/F24 -> 0.075835476 | G35: =G34/G24 -> 0.096202532 | H35: =H34/H24 -> 0.084019769 | I35: =I34/I24 -> 0.046563193 | ... M35: =M34/M24 -> 0.067761807 | N35: 3,41% | O35: 5,09% | P35: 4,49% | Q35: 5,92%
A37: Appels Répondus <30s | B37: ='Daily-DS.M-QS'!AJ17+'Daily-DS.M-QS'!AL17+'Daily-DS.M-QS'!AN17+'Daily-DS.M-QS'!AP17+'Daily-DS.M-QS'!AR17+'Daily-DS.M-QS'!AT17+'Daily-DS.M-QS'!AV17 -> 535 | C37: ='Daily-DS.M-QS'!AK17+'Daily-DS.M-QS'!AM17+'Daily-DS.M-QS'!AO17+'Daily-DS.M-QS'!AQ17+'Daily-DS.M-QS'!AS17+'Daily-DS.M-QS'!AU17+'Daily-DS.M-QS'!AW17 -> 373 | D37: ='Daily-DS.M-QS'!AX17+'Daily-DS.M-QS'!AZ17+'Daily-DS.M-QS'!BB17+'Daily-DS.M-QS'!BD17+'Daily-DS.M-QS'!BF17+'Daily-DS.M-QS'!BH17+'Daily-DS.M-QS'!BJ17 -> 548 | E37: ='Daily-DS.M-QS'!AY17+'Daily-DS.M-QS'!BA17+'Daily-DS.M-QS'!BC17+'Daily-DS.M-QS'!BE17+'Daily-DS.M-QS'!BG17+'Daily-DS.M-QS'!BI17+'Daily-DS.M-QS'!BK17 -> 478 | F37: ='Daily-DS.M-QS'!BL17+'Daily-DS.M-QS'!BN17+'Daily-DS.M-QS'!BP17+'Daily-DS.M-QS'!BR17+'Daily-DS.M-QS'!BT17+'Daily-DS.M-QS'!BV17+'Daily-DS.M-QS'!BX17 -> 626 | G37: ='Daily-DS.M-QS'!BM17+'Daily-DS.M-QS'!BO17+'Daily-DS.M-QS'!BQ17+'Daily-DS.M-QS'!BS17+'Daily-DS.M-QS'!BU17+'Daily-DS.M-QS'!BW17+'Daily-DS.M-QS'!BY17 -> 338 | H37: ='Daily-DS.M-QS'!BZ17+'Daily-DS.M-QS'!CB17+'Daily-DS.M-QS'!CD17+'Daily-DS.M-QS'!CF17+'Daily-DS.M-QS'!CH17+'Daily-DS.M-QS'!CJ17+'Daily-DS.M-QS'!CL17 -> 479 | I37: ='Daily-DS.M-QS'!CA17+'Daily-DS.M-QS'!CC17+'Daily-DS.M-QS'!CE17+'Daily-DS.M-QS'!CG17+'Daily-DS.M-QS'!CI17+'Daily-DS.M-QS'!CK17+'Daily-DS.M-QS'!CM17 -> 403 | J37: ='Daily-DS.M-QS'!CN17+'Daily-DS.M-QS'!CP17+'Daily-DS.M-QS'!CR17+'Daily-DS.M-QS'!CT17+'Daily-DS.M-QS'!CV17+'Daily-DS.M-QS'!CX17+'Daily-DS.M-QS'!CZ17 -> 556 | K37: ='Daily-DS.M-QS'!CO17+'Daily-DS.M-QS'!CQ17+'Daily-DS.M-QS'!CS17+'Daily-DS.M-QS'!CU17+'Daily-DS.M-QS'!CW17+'Daily-DS.M-QS'!CY17+'Daily-DS.M-QS'!DA17 -> 313 | L37: ='Daily-DS.M-QS'!DB17+'Daily-DS.M-QS'!DD17+'Daily-DS.M-QS'!DF17+'Daily-DS.M-QS'!DH17+'Daily-DS.M-QS'!DJ17+'Daily-DS.M-QS'!DL17+'Daily-DS.M-QS'!DN17 -> 528 | M37: ='Daily-DS.M-QS'!DC17+'Daily-DS.M-QS'!DE17+'Daily-DS.M-QS'!DG17+'Daily-DS.M-QS'!DI17+'Daily-DS.M-QS'!DK17+'Daily-DS.M-QS'!DM17+'Daily-DS.M-QS'!DO17 -> 415 | N37: 469 | O37: 482 | P37: 443 | Q37: 398
A38: SLA (30s) | B38: =B37/B24 -> 0.82561728 | C38: =C37/C24 -> 0.83632287 | D38: =D37/D24 -> 0.85625 | E38: =E37/E24 -> 0.8400703 | F38: =F37/F24 -> 0.80462725 | G38: =G37/G24 -> 0.8556962 | H38: =H37/H24 -> 0.78912685 | I38: =I37/I24 -> 0.89356984 | ... M38: =M37/M24 -> 0.85215606 | N38: 66,62% | O38: 84,56% | P38: 76,51% | Q38: 84,14%

Sheet Daily-DS.M-QS
A1: DS | B1: 46022 | D1: 46021 | F1: 46020 | H1: 46019 | J1: 46018 | L1: 46017 | N1: 46016 | P1: 46015 | R1: 46014 | T1: 46013 | V1: 46012 | X1: 46011 | Z1: 46010 | AB1: 46009 | AD1: 46008 | AF1: 46007 | AH1: 46006 | AJ1: 46005 | AL1: 46004 | AN1: 46003 | AP1: 46002 | AR1: 46001 | AT1: 46000 | AV1: 45999 | AX1: 45998 | AZ1: 45997 | BB1: 45996 | BD1: 45995 | BF1: 45994 | BH1: 45993 | BJ1: 45992 | BL1: 45991 | BN1: 45990 | BP1: 45989 | BR1: 45988 | BT1: 45987 | BV1: 45986 | BX1: 45985 | BZ1: 45984 | CB1: 45983 | CD1: 45982 | CF1: 45981 | CH1: 45980 | CJ1: 45979 | CL1: 45978 | CN1: 45977 | CP1: 45976 | CR1: 45975 | CT1: 45974 | CV1: 45973 | CX1: 45972 | CZ1: 45971 | DB1: 45970 | DD1: 45969 | DF1: 45968 | DH1: 45967 | DJ1: 45966 | DL1: 45965 | DN1: 45964 | DP1: 45963 | DR1: 45962 | DT1: 45961 | DV1: 45960 | DX1: 45959 | DZ1: 45958 | EB1: 45957 | ED1: 45956 | EF1: 45955 | EH1: 45954 | EJ1: 45953 | EL1: 45952 | EN1: 45951 | EP1: 45950
B2: Magasin FO | C2: Magasin BO | D2: Magasin FO | E2: Magasin BO | F2: Magasin FO | G2: Magasin BO | H2: Magasin FO | I2: Magasin BO | J2: Magasin FO | K2: Magasin BO | L2: Magasin FO | M2: Magasin BO | N2: Magasin FO | O2: Magasin BO | P2: Magasin FO | Q2: Magasin BO | R2: Magasin FO | S2: Magasin BO | T2: Magasin FO | U2: Magasin BO | V2: Magasin FO | W2: Magasin BO | X2: Magasin FO | Y2: Magasin BO | Z2: Magasin FO | AA2: Magasin BO | AB2: Magasin FO | AC2: Magasin BO | AD2: Magasin FO | AE2: Magasin BO | AF2: Magasin FO | AG2: Magasin BO | AH2: Magasin FO | AI2: Magasin BO | AJ2: Magasin FO | AK2: Magasin BO | AL2: Magasin FO | AM2: Magasin BO | AN2: Magasin FO | AO2: Magasin BO | AP2: Magasin FO | AQ2: Magasin BO | AR2: Magasin FO | AS2: Magasin BO | AT2: Magasin FO | AU2: Magasin BO | AV2: Magasin FO | AW2: Magasin BO | AX2: Magasin FO | AY2: Magasin BO | AZ2: Magasin FO | BA2: Magasin BO | BB2: Magasin FO | BC2: Magasin BO | BD2: Magasin FO | BE2: Magasin BO | BF2: Magasin FO | BG2: Magasin BO | BH2: Magasin FO | BI2: Magasin BO | BJ2: Magasin FO | BK2: Magasin BO | BL2: Magasin FO | BM2: Magasin BO | BN2: Magasin FO | BO2: Magasin BO | BP2: Magasin FO | BQ2: Magasin BO | BR2: Magasin FO | BS2: Magasin BO | BT2: Magasin FO | BU2: Magasin BO | BV2: Magasin FO | BW2: Magasin BO | BX2: Magasin FO | BY2: Magasin BO | BZ2: Magasin FO | CA2: Magasin BO | CB2: Magasin FO | CC2: Magasin BO | CD2: Magasin FO | CE2: Magasin BO | CF2: Magasin FO | CG2: Magasin BO | CH2: Magasin FO | CI2: Magasin BO | CJ2: Magasin FO | CK2: Magasin BO | CL2: Magasin FO | CM2: Magasin BO | CN2: Magasin FO | CO2: Magasin BO | CP2: Magasin FO | CQ2: Magasin BO | CR2: Magasin FO | CS2: Magasin BO | CT2: Magasin FO | CU2: Magasin BO | CV2: Magasin FO | CW2: Magasin BO | CX2: Magasin FO | CY2: Magasin BO | CZ2: Magasin FO | DA2: Magasin BO | DB2: Magasin FO | DC2: Magasin BO | DD2: Magasin FO | DE2: Magasin BO | DF2: Magasin FO | DG2: Magasin BO | DH2: Magasin FO | DI2: Magasin BO | DJ2: Magasin FO | DK2: Magasin BO | DL2: Magasin FO | DM2: Magasin BO | DN2: Magasin FO | DO2: Magasin BO | DP2: Magasin FO | DQ2: Magasin BO | DR2: Magasin FO | DS2: Magasin BO | DT2: Magasin FO | DU2: Magasin BO | DV2: Magasin FO | DW2: Magasin BO | DX2: Magasin FO | DY2: Magasin BO | DZ2: Magasin FO | EA2: Magasin BO | EB2: Magasin FO | EC2: Magasin BO | ED2: Magasin FO | EE2: Magasin BO | EF2: Magasin FO | EG2: Magasin BO | EH2: Magasin FO | EI2: Magasin BO | EJ2: Magasin FO | EK2: Magasin BO | EL2: Magasin FO | EM2: Magasin BO | EN2: Magasin FO | EO2: Magasin BO | EP2: Magasin FO | EQ2: Magasin BO
A3: Appels comptabilisés | AF3: 117 | AG3: 71 | AH3: 138 | AI3: 108 | AJ3: 32 | AK3: 3 | AL3: 100 | AM3: 42 | AN3: 108 | AO3: 65 | AP3: 101 | AQ3: 85 | AR3: 104 | AS3: 86 | AT3: 114 | AU3: 97 | AV3: 110 | AW3: 79 | AX3: 35 | AY3: 4 | AZ3: 91 | BA3: 45 | BB3: 82 | BC3: 87 | BD3: 103 | BE3: 77 | BF3: 102 | BG3: 83 | BH3: 121 | BI3: 105 | BJ3: 116 | BK3: 182 | BL3: 41 | BM3: 6 | BN3: 136 | BO3: 53 | BP3: 133 | BQ3: 79 | BR3: 99 | BS3: 75 | BT3: 119 | BU3: 66 | BV3: 149 | BW3: 55 | BX3: 122 | BY3: 76 | BZ3: 29 | CA3: 4 | CB3: 119 | CC3: 38 | CD3: 112 | CE3: 77 | CF3: 82 | CG3: 94 | CH3: 101 | CI3: 81 | CJ3: 73 | CK3: 92 | CL3: 107 | CM3: 70 | CN3: 14 | CO3: 1 | CP3: 97 | CQ3: 40 | CR3: 104 | CS3: 82 | CT3: 146 | CU3: 67 | CV3: 122 | CW3: 80 | CX3: 49 | CY3: 22 | CZ3: 230 | DA3: 59 | DB3: 19 | DC3: 8 | DD3: 99 | DE3: 24 | DF3: 99 | DG3: 59 | DH3: 130 | DI3: 81 | DJ3: 116 | DK3: 82 | DL3: 155 | DM3: 106 | DN3: 139 | DO3: 136 | DP3: 21 | DQ3: 1 | DR3: 135 | DS3: 53 | DT3: 164 | DU3: 173 | DV3: 153 | DW3: 100 | DX3: 133 | DY3: 165 | DZ3: 91 | EA3: 84 | EB3: 115 | EC3: 66 | ED3: 24 | EE3: 9 | EF3: 74 | EG3: 68 | EH3: 110 | EI3: 62 | EJ3: 116 | EK3: 91 | EL3: 138 | EM3: 56 | EN3: 70 | EO3: 104 | EP3: 81 | EQ3: 91
A4: Appels Répondus | AF4: 114 | AG4: 71 | AH4: 133 | AI4: 101 | AJ4: 28 | AK4: 3 | AL4: 97 | AM4: 40 | AN4: 105 | AO4: 63 | AP4: 99 | AQ4: 82 | AR4: 99 | AS4: 84 | AT4: 111 | AU4: 96 | AV4: 109 | AW4: 78 | AX4: 34 | AY4: 4 | AZ4: 88 | BA4: 44 | BB4: 81 | BC4: 87 | BD4: 102 | BE4: 76 | BF4: 102 | BG4: 83 | BH4: 118 | BI4: 104 | BJ4: 115 | BK4: 171 | BL4: 35 | BM4: 1 | BN4: 132 | BO4: 53 | BP4: 133 | BQ4: 74 | BR4: 99 | BS4: 75 | BT4: 117 | BU4: 66 | BV4: 142 | BW4: 50 | BX4: 120 | BY4: 76 | BZ4: 29 | CA4: 4 | CB4: 112 | CC4: 38 | CD4: 112 | CE4: 77 | CF4: 82 | CG4: 94 | CH4: 101 | CI4: 81 | CJ4: 72 | CK4: 91 | CL4: 99 | CM4: 66 | CN4: 12 | CO4: 1 | CP4: 90 | CQ4: 40 | CR4: 101 | CS4: 82 | CT4: 142 | CU4: 67 | CV4: 120 | CW4: 80 | CX4: 48 | CY4: 22 | CZ4: 177 | DA4: 59 | DB4: 19 | DC4: 7 | DD4: 93 | DE4: 24 | DF4: 98 | DG4: 59 | DH4: 124 | DI4: 80 | DJ4: 114 | DK4: 82 | DL4: 148 | DM4: 99 | DN4: 124 | DO4: 136 | DP4: 17 | DQ4: 1 | DR4: 85 | DS4: 52 | DT4: 135 | DU4: 110 | DV4: 143 | DW4: 99 | DX4: 124 | DY4: 165 | DZ4: 88 | EA4: 84 | EB4: 112 | EC4: 59 | ED4: 20 | EE4: 9 | EF4: 70 | EG4: 65 | EH4: 105 | EI4: 62 | EJ4: 111 | EK4: 89 | EL4: 133 | EM4: 55 | EN4: 63 | EO4: 102 | EP4: 77 | EQ4: 91
A5: Appels Perdus | AF5: 3 | AG5: 0 | AH5: 5 | AI5: 7 | AJ5: 4 | AK5: 0 | AL5: 3 | AM5: 2 | AN5: 3 | AO5: 2 | AP5: 2 | AQ5: 3 | AR5: 5 | AS5: 2 | AT5: 3 | AU5: 1 | AV5: 1 | AW5: 1 | AX5: 1 | AY5: 0 | AZ5: 3 | BA5: 1 | BB5: 1 | BC5: 0 | BD5: 1 | BE5: 1 | BF5: 0 | BG5: 0 | BH5: 3 | BI5: 1 | BJ5: 1 | BK5: 11 | BL5: 6 | BM5: 5 | BN5: 4 | BO5: 0 | BP5: 0 | BQ5: 5 | BR5: 0 | BS5: 0 | BT5: 2 | BU5: 0 | BV5: 7 | BW5: 5 | BX5: 2 | BY5: 0 | BZ5: 0 | CA5: 0 | CB5: 7 | CC5: 0 | CD5: 0 | CE5: 0 | CF5: 0 | CG5: 0 | CH5: 0 | CI5: 0 | CJ5: 1 | CK5: 1 | CL5: 8 | CM5: 4 | CN5: 2 | CO5: 0 | CP5: 7 | CQ5: 0 | CR5: 3 | CS5: 0 | CT5: 4 | CU5: 0 | CV5: 2 | CW5: 0 | CX5: 1 | CY5: 0 | CZ5: 53 | DA5: 0 | DB5: 0 | DC5: 1 | DD5: 6 | DE5: 0 | DF5: 1 | DG5: 0 | DH5: 6 | DI5: 1 | DJ5: 2 | DK5: 0 | DL5: 7 | DM5: 7 | DN5: 15 | DO5: 0 | DP5: 4 | DQ5: 0 | DR5: 50 | DS5: 1 | DT5: 29 | DU5: 63 | DV5: 10 | DW5: 1 | DX5: 9 | DY5: 0 | DZ5: 3 | EA5: 0 | EB5: 3 | EC5: 7 | ED5: 4 | EE5: 0 | EF5: 4 | EG5: 3 | EH5: 5 | EI5: 0 | EJ5: 5 | EK5: 2 | EL5: 5 | EM5: 1 | EN5: 7 | EO5: 2 | EP5: 4 | EQ5: 0
A6: Appels Abandonnés | AF6: 0 | AG6: 1 | AH6: 3 | AI6: 4 | AJ6: 0 | AK6: 0 | AL6: 1 | AM6: 0 | AN6: 2 | AO6: 0 | AP6: 2 | AQ6: 4 | AR6: 1 | AS6: 0 | AT6: 1 | AU6: 2 | AV6: 3 | AW6: 1 | AX6: 0 | AY6: 0 | AZ6: 0 | BA6: 0 | BB6: 2 | BC6: 1 | BD6: 0 | BE6: 0 | BF6: 0 | BG6: 1 | BH6: 0 | BI6: 0 | BJ6: 1 | BK6: 0 | BL6: 0 | BM6: 0 | BN6: 1 | BO6: 0 | BP6: 1 | BQ6: 0 | BR6: 0 | BS6: 4 | BT6: 0 | BU6: 1 | BV6: 3 | BW6: 0 | BX6: 2 | BY6: 2 | BZ6: 0 | CA6: 0 | CB6: 1 | CC6: 0 | CD6: 0 | CE6: 1 | CF6: 0 | CG6: 4 | CH6: 0 | CI6: 0 | CJ6: 1 | CK6: 2 | CL6: 0 | CM6: 1 | CN6: 0 | CO6: 0 | CP6: 2 | CQ6: 0 | CR6: 0 | CS6: 1 | CT6: 2 | CU6: 1 | CV6: 3 | CW6: 0 | CX6: 1 | CY6: 0 | CZ6: 49 | DA6: 0 | DB6: 0 | DC6: 0 | DD6: 1 | DE6: 0 | DF6: 1 | DG6: 2 | DH6: 8 | DI6: 0 | DJ6: 1 | DK6: 3 | DL6: 8 | DM6: 2 | DN6: 7 | DO6: 0 | DP6: 0 | DQ6: 0 | DR6: 7 | DS6: 1 | DT6: 2 | DU6: 11 | DV6: 1 | DW6: 0 | DX6: 1 | DY6: 0 | DZ6: 3 | EA6: 2 | EB6: 1 | EC6: 2 | ED6: 1 | EE6: 0 | EF6: 0 | EG6: 1 | EH6: 2 | EI6: 0 | EJ6: 1 | EK6: 2 | EL6: 4 | EM6: 3 | EN6: 2 | EO6: 2 | EP6: 1 | EQ6: 0
A7: Taux de décroché | AF7: 0.97 | AG7: 1 | AH7: 0.96 | AI7: 0.935 | AJ7: 0.88 | AK7: 1 | AL7: 0.97 | AM7: 0.952 | AN7: 0.97 | AO7: 0.969 | AP7: 0.98 | AQ7: 0.965 | AR7: 0.95 | AS7: 0.98 | AT7: 0.97 | AU7: 0.99 | AV7: 0.99 | AW7: 0.99 | AX7: 0.97 | AY7: 1 | AZ7: 0.97 | BA7: 0.98 | BB7: 0.99 | BC7: 1 | BD7: 0.99 | BE7: 0.99 | BF7: 1 | BG7: 1 | BH7: 0.98 | BI7: 0.99 | BJ7: 0.99 | BK7: 0.94 | BL7: 0.85 | BM7: 0.17 | BN7: 0.97 | BO7: 1 | BP7: 1 | BQ7: 0.94 | BR7: 1 | BS7: 1 | BT7: 0.98 | BU7: 1 | BV7: 0.95 | BW7: 0.91 | BX7: 0.98 | BY7: 1 | BZ7: 1 | CA7: 1 | CB7: 0.94 | CC7: 1 | CD7: 1 | CE7: 1 | CF7: 1 | CG7: 1 | CH7: 1 | CI7: 1 | CJ7: 0.99 | CK7: 0.99 | CL7: 0.93 | CM7: 0.94 | CN7: 0.857 | CO7: 1 | CP7: 0.928 | CQ7: 1 | CR7: 0.971 | CS7: 1 | CT7: 0.973 | CU7: 1 | CV7: 0.984 | CW7: 1 | CX7: 0.98 | CY7: 1 | CZ7: 0.77 | DA7: 1 | DB7: 1 | DC7: 0.88 | DD7: 0.94 | DE7: 1 | DF7: 0.99 | DG7: 1 | DH7: 0.95 | DI7: 0.99 | DJ7: 0.98 | DK7: 1 | DL7: 0.96 | DM7: 0.93 | DN7: 0.89 | DO7: 1 | DP7: 0.81 | DQ7: 1 | DR7: 0.63 | DS7: 0.98 | DT7: 0.82 | DU7: 0.64 | DV7: 0.94 | DW7: 0.99 | DX7: 0.93 | DY7: 1 | DZ7: 0.97 | EA7: 1 | EB7: 0.97 | EC7: 0.89 | ED7: 0.83 | EE7: 1 | EF7: 0.95 | EG7: 0.96 | EH7: 0.96 | EI7: 1 | EJ7: 0.96 | EK7: 0.98 | EL7: 0.96 | EM7: 0.98 | EN7: 0.9 | EO7: 0.98 | EP7: 0.95 | EQ7: 1
A8: Taux des perdus | AF8: 0.03 | AG8: 0 | AH8: 0.04 | AI8: 0.065 | AJ8: 0.13 | AK8: 0 | AL8: 0.03 | AM8: 0.048 | AN8: 0.03 | AO8: 0.031 | AP8: 0.02 | AQ8: 0.035 | AR8: 0.05 | AS8: 0.023 | AT8: 0.03 | AU8: 0.01 | AV8: 0.01 | AW8: 0.013 | AX8: 0.03 | AY8: 0 | AZ8: 0.03 | BA8: 0.022 | BB8: 0.01 | BC8: 0 | BD8: 0.01 | BE8: 0.013 | BF8: 0 | BG8: 0 | BH8: 0.02 | BI8: 0.01 | BJ8: 0.01 | BK8: 0.06 | BL8: 0.15 | BM8: 0.833 | BN8: 0.03 | BO8: 0 | BP8: 0 | BQ8: 0.063 | BR8: 0 | BS8: 0 | BT8: 0.02 | BU8: 0 | BV8: 0.05 | BW8: 0.091 | BX8: 0.02 | BY8: 0 | BZ8: 0 | CA8: 0 | CB8: 0.06 | CC8: 0 | CD8: 0 | CE8: 0 | CF8: 0 | CG8: 0 | CH8: 0 | CI8: 0 | CJ8: 0.01 | CK8: 0.011 | CL8: 0.07 | CM8: 0.057 | CN8: 0.143 | CO8: 0 | CP8: 0.072 | CQ8: 0 | CR8: 0.029 | CS8: 0 | CT8: 0.027 | CU8: 0 | CV8: 0.016 | CW8: 0 | CX8: 0.02 | CY8: 0 | CZ8: 0.23 | DA8: 0 | DB8: 0 | DC8: 0.13 | DD8: 0.06 | DE8: 0 | DF8: 0.01 | DG8: 0 | DH8: 0.05 | DI8: 0.01 | DJ8: 0.02 | DK8: 0 | DL8: 0.05 | DM8: 0.07 | DN8: 0.11 | DO8: 0 | DP8: 0.19 | DQ8: 0 | DR8: 0.37 | DS8: 0.02 | DT8: 0.18 | DU8: 0.36 | DV8: 0.07 | DW8: 0.01 | DX8: 0.07 | DY8: 0 | DZ8: 0.03 | EA8: 0 | EB8: 0.03 | EC8: 0.11 | ED8: 0.17 | EE8: 0 | EF8: 0.05 | EG8: 0.04 | EH8: 0.05 | EI8: 0 | EJ8: 0.04 | EK8: 0.02 | EL8: 0.04 | EM8: 0.02 | EN8: 0.1 | EO8: 0.02 | EP8: 0.05 | EQ8: 0
A9: Taux des abandonnés | AF9: 0 | AG9: 0.014 | AH9: 0.022 | AI9: 0.037 | AJ9: 0 | AK9: 0 | AL9: 0.01 | AM9: 0 | AN9: 0.019 | AO9: 0 | AP9: 0.02 | AQ9: 0.047 | AR9: 0.01 | AS9: 0 | AT9: 0.009 | AU9: 0.021 | AV9: 0.027 | AW9: 0.013 | AX9: 0 | AY9: 0 | AZ9: 0 | BA9: 0 | BB9: 0.024 | BC9: 0.011 | BD9: 0 | BE9: 0 | BF9: 0 | BG9: 0.012 | BH9: 0 | BI9: 0 | BJ9: 0.009 | BK9: 0 | BL9: 0 | BM9: 0 | BN9: 0.007 | BO9: 0 | BP9: 0.008 | BQ9: 0 | BR9: 0 | BS9: 0.053 | BT9: 0 | BU9: 0.015 | BV9: 0.02 | BW9: 0 | BX9: 0.016 | BY9: 0.026 | BZ9: 0 | CA9: 0 | CB9: 0.008 | CC9: 0 | CD9: 0 | CE9: 0.013 | CF9: 0 | CG9: 0.043 | CH9: 0 | CI9: 0 | CJ9: 0.014 | CK9: 0.022 | CL9: 0 | CM9: 0.014 | CN9: 0 | CO9: 0 | CP9: 0.021 | CQ9: 0 | CR9: 0 | CS9: 0.012 | CT9: 0.014 | CU9: 0.015 | CV9: 0.025 | CW9: 0 | CX9: 0.02 | CY9: 0 | CZ9: 0.213 | DA9: 0 | DB9: 0 | DC9: 0 | DD9: 0.01 | DE9: 0 | DF9: 0.01 | DG9: 0.034 | DH9: 0.062 | DI9: 0 | DJ9: 0.009 | DK9: 0.037 | DL9: 0.052 | DM9: 0.019 | DN9: 0.05 | DO9: 0 | DP9: 0 | DQ9: 0 | DR9: 0.052 | DS9: 0.019 | DT9: 0.012 | DU9: 0.064 | DV9: 0.007 | DW9: 0 | DX9: 0.008 | DY9: 0 | DZ9: 0.033 | EA9: 0.02 | EB9: 0.009 | EC9: 0.03 | ED9: 0.042 | EE9: 0 | EF9: 0 | EG9: 0.015 | EH9: 0.018 | EI9: 0 | EJ9: 0.009 | EK9: 0.022 | EL9: 0.029 | EM9: 0.054 | EN9: 0.029 | EO9: 0.019 | EP9: 0.012 | EQ9: 0
CN10: ='Daily-DS.M-QS'!CN3+'Daily-DS.M-QS'!CP3+'Daily-DS.M-QS'!CR3+'Daily-DS.M-QS'!CT3+'Daily-DS.M-QS'!CV3+'Daily-DS.M-QS'!CX3+'Daily-DS.M-QS'!CZ3 -> 762
A11: Durée Moy. d'attente | AF11: 0.038194444 | AG11: 0.01875 | AH11: 0.041666667 | AI11: 0.032638889 | AJ11: 0.0090277778 | AK11: 0.0069444444 | AL11: 0.020138889 | AM11: 0.045138889 | AN11: 0.03125 | AO11: 0.025 | AP11: 0.033333333 | AQ11: 0.026388889 | AR11: 0.020138889 | AS11: 0.03125 | AT11: 0.020138889 | AU11: 0.03125 | AV11: 0.013888889 | AW11: 0.015972222 | AX11: 0.021527778 | AY11: 0.011805556 | AZ11: 0.020138889 | BA11: 0.011805556 | BB11: 0.011805556 | BC11: 0.0125 | BD11: 0.0090277778 | BE11: 0.020138889 | BF11: 0.017361111 | BG11: 0.011805556 | BH11: 0.022916667 | BI11: 0.019444444 | BJ11: 0.013888889 | BK11: 0.022222222 | BL11: 0.0375 | BM11: 0.0013888889 | BN11: 0.042361111 | BO11: 0.016666667 | BP11: 0.011111111 | BQ11: 0.025694444 | BR11: 0.011111111 | BS11: 0.0125 | BT11: 0.0097222222 | BU11: 0.016666667 | BV11: 0.025694444 | BW11: 0.044444444 | BX11: 0.020833333 | BY11: 0.0125 | BZ11: 0.0069444444 | CA11: 0.0097222222 | CB11: 0.054861111 | CC11: 0.019444444 | CD11: 0.013194444 | CE11: 0.0097222222 | CF11: 0.019444444 | CG11: 0.013194444 | CH11: 0.015972222 | CI11: 0.011111111 | CJ11: 0.011805556 | CK11: 0.022916667 | CL11: 0.036805556 | CM11: 0.015972222 | CN11: 0.020833333 | CO11: 0.0069444444 | CP11: 0.05 | CQ11: 0.011805556 | CR11: 0.014583333 | CS11: 0.020138889 | CT11: 0.022916667 | CU11: 0.010416667 | CV11: 0.015972222 | CW11: 0.0125 | CX11: 0.015972222 | CY11: 0.011111111 | CZ11: 0.016666667 | DA11: 0.013194444 | DB11: 0.038888889 | DC11: 0.011111111 | DD11: 0.052777778 | DE11: 0.011805556 | DF11: 0.020833333 | DG11: 0.011805556 | DH11: 0.028472222 | DI11: 0.020833333 | DJ11: 0.014583333 | DK11: 0.031944444 | DL11: 0.034027778 | DM11: 0.038888889 | DN11: 0.049305556 | DO11: 0.011805556 | DP11: 0.092361111 | DQ11: 0.0069444444 | DR11: 0.11597222 | DS11: 0.014583333 | DT11: 0.10277778 | DU11: 0.01875 | DV11: 0.034027778 | DW11: 0.0125 | DX11: 0.052083333 | DY11: 0.014583333 | DZ11: 0.020138889 | EA11: 0.015972222 | EB11: 0.034027778 | EC11: 0.013194444 | ED11: 0.017361111 | EE11: 0.011111111 | EF11: 0.042361111 | EG11: 0.025 | EH11: 0.027777778 | EI11: 0.021527778 | EJ11: 0.038888889 | EK11: 0.028472222 | EL11: 0.040972222 | EM11: 0.016666667 | EN11: 0.050694444 | EO11: 0.01875 | EP11: 0.033333333 | EQ11: 0.011805556
A12: Durée Moy. de communication | AF12: 0.22916667 | AG12: 0.30277778 | AH12: 0.22916667 | AI12: 0.19027778 | AJ12: 0.27847222 | AK12: 0.10069444 | AL12: 0.29166667 | AM12: 0.18541667 | AN12: 0.3125 | AO12: 0.22847222 | AP12: 0.22361111 | AQ12: 0.19097222 | AR12: 0.25 | AS12: 0.17430556 | AT12: 0.33958333 | AU12: 0.19513889 | AV12: 0.26597222 | AW12: 0.17222222 | AX12: 0.39722222 | AY12: 0.15277778 | AZ12: 0.40763889 | BA12: 0.21458333 | BB12: 0.25416667 | BC12: 0.2125 | BD12: 0.23888889 | BE12: 0.175 | BF12: 0.25625 | BG12: 0.30277778 | BH12: 0.27708333 | BI12: 0.19583333 | BJ12: 0.30277778 | BK12: 0.15833333 | BL12: 0.19652778 | BM12: 0.0125 | BN12: 0.27152778 | BO12: 0.27777778 | BP12: 0.24097222 | BQ12: 0.21944444 | BR12: 0.26041667 | BS12: 0.21111111 | BT12: 0.26180556 | BU12: 0.14444444 | BV12: 0.29305556 | BW12: 0.18819444 | BX12: 0.32777778 | BY12: 0.19236111 | BZ12: 0.19722222 | CA12: 0.43194444 | CB12: 0.3875 | CC12: 0.24027778 | CD12: 0.26805556 | CE12: 0.19097222 | CF12: 0.3875 | CG12: 0.15972222 | CH12: 0.25763889 | CI12: 0.18402778 | CJ12: 0.225 | CK12: 0.20833333 | CL12: 0.27916667 | CM12: 0.22222222 | CN12: 0.31111111 | CO12: 0.45347222 | CP12: 0.33958333 | CQ12: 0.22986111 | CR12: 0.32916667 | CS12: 0.22986111 | CT12: 0.32708333 | CU12: 0.26736111 | CV12: 0.22986111 | CW12: 0.24236111 | CX12: 0.34861111 | CY12: 0.18611111 | CZ12: 0.15902778 | DA12: 0.26458333 | DB12: 0.24861111 | DC12: 0.18680556 | DD12: 0.32291667 | DE12: 0.23055556 | DF12: 0.4 | DG12: 0.23055556 | DH12: 0.32083333 | DI12: 0.21041667 | DJ12: 0.32013889 | DK12: 0.22708333 | DL12: 0.31388889 | DM12: 0.18958333 | DN12: 0.32777778 | DO12: 0.22430556 | DP12: 0.38819444 | DQ12: 0.40555556 | DR12: 0.21666667 | DS12: 0.20833333 | DT12: 0.29791667 | DU12: 0.12013889 | DV12: 0.33194444 | DW12: 0.21319444 | DX12: 0.37222222 | DY12: 0.19166667 | DZ12: 0.24930556 | EA12: 0.21458333 | EB12: 0.26319444 | EC12: 0.20347222 | ED12: 0.43472222 | EE12: 0.090972222 | EF12: 0.41736111 | EG12: 0.17430556 | EH12: 0.31805556 | EI12: 0.20972222 | EJ12: 0.2375 | EK12: 0.19930556 | EL12: 0.30902778 | EM12: 0.22708333 | EN12: 0.24861111 | EO12: 0.17916667 | EP12: 0.28680556 | EQ12: 0.22708333
A14: Appels courts < 15s | AF14: 12 | AG14: 7 | AH14: 9 | AI14: 11 | AJ14: 1 | AK14: 1 | AL14: 4 | AM14: 3 | AN14: 9 | AO14: 6 | AP14: 5 | AQ14: 5 | AR14: 0 | AS14: 4 | AT14: 10 | AU14: 3 | AV14: 13 | AW14: 4 | AX14: 0 | AY14: 0 | AZ14: 5 | BA14: 3 | BB14: 3 | BC14: 6 | BD14: 6 | BE14: 8 | BF14: 6 | BG14: 6 | BH14: 7 | BI14: 8 | BJ14: 7 | BK14: 15 | BL14: 4 | BM14: 0 | BN14: 5 | BO14: 5 | BP14: 7 | BQ14: 5 | BR14: 11 | BS14: 11 | BT14: 10 | BU14: 9 | BV14: 8 | BW14: 3 | BX14: 14 | BY14: 5 | BZ14: 3 | CA14: 0 | CB14: 11 | CC14: 1 | CD14: 10 | CE14: 4 | CF14: 2 | CG14: 4 | CH14: 4 | CI14: 4 | CJ14: 7 | CK14: 7 | CL14: 14 | CM14: 1 | CN14: 1 | CO14: 0 | CP14: 1 | CQ14: 2 | CR14: 4 | CS14: 3 | CT14: 5 | CU14: 3 | CV14: 7 | CW14: 7 | CX14: 2 | CY14: 3 | CZ14: 27 | DA14: 2 | DB14: 2 | DC14: 0 | DD14: 6 | DE14: 2 | DF14: 1 | DG14: 4 | DH14: 7 | DI14: 4 | DJ14: 5 | DK14: 7 | DL14: 7 | DM14: 6 | DN14: 4 | DO14: 10 | DP14: 0 | DQ14: 0 | DR14: 4 | DS14: 3 | DT14: 8 | DU14: 6 | DV14: 4 | DW14: 8 | DX14: 3 | DY14: 6 | DZ14: 1 | EA14: 5 | EB14: 4 | EC14: 1 | ED14: 2 | EE14: 1 | EF14: 2 | EG14: 3 | EH14: 5 | EI14: 5 | EJ14: 4 | EK14: 10 | EL14: 11 | EM14: 1 | EN14: 1 | EO14: 6 | EP14: 1 | EQ14: 2
A15: Taux de conformité | AF15: 0.1053 | AG15: 0.0986 | AH15: 0.0677 | AI15: 0.1089 | AJ15: 0.0357 | AK15: 0.3333 | AL15: 0.0412 | AM15: 0.075 | AN15: 0.0857 | AO15: 0.0952 | AP15: 0.0505 | AQ15: 0.061 | AR15: 0 | AS15: 0.0476 | AT15: 0.0901 | AU15: 0.0313 | AV15: 0.1193 | AW15: 0.0513 | AX15: 0 | AY15: 0 | AZ15: 0.0568 | BA15: 0.0682 | BB15: 0.037 | BC15: 0.069 | BD15: 0.0588 | BE15: 0.1053 | BF15: 0.0588 | BG15: 0.0723 | BH15: 0.0593 | BI15: 0.0769 | BJ15: 0.0609 | BK15: 0.0877 | BL15: 0.1143 | BM15: 0 | BN15: 0.0379 | BO15: 0.0943 | BP15: 0.0526 | BQ15: 0.0676 | BR15: 0.1111 | BS15: 0.1467 | BT15: 0.0855 | BU15: 0.1364 | BV15: 0.0563 | BW15: 0.06 | BX15: 0.1167 | BY15: 0.0658 | BZ15: 0.1034 | CA15: 0 | CB15: 0.0982 | CC15: 0.0263 | CD15: 0.0893 | CE15: 0.0519 | CF15: 0.0244 | CG15: 0.0426 | CH15: 0.0396 | CI15: 0.0494 | CJ15: 0.0972 | CK15: 0.0769 | CL15: 0.1414 | CM15: 0.0152 | CN15: 0.0833 | CO15: 0 | CP15: 0.0111 | CQ15: 0.05 | CR15: 0.0396 | CS15: 0.0366 | CT15: 0.0352 | CU15: 0.0448 | CV15: 0.0583 | CW15: 0.0875 | CX15: 0.0417 | CY15: 0.1364 | CZ15: 0.1525 | DA15: 0.0339 | DB15: 0.1053 | DC15: 0 | DD15: 0.0645 | DE15: 0.0833 | DF15: 0.0102 | DG15: 0.0678 | DH15: 5,65% | DI15: 5,00% | DJ15: 4,39% | DK15: 8,54% | DL15: 4,73% | DM15: 6,06% | DN15: 3,23% | DO15: 7,35% | DP15: 0,00% | DQ15: 0,00% | DR15: 4,71% | DS15: 5,77% | DT15: 5,93% | DU15: 5,45% | DV15: 2,80% | DW15: 8,08% | DX15: 2,42% | DY15: 3,64% | DZ15: 1,14% | EA15: 5,95% | EB15: 3,57% | EC15: 1,69% | ED15: 10,00% | EE15: 11,11% | EF15: 2,86% | EG15: 4,62% | EH15: 4,76% | EI15: 8,06% | EJ15: 3,60% | EK15: 11,24% | EL15: 8,30% | EM15: 8,30% | EN15: 1,60% | EO15: 1,60% | EP15: 1,30% | EQ15: 1,30%
A17: Appels Répondus <30s | AF17: 87 | AG17: 57 | AH17: 89 | AI17: 75 | AJ17: 28 | AK17: 3 | AL17: 80 | AM17: 38 | AN17: 81 | AO17: 48 | AP17: 77 | AQ17: 66 | AR17: 79 | AS17: 67 | AT17: 95 | AU17: 83 | AV17: 95 | AW17: 68 | AX17: 26 | AY17: 4 | AZ17: 66 | BA17: 40 | BB17: 73 | BC17: 80 | BD17: 97 | BE17: 59 | BF17: 95 | BG17: 73 | BH17: 101 | BI17: 84 | BJ17: 90 | BK17: 138 | BL17: 29 | BM17: 1 | BN17: 79 | BO17: 39 | BP17: 113 | BQ17: 64 | BR17: 87 | BS17: 65 | BT17: 110 | BU17: 59 | BV17: 117 | BW17: 43 | BX17: 91 | BY17: 67 | BZ17: 29 | CA17: 4 | CB17: 58 | CC17: 36 | CD17: 93 | CE17: 72 | CF17: 66 | CG17: 85 | CH17: 86 | CI17: 75 | CJ17: 67 | CK17: 75 | CL17: 80 | CM17: 56 | CN17: 12 | CO17: 1 | CP17: 61 | CQ17: 38 | CR17: 90 | CS17: 71 | CT17: 103 | CU17: 62 | CV17: 106 | CW17: 73 | CX17: 43 | CY17: 19 | CZ17: 141 | DA17: 49 | DB17: 15 | DC17: 6 | DD17: 55 | DE17: 22 | DF17: 78 | DG17: 55 | DH17: 94 | DI17: 67 | DJ17: 101 | DK17: 69 | DL17: 93 | DM17: 78 | DN17: 92 | DO17: 118 | DP17: 11 | DQ17: 1 | DR17: 36 | DS17: 46 | DT17: 70 | DU17: 71 | DV17: 110 | DW17: 91 | DX17: 82 | DY17: 144 | DZ17: 81 | EA17: 79 | EB17: 79 | EC17: 50 | ED17: 19 | EE17: 8 | EF17: 52 | EG17: 56 | EH17: 86 | EI17: 49 | EJ17: 70 | EK17: 72 | EL17: 104 | EM17: 51 | EN17: 51 | EO17: 80 | EP17: 61 | EQ17: 82
A18: SLA (30s) | AF18: 0.763 | AG18: 0.803 | AH18: 0.669 | AI18: 0.743 | AJ18: 1 | AK18: 1 | AL18: 0.825 | AM18: 0.95 | AN18: 0.771 | AO18: 0.762 | AP18: 0.778 | AQ18: 0.805 | AR18: 0.798 | AS18: 0.798 | AT18: 0.856 | AU18: 0.865 | AV18: 0.872 | AW18: 0.872 | AX18: 0.765 | AY18: 1 | AZ18: 0.75 | BA18: 0.909 | BB18: 0.901 | BC18: 0.92 | BD18: 0.951 | BE18: 0.776 | BF18: 0.931 | BG18: 0.88 | BH18: 0.856 | BI18: 0.808 | BJ18: 0.783 | BK18: 0.807 | BL18: 0.829 | BM18: 1 | BN18: 0.598 | BO18: 0.736 | BP18: 0.85 | BQ18: 0.865 | BR18: 0.879 | BS18: 0.867 | BT18: 0.94 | BU18: 0.894 | BV18: 0.824 | BW18: 0.86 | BX18: 0.758 | BY18: 0.882 | BZ18: 1 | CA18: 1 | CB18: 0.518 | CC18: 0.947 | CD18: 0.83 | CE18: 0.935 | CF18: 0.805 | CG18: 0.904 | CH18: 0.851 | CI18: 0.926 | CJ18: 0.931 | CK18: 0.824 | CL18: 0.808 | CM18: 0.848 | CN18: 1 | CO18: 1 | CP18: 0.678 | CQ18: 0.95 | CR18: 0.891 | CS18: 0.866 | CT18: 0.725 | CU18: 0.925 | CV18: 0.883 | CW18: 0.913 | CX18: 0.896 | CY18: 0.864 | CZ18: 0.797 | DA18: 0.831 | DB18: 0.789 | DC18: 0.857 | DD18: 0.591 | DE18: 0.917 | DF18: 0.796 | DG18: 0.932 | DH18: 75,80% | DI18: 83,80% | DJ18: 88,60% | DK18: 84,10% | DL18: 62,80% | DM18: 78,80% | DN18: 74,20% | DO18: 86,80% | DP18: 64,70% | DQ18: 100,00% | DR18: 42,40% | DS18: 88,50% | DT18: 0,519 | DU18: 0,645 | DV18: 76,9% | DW18: 91,9% | DX18: 66,1% | DY18: 87,3% | DZ18: 92,00% | EA18: 94,00% | EB18: 70,50% | EC18: 84,70% | ED18: 95,00% | EE18: 88,90% | EF18: 74,30% | EG18: 86,20% | EH18: 81,90% | EI18: 79,00% | EJ18: 63,10% | EK18: 80,90% | EL18: 78,20% | EM18: 78,20% | EN18: 81,00% | EO18: 81,00% | EP18: 79,20% | EQ18: 79,20%
DI27: <

Sheet W&M-DS.M-Prod.
A1: FO | B1: Total Avril 2026 | I1: Moyenne Avril 2026 | L1: Total Mars 2026 | S1: Moyenne Mars 2026 | V1: Total Février 2026 | AC1: Moyenne Février 2026 | AF1: Total Janvier 2026 | AM1: Moyenne Janvier 2026 | AP1: Total Décembre 2025 | AW1: Moyenne Décembre 2025 | AZ1: Total Novembre 2025 | BG1: Moyenne Novembre 2025 | BJ1: Total Octobre 2025 | BQ1: Moyenne 0ctobre 2025
A2: Agent | B2: % Résol. | C2: %Escalade | D2: % Transfert | E2: Tickets | F2: Appels Reçus | G2: Appels répondus | H2: QS | I2: Tickets | J2: Appels Reçus | K2: Appels répondus | L2: % Résol. | M2: %Escalade | N2: % Transfert | O2: Tickets | P2: Appels Reçus | Q2: Appels répondus | R2: QS | S2: Tickets | T2: Appels Reçus | U2: Appels répondus | V2: % Résol. | W2: %Escalade | X2: % Transfert | Y2: Tickets | Z2: Appels Reçus | AA2: Appels répondus | AB2: QS | AC2: Tickets | AD2: Appels Reçus | AE2: Appels répondus | AF2: % Résol. | AG2: %Escalade | AH2: % Transfert | AI2: Tickets | AJ2: Appels Reçus | AK2: Appels répondus | AL2: QS | AM2: Tickets | AN2: Appels Reçus | AO2: Appels répondus | AP2: % Résol. | AQ2: %Escalade | AR2: % Transfert | AS2: Tickets | AT2: Appels Reçus | AU2: Appels répondus | AV2: QS | AW2: Tickets | AX2: Appels Reçus | AY2: Appels répondus | AZ2: % Résol. | BA2: %Escalade | BB2: % Transfert | BC2: Tickets | BD2: Appels Reçus | BE2: Appels répondus | BF2: QS | BG2: Tickets | BH2: Appels Reçus | BI2: Appels répondus | BJ2: % Résol. | BK2: %Escalade | BL2: % Transfert | BM2: Tickets | BN2: Appels Reçus | BO2: Appels répondus | BP2: QS | BQ2: Tickets | BR2: Appels Reçus | BS2: Appels répondus
A3: Abdelilah SAOUDI | B3: =IFERROR(('Daily-Prod.'!JC3+'Daily-Prod.'!IT3+'Daily-Prod.'!IK3+'Daily-Prod.'!IB3+'Daily-Prod.'!HS3+'Daily-Prod.'!HJ3+'Daily-Prod.'!HA3+'Daily-Prod.'!GR3+'Daily-Prod.'!GI3+'Daily-Prod.'!FZ3+'Daily-Prod.'!FQ3+'Daily-Prod.'!FH3+'Daily-Prod.'!EY3+'Daily-Prod.'!EP3+'Daily-Prod.'!EG3+'Daily-Prod.'!DX3+'Daily-Prod.'!DO3+'Daily-Prod.'!DF3+'Daily-Prod.'!CW3+'Daily-Prod.'!CN3+'Daily-Prod.'!CE3+'Daily-Prod.'!BV3+'Daily-Prod.'!BM3+'Daily-Prod.'!BD3+'Daily-Prod.'!AU3+'Daily-Prod.'!AL3+'Daily-Prod.'!AC3+'Daily-Prod.'!T3+'Daily-Prod.'!K3+'Daily-Prod.'!B3)/E3,"") -> 0.49260042 | C3: =IFERROR(('Daily-Prod.'!JD3+'Daily-Prod.'!IU3+'Daily-Prod.'!IL3+'Daily-Prod.'!IC3+'Daily-Prod.'!HT3+'Daily-Prod.'!HK3+'Daily-Prod.'!HB3+'Daily-Prod.'!GS3+'Daily-Prod.'!GJ3+'Daily-Prod.'!GA3+'Daily-Prod.'!FR3+'Daily-Prod.'!FI3+'Daily-Prod.'!EZ3+'Daily-Prod.'!EQ3+'Daily-Prod.'!EH3+'Daily-Prod.'!DY3+'Daily-Prod.'!DP3+'Daily-Prod.'!DG3+'Daily-Prod.'!CX3+'Daily-Prod.'!CO3+'Daily-Prod.'!CF3+'Daily-Prod.'!BW3+'Daily-Prod.'!BN3+'Daily-Prod.'!BE3+'Daily-Prod.'!AV3+'Daily-Prod.'!AM3+'Daily-Prod.'!AD3+'Daily-Prod.'!U3+'Daily-Prod.'!L3+'Daily-Prod.'!C3)/E3,"") -> 0.205074 | D3: =IFERROR(('Daily-Prod.'!JF3+'Daily-Prod.'!IW3+'Daily-Prod.'!IN3+'Daily-Prod.'!IE3+'Daily-Prod.'!HV3+'Daily-Prod.'!HM3+'Daily-Prod.'!HD3+'Daily-Prod.'!GU3+'Daily-Prod.'!GL3+'Daily-Prod.'!GC3+'Daily-Prod.'!FT3+'Daily-Prod.'!FK3+'Daily-Prod.'!FB3+'Daily-Prod.'!ES3+'Daily-Prod.'!EJ3+'Daily-Prod.'!EA3+'Daily-Prod.'!DR3+'Daily-Prod.'!DI3+'Daily-Prod.'!CZ3+'Daily-Prod.'!CQ3+'Daily-Prod.'!CH3+'Daily-Prod.'!BY3+'Daily-Prod.'!BP3+'Daily-Prod.'!BG3+'Daily-Prod.'!AX3+'Daily-Prod.'!AO3+'Daily-Prod.'!AF3+'Daily-Prod.'!W3+'Daily-Prod.'!N3+'Daily-Prod.'!E3+'Daily-Prod.'!JG3+'Daily-Prod.'!IX3+'Daily-Prod.'!IO3+'Daily-Prod.'!IF3+'Daily-Prod.'!HW3+'Daily-Prod.'!HN3+'Daily-Prod.'!HE3+'Daily-Prod.'!GV3+'Daily-Prod.'!GM3+'Daily-Prod.'!GD3+'Daily-Prod.'!FU3+'Daily-Prod.'!FL3+'Daily-Prod.'!FC3+'Daily-Prod.'!ET3+'Daily-Prod.'!EK3+'Daily-Prod.'!EB3+'Daily-Prod.'!DS3+'Daily-Prod.'!DJ3+'Daily-Prod.'!DA3+'Daily-Prod.'!CR3+'Daily-Prod.'!CI3+'Daily-Prod.'!BZ3+'Daily-Prod.'!BQ3+'Daily-Prod.'!BH3+'Daily-Prod.'!AY3+'Daily-Prod.'!AP3+'Daily-Prod.'!AG3+'Daily-Prod.'!X3+'Daily-Prod.'!O3+'Daily-Prod.'!F3)/E3,"") -> 0.30232558 | E3: =IFERROR(('Daily-Prod.'!JH3+'Daily-Prod.'!IY3+'Daily-Prod.'!IP3+'Daily-Prod.'!IG3+'Daily-Prod.'!HX3+'Daily-Prod.'!HO3+'Daily-Prod.'!HF3+'Daily-Prod.'!GW3+'Daily-Prod.'!GN3+'Daily-Prod.'!GE3+'Daily-Prod.'!FV3+'Daily-Prod.'!FM3+'Daily-Prod.'!FD3+'Daily-Prod.'!EU3+'Daily-Prod.'!EL3+'Daily-Prod.'!EC3+'Daily-Prod.'!DT3+'Daily-Prod.'!DK3+'Daily-Prod.'!DB3+'Daily-Prod.'!CS3+'Daily-Prod.'!CJ3+'Daily-Prod.'!CA3+'Daily-Prod.'!BR3+'Daily-Prod.'!BI3+'Daily-Prod.'!AZ3+'Daily-Prod.'!AQ3+'Daily-Prod.'!AH3+'Daily-Prod.'!Y3+'Daily-Prod.'!P3+'Daily-Prod.'!G3),"") -> 473 | G3: =IFERROR(('Daily-Prod.'!JJ3+'Daily-Prod.'!JA3+'Daily-Prod.'!IR3+'Daily-Prod.'!II3+'Daily-Prod.'!HZ3+'Daily-Prod.'!HQ3+'Daily-Prod.'!HH3+'Daily-Prod.'!GY3+'Daily-Prod.'!GP3+'Daily-Prod.'!GG3+'Daily-Prod.'!FX3+'Daily-Prod.'!FO3+'Daily-Prod.'!FF3+'Daily-Prod.'!EW3+'Daily-Prod.'!EN3+'Daily-Prod.'!EE3+'Daily-Prod.'!DV3+'Daily-Prod.'!DM3+'Daily-Prod.'!DD3+'Daily-Prod.'!CU3+'Daily-Prod.'!CL3+'Daily-Prod.'!CC3+'Daily-Prod.'!BT3+'Daily-Prod.'!BK3+'Daily-Prod.'!BB3+'Daily-Prod.'!AS3+'Daily-Prod.'!AJ3+'Daily-Prod.'!AA3+'Daily-Prod.'!R3+'Daily-Prod.'!I3),"") -> 106 | H3: =IFERROR((G3/F3),"") | I3: =IFERROR(AVERAGE('Daily-Prod.'!JH3,'Daily-Prod.'!IY3,'Daily-Prod.'!IP3,'Daily-Prod.'!IG3,'Daily-Prod.'!HX3,'Daily-Prod.'!HO3,'Daily-Prod.'!HF3,'Daily-Prod.'!GW3,'Daily-Prod.'!GN3,'Daily-Prod.'!GE3,'Daily-Prod.'!FV3,'Daily-Prod.'!FM3,'Daily-Prod.'!FD3,'Daily-Prod.'!EU3,'Daily-Prod.'!EL3,'Daily-Prod.'!EC3,'Daily-Prod.'!DT3,'Daily-Prod.'!DK3,'Daily-Prod.'!DB3,'Daily-Prod.'!CS3,'Daily-Prod.'!CJ3,'Daily-Prod.'!CA3,'Daily-Prod.'!BR3,'Daily-Prod.'!BI3,'Daily-Prod.'!AZ3,'Daily-Prod.'!AQ3,'Daily-Prod.'!AH3,'Daily-Prod.'!Y3,'Daily-Prod.'!P3,'Daily-Prod.'!G3),"") -> 21.5 | J3: =IFERROR(AVERAGE('Daily-Prod.'!JI3,'Daily-Prod.'!IZ3,'Daily-Prod.'!IQ3,'Daily-Prod.'!IH3,'Daily-Prod.'!HY3,'Daily-Prod.'!HP3,'Daily-Prod.'!HG3,'Daily-Prod.'!GX3,'Daily-Prod.'!GO3,'Daily-Prod.'!GF3,'Daily-Prod.'!FW3,'Daily-Prod.'!FN3,'Daily-Prod.'!FE3,'Daily-Prod.'!EV3,'Daily-Prod.'!EM3,'Daily-Prod.'!ED3,'Daily-Prod.'!DU3,'Daily-Prod.'!DL3,'Daily-Prod.'!DC3,'Daily-Prod.'!CT3,'Daily-Prod.'!CK3,'Daily-Prod.'!CB3,'Daily-Prod.'!BS3,'Daily-Prod.'!BJ3,'Daily-Prod.'!BA3,'Daily-Prod.'!AR3,'Daily-Prod.'!AI3,'Daily-Prod.'!Z3,'Daily-Prod.'!Q3,'Daily-Prod.'!H3),"") | K3: =IFERROR(AVERAGE('Daily-Prod.'!JJ3,'Daily-Prod.'!JA3,'Daily-Prod.'!IR3,'Daily-Prod.'!II3,'Daily-Prod.'!HZ3,'Daily-Prod.'!HQ3,'Daily-Prod.'!HH3,'Daily-Prod.'!GY3,'Daily-Prod.'!GP3,'Daily-Prod.'!GG3,'Daily-Prod.'!FX3,'Daily-Prod.'!FO3,'Daily-Prod.'!FF3,'Daily-Prod.'!EW3,'Daily-Prod.'!EN3,'Daily-Prod.'!EE3,'Daily-Prod.'!DV3,'Daily-Prod.'!DM3,'Daily-Prod.'!DD3,'Daily-Prod.'!CU3,'Daily-Prod.'!CL3,'Daily-Prod.'!CC3,'Daily-Prod.'!BT3,'Daily-Prod.'!BK3,'Daily-Prod.'!BB3,'Daily-Prod.'!AS3,'Daily-Prod.'!AJ3,'Daily-Prod.'!AA3,'Daily-Prod.'!R3,'Daily-Prod.'!I3),"") -> 7.5714286 | L3: =IFERROR(('Daily-Prod.'!TV3+'Daily-Prod.'!TM3+'Daily-Prod.'!TD3+'Daily-Prod.'!SU3+'Daily-Prod.'!SL3+'Daily-Prod.'!SC3+'Daily-Prod.'!RT3+'Daily-Prod.'!RK3+'Daily-Prod.'!RB3+'Daily-Prod.'!QS3+'Daily-Prod.'!QJ3+'Daily-Prod.'!QA3+'Daily-Prod.'!PR3+'Daily-Prod.'!PI3+'Daily-Prod.'!OZ3+'Daily-Prod.'!OQ3+'Daily-Prod.'!OH3+'Daily-Prod.'!NY3+'Daily-Prod.'!NP3+'Daily-Prod.'!NG3+'Daily-Prod.'!MX3+'Daily-Prod.'!MO3+'Daily-Prod.'!MF3+'Daily-Prod.'!LW3+'Daily-Prod.'!LN3+'Daily-Prod.'!LE3+'Daily-Prod.'!KV3+'Daily-Prod.'!KM3+'Daily-Prod.'!KD3+'Daily-Prod.'!JU3+'Daily-Prod.'!JL3)/O3,"") -> 0.50869565 | M3: =IFERROR(('Daily-Prod.'!TW3+'Daily-Prod.'!TN3+'Daily-Prod.'!TE3+'Daily-Prod.'!SV3+'Daily-Prod.'!SM3+'Daily-Prod.'!SD3+'Daily-Prod.'!RU3+'Daily-Prod.'!RL3+'Daily-Prod.'!RC3+'Daily-Prod.'!QT3+'Daily-Prod.'!QK3+'Daily-Prod.'!QB3+'Daily-Prod.'!PS3+'Daily-Prod.'!PJ3+'Daily-Prod.'!PA3+'Daily-Prod.'!OR3+'Daily-Prod.'!OI3+'Daily-Prod.'!NZ3+'Daily-Prod.'!NQ3+'Daily-Prod.'!NH3+'Daily-Prod.'!MY3+'Daily-Prod.'!MP3+'Daily-Prod.'!MG3+'Daily-Prod.'!LX3+'Daily-Prod.'!LO3+'Daily-Prod.'!LF3+'Daily-Prod.'!KW3+'Daily-Prod.'!KN3+'Daily-Prod.'!KE3+'Daily-Prod.'!JV3+'Daily-Prod.'!JM3)/O3,"") -> 0.20652174 | N3: =IFERROR(('Daily-Prod.'!TY3+'Daily-Prod.'!TP3+'Daily-Prod.'!TG3+'Daily-Prod.'!SX3+'Daily-Prod.'!SO3+'Daily-Prod.'!SF3+'Daily-Prod.'!RW3+'Daily-Prod.'!RN3+'Daily-Prod.'!RE3+'Daily-Prod.'!QV3+'Daily-Prod.'!QM3+'Daily-Prod.'!QD3+'Daily-Prod.'!PU3+'Daily-Prod.'!PL3+'Daily-Prod.'!PC3+'Daily-Prod.'!OT3+'Daily-Prod.'!OK3+'Daily-Prod.'!OB3+'Daily-Prod.'!NS3+'Daily-Prod.'!NJ3+'Daily-Prod.'!NA3+'Daily-Prod.'!MR3+'Daily-Prod.'!MI3+'Daily-Prod.'!LZ3+'Daily-Prod.'!LQ3+'Daily-Prod.'!LH3+'Daily-Prod.'!KY3+'Daily-Prod.'!KP3+'Daily-Prod.'!KG3+'Daily-Prod.'!JX3+'Daily-Prod.'!JO3+'Daily-Prod.'!TZ3+'Daily-Prod.'!TQ3+'Daily-Prod.'!TH3+'Daily-Prod.'!SY3+'Daily-Prod.'!SP3+'Daily-Prod.'!SG3+'Daily-Prod.'!RX3+'Daily-Prod.'!RO3+'Daily-Prod.'!RF3+'Daily-Prod.'!QW3+'Daily-Prod.'!QN3+'Daily-Prod.'!QE3+'Daily-Prod.'!PV3+'Daily-Prod.'!PM3+'Daily-Prod.'!PD3+'Daily-Prod.'!OU3+'Daily-Prod.'!OL3+'Daily-Prod.'!OC3+'Daily-Prod.'!NT3+'Daily-Prod.'!NK3+'Daily-Prod.'!NB3+'Daily-Prod.'!MS3+'Daily-Prod.'!MJ3+'Daily-Prod.'!MA3+'Daily-Prod.'!LR3+'Daily-Prod.'!LI3+'Daily-Prod.'!KZ3+'Daily-Prod.'!KQ3+'Daily-Prod.'!KH3+'Daily-Prod.'!JY3+'Daily-Prod.'!JP3)/O3,"") -> 0.28478261 | O3: =IFERROR(('Daily-Prod.'!UA3+'Daily-Prod.'!TR3+'Daily-Prod.'!TI3+'Daily-Prod.'!SZ3+'Daily-Prod.'!SQ3+'Daily-Prod.'!SH3+'Daily-Prod.'!RY3+'Daily-Prod.'!RP3+'Daily-Prod.'!RG3+'Daily-Prod.'!QX3+'Daily-Prod.'!QO3+'Daily-Prod.'!QF3+'Daily-Prod.'!PW3+'Daily-Prod.'!PN3+'Daily-Prod.'!PE3+'Daily-Prod.'!OV3+'Daily-Prod.'!OM3+'Daily-Prod.'!OD3+'Daily-Prod.'!NU3+'Daily-Prod.'!NL3+'Daily-Prod.'!NC3+'Daily-Prod.'!MT3+'Daily-Prod.'!MK3+'Daily-Prod.'!MB3+'Daily-Prod.'!LS3+'Daily-Prod.'!LJ3+'Daily-Prod.'!LA3+'Daily-Prod.'!KR3+'Daily-Prod.'!KI3+'Daily-Prod.'!JZ3+'Daily-Prod.'!JQ3),"") -> 460 | Q3: =IFERROR(('Daily-Prod.'!UC3+'Daily-Prod.'!TT3+'Daily-Prod.'!TK3+'Daily-Prod.'!TB3+'Daily-Prod.'!SS3+'Daily-Prod.'!SJ3+'Daily-Prod.'!SA3+'Daily-Prod.'!RR3+'Daily-Prod.'!RI3+'Daily-Prod.'!QZ3+'Daily-Prod.'!QQ3+'Daily-Prod.'!QH3+'Daily-Prod.'!PY3+'Daily-Prod.'!PP3+'Daily-Prod.'!PG3+'Daily-Prod.'!OX3+'Daily-Prod.'!OO3+'Daily-Prod.'!OF3+'Daily-Prod.'!NW3+'Daily-Prod.'!NN3+'Daily-Prod.'!NE3+'Daily-Prod.'!MV3+'Daily-Prod.'!MM3+'Daily-Prod.'!MD3+'Daily-Prod.'!LU3+'Daily-Prod.'!LL3+'Daily-Prod.'!LC3+'Daily-Prod.'!KT3+'Daily-Prod.'!KK3+'Daily-Prod.'!KB3+'Daily-Prod.'!JS3),"") -> 240 | R3: =IFERROR((Q3/P3),"") | S3: =IFERROR(AVERAGE('Daily-Prod.'!TR3,'Daily-Prod.'!UA3,'Daily-Prod.'!TI3,'Daily-Prod.'!SZ3,'Daily-Prod.'!SQ3,'Daily-Prod.'!SH3,'Daily-Prod.'!RY3,'Daily-Prod.'!RP3,'Daily-Prod.'!RG3,'Daily-Prod.'!QX3,'Daily-Prod.'!QO3,'Daily-Prod.'!QF3,'Daily-Prod.'!PW3,'Daily-Prod.'!PN3,'Daily-Prod.'!PE3,'Daily-Prod.'!OV3,'Daily-Prod.'!OM3,'Daily-Prod.'!OD3,'Daily-Prod.'!NU3,'Daily-Prod.'!NL3,'Daily-Prod.'!NC3,'Daily-Prod.'!MT3,'Daily-Prod.'!MK3,'Daily-Prod.'!MB3,'Daily-Prod.'!LS3,'Daily-Prod.'!LJ3,'Daily-Prod.'!LA3,'Daily-Prod.'!KR3,'Daily-Prod.'!KI3,'Daily-Prod.'!JZ3),"") -> 21.904762 | T3: =IFERROR(AVERAGE('Daily-Prod.'!TS3,'Daily-Prod.'!UB3,'Daily-Prod.'!TJ3,'Daily-Prod.'!TA3,'Daily-Prod.'!SR3,'Daily-Prod.'!SI3,'Daily-Prod.'!RZ3,'Daily-Prod.'!RQ3,'Daily-Prod.'!RH3,'Daily-Prod.'!QY3,'Daily-Prod.'!QP3,'Daily-Prod.'!QG3,'Daily-Prod.'!PX3,'Daily-Prod.'!PO3,'Daily-Prod.'!PF3,'Daily-Prod.'!OW3,'Daily-Prod.'!ON3,'Daily-Prod.'!OE3,'Daily-Prod.'!NV3,'Daily-Prod.'!NM3,'Daily-Prod.'!ND3,'Daily-Prod.'!MU3,'Daily-Prod.'!ML3,'Daily-Prod.'!MC3,'Daily-Prod.'!LT3,'Daily-Prod.'!LK3,'Daily-Prod.'!LB3,'Daily-Prod.'!KS3,'Daily-Prod.'!KJ3,'Daily-Prod.'!KA3),"") | U3: =IFERROR(AVERAGE('Daily-Prod.'!TT3,'Daily-Prod.'!UC3,'Daily-Prod.'!TK3,'Daily-Prod.'!TB3,'Daily-Prod.'!SS3,'Daily-Prod.'!SJ3,'Daily-Prod.'!SA3,'Daily-Prod.'!RR3,'Daily-Prod.'!RI3,'Daily-Prod.'!QZ3,'Daily-Prod.'!QQ3,'Daily-Prod.'!QH3,'Daily-Prod.'!PY3,'Daily-Prod.'!PP3,'Daily-Prod.'!PG3,'Daily-Prod.'!OX3,'Daily-Prod.'!OO3,'Daily-Prod.'!OF3,'Daily-Prod.'!NW3,'Daily-Prod.'!NN3,'Daily-Prod.'!NE3,'Daily-Prod.'!MV3,'Daily-Prod.'!MM3,'Daily-Prod.'!MD3,'Daily-Prod.'!LU3,'Daily-Prod.'!LL3,'Daily-Prod.'!LC3,'Daily-Prod.'!KT3,'Daily-Prod.'!KK3,'Daily-Prod.'!KB3),"") -> 11.428571 | V3: =IFERROR(('Daily-Prod.'!ADN3+'Daily-Prod.'!ADE3+'Daily-Prod.'!ACV3+'Daily-Prod.'!ACM3+'Daily-Prod.'!ACD3+'Daily-Prod.'!ABU3+'Daily-Prod.'!ABL3+'Daily-Prod.'!ABC3+'Daily-Prod.'!AAT3+'Daily-Prod.'!AAK3+'Daily-Prod.'!AAB3+'Daily-Prod.'!ZS3+'Daily-Prod.'!ZJ3+'Daily-Prod.'!ZA3+'Daily-Prod.'!YR3+'Daily-Prod.'!YI3+'Daily-Prod.'!XZ3+'Daily-Prod.'!XQ3+'Daily-Prod.'!XH3+'Daily-Prod.'!WY3+'Daily-Prod.'!WP3+'Daily-Prod.'!WG3+'Daily-Prod.'!VX3+'Daily-Prod.'!VO3+'Daily-Prod.'!VF3+'Daily-Prod.'!UW3+'Daily-Prod.'!UN3+'Daily-Prod.'!UE3)/Y3,"") -> 0.50862069 | W3: =IFERROR(('Daily-Prod.'!ADO3+'Daily-Prod.'!ADF3+'Daily-Prod.'!ACW3+'Daily-Prod.'!ACN3+'Daily-Prod.'!ACE3+'Daily-Prod.'!ABV3+'Daily-Prod.'!ABM3+'Daily-Prod.'!ABD3+'Daily-Prod.'!AAU3+'Daily-Prod.'!AAL3+'Daily-Prod.'!AAC3+'Daily-Prod.'!ZT3+'Daily-Prod.'!ZK3+'Daily-Prod.'!ZB3+'Daily-Prod.'!YS3+'Daily-Prod.'!YJ3+'Daily-Prod.'!YA3+'Daily-Prod.'!XR3+'Daily-Prod.'!XI3+'Daily-Prod.'!WZ3+'Daily-Prod.'!WQ3+'Daily-Prod.'!WH3+'Daily-Prod.'!VY3+'Daily-Prod.'!VP3+'Daily-Prod.'!VG3+'Daily-Prod.'!UX3+'Daily-Prod.'!UO3+'Daily-Prod.'!UF3)/Y3,"") -> 0.21264368 | X3: =IFERROR(('Daily-Prod.'!ADR3+'Daily-Prod.'!ADI3+'Daily-Prod.'!ACZ3+'Daily-Prod.'!ACQ3+'Daily-Prod.'!ACH3+'Daily-Prod.'!ABY3+'Daily-Prod.'!ABP3+'Daily-Prod.'!ABG3+'Daily-Prod.'!AAX3+'Daily-Prod.'!AAO3+'Daily-Prod.'!AAF3+'Daily-Prod.'!ZW3+'Daily-Prod.'!ZN3+'Daily-Prod.'!ZE3+'Daily-Prod.'!YV3+'Daily-Prod.'!YM3+'Daily-Prod.'!YD3+'Daily-Prod.'!XU3+'Daily-Prod.'!XL3+'Daily-Prod.'!XC3+'Daily-Prod.'!WT3+'Daily-Prod.'!WK3+'Daily-Prod.'!WB3+'Daily-Prod.'!VS3+'Daily-Prod.'!VJ3+'Daily-Prod.'!VA3+'Daily-Prod.'!UR3+'Daily-Prod.'!UI3+'Daily-Prod.'!ADQ3+'Daily-Prod.'!ADH3+'Daily-Prod.'!ACY3+'Daily-Prod.'!ACP3+'Daily-Prod.'!ACG3+'Daily-Prod.'!ABX3+'Daily-Prod.'!ABO3+'Daily-Prod.'!ABF3+'Daily-Prod.'!AAW3+'Daily-Prod.'!AAN3+'Daily-Prod.'!AAE3+'Daily-Prod.'!ZV3+'Daily-Prod.'!ZM3+'Daily-Prod.'!ZD3+'Daily-Prod.'!YU3+'Daily-Prod.'!YL3+'Daily-Prod.'!YC3+'Daily-Prod.'!XT3+'Daily-Prod.'!XK3+'Daily-Prod.'!XB3+'Daily-Prod.'!WS3+'Daily-Prod.'!WJ3+'Daily-Prod.'!WA3+'Daily-Prod.'!VR3+'Daily-Prod.'!VI3+'Daily-Prod.'!UZ3+'Daily-Prod.'!UQ3+'Daily-Prod.'!UH3)/Y3,"") -> 0.27873563 | Y3: =IFERROR(('Daily-Prod.'!ADS3+'Daily-Prod.'!ADJ3+'Daily-Prod.'!ADA3+'Daily-Prod.'!ACR3+'Daily-Prod.'!ACI3+'Daily-Prod.'!ABZ3+'Daily-Prod.'!ABQ3+'Daily-Prod.'!ABH3+'Daily-Prod.'!AAY3+'Daily-Prod.'!AAP3+'Daily-Prod.'!AAG3+'Daily-Prod.'!ZX3+'Daily-Prod.'!ZO3+'Daily-Prod.'!ZF3+'Daily-Prod.'!YW3+'Daily-Prod.'!YN3+'Daily-Prod.'!YE3+'Daily-Prod.'!XV3+'Daily-Prod.'!XM3+'Daily-Prod.'!XD3+'Daily-Prod.'!WU3+'Daily-Prod.'!WL3+'Daily-Prod.'!WC3+'Daily-Prod.'!VT3+'Daily-Prod.'!VK3+'Daily-Prod.'!VB3+'Daily-Prod.'!US3+'Daily-Prod.'!UJ3),"") -> 348 | AA3: =IFERROR(('Daily-Prod.'!ADU3+'Daily-Prod.'!ADL3+'Daily-Prod.'!ADC3+'Daily-Prod.'!ACT3+'Daily-Prod.'!ACK3+'Daily-Prod.'!ACB3+'Daily-Prod.'!ABS3+'Daily-Prod.'!ABJ3+'Daily-Prod.'!ABA3+'Daily-Prod.'!AAR3+'Daily-Prod.'!AAI3+'Daily-Prod.'!ZZ3+'Daily-Prod.'!ZQ3+'Daily-Prod.'!ZH3+'Daily-Prod.'!YY3+'Daily-Prod.'!YP3+'Daily-Prod.'!YG3+'Daily-Prod.'!XX3+'Daily-Prod.'!XO3+'Daily-Prod.'!XF3+'Daily-Prod.'!WW3+'Daily-Prod.'!WN3+'Daily-Prod.'!WE3+'Daily-Prod.'!VV3+'Daily-Prod.'!VM3+'Daily-Prod.'!VD3+'Daily-Prod.'!UU3+'Daily-Prod.'!UL3),"") -> 192 | AB3: =IFERROR((AA3/Z3),"") | AC3: =IFERROR(AVERAGE('Daily-Prod.'!ADS3,'Daily-Prod.'!ADJ3,'Daily-Prod.'!ADA3,'Daily-Prod.'!ACR3,'Daily-Prod.'!ACI3,'Daily-Prod.'!ABZ3,'Daily-Prod.'!ABQ3,'Daily-Prod.'!ABH3,'Daily-Prod.'!AAY3,'Daily-Prod.'!AAP3,'Daily-Prod.'!AAG3,'Daily-Prod.'!ZX3,'Daily-Prod.'!ZO3,'Daily-Prod.'!ZF3,'Daily-Prod.'!YW3,'Daily-Prod.'!YN3,'Daily-Prod.'!YE3,'Daily-Prod.'!XV3,'Daily-Prod.'!XM3,'Daily-Prod.'!XD3,'Daily-Prod.'!WU3,'Daily-Prod.'!WL3,'Daily-Prod.'!WC3,'Daily-Prod.'!VT3,'Daily-Prod.'!VK3,'Daily-Prod.'!VB3,'Daily-Prod.'!US3,'Daily-Prod.'!UJ3),"") -> 17.4 | AE3: =IFERROR(AVERAGE('Daily-Prod.'!ADU3,'Daily-Prod.'!ADL3,'Daily-Prod.'!ADC3,'Daily-Prod.'!ACT3,'Daily-Prod.'!ACK3,'Daily-Prod.'!ACB3,'Daily-Prod.'!ABS3,'Daily-Prod.'!ABJ3,'Daily-Prod.'!ABA3,'Daily-Prod.'!AAR3,'Daily-Prod.'!AAI3,'Daily-Prod.'!ZZ3,'Daily-Prod.'!ZQ3,'Daily-Prod.'!ZH3,'Daily-Prod.'!YY3,'Daily-Prod.'!YP3,'Daily-Prod.'!YG3,'Daily-Prod.'!XX3,'Daily-Prod.'!XO3,'Daily-Prod.'!XF3,'Daily-Prod.'!WW3,'Daily-Prod.'!WN3,'Daily-Prod.'!WE3,'Daily-Prod.'!VV3,'Daily-Prod.'!VM3,'Daily-Prod.'!VD3,'Daily-Prod.'!UU3,'Daily-Prod.'!UL3),"") -> 10.666667 | AF3: =IFERROR(('Daily-Prod.'!AOG3+'Daily-Prod.'!ANX3+'Daily-Prod.'!ANO3+'Daily-Prod.'!ANF3+'Daily-Prod.'!AMW3+'Daily-Prod.'!AMN3+'Daily-Prod.'!AME3+'Daily-Prod.'!ALV3+'Daily-Prod.'!ALM3+'Daily-Prod.'!ALD3+'Daily-Prod.'!AKU3+'Daily-Prod.'!AKL3+'Daily-Prod.'!AKC3+'Daily-Prod.'!AJT3+'Daily-Prod.'!AJK3+'Daily-Prod.'!AJB3+'Daily-Prod.'!AIS3+'Daily-Prod.'!AIJ3+'Daily-Prod.'!AIA3+'Daily-Prod.'!AHR3+'Daily-Prod.'!AHI3+'Daily-Prod.'!AGZ3+'Daily-Prod.'!AGQ3+'Daily-Prod.'!AGH3+'Daily-Prod.'!AFY3+'Daily-Prod.'!AFP3+'Daily-Prod.'!AFG3+'Daily-Prod.'!AEX3+'Daily-Prod.'!AEO3+'Daily-Prod.'!AEF3+'Daily-Prod.'!ADW3)/AI3,"") -> 0.56682028 | AG3: =IFERROR(('Daily-Prod.'!AOH3+'Daily-Prod.'!ANY3+'Daily-Prod.'!ANP3+'Daily-Prod.'!ANG3+'Daily-Prod.'!AMX3+'Daily-Prod.'!AMO3+'Daily-Prod.'!AMF3+'Daily-Prod.'!ALW3+'Daily-Prod.'!ALN3+'Daily-Prod.'!ALE3+'Daily-Prod.'!AKV3+'Daily-Prod.'!AKM3+'Daily-Prod.'!AKD3+'Daily-Prod.'!AJU3+'Daily-Prod.'!AJL3+'Daily-Prod.'!AJC3+'Daily-Prod.'!AIT3+'Daily-Prod.'!AIK3+'Daily-Prod.'!AIB3+'Daily-Prod.'!AHS3+'Daily-Prod.'!AHJ3+'Daily-Prod.'!AHA3+'Daily-Prod.'!AGR3+'Daily-Prod.'!AGI3+'Daily-Prod.'!AFZ3+'Daily-Prod.'!AFQ3+'Daily-Prod.'!AFH3+'Daily-Prod.'!AEY3+'Daily-Prod.'!AEP3+'Daily-Prod.'!AEG3+'Daily-Prod.'!ADX3)/AI3,"") -> 0.17281106 | AH3: =IFERROR(('Daily-Prod.'!AOK3+'Daily-Prod.'!AOB3+'Daily-Prod.'!ANS3+'Daily-Prod.'!ANJ3+'Daily-Prod.'!ANA3+'Daily-Prod.'!AMR3+'Daily-Prod.'!AMI3+'Daily-Prod.'!ALZ3+'Daily-Prod.'!ALQ3+'Daily-Prod.'!ALH3+'Daily-Prod.'!AKY3+'Daily-Prod.'!AKP3+'Daily-Prod.'!AKG3+'Daily-Prod.'!AJX3+'Daily-Prod.'!AJO3+'Daily-Prod.'!AJF3+'Daily-Prod.'!AIW3+'Daily-Prod.'!AIN3+'Daily-Prod.'!AIE3+'Daily-Prod.'!AHV3+'Daily-Prod.'!AHM3+'Daily-Prod.'!AHD3+'Daily-Prod.'!AGU3+'Daily-Prod.'!AGL3+'Daily-Prod.'!AGC3+'Daily-Prod.'!AFT3+'Daily-Prod.'!AFK3+'Daily-Prod.'!AFB3+'Daily-Prod.'!AES3+'Daily-Prod.'!AEJ3+'Daily-Prod.'!AEA3+'Daily-Prod.'!AOJ3+'Daily-Prod.'!AOA3+'Daily-Prod.'!ANR3+'Daily-Prod.'!ANI3+'Daily-Prod.'!AMZ3+'Daily-Prod.'!AMQ3+'Daily-Prod.'!AMH3+'Daily-Prod.'!ALY3+'Daily-Prod.'!ALP3+'Daily-Prod.'!ALG3+'Daily-Prod.'!AKX3+'Daily-Prod.'!AKO3+'Daily-Prod.'!AKF3+'Daily-Prod.'!AJW3+'Daily-Prod.'!AJN3+'Daily-Prod.'!AJE3+'Daily-Prod.'!AIV3+'Daily-Prod.'!AIM3+'Daily-Prod.'!AID3+'Daily-Prod.'!AHU3+'Daily-Prod.'!AHL3+'Daily-Prod.'!AHC3+'Daily-Prod.'!AGT3+'Daily-Prod.'!AGK3+'Daily-Prod.'!AGB3+'Daily-Prod.'!AFS3+'Daily-Prod.'!AFJ3+'Daily-Prod.'!AFA3+'Daily-Prod.'!AER3+'Daily-Prod.'!AEI3+'Daily-Prod.'!ADZ3)/AI3,"") -> 0.26036866 | AI3: =IFERROR(('Daily-Prod.'!AOL3+'Daily-Prod.'!AOC3+'Daily-Prod.'!ANT3+'Daily-Prod.'!ANK3+'Daily-Prod.'!ANB3+'Daily-Prod.'!AMS3+'Daily-Prod.'!AMJ3+'Daily-Prod.'!AMA3+'Daily-Prod.'!ALR3+'Daily-Prod.'!ALI3+'Daily-Prod.'!AKZ3+'Daily-Prod.'!AKQ3+'Daily-Prod.'!AKH3+'Daily-Prod.'!AJY3+'Daily-Prod.'!AJP3+'Daily-Prod.'!AJG3+'Daily-Prod.'!AIX3+'Daily-Prod.'!AIO3+'Daily-Prod.'!AIF3+'Daily-Prod.'!AHW3+'Daily-Prod.'!AHN3+'Daily-Prod.'!AHE3+'Daily-Prod.'!AGV3+'Daily-Prod.'!AGM3+'Daily-Prod.'!AGD3+'Daily-Prod.'!AFU3+'Daily-Prod.'!AFL3+'Daily-Prod.'!AFC3+'Daily-Prod.'!AET3+'Daily-Prod.'!AEK3+'Daily-Prod.'!AEB3),"") -> 434 | AK3: =IFERROR(('Daily-Prod.'!AON3+'Daily-Prod.'!AOE3+'Daily-Prod.'!ANV3+'Daily-Prod.'!ANM3+'Daily-Prod.'!AND3+'Daily-Prod.'!AMU3+'Daily-Prod.'!AML3+'Daily-Prod.'!AMC3+'Daily-Prod.'!ALT3+'Daily-Prod.'!ALK3+'Daily-Prod.'!ALB3+'Daily-Prod.'!AKS3+'Daily-Prod.'!AKJ3+'Daily-Prod.'!AKA3+'Daily-Prod.'!AJR3+'Daily-Prod.'!AJI3+'Daily-Prod.'!AIZ3+'Daily-Prod.'!AIQ3+'Daily-Prod.'!AIH3+'Daily-Prod.'!AHY3+'Daily-Prod.'!AHP3+'Daily-Prod.'!AHG3+'Daily-Prod.'!AGX3+'Daily-Prod.'!AGO3+'Daily-Prod.'!AGF3+'Daily-Prod.'!AFW3+'Daily-Prod.'!AFN3+'Daily-Prod.'!AFE3+'Daily-Prod.'!AEV3+'Daily-Prod.'!AEM3+'Daily-Prod.'!AED3),"") -> 251 | AL3: =IFERROR((AK3/AJ3),"") | AM3: =IFERROR(AVERAGE('Daily-Prod.'!AOL3,'Daily-Prod.'!AOC3,'Daily-Prod.'!ANT3,'Daily-Prod.'!ANK3,'Daily-Prod.'!ANB3,'Daily-Prod.'!AMS3,'Daily-Prod.'!AMJ3,'Daily-Prod.'!AMA3,'Daily-Prod.'!ALR3,'Daily-Prod.'!ALI3,'Daily-Prod.'!AKZ3,'Daily-Prod.'!AKQ3,'Daily-Prod.'!AKH3,'Daily-Prod.'!AJY3,'Daily-Prod.'!AJP3,'Daily-Prod.'!AJG3,'Daily-Prod.'!AIX3,'Daily-Prod.'!AIO3,'Daily-Prod.'!AIF3,'Daily-Prod.'!AHW3,'Daily-Prod.'!AHN3,'Daily-Prod.'!AHE3,'Daily-Prod.'!AGV3,'Daily-Prod.'!AGM3,'Daily-Prod.'!AGD3,'Daily-Prod.'!AFU3,'Daily-Prod.'!AFL3,'Daily-Prod.'!AFC3,'Daily-Prod.'!AET3,'Daily-Prod.'!AEK3,'Daily-Prod.'!AEB3),"") -> 19.727273 | AN3: =IFERROR(AVERAGE('Daily-Prod.'!AOM3,'Daily-Prod.'!AOD3,'Daily-Prod.'!ANU3,'Daily-Prod.'!ANL3,'Daily-Prod.'!ANC3,'Daily-Prod.'!AMT3,'Daily-Prod.'!AMK3,'Daily-Prod.'!AMB3,'Daily-Prod.'!ALS3,'Daily-Prod.'!ALJ3,'Daily-Prod.'!ALA3,'Daily-Prod.'!AKR3,'Daily-Prod.'!AKI3,'Daily-Prod.'!AJZ3,'Daily-Prod.'!AJQ3,'Daily-Prod.'!AJH3,'Daily-Prod.'!AIY3,'Daily-Prod.'!AIP3,'Daily-Prod.'!AIG3,'Daily-Prod.'!AHX3,'Daily-Prod.'!AHO3,'Daily-Prod.'!AHF3,'Daily-Prod.'!AGW3,'Daily-Prod.'!AGN3,'Daily-Prod.'!AGE3,'Daily-Prod.'!AFV3,'Daily-Prod.'!AFM3,'Daily-Prod.'!AFD3,'Daily-Prod.'!AEU3,'Daily-Prod.'!AEL3,'Daily-Prod.'!AEC3),"") | AO3: =IFERROR(AVERAGE('Daily-Prod.'!AON3,'Daily-Prod.'!AOE3,'Daily-Prod.'!ANV3,'Daily-Prod.'!ANM3,'Daily-Prod.'!AND3,'Daily-Prod.'!AMU3,'Daily-Prod.'!AML3,'Daily-Prod.'!AMC3,'Daily-Prod.'!ALT3,'Daily-Prod.'!ALK3,'Daily-Prod.'!ALB3,'Daily-Prod.'!AKS3,'Daily-Prod.'!AKJ3,'Daily-Prod.'!AKA3,'Daily-Prod.'!AJR3,'Daily-Prod.'!AJI3,'Daily-Prod.'!AIZ3,'Daily-Prod.'!AIQ3,'Daily-Prod.'!AIH3,'Daily-Prod.'!AHY3,'Daily-Prod.'!AHP3,'Daily-Prod.'!AHG3,'Daily-Prod.'!AGX3,'Daily-Prod.'!AGO3,'Daily-Prod.'!AGF3,'Daily-Prod.'!AFW3,'Daily-Prod.'!AFN3,'Daily-Prod.'!AFE3,'Daily-Prod.'!AEV3,'Daily-Prod.'!AEM3,'Daily-Prod.'!AED3),"") -> 11.952381 | AP3: =IFERROR(('Daily-Prod.'!AYZ3+'Daily-Prod.'!AYQ3+'Daily-Prod.'!AYH3+'Daily-Prod.'!AXY3+'Daily-Prod.'!AXP3+'Daily-Prod.'!AXG3+'Daily-Prod.'!AWX3+'Daily-Prod.'!AWO3+'Daily-Prod.'!AWF3+'Daily-Prod.'!AVW3+'Daily-Prod.'!AVN3+'Daily-Prod.'!AVE3+'Daily-Prod.'!AUV3+'Daily-Prod.'!AUM3+'Daily-Prod.'!AUD3+'Daily-Prod.'!ATU3+'Daily-Prod.'!ATL3+'Daily-Prod.'!ATC3+'Daily-Prod.'!AST3+'Daily-Prod.'!ASK3+'Daily-Prod.'!ASB3+'Daily-Prod.'!ARS3+'Daily-Prod.'!ARJ3+'Daily-Prod.'!ARA3+'Daily-Prod.'!AQR3+'Daily-Prod.'!AQI3+'Daily-Prod.'!APZ3+'Daily-Prod.'!APQ3+'Daily-Prod.'!APH3+'Daily-Prod.'!AOY3+'Daily-Prod.'!AOP3)/AS3,"") -> 0.51158301 | AQ3: =IFERROR(('Daily-Prod.'!AZA3+'Daily-Prod.'!AYR3+'Daily-Prod.'!AYI3+'Daily-Prod.'!AXZ3+'Daily-Prod.'!AXQ3+'Daily-Prod.'!AXH3+'Daily-Prod.'!AWY3+'Daily-Prod.'!AWP3+'Daily-Prod.'!AWG3+'Daily-Prod.'!AVX3+'Daily-Prod.'!AVO3+'Daily-Prod.'!AVF3+'Daily-Prod.'!AUW3+'Daily-Prod.'!AUN3+'Daily-Prod.'!AUE3+'Daily-Prod.'!ATV3+'Daily-Prod.'!ATM3+'Daily-Prod.'!ATD3+'Daily-Prod.'!ASU3+'Daily-Prod.'!ASL3+'Daily-Prod.'!ASC3+'Daily-Prod.'!ART3+'Daily-Prod.'!ARK3+'Daily-Prod.'!ARB3+'Daily-Prod.'!AQS3+'Daily-Prod.'!AQJ3+'Daily-Prod.'!AQA3+'Daily-Prod.'!APR3+'Daily-Prod.'!API3+'Daily-Prod.'!AOZ3+'Daily-Prod.'!AOQ3)/AS3,"") -> 0.13320463 | AR3: =IFERROR(('Daily-Prod.'!AZC3+'Daily-Prod.'!AYT3+'Daily-Prod.'!AYK3+'Daily-Prod.'!AYB3+'Daily-Prod.'!AXS3+'Daily-Prod.'!AXJ3+'Daily-Prod.'!AXA3+'Daily-Prod.'!AWR3+'Daily-Prod.'!AWI3+'Daily-Prod.'!AVZ3+'Daily-Prod.'!AVQ3+'Daily-Prod.'!AVH3+'Daily-Prod.'!AUY3+'Daily-Prod.'!AUP3+'Daily-Prod.'!AUG3+'Daily-Prod.'!ATX3+'Daily-Prod.'!ATO3+'Daily-Prod.'!ATF3+'Daily-Prod.'!ASW3+'Daily-Prod.'!ASN3+'Daily-Prod.'!ASE3+'Daily-Prod.'!ARV3+'Daily-Prod.'!ARM3+'Daily-Prod.'!ARD3+'Daily-Prod.'!AQU3+'Daily-Prod.'!AQL3+'Daily-Prod.'!AQC3+'Daily-Prod.'!APT3+'Daily-Prod.'!APK3+'Daily-Prod.'!APB3+'Daily-Prod.'!AOS3+'Daily-Prod.'!AZD3+'Daily-Prod.'!AYU3+'Daily-Prod.'!AYL3+'Daily-Prod.'!AYC3+'Daily-Prod.'!AXT3+'Daily-Prod.'!AXK3+'Daily-Prod.'!AXB3+'Daily-Prod.'!AWS3+'Daily-Prod.'!AWJ3+'Daily-Prod.'!AWA3+'Daily-Prod.'!AVR3+'Daily-Prod.'!AVI3+'Daily-Prod.'!AUZ3+'Daily-Prod.'!AUQ3+'Daily-Prod.'!AUH3+'Daily-Prod.'!ATY3+'Daily-Prod.'!ATP3+'Daily-Prod.'!ATG3+'Daily-Prod.'!ASX3+'Daily-Prod.'!ASO3+'Daily-Prod.'!ASF3+'Daily-Prod.'!ARW3+'Daily-Prod.'!ARN3+'Daily-Prod.'!ARE3+'Daily-Prod.'!AQV3+'Daily-Prod.'!AQM3+'Daily-Prod.'!AQD3+'Daily-Prod.'!APU3+'Daily-Prod.'!APL3+'Daily-Prod.'!APC3+'Daily-Prod.'!AOT3)/AS3,"") -> 0.35521236 | AS3: =IFERROR(('Daily-Prod.'!AZE3+'Daily-Prod.'!AYV3+'Daily-Prod.'!AYM3+'Daily-Prod.'!AYD3+'Daily-Prod.'!AXU3+'Daily-Prod.'!AXL3+'Daily-Prod.'!AXC3+'Daily-Prod.'!AWT3+'Daily-Prod.'!AWK3+'Daily-Prod.'!AWB3+'Daily-Prod.'!AVS3+'Daily-Prod.'!AVJ3+'Daily-Prod.'!AVA3+'Daily-Prod.'!AUR3+'Daily-Prod.'!AUI3+'Daily-Prod.'!ATZ3+'Daily-Prod.'!ATQ3+'Daily-Prod.'!ATH3+'Daily-Prod.'!ASY3+'Daily-Prod.'!ASP3+'Daily-Prod.'!ASG3+'Daily-Prod.'!ARX3+'Daily-Prod.'!ARO3+'Daily-Prod.'!ARF3+'Daily-Prod.'!AQW3+'Daily-Prod.'!AQN3+'Daily-Prod.'!AQE3+'Daily-Prod.'!APV3+'Daily-Prod.'!APM3+'Daily-Prod.'!APD3+'Daily-Prod.'!AOU3),"") -> 518 | AU3: =IFERROR(('Daily-Prod.'!AZG3+'Daily-Prod.'!AYX3+'Daily-Prod.'!AYO3+'Daily-Prod.'!AYF3+'Daily-Prod.'!AXW3+'Daily-Prod.'!AXN3+'Daily-Prod.'!AXE3+'Daily-Prod.'!AWV3+'Daily-Prod.'!AWM3+'Daily-Prod.'!AWD3+'Daily-Prod.'!AVU3+'Daily-Prod.'!AVL3+'Daily-Prod.'!AVC3+'Daily-Prod.'!AUT3+'Daily-Prod.'!AUK3+'Daily-Prod.'!AUB3+'Daily-Prod.'!ATS3+'Daily-Prod.'!ATJ3+'Daily-Prod.'!ATA3+'Daily-Prod.'!ASR3+'Daily-Prod.'!ASI3+'Daily-Prod.'!ARZ3+'Daily-Prod.'!ARQ3+'Daily-Prod.'!ARH3+'Daily-Prod.'!AQY3+'Daily-Prod.'!AQP3+'Daily-Prod.'!AQG3+'Daily-Prod.'!APX3+'Daily-Prod.'!APO3+'Daily-Prod.'!APF3+'Daily-Prod.'!AOW3),"") -> 299 | AV3: =IFERROR((AU3/AT3),"") | AW3: =IFERROR(AVERAGE('Daily-Prod.'!AZE3,'Daily-Prod.'!AYV3,'Daily-Prod.'!AYM3,'Daily-Prod.'!AYD3,'Daily-Prod.'!AXU3,'Daily-Prod.'!AXL3,'Daily-Prod.'!AXC3,'Daily-Prod.'!AWT3,'Daily-Prod.'!AWK3,'Daily-Prod.'!AWB3,'Daily-Prod.'!AVS3,'Daily-Prod.'!AVJ3,'Daily-Prod.'!AVA3,'Daily-Prod.'!AUR3,'Daily-Prod.'!AUI3,'Daily-Prod.'!ATZ3,'Daily-Prod.'!ATQ3,'Daily-Prod.'!ATH3,'Daily-Prod.'!ASY3,'Daily-Prod.'!ASP3,'Daily-Prod.'!ASG3,'Daily-Prod.'!ARX3,'Daily-Prod.'!ARO3,'Daily-Prod.'!ARF3,'Daily-Prod.'!AQW3,'Daily-Prod.'!AQN3,'Daily-Prod.'!AQE3,'Daily-Prod.'!APV3,'Daily-Prod.'!APM3,'Daily-Prod.'!APD3,'Daily-Prod.'!AOU3),"") -> 22.521739 | AY3: =IFERROR(AVERAGE('Daily-Prod.'!AZG3,'Daily-Prod.'!AYX3,'Daily-Prod.'!AYO3,'Daily-Prod.'!AYF3,'Daily-Prod.'!AXW3,'Daily-Prod.'!AXN3,'Daily-Prod.'!AXE3,'Daily-Prod.'!AWV3,'Daily-Prod.'!AWM3,'Daily-Prod.'!AWD3,'Daily-Prod.'!AVU3,'Daily-Prod.'!AVL3,'Daily-Prod.'!AVC3,'Daily-Prod.'!AUT3,'Daily-Prod.'!AUK3,'Daily-Prod.'!AUB3,'Daily-Prod.'!ATS3,'Daily-Prod.'!ATJ3,'Daily-Prod.'!ATA3,'Daily-Prod.'!ASR3,'Daily-Prod.'!ASI3,'Daily-Prod.'!ARZ3,'Daily-Prod.'!ARQ3,'Daily-Prod.'!ARH3,'Daily-Prod.'!AQY3,'Daily-Prod.'!AQP3,'Daily-Prod.'!AQG3,'Daily-Prod.'!APX3,'Daily-Prod.'!APO3,'Daily-Prod.'!APF3,'Daily-Prod.'!AOW3),"") -> 11.074074 | AZ3: =IFERROR(('Daily-Prod.'!BJJ3+'Daily-Prod.'!BJA3+'Daily-Prod.'!BIR3+'Daily-Prod.'!BII3+'Daily-Prod.'!BHZ3+'Daily-Prod.'!BHQ3+'Daily-Prod.'!BHH3+'Daily-Prod.'!BGY3+'Daily-Prod.'!BGP3+'Daily-Prod.'!BGG3+'Daily-Prod.'!BFX3+'Daily-Prod.'!BFO3+'Daily-Prod.'!BFF3+'Daily-Prod.'!BEW3+'Daily-Prod.'!BEN3+'Daily-Prod.'!BEE3+'Daily-Prod.'!BDV3+'Daily-Prod.'!BDM3+'Daily-Prod.'!BDD3+'Daily-Prod.'!BCU3+'Daily-Prod.'!BCL3+'Daily-Prod.'!BCC3+'Daily-Prod.'!BBT3+'Daily-Prod.'!BBK3+'Daily-Prod.'!BBB3+'Daily-Prod.'!BAS3+'Daily-Prod.'!BAJ3+'Daily-Prod.'!BAA3+'Daily-Prod.'!AZR3+'Daily-Prod.'!AZI3)/BC3,"") -> 0.47956403 | BA3: =IFERROR(('Daily-Prod.'!BJK3+'Daily-Prod.'!BJB3+'Daily-Prod.'!BIS3+'Daily-Prod.'!BIJ3+'Daily-Prod.'!BIA3+'Daily-Prod.'!BHR3+'Daily-Prod.'!BHI3+'Daily-Prod.'!BGZ3+'Daily-Prod.'!BGQ3+'Daily-Prod.'!BGH3+'Daily-Prod.'!BFY3+'Daily-Prod.'!BFP3+'Daily-Prod.'!BFG3+'Daily-Prod.'!BEX3+'Daily-Prod.'!BEO3+'Daily-Prod.'!BEF3+'Daily-Prod.'!BDW3+'Daily-Prod.'!BDN3+'Daily-Prod.'!BDE3+'Daily-Prod.'!BCV3+'Daily-Prod.'!BCM3+'Daily-Prod.'!BCD3+'Daily-Prod.'!BBU3+'Daily-Prod.'!BBL3+'Daily-Prod.'!BBC3+'Daily-Prod.'!BAT3+'Daily-Prod.'!BAK3+'Daily-Prod.'!BAB3+'Daily-Prod.'!AZS3+'Daily-Prod.'!AZJ3)/BC3,"") -> 0.11989101 | BB3: =IFERROR(('Daily-Prod.'!BJM3+'Daily-Prod.'!BJD3+'Daily-Prod.'!BIU3+'Daily-Prod.'!BIL3+'Daily-Prod.'!BIC3+'Daily-Prod.'!BHT3+'Daily-Prod.'!BHK3+'Daily-Prod.'!BHB3+'Daily-Prod.'!BGS3+'Daily-Prod.'!BGJ3+'Daily-Prod.'!BGA3+'Daily-Prod.'!BFR3+'Daily-Prod.'!BFI3+'Daily-Prod.'!BEZ3+'Daily-Prod.'!BEQ3+'Daily-Prod.'!BEH3+'Daily-Prod.'!BDY3+'Daily-Prod.'!BDP3+'Daily-Prod.'!BDG3+'Daily-Prod.'!BCX3+'Daily-Prod.'!BCO3+'Daily-Prod.'!BCF3+'Daily-Prod.'!BBW3+'Daily-Prod.'!BBN3+'Daily-Prod.'!BBE3+'Daily-Prod.'!BAV3+'Daily-Prod.'!BAM3+'Daily-Prod.'!BAD3+'Daily-Prod.'!AZU3+'Daily-Prod.'!AZL3+'Daily-Prod.'!BJN3+'Daily-Prod.'!BJE3+'Daily-Prod.'!BIV3+'Daily-Prod.'!BIM3+'Daily-Prod.'!BID3+'Daily-Prod.'!BHU3+'Daily-Prod.'!BHL3+'Daily-Prod.'!BHC3+'Daily-Prod.'!BGT3+'Daily-Prod.'!BGK3+'Daily-Prod.'!BGB3+'Daily-Prod.'!BFS3+'Daily-Prod.'!BFJ3+'Daily-Prod.'!BFA3+'Daily-Prod.'!BER3+'Daily-Prod.'!BEI3+'Daily-Prod.'!BDZ3+'Daily-Prod.'!BDQ3+'Daily-Prod.'!BDH3+'Daily-Prod.'!BCY3+'Daily-Prod.'!BCP3+'Daily-Prod.'!BCG3+'Daily-Prod.'!BBX3+'Daily-Prod.'!BBO3+'Daily-Prod.'!BBF3+'Daily-Prod.'!BAW3+'Daily-Prod.'!BAN3+'Daily-Prod.'!BAE3+'Daily-Prod.'!AZV3+'Daily-Prod.'!AZM3)/BC3,"") -> 0.40054496 | BC3: =IFERROR(('Daily-Prod.'!BJO3+'Daily-Prod.'!BJF3+'Daily-Prod.'!BIW3+'Daily-Prod.'!BIN3+'Daily-Prod.'!BIE3+'Daily-Prod.'!BHV3+'Daily-Prod.'!BHM3+'Daily-Prod.'!BHD3+'Daily-Prod.'!BGU3+'Daily-Prod.'!BGL3+'Daily-Prod.'!BGC3+'Daily-Prod.'!BFT3+'Daily-Prod.'!BFK3+'Daily-Prod.'!BFB3+'Daily-Prod.'!BES3+'Daily-Prod.'!BEJ3+'Daily-Prod.'!BEA3+'Daily-Prod.'!BDR3+'Daily-Prod.'!BDI3+'Daily-Prod.'!BCZ3+'Daily-Prod.'!BCQ3+'Daily-Prod.'!BCH3+'Daily-Prod.'!BBY3+'Daily-Prod.'!BBP3+'Daily-Prod.'!BBG3+'Daily-Prod.'!BAX3+'Daily-Prod.'!BAO3+'Daily-Prod.'!BAF3+'Daily-Prod.'!AZW3+'Daily-Prod.'!AZN3),"") -> 367 | BD3: =IFERROR(('Daily-Prod.'!BJP3+'Daily-Prod.'!BJG3+'Daily-Prod.'!BIX3+'Daily-Prod.'!BIO3+'Daily-Prod.'!BIF3+'Daily-Prod.'!BHW3+'Daily-Prod.'!BHN3+'Daily-Prod.'!BHE3+'Daily-Prod.'!BGV3+'Daily-Prod.'!BGM3+'Daily-Prod.'!BGD3+'Daily-Prod.'!BFU3+'Daily-Prod.'!BFL3+'Daily-Prod.'!BFC3+'Daily-Prod.'!BET3+'Daily-Prod.'!BEK3+'Daily-Prod.'!BEB3+'Daily-Prod.'!BDS3+'Daily-Prod.'!BDJ3+'Daily-Prod.'!BDA3+'Daily-Prod.'!BCR3+'Daily-Prod.'!BCI3+'Daily-Prod.'!BBZ3+'Daily-Prod.'!BBQ3+'Daily-Prod.'!BBH3+'Daily-Prod.'!BAY3+'Daily-Prod.'!BAP3+'Daily-Prod.'!BAG3+'Daily-Prod.'!AZX3+'Daily-Prod.'!AZO3),"") -> 182 | BE3: =IFERROR(('Daily-Prod.'!BJQ3+'Daily-Prod.'!BJH3+'Daily-Prod.'!BIY3+'Daily-Prod.'!BIP3+'Daily-Prod.'!BIG3+'Daily-Prod.'!BHX3+'Daily-Prod.'!BHO3+'Daily-Prod.'!BHF3+'Daily-Prod.'!BGW3+'Daily-Prod.'!BGN3+'Daily-Prod.'!BGE3+'Daily-Prod.'!BFV3+'Daily-Prod.'!BFM3+'Daily-Prod.'!BFD3+'Daily-Prod.'!BEU3+'Daily-Prod.'!BEL3+'Daily-Prod.'!BEC3+'Daily-Prod.'!BDT3+'Daily-Prod.'!BDK3+'Daily-Prod.'!BDB3+'Daily-Prod.'!BCS3+'Daily-Prod.'!BCJ3+'Daily-Prod.'!BCA3+'Daily-Prod.'!BBR3+'Daily-Prod.'!BBI3+'Daily-Prod.'!BAZ3+'Daily-Prod.'!BAQ3+'Daily-Prod.'!BAH3+'Daily-Prod.'!AZY3+'Daily-Prod.'!AZP3),"") -> 182 | BF3: =IFERROR((BE3/BD3),"") -> 1 | BG3: =IFERROR(AVERAGE('Daily-Prod.'!BJO3,'Daily-Prod.'!BJF3,'Daily-Prod.'!BIW3,'Daily-Prod.'!BIN3,'Daily-Prod.'!BIE3,'Daily-Prod.'!BHV3,'Daily-Prod.'!BHM3,'Daily-Prod.'!BHD3,'Daily-Prod.'!BGU3,'Daily-Prod.'!BGL3,'Daily-Prod.'!BGC3,'Daily-Prod.'!BFT3,'Daily-Prod.'!BFK3,'Daily-Prod.'!BFB3,'Daily-Prod.'!BES3,'Daily-Prod.'!BEJ3,'Daily-Prod.'!BEA3,'Daily-Prod.'!BDR3,'Daily-Prod.'!BDI3,'Daily-Prod.'!BCZ3,'Daily-Prod.'!BCQ3,'Daily-Prod.'!BCH3,'Daily-Prod.'!BBY3,'Daily-Prod.'!BBP3,'Daily-Prod.'!BBG3,'Daily-Prod.'!BAX3,'Daily-Prod.'!BAO3,'Daily-Prod.'!BAF3,'Daily-Prod.'!AZW3,'Daily-Prod.'!AZN3),"") -> 19.315789 | BH3: =IFERROR(AVERAGE('Daily-Prod.'!BJP3,'Daily-Prod.'!BJG3,'Daily-Prod.'!BIX3,'Daily-Prod.'!BIO3,'Daily-Prod.'!BIF3,'Daily-Prod.'!BHW3,'Daily-Prod.'!BHN3,'Daily-Prod.'!BHE3,'Daily-Prod.'!BGV3,'Daily-Prod.'!BGM3,'Daily-Prod.'!BGD3,'Daily-Prod.'!BFU3,'Daily-Prod.'!BFL3,'Daily-Prod.'!BFC3,'Daily-Prod.'!BET3,'Daily-Prod.'!BEK3,'Daily-Prod.'!BEB3,'Daily-Prod.'!BDS3,'Daily-Prod.'!BDJ3,'Daily-Prod.'!BDA3,'Daily-Prod.'!BCR3,'Daily-Prod.'!BCI3,'Daily-Prod.'!BBZ3,'Daily-Prod.'!BBQ3,'Daily-Prod.'!BBH3,'Daily-Prod.'!BAY3,'Daily-Prod.'!BAP3,'Daily-Prod.'!BAG3,'Daily-Prod.'!AZX3,'Daily-Prod.'!AZO3),"") -> 6.0666667 | BI3: =IFERROR(AVERAGE('Daily-Prod.'!BJQ3,'Daily-Prod.'!BJH3,'Daily-Prod.'!BIY3,'Daily-Prod.'!BIP3,'Daily-Prod.'!BIG3,'Daily-Prod.'!BHX3,'Daily-Prod.'!BHO3,'Daily-Prod.'!BHF3,'Daily-Prod.'!BGW3,'Daily-Prod.'!BGN3,'Daily-Prod.'!BGE3,'Daily-Prod.'!BFV3,'Daily-Prod.'!BFM3,'Daily-Prod.'!BFD3,'Daily-Prod.'!BEU3,'Daily-Prod.'!BEL3,'Daily-Prod.'!BEC3,'Daily-Prod.'!BDT3,'Daily-Prod.'!BDK3,'Daily-Prod.'!BDB3,'Daily-Prod.'!BCS3,'Daily-Prod.'!BCJ3,'Daily-Prod.'!BCA3,'Daily-Prod.'!BBR3,'Daily-Prod.'!BBI3,'Daily-Prod.'!BAZ3,'Daily-Prod.'!BAQ3,'Daily-Prod.'!BAH3,'Daily-Prod.'!AZY3,'Daily-Prod.'!AZP3),"") -> 6.0666667 | BJ3: =IFERROR((('Daily-Prod.'!BUC3+'Daily-Prod.'!BTT3+'Daily-Prod.'!BTK3+'Daily-Prod.'!BTB3+'Daily-Prod.'!BSS3+'Daily-Prod.'!BSJ3+'Daily-Prod.'!BSA3+'Daily-Prod.'!BRR3+'Daily-Prod.'!BRI3+'Daily-Prod.'!BQZ3+'Daily-Prod.'!BQQ3+'Daily-Prod.'!BQH3+'Daily-Prod.'!BPY3+'Daily-Prod.'!BPP3+'Daily-Prod.'!BPG3+'Daily-Prod.'!BOX3+'Daily-Prod.'!BOO3+'Daily-Prod.'!BOF3+'Daily-Prod.'!BNW3+'Daily-Prod.'!BNN3+'Daily-Prod.'!BNE3+'Daily-Prod.'!BMV3+'Daily-Prod.'!BMM3+'Daily-Prod.'!BMD3+'Daily-Prod.'!BLU3+'Daily-Prod.'!BLL3+'Daily-Prod.'!BLC3+'Daily-Prod.'!BKT3+'Daily-Prod.'!BKK3+'Daily-Prod.'!BKB3+'Daily-Prod.'!BJS3)/BM3),"") -> 0.39072848 | BK3: =IFERROR((('Daily-Prod.'!BUD3+'Daily-Prod.'!BTU3+'Daily-Prod.'!BTL3+'Daily-Prod.'!BTC3+'Daily-Prod.'!BST3+'Daily-Prod.'!BSK3+'Daily-Prod.'!BSB3+'Daily-Prod.'!BRS3+'Daily-Prod.'!BRJ3+'Daily-Prod.'!BRA3+'Daily-Prod.'!BQR3+'Daily-Prod.'!BQI3+'Daily-Prod.'!BPZ3+'Daily-Prod.'!BPQ3+'Daily-Prod.'!BPH3+'Daily-Prod.'!BOY3+'Daily-Prod.'!BOP3+'Daily-Prod.'!BOG3+'Daily-Prod.'!BNX3+'Daily-Prod.'!BNO3+'Daily-Prod.'!BNF3+'Daily-Prod.'!BMW3+'Daily-Prod.'!BMN3+'Daily-Prod.'!BME3+'Daily-Prod.'!BLV3+'Daily-Prod.'!BLM3+'Daily-Prod.'!BLD3+'Daily-Prod.'!BKU3+'Daily-Prod.'!BKL3+'Daily-Prod.'!BKC3+'Daily-Prod.'!BJT3)/BM3),"") -> 0.14348786 | BL3: =IFERROR((('Daily-Prod.'!BUG3+'Daily-Prod.'!BTX3+'Daily-Prod.'!BTO3+'Daily-Prod.'!BTF3+'Daily-Prod.'!BSW3+'Daily-Prod.'!BSN3+'Daily-Prod.'!BSE3+'Daily-Prod.'!BRV3+'Daily-Prod.'!BRM3+'Daily-Prod.'!BRD3+'Daily-Prod.'!BQU3+'Daily-Prod.'!BQL3+'Daily-Prod.'!BQC3+'Daily-Prod.'!BPT3+'Daily-Prod.'!BPK3+'Daily-Prod.'!BPB3+'Daily-Prod.'!BOS3+'Daily-Prod.'!BOJ3+'Daily-Prod.'!BOA3+'Daily-Prod.'!BNR3+'Daily-Prod.'!BNI3+'Daily-Prod.'!BMZ3+'Daily-Prod.'!BMQ3+'Daily-Prod.'!BMH3+'Daily-Prod.'!BLY3+'Daily-Prod.'!BLP3+'Daily-Prod.'!BLG3+'Daily-Prod.'!BKX3+'Daily-Prod.'!BKO3+'Daily-Prod.'!BKF3+'Daily-Prod.'!BJW3+'Daily-Prod.'!BUF3+'Daily-Prod.'!BTW3+'Daily-Prod.'!BTN3+'Daily-Prod.'!BTE3+'Daily-Prod.'!BSV3+'Daily-Prod.'!BSM3+'Daily-Prod.'!BSD3+'Daily-Prod.'!BRU3+'Daily-Prod.'!BRL3+'Daily-Prod.'!BRC3+'Daily-Prod.'!BQT3+'Daily-Prod.'!BQK3+'Daily-Prod.'!BQB3+'Daily-Prod.'!BPS3+'Daily-Prod.'!BPJ3+'Daily-Prod.'!BPA3+'Daily-Prod.'!BOR3+'Daily-Prod.'!BOI3+'Daily-Prod.'!BNZ3+'Daily-Prod.'!BNQ3+'Daily-Prod.'!BNH3+'Daily-Prod.'!BMY3+'Daily-Prod.'!BMP3+'Daily-Prod.'!BMG3+'Daily-Prod.'!BLX3+'Daily-Prod.'!BLO3+'Daily-Prod.'!BLF3+'Daily-Prod.'!BKW3+'Daily-Prod.'!BKN3+'Daily-Prod.'!BKE3+'Daily-Prod.'!BJV3)/BM3),"") -> 0.46578366 | BM3: =IFERROR(('Daily-Prod.'!BUH3+'Daily-Prod.'!BTY3+'Daily-Prod.'!BTP3+'Daily-Prod.'!BTG3+'Daily-Prod.'!BSX3+'Daily-Prod.'!BSO3+'Daily-Prod.'!BSF3+'Daily-Prod.'!BRW3+'Daily-Prod.'!BRN3+'Daily-Prod.'!BRE3+'Daily-Prod.'!BQV3+'Daily-Prod.'!BQM3+'Daily-Prod.'!BQD3+'Daily-Prod.'!BPU3+'Daily-Prod.'!BPL3+'Daily-Prod.'!BPC3+'Daily-Prod.'!BOT3+'Daily-Prod.'!BOK3+'Daily-Prod.'!BOB3+'Daily-Prod.'!BNS3+'Daily-Prod.'!BNJ3+'Daily-Prod.'!BNA3+'Daily-Prod.'!BMR3+'Daily-Prod.'!BMI3+'Daily-Prod.'!BLZ3+'Daily-Prod.'!BLQ3+'Daily-Prod.'!BLH3+'Daily-Prod.'!BKY3+'Daily-Prod.'!BKP3+'Daily-Prod.'!BKG3+'Daily-Prod.'!BJX3),"") -> 453 | BO3: =IFERROR(('Daily-Prod.'!BUJ3+'Daily-Prod.'!BUA3+'Daily-Prod.'!BTR3+'Daily-Prod.'!BTI3+'Daily-Prod.'!BSZ3+'Daily-Prod.'!BSQ3+'Daily-Prod.'!BSH3+'Daily-Prod.'!BRY3+'Daily-Prod.'!BRP3+'Daily-Prod.'!BRG3+'Daily-Prod.'!BQX3+'Daily-Prod.'!BQO3+'Daily-Prod.'!BQF3+'Daily-Prod.'!BPW3+'Daily-Prod.'!BPN3+'Daily-Prod.'!BPE3+'Daily-Prod.'!BOV3+'Daily-Prod.'!BOM3+'Daily-Prod.'!BOD3+'Daily-Prod.'!BNU3+'Daily-Prod.'!BNL3+'Daily-Prod.'!BNC3+'Daily-Prod.'!BMT3+'Daily-Prod.'!BMK3+'Daily-Prod.'!BMB3+'Daily-Prod.'!BLS3+'Daily-Prod.'!BLJ3+'Daily-Prod.'!BLA3+'Daily-Prod.'!BKR3+'Daily-Prod.'!BKI3+'Daily-Prod.'!BJZ3),"") -> 105 | BP3: =IFERROR((BO3/BN3),"") | BQ3: =IFERROR(AVERAGE(('Daily-Prod.'!BUH3,'Daily-Prod.'!BTY3,'Daily-Prod.'!BTP3,'Daily-Prod.'!BTG3,'Daily-Prod.'!BSX3,'Daily-Prod.'!BSO3,'Daily-Prod.'!BSF3,'Daily-Prod.'!BRW3,'Daily-Prod.'!BRN3,'Daily-Prod.'!BRE3,'Daily-Prod.'!BQV3,'Daily-Prod.'!BQM3,'Daily-Prod.'!BQD3,'Daily-Prod.'!BPU3,'Daily-Prod.'!BPL3,'Daily-Prod.'!BPC3,'Daily-Prod.'!BOT3,'Daily-Prod.'!BOK3,'Daily-Prod.'!BOB3,'Daily-Prod.'!BNS3,'Daily-Prod.'!BNJ3,'Daily-Prod.'!BNA3,'Daily-Prod.'!BMR3,'Daily-Prod.'!BMI3,'Daily-Prod.'!BLZ3,'Daily-Prod.'!BLQ3,'Daily-Prod.'!BLH3,'Daily-Prod.'!BKY3,'Daily-Prod.'!BKP3,'Daily-Prod.'!BKG3,'Daily-Prod.'!BJX3)),"") -> 19.695652 | BS3: =IFERROR((AVERAGE('Daily-Prod.'!BUJ3,'Daily-Prod.'!BUA3,'Daily-Prod.'!BTR3,'Daily-Prod.'!BTI3,'Daily-Prod.'!BSZ3,'Daily-Prod.'!BSQ3,'Daily-Prod.'!BSH3,'Daily-Prod.'!BRY3,'Daily-Prod.'!BRP3,'Daily-Prod.'!BRG3,'Daily-Prod.'!BQX3,'Daily-Prod.'!BQO3,'Daily-Prod.'!BQF3,'Daily-Prod.'!BPW3,'Daily-Prod.'!BPN3,'Daily-Prod.'!BPE3,'Daily-Prod.'!BOV3,'Daily-Prod.'!BOM3,'Daily-Prod.'!BOD3,'Daily-Prod.'!BNU3,'Daily-Prod.'!BNL3,'Daily-Prod.'!BNC3,'Daily-Prod.'!BMT3,'Daily-Prod.'!BMK3,'Daily-Prod.'!BMB3,'Daily-Prod.'!BLS3,'Daily-Prod.'!BLJ3,'Daily-Prod.'!BLA3,'Daily-Prod.'!BKR3,'Daily-Prod.'!BKI3,'Daily-Prod.'!BJZ3)),"") -> 9.5454545
A4: Abdelmoughit ARRABIH | B4: =IFERROR(('Daily-Prod.'!JC4+'Daily-Prod.'!IT4+'Daily-Prod.'!IK4+'Daily-Prod.'!IB4+'Daily-Prod.'!HS4+'Daily-Prod.'!HJ4+'Daily-Prod.'!HA4+'Daily-Prod.'!GR4+'Daily-Prod.'!GI4+'Daily-Prod.'!FZ4+'Daily-Prod.'!FQ4+'Daily-Prod.'!FH4+'Daily-Prod.'!EY4+'Daily-Prod.'!EP4+'Daily-Prod.'!EG4+'Daily-Prod.'!DX4+'Daily-Prod.'!DO4+'Daily-Prod.'!DF4+'Daily-Prod.'!CW4+'Daily-Prod.'!CN4+'Daily-Prod.'!CE4+'Daily-Prod.'!BV4+'Daily-Prod.'!BM4+'Daily-Prod.'!BD4+'Daily-Prod.'!AU4+'Daily-Prod.'!AL4+'Daily-Prod.'!AC4+'Daily-Prod.'!T4+'Daily-Prod.'!K4+'Daily-Prod.'!B4)/E4,"") -> 0.36546185 | C4: =IFERROR(('Daily-Prod.'!JD4+'Daily-Prod.'!IU4+'Daily-Prod.'!IL4+'Daily-Prod.'!IC4+'Daily-Prod.'!HT4+'Daily-Prod.'!HK4+'Daily-Prod.'!HB4+'Daily-Prod.'!GS4+'Daily-Prod.'!GJ4+'Daily-Prod.'!GA4+'Daily-Prod.'!FR4+'Daily-Prod.'!FI4+'Daily-Prod.'!EZ4+'Daily-Prod.'!EQ4+'Daily-Prod.'!EH4+'Daily-Prod.'!DY4+'Daily-Prod.'!DP4+'Daily-Prod.'!DG4+'Daily-Prod.'!CX4+'Daily-Prod.'!CO4+'Daily-Prod.'!CF4+'Daily-Prod.'!BW4+'Daily-Prod.'!BN4+'Daily-Prod.'!BE4+'Daily-Prod.'!AV4+'Daily-Prod.'!AM4+'Daily-Prod.'!AD4+'Daily-Prod.'!U4+'Daily-Prod.'!L4+'Daily-Prod.'!C4)/E4,"") -> 0.064257028 | D4: =IFERROR(('Daily-Prod.'!JF4+'Daily-Prod.'!IW4+'Daily-Prod.'!IN4+'Daily-Prod.'!IE4+'Daily-Prod.'!HV4+'Daily-Prod.'!HM4+'Daily-Prod.'!HD4+'Daily-Prod.'!GU4+'Daily-Prod.'!GL4+'Daily-Prod.'!GC4+'Daily-Prod.'!FT4+'Daily-Prod.'!FK4+'Daily-Prod.'!FB4+'Daily-Prod.'!ES4+'Daily-Prod.'!EJ4+'Daily-Prod.'!EA4+'Daily-Prod.'!DR4+'Daily-Prod.'!DI4+'Daily-Prod.'!CZ4+'Daily-Prod.'!CQ4+'Daily-Prod.'!CH4+'Daily-Prod.'!BY4+'Daily-Prod.'!BP4+'Daily-Prod.'!BG4+'Daily-Prod.'!AX4+'Daily-Prod.'!AO4+'Daily-Prod.'!AF4+'Daily-Prod.'!W4+'Daily-Prod.'!N4+'Daily-Prod.'!E4+'Daily-Prod.'!JG4+'Daily-Prod.'!IX4+'Daily-Prod.'!IO4+'Daily-Prod.'!IF4+'Daily-Prod.'!HW4+'Daily-Prod.'!HN4+'Daily-Prod.'!HE4+'Daily-Prod.'!GV4+'Daily-Prod.'!GM4+'Daily-Prod.'!GD4+'Daily-Prod.'!FU4+'Daily-Prod.'!FL4+'Daily-Prod.'!FC4+'Daily-Prod.'!ET4+'Daily-Prod.'!EK4+'Daily-Prod.'!EB4+'Daily-Prod.'!DS4+'Daily-Prod.'!DJ4+'Daily-Prod.'!DA4+'Daily-Prod.'!CR4+'Daily-Prod.'!CI4+'Daily-Prod.'!BZ4+'Daily-Prod.'!BQ4+'Daily-Prod.'!BH4+'Daily-Prod.'!AY4+'Daily-Prod.'!AP4+'Daily-Prod.'!AG4+'Daily-Prod.'!X4+'Daily-Prod.'!O4+'Daily-Prod.'!F4)/E4,"") -> 0.57028112 | E4: =IFERROR(('Daily-Prod.'!JH4+'Daily-Prod.'!IY4+'Daily-Prod.'!IP4+'Daily-Prod.'!IG4+'Daily-Prod.'!HX4+'Daily-Prod.'!HO4+'Daily-Prod.'!HF4+'Daily-Prod.'!GW4+'Daily-Prod.'!GN4+'Daily-Prod.'!GE4+'Daily-Prod.'!FV4+'Daily-Prod.'!FM4+'Daily-Prod.'!FD4+'Daily-Prod.'!EU4+'Daily-Prod.'!EL4+'Daily-Prod.'!EC4+'Daily-Prod.'!DT4+'Daily-Prod.'!DK4+'Daily-Prod.'!DB4+'Daily-Prod.'!CS4+'Daily-Prod.'!CJ4+'Daily-Prod.'!CA4+'Daily-Prod.'!BR4+'Daily-Prod.'!BI4+'Daily-Prod.'!AZ4+'Daily-Prod.'!AQ4+'Daily-Prod.'!AH4+'Daily-Prod.'!Y4+'Daily-Prod.'!P4+'Daily-Prod.'!G4),"") -> 498 | G4: =IFERROR(('Daily-Prod.'!JJ4+'Daily-Prod.'!JA4+'Daily-Prod.'!IR4+'Daily-Prod.'!II4+'Daily-Prod.'!HZ4+'Daily-Prod.'!HQ4+'Daily-Prod.'!HH4+'Daily-Prod.'!GY4+'Daily-Prod.'!GP4+'Daily-Prod.'!GG4+'Daily-Prod.'!FX4+'Daily-Prod.'!FO4+'Daily-Prod.'!FF4+'Daily-Prod.'!EW4+'Daily-Prod.'!EN4+'Daily-Prod.'!EE4+'Daily-Prod.'!DV4+'Daily-Prod.'!DM4+'Daily-Prod.'!DD4+'Daily-Prod.'!CU4+'Daily-Prod.'!CL4+'Daily-Prod.'!CC4+'Daily-Prod.'!BT4+'Daily-Prod.'!BK4+'Daily-Prod.'!BB4+'Daily-Prod.'!AS4+'Daily-Prod.'!AJ4+'Daily-Prod.'!AA4+'Daily-Prod.'!R4+'Daily-Prod.'!I4),"") -> 122 | H4: =IFERROR((G4/F4),"") | I4: =IFERROR(AVERAGE('Daily-Prod.'!JH4,'Daily-Prod.'!IY4,'Daily-Prod.'!IP4,'Daily-Prod.'!IG4,'Daily-Prod.'!HX4,'Daily-Prod.'!HO4,'Daily-Prod.'!HF4,'Daily-Prod.'!GW4,'Daily-Prod.'!GN4,'Daily-Prod.'!GE4,'Daily-Prod.'!FV4,'Daily-Prod.'!FM4,'Daily-Prod.'!FD4,'Daily-Prod.'!EU4,'Daily-Prod.'!EL4,'Daily-Prod.'!EC4,'Daily-Prod.'!DT4,'Daily-Prod.'!DK4,'Daily-Prod.'!DB4,'Daily-Prod.'!CS4,'Daily-Prod.'!CJ4,'Daily-Prod.'!CA4,'Daily-Prod.'!BR4,'Daily-Prod.'!BI4,'Daily-Prod.'!AZ4,'Daily-Prod.'!AQ4,'Daily-Prod.'!AH4,'Daily-Prod.'!Y4,'Daily-Prod.'!P4,'Daily-Prod.'!G4),"") -> 23.714286 | J4: =IFERROR(AVERAGE('Daily-Prod.'!JI4,'Daily-Prod.'!IZ4,'Daily-Prod.'!IQ4,'Daily-Prod.'!IH4,'Daily-Prod.'!HY4,'Daily-Prod.'!HP4,'Daily-Prod.'!HG4,'Daily-Prod.'!GX4,'Daily-Prod.'!GO4,'Daily-Prod.'!GF4,'Daily-Prod.'!FW4,'Daily-Prod.'!FN4,'Daily-Prod.'!FE4,'Daily-Prod.'!EV4,'Daily-Prod.'!EM4,'Daily-Prod.'!ED4,'Daily-Prod.'!DU4,'Daily-Prod.'!DL4,'Daily-Prod.'!DC4,'Daily-Prod.'!CT4,'Daily-Prod.'!CK4,'Daily-Prod.'!CB4,'Daily-Prod.'!BS4,'Daily-Prod.'!BJ4,'Daily-Prod.'!BA4,'Daily-Prod.'!AR4,'Daily-Prod.'!AI4,'Daily-Prod.'!Z4,'Daily-Prod.'!Q4,'Daily-Prod.'!H4),"") | K4: =IFERROR(AVERAGE('Daily-Prod.'!JJ4,'Daily-Prod.'!JA4,'Daily-Prod.'!IR4,'Daily-Prod.'!II4,'Daily-Prod.'!HZ4,'Daily-Prod.'!HQ4,'Daily-Prod.'!HH4,'Daily-Prod.'!GY4,'Daily-Prod.'!GP4,'Daily-Prod.'!GG4,'Daily-Prod.'!FX4,'Daily-Prod.'!FO4,'Daily-Prod.'!FF4,'Daily-Prod.'!EW4,'Daily-Prod.'!EN4,'Daily-Prod.'!EE4,'Daily-Prod.'!DV4,'Daily-Prod.'!DM4,'Daily-Prod.'!DD4,'Daily-Prod.'!CU4,'Daily-Prod.'!CL4,'Daily-Prod.'!CC4,'Daily-Prod.'!BT4,'Daily-Prod.'!BK4,'Daily-Prod.'!BB4,'Daily-Prod.'!AS4,'Daily-Prod.'!AJ4,'Daily-Prod.'!AA4,'Daily-Prod.'!R4,'Daily-Prod.'!I4),"") -> 9.3846154 | L4: =IFERROR(('Daily-Prod.'!TV4+'Daily-Prod.'!TM4+'Daily-Prod.'!TD4+'Daily-Prod.'!SU4+'Daily-Prod.'!SL4+'Daily-Prod.'!SC4+'Daily-Prod.'!RT4+'Daily-Prod.'!RK4+'Daily-Prod.'!RB4+'Daily-Prod.'!QS4+'Daily-Prod.'!QJ4+'Daily-Prod.'!QA4+'Daily-Prod.'!PR4+'Daily-Prod.'!PI4+'Daily-Prod.'!OZ4+'Daily-Prod.'!OQ4+'Daily-Prod.'!OH4+'Daily-Prod.'!NY4+'Daily-Prod.'!NP4+'Daily-Prod.'!NG4+'Daily-Prod.'!MX4+'Daily-Prod.'!MO4+'Daily-Prod.'!MF4+'Daily-Prod.'!LW4+'Daily-Prod.'!LN4+'Daily-Prod.'!LE4+'Daily-Prod.'!KV4+'Daily-Prod.'!KM4+'Daily-Prod.'!KD4+'Daily-Prod.'!JU4+'Daily-Prod.'!JL4)/O4,"") -> 0.36801541 | M4: =IFERROR(('Daily-Prod.'!TW4+'Daily-Prod.'!TN4+'Daily-Prod.'!TE4+'Daily-Prod.'!SV4+'Daily-Prod.'!SM4+'Daily-Prod.'!SD4+'Daily-Prod.'!RU4+'Daily-Prod.'!RL4+'Daily-Prod.'!RC4+'Daily-Prod.'!QT4+'Daily-Prod.'!QK4+'Daily-Prod.'!QB4+'Daily-Prod.'!PS4+'Daily-Prod.'!PJ4+'Daily-Prod.'!PA4+'Daily-Prod.'!OR4+'Daily-Prod.'!OI4+'Daily-Prod.'!NZ4+'Daily-Prod.'!NQ4+'Daily-Prod.'!NH4+'Daily-Prod.'!MY4+'Daily-Prod.'!MP4+'Daily-Prod.'!MG4+'Daily-Prod.'!LX4+'Daily-Prod.'!LO4+'Daily-Prod.'!LF4+'Daily-Prod.'!KW4+'Daily-Prod.'!KN4+'Daily-Prod.'!KE4+'Daily-Prod.'!JV4+'Daily-Prod.'!JM4)/O4,"") -> 0.075144509 | N4: =IFERROR(('Daily-Prod.'!TY4+'Daily-Prod.'!TP4+'Daily-Prod.'!TG4+'Daily-Prod.'!SX4+'Daily-Prod.'!SO4+'Daily-Prod.'!SF4+'Daily-Prod.'!RW4+'Daily-Prod.'!RN4+'Daily-Prod.'!RE4+'Daily-Prod.'!QV4+'Daily-Prod.'!QM4+'Daily-Prod.'!QD4+'Daily-Prod.'!PU4+'Daily-Prod.'!PL4+'Daily-Prod.'!PC4+'Daily-Prod.'!OT4+'Daily-Prod.'!OK4+'Daily-Prod.'!OB4+'Daily-Prod.'!NS4+'Daily-Prod.'!NJ4+'Daily-Prod.'!NA4+'Daily-Prod.'!MR4+'Daily-Prod.'!MI4+'Daily-Prod.'!LZ4+'Daily-Prod.'!LQ4+'Daily-Prod.'!LH4+'Daily-Prod.'!KY4+'Daily-Prod.'!KP4+'Daily-Prod.'!KG4+'Daily-Prod.'!JX4+'Daily-Prod.'!JO4+'Daily-Prod.'!TZ4+'Daily-Prod.'!TQ4+'Daily-Prod.'!TH4+'Daily-Prod.'!SY4+'Daily-Prod.'!SP4+'Daily-Prod.'!SG4+'Daily-Prod.'!RX4+'Daily-Prod.'!RO4+'Daily-Prod.'!RF4+'Daily-Prod.'!QW4+'Daily-Prod.'!QN4+'Daily-Prod.'!QE4+'Daily-Prod.'!PV4+'Daily-Prod.'!PM4+'Daily-Prod.'!PD4+'Daily-Prod.'!OU4+'Daily-Prod.'!OL4+'Daily-Prod.'!OC4+'Daily-Prod.'!NT4+'Daily-Prod.'!NK4+'Daily-Prod.'!NB4+'Daily-Prod.'!MS4+'Daily-Prod.'!MJ4+'Daily-Prod.'!MA4+'Daily-Prod.'!LR4+'Daily-Prod.'!LI4+'Daily-Prod.'!KZ4+'Daily-Prod.'!KQ4+'Daily-Prod.'!KH4+'Daily-Prod.'!JY4+'Daily-Prod.'!JP4)/O4,"") -> 0.55684008 | O4: =IFERROR(('Daily-Prod.'!UA4+'Daily-Prod.'!TR4+'Daily-Prod.'!TI4+'Daily-Prod.'!SZ4+'Daily-Prod.'!SQ4+'Daily-Prod.'!SH4+'Daily-Prod.'!RY4+'Daily-Prod.'!RP4+'Daily-Prod.'!RG4+'Daily-Prod.'!QX4+'Daily-Prod.'!QO4+'Daily-Prod.'!QF4+'Daily-Prod.'!PW4+'Daily-Prod.'!PN4+'Daily-Prod.'!PE4+'Daily-Prod.'!OV4+'Daily-Prod.'!OM4+'Daily-Prod.'!OD4+'Daily-Prod.'!NU4+'Daily-Prod.'!NL4+'Daily-Prod.'!NC4+'Daily-Prod.'!MT4+'Daily-Prod.'!MK4+'Daily-Prod.'!MB4+'Daily-Prod.'!LS4+'Daily-Prod.'!LJ4+'Daily-Prod.'!LA4+'Daily-Prod.'!KR4+'Daily-Prod.'!KI4+'Daily-Prod.'!JZ4+'Daily-Prod.'!JQ4),"") -> 519 | Q4: =IFERROR(('Daily-Prod.'!UC4+'Daily-Prod.'!TT4+'Daily-Prod.'!TK4+'Daily-Prod.'!TB4+'Daily-Prod.'!SS4+'Daily-Prod.'!SJ4+'Daily-Prod.'!SA4+'Daily-Prod.'!RR4+'Daily-Prod.'!RI4+'Daily-Prod.'!QZ4+'Daily-Prod.'!QQ4+'Daily-Prod.'!QH4+'Daily-Prod.'!PY4+'Daily-Prod.'!PP4+'Daily-Prod.'!PG4+'Daily-Prod.'!OX4+'Daily-Prod.'!OO4+'Daily-Prod.'!OF4+'Daily-Prod.'!NW4+'Daily-Prod.'!NN4+'Daily-Prod.'!NE4+'Daily-Prod.'!MV4+'Daily-Prod.'!MM4+'Daily-Prod.'!MD4+'Daily-Prod.'!LU4+'Daily-Prod.'!LL4+'Daily-Prod.'!LC4+'Daily-Prod.'!KT4+'Daily-Prod.'!KK4+'Daily-Prod.'!KB4+'Daily-Prod.'!JS4),"") -> 188 | R4: =IFERROR((Q4/P4),"") | S4: =IFERROR(AVERAGE('Daily-Prod.'!TR4,'Daily-Prod.'!UA4,'Daily-Prod.'!TI4,'Daily-Prod.'!SZ4,'Daily-Prod.'!SQ4,'Daily-Prod.'!SH4,'Daily-Prod.'!RY4,'Daily-Prod.'!RP4,'Daily-Prod.'!RG4,'Daily-Prod.'!QX4,'Daily-Prod.'!QO4,'Daily-Prod.'!QF4,'Daily-Prod.'!PW4,'Daily-Prod.'!PN4,'Daily-Prod.'!PE4,'Daily-Prod.'!OV4,'Daily-Prod.'!OM4,'Daily-Prod.'!OD4,'Daily-Prod.'!NU4,'Daily-Prod.'!NL4,'Daily-Prod.'!NC4,'Daily-Prod.'!MT4,'Daily-Prod.'!MK4,'Daily-Prod.'!MB4,'Daily-Prod.'!LS4,'Daily-Prod.'!LJ4,'Daily-Prod.'!LA4,'Daily-Prod.'!KR4,'Daily-Prod.'!KI4,'Daily-Prod.'!JZ4),"") -> 24.7 | T4: =IFERROR(AVERAGE('Daily-Prod.'!TS4,'Daily-Prod.'!UB4,'Daily-Prod.'!TJ4,'Daily-Prod.'!TA4,'Daily-Prod.'!SR4,'Daily-Prod.'!SI4,'Daily-Prod.'!RZ4,'Daily-Prod.'!RQ4,'Daily-Prod.'!RH4,'Daily-Prod.'!QY4,'Daily-Prod.'!QP4,'Daily-Prod.'!QG4,'Daily-Prod.'!PX4,'Daily-Prod.'!PO4,'Daily-Prod.'!PF4,'Daily-Prod.'!OW4,'Daily-Prod.'!ON4,'Daily-Prod.'!OE4,'Daily-Prod.'!NV4,'Daily-Prod.'!NM4,'Daily-Prod.'!ND4,'Daily-Prod.'!MU4,'Daily-Prod.'!ML4,'Daily-Prod.'!MC4,'Daily-Prod.'!LT4,'Daily-Prod.'!LK4,'Daily-Prod.'!LB4,'Daily-Prod.'!KS4,'Daily-Prod.'!KJ4,'Daily-Prod.'!KA4),"") | U4: =IFERROR(AVERAGE('Daily-Prod.'!TT4,'Daily-Prod.'!UC4,'Daily-Prod.'!TK4,'Daily-Prod.'!TB4,'Daily-Prod.'!SS4,'Daily-Prod.'!SJ4,'Daily-Prod.'!SA4,'Daily-Prod.'!RR4,'Daily-Prod.'!RI4,'Daily-Prod.'!QZ4,'Daily-Prod.'!QQ4,'Daily-Prod.'!QH4,'Daily-Prod.'!PY4,'Daily-Prod.'!PP4,'Daily-Prod.'!PG4,'Daily-Prod.'!OX4,'Daily-Prod.'!OO4,'Daily-Prod.'!OF4,'Daily-Prod.'!NW4,'Daily-Prod.'!NN4,'Daily-Prod.'!NE4,'Daily-Prod.'!MV4,'Daily-Prod.'!MM4,'Daily-Prod.'!MD4,'Daily-Prod.'!LU4,'Daily-Prod.'!LL4,'Daily-Prod.'!LC4,'Daily-Prod.'!KT4,'Daily-Prod.'!KK4,'Daily-Prod.'!KB4),"") -> 9 | V4: =IFERROR(('Daily-Prod.'!ADN4+'Daily-Prod.'!ADE4+'Daily-Prod.'!ACV4+'Daily-Prod.'!ACM4+'Daily-Prod.'!ACD4+'Daily-Prod.'!ABU4+'Daily-Prod.'!ABL4+'Daily-Prod.'!ABC4+'Daily-Prod.'!AAT4+'Daily-Prod.'!AAK4+'Daily-Prod.'!AAB4+'Daily-Prod.'!ZS4+'Daily-Prod.'!ZJ4+'Daily-Prod.'!ZA4+'Daily-Prod.'!YR4+'Daily-Prod.'!YI4+'Daily-Prod.'!XZ4+'Daily-Prod.'!XQ4+'Daily-Prod.'!XH4+'Daily-Prod.'!WY4+'Daily-Prod.'!WP4+'Daily-Prod.'!WG4+'Daily-Prod.'!VX4+'Daily-Prod.'!VO4+'Daily-Prod.'!VF4+'Daily-Prod.'!UW4+'Daily-Prod.'!UN4+'Daily-Prod.'!UE4)/Y4,"") -> 0.36117381 | W4: =IFERROR(('Daily-Prod.'!ADO4+'Daily-Prod.'!ADF4+'Daily-Prod.'!ACW4+'Daily-Prod.'!ACN4+'Daily-Prod.'!ACE4+'Daily-Prod.'!ABV4+'Daily-Prod.'!ABM4+'Daily-Prod.'!ABD4+'Daily-Prod.'!AAU4+'Daily-Prod.'!AAL4+'Daily-Prod.'!AAC4+'Daily-Prod.'!ZT4+'Daily-Prod.'!ZK4+'Daily-Prod.'!ZB4+'Daily-Prod.'!YS4+'Daily-Prod.'!YJ4+'Daily-Prod.'!YA4+'Daily-Prod.'!XR4+'Daily-Prod.'!XI4+'Daily-Prod.'!WZ4+'Daily-Prod.'!WQ4+'Daily-Prod.'!WH4+'Daily-Prod.'!VY4+'Daily-Prod.'!VP4+'Daily-Prod.'!VG4+'Daily-Prod.'!UX4+'Daily-Prod.'!UO4+'Daily-Prod.'!UF4)/Y4,"") -> 0.063205418 | X4: =IFERROR(('Daily-Prod.'!ADR4+'Daily-Prod.'!ADI4+'Daily-Prod.'!ACZ4+'Daily-Prod.'!ACQ4+'Daily-Prod.'!ACH4+'Daily-Prod.'!ABY4+'Daily-Prod.'!ABP4+'Daily-Prod.'!ABG4+'Daily-Prod.'!AAX4+'Daily-Prod.'!AAO4+'Daily-Prod.'!AAF4+'Daily-Prod.'!ZW4+'Daily-Prod.'!ZN4+'Daily-Prod.'!ZE4+'Daily-Prod.'!YV4+'Daily-Prod.'!YM4+'Daily-Prod.'!YD4+'Daily-Prod.'!XU4+'Daily-Prod.'!XL4+'Daily-Prod.'!XC4+'Daily-Prod.'!WT4+'Daily-Prod.'!WK4+'Daily-Prod.'!WB4+'Daily-Prod.'!VS4+'Daily-Prod.'!VJ4+'Daily-Prod.'!VA4+'Daily-Prod.'!UR4+'Daily-Prod.'!UI4+'Daily-Prod.'!ADQ4+'Daily-Prod.'!ADH4+'Daily-Prod.'!ACY4+'Daily-Prod.'!ACP4+'Daily-Prod.'!ACG4+'Daily-Prod.'!ABX4+'Daily-Prod.'!ABO4+'Daily-Prod.'!ABF4+'Daily-Prod.'!AAW4+'Daily-Prod.'!AAN4+'Daily-Prod.'!AAE4+'Daily-Prod.'!ZV4+'Daily-Prod.'!ZM4+'Daily-Prod.'!ZD4+'Daily-Prod.'!YU4+'Daily-Prod.'!YL4+'Daily-Prod.'!YC4+'Daily-Prod.'!XT4+'Daily-Prod.'!XK4+'Daily-Prod.'!XB4+'Daily-Prod.'!WS4+'Daily-Prod.'!WJ4+'Daily-Prod.'!WA4+'Daily-Prod.'!VR4+'Daily-Prod.'!VI4+'Daily-Prod.'!UZ4+'Daily-Prod.'!UQ4+'Daily-Prod.'!UH4)/Y4,"") -> 0.57562077 | Y4: =IFERROR(('Daily-Prod.'!ADS4+'Daily-Prod.'!ADJ4+'Daily-Prod.'!ADA4+'Daily-Prod.'!ACR4+'Daily-Prod.'!ACI4+'Daily-Prod.'!ABZ4+'Daily-Prod.'!ABQ4+'Daily-Prod.'!ABH4+'Daily-Prod.'!AAY4+'Daily-Prod.'!AAP4+'Daily-Prod.'!AAG4+'Daily-Prod.'!ZX4+'Daily-Prod.'!ZO4+'Daily-Prod.'!ZF4+'Daily-Prod.'!YW4+'Daily-Prod.'!YN4+'Daily-Prod.'!YE4+'Daily-Prod.'!XV4+'Daily-Prod.'!XM4+'Daily-Prod.'!XD4+'Daily-Prod.'!WU4+'Daily-Prod.'!WL4+'Daily-Prod.'!WC4+'Daily-Prod.'!VT4+'Daily-Prod.'!VK4+'Daily-Prod.'!VB4+'Daily-Prod.'!US4+'Daily-Prod.'!UJ4),"") -> 443 | AA4: =IFERROR(('Daily-Prod.'!ADU4+'Daily-Prod.'!ADL4+'Daily-Prod.'!ADC4+'Daily-Prod.'!ACT4+'Daily-Prod.'!ACK4+'Daily-Prod.'!ACB4+'Daily-Prod.'!ABS4+'Daily-Prod.'!ABJ4+'Daily-Prod.'!ABA4+'Daily-Prod.'!AAR4+'Daily-Prod.'!AAI4+'Daily-Prod.'!ZZ4+'Daily-Prod.'!ZQ4+'Daily-Prod.'!ZH4+'Daily-Prod.'!YY4+'Daily-Prod.'!YP4+'Daily-Prod.'!YG4+'Daily-Prod.'!XX4+'Daily-Prod.'!XO4+'Daily-Prod.'!XF4+'Daily-Prod.'!WW4+'Daily-Prod.'!WN4+'Daily-Prod.'!WE4+'Daily-Prod.'!VV4+'Daily-Prod.'!VM4+'Daily-Prod.'!VD4+'Daily-Prod.'!UU4+'Daily-Prod.'!UL4),"") -> 168 | AB4: =IFERROR((AA4/Z4),"") | AC4: =IFERROR(AVERAGE('Daily-Prod.'!ADS4,'Daily-Prod.'!ADJ4,'Daily-Prod.'!ADA4,'Daily-Prod.'!ACR4,'Daily-Prod.'!ACI4,'Daily-Prod.'!ABZ4,'Daily-Prod.'!ABQ4,'Daily-Prod.'!ABH4,'Daily-Prod.'!AAY4,'Daily-Prod.'!AAP4,'Daily-Prod.'!AAG4,'Daily-Prod.'!ZX4,'Daily-Prod.'!ZO4,'Daily-Prod.'!ZF4,'Daily-Prod.'!YW4,'Daily-Prod.'!YN4,'Daily-Prod.'!YE4,'Daily-Prod.'!XV4,'Daily-Prod.'!XM4,'Daily-Prod.'!XD4,'Daily-Prod.'!WU4,'Daily-Prod.'!WL4,'Daily-Prod.'!WC4,'Daily-Prod.'!VT4,'Daily-Prod.'!VK4,'Daily-Prod.'!VB4,'Daily-Prod.'!US4,'Daily-Prod.'!UJ4),"") -> 23.315789 | AE4: =IFERROR(AVERAGE('Daily-Prod.'!ADU4,'Daily-Prod.'!ADL4,'Daily-Prod.'!ADC4,'Daily-Prod.'!ACT4,'Daily-Prod.'!ACK4,'Daily-Prod.'!ACB4,'Daily-Prod.'!ABS4,'Daily-Prod.'!ABJ4,'Daily-Prod.'!ABA4,'Daily-Prod.'!AAR4,'Daily-Prod.'!AAI4,'Daily-Prod.'!ZZ4,'Daily-Prod.'!ZQ4,'Daily-Prod.'!ZH4,'Daily-Prod.'!YY4,'Daily-Prod.'!YP4,'Daily-Prod.'!YG4,'Daily-Prod.'!XX4,'Daily-Prod.'!XO4,'Daily-Prod.'!XF4,'Daily-Prod.'!WW4,'Daily-Prod.'!WN4,'Daily-Prod.'!WE4,'Daily-Prod.'!VV4,'Daily-Prod.'!VM4,'Daily-Prod.'!VD4,'Daily-Prod.'!UU4,'Daily-Prod.'!UL4),"") -> 9.3333333 | AF4: =IFERROR(('Daily-Prod.'!AOG4+'Daily-Prod.'!ANX4+'Daily-Prod.'!ANO4+'Daily-Prod.'!ANF4+'Daily-Prod.'!AMW4+'Daily-Prod.'!AMN4+'Daily-Prod.'!AME4+'Daily-Prod.'!ALV4+'Daily-Prod.'!ALM4+'Daily-Prod.'!ALD4+'Daily-Prod.'!AKU4+'Daily-Prod.'!AKL4+'Daily-Prod.'!AKC4+'Daily-Prod.'!AJT4+'Daily-Prod.'!AJK4+'Daily-Prod.'!AJB4+'Daily-Prod.'!AIS4+'Daily-Prod.'!AIJ4+'Daily-Prod.'!AIA4+'Daily-Prod.'!AHR4+'Daily-Prod.'!AHI4+'Daily-Prod.'!AGZ4+'Daily-Prod.'!AGQ4+'Daily-Prod.'!AGH4+'Daily-Prod.'!AFY4+'Daily-Prod.'!AFP4+'Daily-Prod.'!AFG4+'Daily-Prod.'!AEX4+'Daily-Prod.'!AEO4+'Daily-Prod.'!AEF4+'Daily-Prod.'!ADW4)/AI4,"") -> 0.34936709 | AG4: =IFERROR(('Daily-Prod.'!AOH4+'Daily-Prod.'!ANY4+'Daily-Prod.'!ANP4+'Daily-Prod.'!ANG4+'Daily-Prod.'!AMX4+'Daily-Prod.'!AMO4+'Daily-Prod.'!AMF4+'Daily-Prod.'!ALW4+'Daily-Prod.'!ALN4+'Daily-Prod.'!ALE4+'Daily-Prod.'!AKV4+'Daily-Prod.'!AKM4+'Daily-Prod.'!AKD4+'Daily-Prod.'!AJU4+'Daily-Prod.'!AJL4+'Daily-Prod.'!AJC4+'Daily-Prod.'!AIT4+'Daily-Prod.'!AIK4+'Daily-Prod.'!AIB4+'Daily-Prod.'!AHS4+'Daily-Prod.'!AHJ4+'Daily-Prod.'!AHA4+'Daily-Prod.'!AGR4+'Daily-Prod.'!AGI4+'Daily-Prod.'!AFZ4+'Daily-Prod.'!AFQ4+'Daily-Prod.'!AFH4+'Daily-Prod.'!AEY4+'Daily-Prod.'!AEP4+'Daily-Prod.'!AEG4+'Daily-Prod.'!ADX4)/AI4,"") -> 0.10126582 | AH4: =IFERROR(('Daily-Prod.'!AOK4+'Daily-Prod.'!AOB4+'Daily-Prod.'!ANS4+'Daily-Prod.'!ANJ4+'Daily-Prod.'!ANA4+'Daily-Prod.'!AMR4+'Daily-Prod.'!AMI4+'Daily-Prod.'!ALZ4+'Daily-Prod.'!ALQ4+'Daily-Prod.'!ALH4+'Daily-Prod.'!AKY4+'Daily-Prod.'!AKP4+'Daily-Prod.'!AKG4+'Daily-Prod.'!AJX4+'Daily-Prod.'!AJO4+'Daily-Prod.'!AJF4+'Daily-Prod.'!AIW4+'Daily-Prod.'!AIN4+'Daily-Prod.'!AIE4+'Daily-Prod.'!AHV4+'Daily-Prod.'!AHM4+'Daily-Prod.'!AHD4+'Daily-Prod.'!AGU4+'Daily-Prod.'!AGL4+'Daily-Prod.'!AGC4+'Daily-Prod.'!AFT4+'Daily-Prod.'!AFK4+'Daily-Prod.'!AFB4+'Daily-Prod.'!AES4+'Daily-Prod.'!AEJ4+'Daily-Prod.'!AEA4+'Daily-Prod.'!AOJ4+'Daily-Prod.'!AOA4+'Daily-Prod.'!ANR4+'Daily-Prod.'!ANI4+'Daily-Prod.'!AMZ4+'Daily-Prod.'!AMQ4+'Daily-Prod.'!AMH4+'Daily-Prod.'!ALY4+'Daily-Prod.'!ALP4+'Daily-Prod.'!ALG4+'Daily-Prod.'!AKX4+'Daily-Prod.'!AKO4+'Daily-Prod.'!AKF4+'Daily-Prod.'!AJW4+'Daily-Prod.'!AJN4+'Daily-Prod.'!AJE4+'Daily-Prod.'!AIV4+'Daily-Prod.'!AIM4+'Daily-Prod.'!AID4+'Daily-Prod.'!AHU4+'Daily-Prod.'!AHL4+'Daily-Prod.'!AHC4+'Daily-Prod.'!AGT4+'Daily-Prod.'!AGK4+'Daily-Prod.'!AGB4+'Daily-Prod.'!AFS4+'Daily-Prod.'!AFJ4+'Daily-Prod.'!AFA4+'Daily-Prod.'!AER4+'Daily-Prod.'!AEI4+'Daily-Prod.'!ADZ4)/AI4,"") -> 0.54936709 | AI4: =IFERROR(('Daily-Prod.'!AOL4+'Daily-Prod.'!AOC4+'Daily-Prod.'!ANT4+'Daily-Prod.'!ANK4+'Daily-Prod.'!ANB4+'Daily-Prod.'!AMS4+'Daily-Prod.'!AMJ4+'Daily-Prod.'!AMA4+'Daily-Prod.'!ALR4+'Daily-Prod.'!ALI4+'Daily-Prod.'!AKZ4+'Daily-Prod.'!AKQ4+'Daily-Prod.'!AKH4+'Daily-Prod.'!AJY4+'Daily-Prod.'!AJP4+'Daily-Prod.'!AJG4+'Daily-Prod.'!AIX4+'Daily-Prod.'!AIO4+'Daily-Prod.'!AIF4+'Daily-Prod.'!AHW4+'Daily-Prod.'!AHN4+'Daily-Prod.'!AHE4+'Daily-Prod.'!AGV4+'Daily-Prod.'!AGM4+'Daily-Prod.'!AGD4+'Daily-Prod.'!AFU4+'Daily-Prod.'!AFL4+'Daily-Prod.'!AFC4+'Daily-Prod.'!AET4+'Daily-Prod.'!AEK4+'Daily-Prod.'!AEB4),"") -> 395 | AK4: =IFERROR(('Daily-Prod.'!AON4+'Daily-Prod.'!AOE4+'Daily-Prod.'!ANV4+'Daily-Prod.'!ANM4+'Daily-Prod.'!AND4+'Daily-Prod.'!AMU4+'Daily-Prod.'!AML4+'Daily-Prod.'!AMC4+'Daily-Prod.'!ALT4+'Daily-Prod.'!ALK4+'Daily-Prod.'!ALB4+'Daily-Prod.'!AKS4+'Daily-Prod.'!AKJ4+'Daily-Prod.'!AKA4+'Daily-Prod.'!AJR4+'Daily-Prod.'!AJI4+'Daily-Prod.'!AIZ4+'Daily-Prod.'!AIQ4+'Daily-Prod.'!AIH4+'Daily-Prod.'!AHY4+'Daily-Prod.'!AHP4+'Daily-Prod.'!AHG4+'Daily-Prod.'!AGX4+'Daily-Prod.'!AGO4+'Daily-Prod.'!AGF4+'Daily-Prod.'!AFW4+'Daily-Prod.'!AFN4+'Daily-Prod.'!AFE4+'Daily-Prod.'!AEV4+'Daily-Prod.'!AEM4+'Daily-Prod.'!AED4),"") -> 211 | AL4: =IFERROR((AK4/AJ4),"") | AM4: =IFERROR(AVERAGE('Daily-Prod.'!AOL4,'Daily-Prod.'!AOC4,'Daily-Prod.'!ANT4,'Daily-Prod.'!ANK4,'Daily-Prod.'!ANB4,'Daily-Prod.'!AMS4,'Daily-Prod.'!AMJ4,'Daily-Prod.'!AMA4,'Daily-Prod.'!ALR4,'Daily-Prod.'!ALI4,'Daily-Prod.'!AKZ4,'Daily-Prod.'!AKQ4,'Daily-Prod.'!AKH4,'Daily-Prod.'!AJY4,'Daily-Prod.'!AJP4,'Daily-Prod.'!AJG4,'Daily-Prod.'!AIX4,'Daily-Prod.'!AIO4,'Daily-Prod.'!AIF4,'Daily-Prod.'!AHW4,'Daily-Prod.'!AHN4,'Daily-Prod.'!AHE4,'Daily-Prod.'!AGV4,'Daily-Prod.'!AGM4,'Daily-Prod.'!AGD4,'Daily-Prod.'!AFU4,'Daily-Prod.'!AFL4,'Daily-Prod.'!AFC4,'Daily-Prod.'!AET4,'Daily-Prod.'!AEK4,'Daily-Prod.'!AEB4),"") -> 18.809524 | AO4: =IFERROR(AVERAGE('Daily-Prod.'!AON4,'Daily-Prod.'!AOE4,'Daily-Prod.'!ANV4,'Daily-Prod.'!ANM4,'Daily-Prod.'!AND4,'Daily-Prod.'!AMU4,'Daily-Prod.'!AML4,'Daily-Prod.'!AMC4,'Daily-Prod.'!ALT4,'Daily-Prod.'!ALK4,'Daily-Prod.'!ALB4,'Daily-Prod.'!AKS4,'Daily-Prod.'!AKJ4,'Daily-Prod.'!AKA4,'Daily-Prod.'!AJR4,'Daily-Prod.'!AJI4,'Daily-Prod.'!AIZ4,'Daily-Prod.'!AIQ4,'Daily-Prod.'!AIH4,'Daily-Prod.'!AHY4,'Daily-Prod.'!AHP4,'Daily-Prod.'!AHG4,'Daily-Prod.'!AGX4,'Daily-Prod.'!AGO4,'Daily-Prod.'!AGF4,'Daily-Prod.'!AFW4,'Daily-Prod.'!AFN4,'Daily-Prod.'!AFE4,'Daily-Prod.'!AEV4,'Daily-Prod.'!AEM4,'Daily-Prod.'!AED4),"") -> 10.047619 | AP4: =IFERROR(('Daily-Prod.'!AYZ4+'Daily-Prod.'!AYQ4+'Daily-Prod.'!AYH4+'Daily-Prod.'!AXY4+'Daily-Prod.'!AXP4+'Daily-Prod.'!AXG4+'Daily-Prod.'!AWX4+'Daily-Prod.'!AWO4+'Daily-Prod.'!AWF4+'Daily-Prod.'!AVW4+'Daily-Prod.'!AVN4+'Daily-Prod.'!AVE4+'Daily-Prod.'!AUV4+'Daily-Prod.'!AUM4+'Daily-Prod.'!AUD4+'Daily-Prod.'!ATU4+'Daily-Prod.'!ATL4+'Daily-Prod.'!ATC4+'Daily-Prod.'!AST4+'Daily-Prod.'!ASK4+'Daily-Prod.'!ASB4+'Daily-Prod.'!ARS4+'Daily-Prod.'!ARJ4+'Daily-Prod.'!ARA4+'Daily-Prod.'!AQR4+'Daily-Prod.'!AQI4+'Daily-Prod.'!APZ4+'Daily-Prod.'!APQ4+'Daily-Prod.'!APH4+'Daily-Prod.'!AOY4+'Daily-Prod.'!AOP4)/AS4,"") -> 0.44117647 | AQ4: =IFERROR(('Daily-Prod.'!AZA4+'Daily-Prod.'!AYR4+'Daily-Prod.'!AYI4+'Daily-Prod.'!AXZ4+'Daily-Prod.'!AXQ4+'Daily-Prod.'!AXH4+'Daily-Prod.'!AWY4+'Daily-Prod.'!AWP4+'Daily-Prod.'!AWG4+'Daily-Prod.'!AVX4+'Daily-Prod.'!AVO4+'Daily-Prod.'!AVF4+'Daily-Prod.'!AUW4+'Daily-Prod.'!AUN4+'Daily-Prod.'!AUE4+'Daily-Prod.'!ATV4+'Daily-Prod.'!ATM4+'Daily-Prod.'!ATD4+'Daily-Prod.'!ASU4+'Daily-Prod.'!ASL4+'Daily-Prod.'!ASC4+'Daily-Prod.'!ART4+'Daily-Prod.'!ARK4+'Daily-Prod.'!ARB4+'Daily-Prod.'!AQS4+'Daily-Prod.'!AQJ4+'Daily-Prod.'!AQA4+'Daily-Prod.'!APR4+'Daily-Prod.'!API4+'Daily-Prod.'!AOZ4+'Daily-Prod.'!AOQ4)/AS4,"") -> 0.029411765 | AR4: =IFERROR(('Daily-Prod.'!AZC4+'Daily-Prod.'!AYT4+'Daily-Prod.'!AYK4+'Daily-Prod.'!AYB4+'Daily-Prod.'!AXS4+'Daily-Prod.'!AXJ4+'Daily-Prod.'!AXA4+'Daily-Prod.'!AWR4+'Daily-Prod.'!AWI4+'Daily-Prod.'!AVZ4+'Daily-Prod.'!AVQ4+'Daily-Prod.'!AVH4+'Daily-Prod.'!AUY4+'Daily-Prod.'!AUP4+'Daily-Prod.'!AUG4+'Daily-Prod.'!ATX4+'Daily-Prod.'!ATO4+'Daily-Prod.'!ATF4+'Daily-Prod.'!ASW4+'Daily-Prod.'!ASN4+'Daily-Prod.'!ASE4+'Daily-Prod.'!ARV4+'Daily-Prod.'!ARM4+'Daily-Prod.'!ARD4+'Daily-Prod.'!AQU4+'Daily-Prod.'!AQL4+'Daily-Prod.'!AQC4+'Daily-Prod.'!APT4+'Daily-Prod.'!APK4+'Daily-Prod.'!APB4+'Daily-Prod.'!AOS4+'Daily-Prod.'!AZD4+'Daily-Prod.'!AYU4+'Daily-Prod.'!AYL4+'Daily-Prod.'!AYC4+'Daily-Prod.'!AXT4+'Daily-Prod.'!AXK4+'Daily-Prod.'!AXB4+'Daily-Prod.'!AWS4+'Daily-Prod.'!AWJ4+'Daily-Prod.'!AWA4+'Daily-Prod.'!AVR4+'Daily-Prod.'!AVI4+'Daily-Prod.'!AUZ4+'Daily-Prod.'!AUQ4+'Daily-Prod.'!AUH4+'Daily-Prod.'!ATY4+'Daily-Prod.'!ATP4+'Daily-Prod.'!ATG4+'Daily-Prod.'!ASX4+'Daily-Prod.'!ASO4+'Daily-Prod.'!ASF4+'Daily-Prod.'!ARW4+'Daily-Prod.'!ARN4+'Daily-Prod.'!ARE4+'Daily-Prod.'!AQV4+'Daily-Prod.'!AQM4+'Daily-Prod.'!AQD4+'Daily-Prod.'!APU4+'Daily-Prod.'!APL4+'Daily-Prod.'!APC4+'Daily-Prod.'!AOT4)/AS4,"") -> 0.52941176 | AS4: =IFERROR(('Daily-Prod.'!AZE4+'Daily-Prod.'!AYV4+'Daily-Prod.'!AYM4+'Daily-Prod.'!AYD4+'Daily-Prod.'!AXU4+'Daily-Prod.'!AXL4+'Daily-Prod.'!AXC4+'Daily-Prod.'!AWT4+'Daily-Prod.'!AWK4+'Daily-Prod.'!AWB4+'Daily-Prod.'!AVS4+'Daily-Prod.'!AVJ4+'Daily-Prod.'!AVA4+'Daily-Prod.'!AUR4+'Daily-Prod.'!AUI4+'Daily-Prod.'!ATZ4+'Daily-Prod.'!ATQ4+'Daily-Prod.'!ATH4+'Daily-Prod.'!ASY4+'Daily-Prod.'!ASP4+'Daily-Prod.'!ASG4+'Daily-Prod.'!ARX4+'Daily-Prod.'!ARO4+'Daily-Prod.'!ARF4+'Daily-Prod.'!AQW4+'Daily-Prod.'!AQN4+'Daily-Prod.'!AQE4+'Daily-Prod.'!APV4+'Daily-Prod.'!APM4+'Daily-Prod.'!APD4+'Daily-Prod.'!AOU4),"") -> 34 | AU4: =IFERROR(('Daily-Prod.'!AZG4+'Daily-Prod.'!AYX4+'Daily-Prod.'!AYO4+'Daily-Prod.'!AYF4+'Daily-Prod.'!AXW4+'Daily-Prod.'!AXN4+'Daily-Prod.'!AXE4+'Daily-Prod.'!AWV4+'Daily-Prod.'!AWM4+'Daily-Prod.'!AWD4+'Daily-Prod.'!AVU4+'Daily-Prod.'!AVL4+'Daily-Prod.'!AVC4+'Daily-Prod.'!AUT4+'Daily-Prod.'!AUK4+'Daily-Prod.'!AUB4+'Daily-Prod.'!ATS4+'Daily-Prod.'!ATJ4+'Daily-Prod.'!ATA4+'Daily-Prod.'!ASR4+'Daily-Prod.'!ASI4+'Daily-Prod.'!ARZ4+'Daily-Prod.'!ARQ4+'Daily-Prod.'!ARH4+'Daily-Prod.'!AQY4+'Daily-Prod.'!AQP4+'Daily-Prod.'!AQG4+'Daily-Prod.'!APX4+'Daily-Prod.'!APO4+'Daily-Prod.'!APF4+'Daily-Prod.'!AOW4),"") -> 7 | AV4: =IFERROR((AU4/AT4),"")
A5: Azzeddine BOUHLAL | B5: =IFERROR(('Daily-Prod.'!JC5+'Daily-Prod.'!IT5+'Daily-Prod.'!IK5+'Daily-Prod.'!IB5+'Daily-Prod.'!HS5+'Daily-Prod.'!HJ5+'Daily-Prod.'!HA5+'Daily-Prod.'!GR5+'Daily-Prod.'!GI5+'Daily-Prod.'!FZ5+'Daily-Prod.'!FQ5+'Daily-Prod.'!FH5+'Daily-Prod.'!EY5+'Daily-Prod.'!EP5+'Daily-Prod.'!EG5+'Daily-Prod.'!DX5+'Daily-Prod.'!DO5+'Daily-Prod.'!DF5+'Daily-Prod.'!CW5+'Daily-Prod.'!CN5+'Daily-Prod.'!CE5+'Daily-Prod.'!BV5+'Daily-Prod.'!BM5+'Daily-Prod.'!BD5+'Daily-Prod.'!AU5+'Daily-Prod.'!AL5+'Daily-Prod.'!AC5+'Daily-Prod.'!T5+'Daily-Prod.'!K5+'Daily-Prod.'!B5)/E5,"") -> 0.64119601 | C5: =IFERROR(('Daily-Prod.'!JD5+'Daily-Prod.'!IU5+'Daily-Prod.'!IL5+'Daily-Prod.'!IC5+'Daily-Prod.'!HT5+'Daily-Prod.'!HK5+'Daily-Prod.'!HB5+'Daily-Prod.'!GS5+'Daily-Prod.'!GJ5+'Daily-Prod.'!GA5+'Daily-Prod.'!FR5+'Daily-Prod.'!FI5+'Daily-Prod.'!EZ5+'Daily-Prod.'!EQ5+'Daily-Prod.'!EH5+'Daily-Prod.'!DY5+'Daily-Prod.'!DP5+'Daily-Prod.'!DG5+'Daily-Prod.'!CX5+'Daily-Prod.'!CO5+'Daily-Prod.'!CF5+'Daily-Prod.'!BW5+'Daily-Prod.'!BN5+'Daily-Prod.'!BE5+'Daily-Prod.'!AV5+'Daily-Prod.'!AM5+'Daily-Prod.'!AD5+'Daily-Prod.'!U5+'Daily-Prod.'!L5+'Daily-Prod.'!C5)/E5,"") -> 0.059800664 | D5: =IFERROR(('Daily-Prod.'!JF5+'Daily-Prod.'!IW5+'Daily-Prod.'!IN5+'Daily-Prod.'!IE5+'Daily-Prod.'!HV5+'Daily-Prod.'!HM5+'Daily-Prod.'!HD5+'Daily-Prod.'!GU5+'Daily-Prod.'!GL5+'Daily-Prod.'!GC5+'Daily-Prod.'!FT5+'Daily-Prod.'!FK5+'Daily-Prod.'!FB5+'Daily-Prod.'!ES5+'Daily-Prod.'!EJ5+'Daily-Prod.'!EA5+'Daily-Prod.'!DR5+'Daily-Prod.'!DI5+'Daily-Prod.'!CZ5+'Daily-Prod.'!CQ5+'Daily-Prod.'!CH5+'Daily-Prod.'!BY5+'Daily-Prod.'!BP5+'Daily-Prod.'!BG5+'Daily-Prod.'!AX5+'Daily-Prod.'!AO5+'Daily-Prod.'!AF5+'Daily-Prod.'!W5+'Daily-Prod.'!N5+'Daily-Prod.'!E5+'Daily-Prod.'!JG5+'Daily-Prod.'!IX5+'Daily-Prod.'!IO5+'Daily-Prod.'!IF5+'Daily-Prod.'!HW5+'Daily-Prod.'!HN5+'Daily-Prod.'!HE5+'Daily-Prod.'!GV5+'Daily-Prod.'!GM5+'Daily-Prod.'!GD5+'Daily-Prod.'!FU5+'Daily-Prod.'!FL5+'Daily-Prod.'!FC5+'Daily-Prod.'!ET5+'Daily-Prod.'!EK5+'Daily-Prod.'!EB5+'Daily-Prod.'!DS5+'Daily-Prod.'!DJ5+'Daily-Prod.'!DA5+'Daily-Prod.'!CR5+'Daily-Prod.'!CI5+'Daily-Prod.'!BZ5+'Daily-Prod.'!BQ5+'Daily-Prod.'!BH5+'Daily-Prod.'!AY5+'Daily-Prod.'!AP5+'Daily-Prod.'!AG5+'Daily-Prod.'!X5+'Daily-Prod.'!O5+'Daily-Prod.'!F5)/E5,"") -> 0.29900332 | E5: =IFERROR(('Daily-Prod.'!JH5+'Daily-Prod.'!IY5+'Daily-Prod.'!IP5+'Daily-Prod.'!IG5+'Daily-Prod.'!HX5+'Daily-Prod.'!HO5+'Daily-Prod.'!HF5+'Daily-Prod.'!GW5+'Daily-Prod.'!GN5+'Daily-Prod.'!GE5+'Daily-Prod.'!FV5+'Daily-Prod.'!FM5+'Daily-Prod.'!FD5+'Daily-Prod.'!EU5+'Daily-Prod.'!EL5+'Daily-Prod.'!EC5+'Daily-Prod.'!DT5+'Daily-Prod.'!DK5+'Daily-Prod.'!DB5+'Daily-Prod.'!CS5+'Daily-Prod.'!CJ5+'Daily-Prod.'!CA5+'Daily-Prod.'!BR5+'Daily-Prod.'!BI5+'Daily-Prod.'!AZ5+'Daily-Prod.'!AQ5+'Daily-Prod.'!AH5+'Daily-Prod.'!Y5+'Daily-Prod.'!P5+'Daily-Prod.'!G5),"") -> 301 | G5: =IFERROR(('Daily-Prod.'!JJ5+'Daily-Prod.'!JA5+'Daily-Prod.'!IR5+'Daily-Prod.'!II5+'Daily-Prod.'!HZ5+'Daily-Prod.'!HQ5+'Daily-Prod.'!HH5+'Daily-Prod.'!GY5+'Daily-Prod.'!GP5+'Daily-Prod.'!GG5+'Daily-Prod.'!FX5+'Daily-Prod.'!FO5+'Daily-Prod.'!FF5+'Daily-Prod.'!EW5+'Daily-Prod.'!EN5+'Daily-Prod.'!EE5+'Daily-Prod.'!DV5+'Daily-Prod.'!DM5+'Daily-Prod.'!DD5+'Daily-Prod.'!CU5+'Daily-Prod.'!CL5+'Daily-Prod.'!CC5+'Daily-Prod.'!BT5+'Daily-Prod.'!BK5+'Daily-Prod.'!BB5+'Daily-Prod.'!AS5+'Daily-Prod.'!AJ5+'Daily-Prod.'!AA5+'Daily-Prod.'!R5+'Daily-Prod.'!I5),"") -> 58 | H5: =IFERROR((G5/F5),"") | I5: =IFERROR(AVERAGE('Daily-Prod.'!JH5,'Daily-Prod.'!IY5,'Daily-Prod.'!IP5,'Daily-Prod.'!IG5,'Daily-Prod.'!HX5,'Daily-Prod.'!HO5,'Daily-Prod.'!HF5,'Daily-Prod.'!GW5,'Daily-Prod.'!GN5,'Daily-Prod.'!GE5,'Daily-Prod.'!FV5,'Daily-Prod.'!FM5,'Daily-Prod.'!FD5,'Daily-Prod.'!EU5,'Daily-Prod.'!EL5,'Daily-Prod.'!EC5,'Daily-Prod.'!DT5,'Daily-Prod.'!DK5,'Daily-Prod.'!DB5,'Daily-Prod.'!CS5,'Daily-Prod.'!CJ5,'Daily-Prod.'!CA5,'Daily-Prod.'!BR5,'Daily-Prod.'!BI5,'Daily-Prod.'!AZ5,'Daily-Prod.'!AQ5,'Daily-Prod.'!AH5,'Daily-Prod.'!Y5,'Daily-Prod.'!P5,'Daily-Prod.'!G5),"") -> 15.05 | J5: =IFERROR(AVERAGE('Daily-Prod.'!JI5,'Daily-Prod.'!IZ5,'Daily-Prod.'!IQ5,'Daily-Prod.'!IH5,'Daily-Prod.'!HY5,'Daily-Prod.'!HP5,'Daily-Prod.'!HG5,'Daily-Prod.'!GX5,'Daily-Prod.'!GO5,'Daily-Prod.'!GF5,'Daily-Prod.'!FW5,'Daily-Prod.'!FN5,'Daily-Prod.'!FE5,'Daily-Prod.'!EV5,'Daily-Prod.'!EM5,'Daily-Prod.'!ED5,'Daily-Prod.'!DU5,'Daily-Prod.'!DL5,'Daily-Prod.'!DC5,'Daily-Prod.'!CT5,'Daily-Prod.'!CK5,'Daily-Prod.'!CB5,'Daily-Prod.'!BS5,'Daily-Prod.'!BJ5,'Daily-Prod.'!BA5,'Daily-Prod.'!AR5,'Daily-Prod.'!AI5,'Daily-Prod.'!Z5,'Daily-Prod.'!Q5,'Daily-Prod.'!H5),"") | K5: =IFERROR(AVERAGE('Daily-Prod.'!JJ5,'Daily-Prod.'!JA5,'Daily-Prod.'!IR5,'Daily-Prod.'!II5,'Daily-Prod.'!HZ5,'Daily-Prod.'!HQ5,'Daily-Prod.'!HH5,'Daily-Prod.'!GY5,'Daily-Prod.'!GP5,'Daily-Prod.'!GG5,'Daily-Prod.'!FX5,'Daily-Prod.'!FO5,'Daily-Prod.'!FF5,'Daily-Prod.'!EW5,'Daily-Prod.'!EN5,'Daily-Prod.'!EE5,'Daily-Prod.'!DV5,'Daily-Prod.'!DM5,'Daily-Prod.'!DD5,'Daily-Prod.'!CU5,'Daily-Prod.'!CL5,'Daily-Prod.'!CC5,'Daily-Prod.'!BT5,'Daily-Prod.'!BK5,'Daily-Prod.'!BB5,'Daily-Prod.'!AS5,'Daily-Prod.'!AJ5,'Daily-Prod.'!AA5,'Daily-Prod.'!R5,'Daily-Prod.'!I5),"") -> 4.4615385 | L5: =IFERROR(('Daily-Prod.'!TV5+'Daily-Prod.'!TM5+'Daily-Prod.'!TD5+'Daily-Prod.'!SU5+'Daily-Prod.'!SL5+'Daily-Prod.'!SC5+'Daily-Prod.'!RT5+'Daily-Prod.'!RK5+'Daily-Prod.'!RB5+'Daily-Prod.'!QS5+'Daily-Prod.'!QJ5+'Daily-Prod.'!QA5+'Daily-Prod.'!PR5+'Daily-Prod.'!PI5+'Daily-Prod.'!OZ5+'Daily-Prod.'!OQ5+'Daily-Prod.'!OH5+'Daily-Prod.'!NY5+'Daily-Prod.'!NP5+'Daily-Prod.'!NG5+'Daily-Prod.'!MX5+'Daily-Prod.'!MO5+'Daily-Prod.'!MF5+'Daily-Prod.'!LW5+'Daily-Prod.'!LN5+'Daily-Prod.'!LE5+'Daily-Prod.'!KV5+'Daily-Prod.'!KM5+'Daily-Prod.'!KD5+'Daily-Prod.'!JU5+'Daily-Prod.'!JL5)/O5,"") -> 0.61764706 | M5: =IFERROR(('Daily-Prod.'!TW5+'Daily-Prod.'!TN5+'Daily-Prod.'!TE5+'Daily-Prod.'!SV5+'Daily-Prod.'!SM5+'Daily-Prod.'!SD5+'Daily-Prod.'!RU5+'Daily-Prod.'!RL5+'Daily-Prod.'!RC5+'Daily-Prod.'!QT5+'Daily-Prod.'!QK5+'Daily-Prod.'!QB5+'Daily-Prod.'!PS5+'Daily-Prod.'!PJ5+'Daily-Prod.'!PA5+'Daily-Prod.'!OR5+'Daily-Prod.'!OI5+'Daily-Prod.'!NZ5+'Daily-Prod.'!NQ5+'Daily-Prod.'!NH5+'Daily-Prod.'!MY5+'Daily-Prod.'!MP5+'Daily-Prod.'!MG5+'Daily-Prod.'!LX5+'Daily-Prod.'!LO5+'Daily-Prod.'!LF5+'Daily-Prod.'!KW5+'Daily-Prod.'!KN5+'Daily-Prod.'!KE5+'Daily-Prod.'!JV5+'Daily-Prod.'!JM5)/O5,"") -> 0.048128342 | N5: =IFERROR(('Daily-Prod.'!TY5+'Daily-Prod.'!TP5+'Daily-Prod.'!TG5+'Daily-Prod.'!SX5+'Daily-Prod.'!SO5+'Daily-Prod.'!SF5+'Daily-Prod.'!RW5+'Daily-Prod.'!RN5+'Daily-Prod.'!RE5+'Daily-Prod.'!QV5+'Daily-Prod.'!QM5+'Daily-Prod.'!QD5+'Daily-Prod.'!PU5+'Daily-Prod.'!PL5+'Daily-Prod.'!PC5+'Daily-Prod.'!OT5+'Daily-Prod.'!OK5+'Daily-Prod.'!OB5+'Daily-Prod.'!NS5+'Daily-Prod.'!NJ5+'Daily-Prod.'!NA5+'Daily-Prod.'!MR5+'Daily-Prod.'!MI5+'Daily-Prod.'!LZ5+'Daily-Prod.'!LQ5+'Daily-Prod.'!LH5+'Daily-Prod.'!KY5+'Daily-Prod.'!KP5+'Daily-Prod.'!KG5+'Daily-Prod.'!JX5+'Daily-Prod.'!JO5+'Daily-Prod.'!TZ5+'Daily-Prod.'!TQ5+'Daily-Prod.'!TH5+'Daily-Prod.'!SY5+'Daily-Prod.'!SP5+'Daily-Prod.'!SG5+'Daily-Prod.'!RX5+'Daily-Prod.'!RO5+'Daily-Prod.'!RF5+'Daily-Prod.'!QW5+'Daily-Prod.'!QN5+'Daily-Prod.'!QE5+'Daily-Prod.'!PV5+'Daily-Prod.'!PM5+'Daily-Prod.'!PD5+'Daily-Prod.'!OU5+'Daily-Prod.'!OL5+'Daily-Prod.'!OC5+'Daily-Prod.'!NT5+'Daily-Prod.'!NK5+'Daily-Prod.'!NB5+'Daily-Prod.'!MS5+'Daily-Prod.'!MJ5+'Daily-Prod.'!MA5+'Daily-Prod.'!LR5+'Daily-Prod.'!LI5+'Daily-Prod.'!KZ5+'Daily-Prod.'!KQ5+'Daily-Prod.'!KH5+'Daily-Prod.'!JY5+'Daily-Prod.'!JP5)/O5,"") -> 0.3342246 | O5: =IFERROR(('Daily-Prod.'!UA5+'Daily-Prod.'!TR5+'Daily-Prod.'!TI5+'Daily-Prod.'!SZ5+'Daily-Prod.'!SQ5+'Daily-Prod.'!SH5+'Daily-Prod.'!RY5+'Daily-Prod.'!RP5+'Daily-Prod.'!RG5+'Daily-Prod.'!QX5+'Daily-Prod.'!QO5+'Daily-Prod.'!QF5+'Daily-Prod.'!PW5+'Daily-Prod.'!PN5+'Daily-Prod.'!PE5+'Daily-Prod.'!OV5+'Daily-Prod.'!OM5+'Daily-Prod.'!OD5+'Daily-Prod.'!NU5+'Daily-Prod.'!NL5+'Daily-Prod.'!NC5+'Daily-Prod.'!MT5+'Daily-Prod.'!MK5+'Daily-Prod.'!MB5+'Daily-Prod.'!LS5+'Daily-Prod.'!LJ5+'Daily-Prod.'!LA5+'Daily-Prod.'!KR5+'Daily-Prod.'!KI5+'Daily-Prod.'!JZ5+'Daily-Prod.'!JQ5),"") -> 374 | Q5: =IFERROR(('Daily-Prod.'!UC5+'Daily-Prod.'!TT5+'Daily-Prod.'!TK5+'Daily-Prod.'!TB5+'Daily-Prod.'!SS5+'Daily-Prod.'!SJ5+'Daily-Prod.'!SA5+'Daily-Prod.'!RR5+'Daily-Prod.'!RI5+'Daily-Prod.'!QZ5+'Daily-Prod.'!QQ5+'Daily-Prod.'!QH5+'Daily-Prod.'!PY5+'Daily-Prod.'!PP5+'Daily-Prod.'!PG5+'Daily-Prod.'!OX5+'Daily-Prod.'!OO5+'Daily-Prod.'!OF5+'Daily-Prod.'!NW5+'Daily-Prod.'!NN5+'Daily-Prod.'!NE5+'Daily-Prod.'!MV5+'Daily-Prod.'!MM5+'Daily-Prod.'!MD5+'Daily-Prod.'!LU5+'Daily-Prod.'!LL5+'Daily-Prod.'!LC5+'Daily-Prod.'!KT5+'Daily-Prod.'!KK5+'Daily-Prod.'!KB5+'Daily-Prod.'!JS5),"") -> 106 | R5: =IFERROR((Q5/P5),"") | S5: =IFERROR(AVERAGE('Daily-Prod.'!TR5,'Daily-Prod.'!UA5,'Daily-Prod.'!TI5,'Daily-Prod.'!SZ5,'Daily-Prod.'!SQ5,'Daily-Prod.'!SH5,'Daily-Prod.'!RY5,'Daily-Prod.'!RP5,'Daily-Prod.'!RG5,'Daily-Prod.'!QX5,'Daily-Prod.'!QO5,'Daily-Prod.'!QF5,'Daily-Prod.'!PW5,'Daily-Prod.'!PN5,'Daily-Prod.'!PE5,'Daily-Prod.'!OV5,'Daily-Prod.'!OM5,'Daily-Prod.'!OD5,'Daily-Prod.'!NU5,'Daily-Prod.'!NL5,'Daily-Prod.'!NC5,'Daily-Prod.'!MT5,'Daily-Prod.'!MK5,'Daily-Prod.'!MB5,'Daily-Prod.'!LS5,'Daily-Prod.'!LJ5,'Daily-Prod.'!LA5,'Daily-Prod.'!KR5,'Daily-Prod.'!KI5,'Daily-Prod.'!JZ5),"") -> 16.571429 | T5: =IFERROR(AVERAGE('Daily-Prod.'!TS5,'Daily-Prod.'!UB5,'Daily-Prod.'!TJ5,'Daily-Prod.'!TA5,'Daily-Prod.'!SR5,'Daily-Prod.'!SI5,'Daily-Prod.'!RZ5,'Daily-Prod.'!RQ5,'Daily-Prod.'!RH5,'Daily-Prod.'!QY5,'Daily-Prod.'!QP5,'Daily-Prod.'!QG5,'Daily-Prod.'!PX5,'Daily-Prod.'!PO5,'Daily-Prod.'!PF5,'Daily-Prod.'!OW5,'Daily-Prod.'!ON5,'Daily-Prod.'!OE5,'Daily-Prod.'!NV5,'Daily-Prod.'!NM5,'Daily-Prod.'!ND5,'Daily-Prod.'!MU5,'Daily-Prod.'!ML5,'Daily-Prod.'!MC5,'Daily-Prod.'!LT5,'Daily-Prod.'!LK5,'Daily-Prod.'!LB5,'Daily-Prod.'!KS5,'Daily-Prod.'!KJ5,'Daily-Prod.'!KA5),"") | U5: =IFERROR(AVERAGE('Daily-Prod.'!TT5,'Daily-Prod.'!UC5,'Daily-Prod.'!TK5,'Daily-Prod.'!TB5,'Daily-Prod.'!SS5,'Daily-Prod.'!SJ5,'Daily-Prod.'!SA5,'Daily-Prod.'!RR5,'Daily-Prod.'!RI5,'Daily-Prod.'!QZ5,'Daily-Prod.'!QQ5,'Daily-Prod.'!QH5,'Daily-Prod.'!PY5,'Daily-Prod.'!PP5,'Daily-Prod.'!PG5,'Daily-Prod.'!OX5,'Daily-Prod.'!OO5,'Daily-Prod.'!OF5,'Daily-Prod.'!NW5,'Daily-Prod.'!NN5,'Daily-Prod.'!NE5,'Daily-Prod.'!MV5,'Daily-Prod.'!MM5,'Daily-Prod.'!MD5,'Daily-Prod.'!LU5,'Daily-Prod.'!LL5,'Daily-Prod.'!LC5,'Daily-Prod.'!KT5,'Daily-Prod.'!KK5,'Daily-Prod.'!KB5),"") -> 4.6363636 | V5: =IFERROR(('Daily-Prod.'!ADN5+'Daily-Prod.'!ADE5+'Daily-Prod.'!ACV5+'Daily-Prod.'!ACM5+'Daily-Prod.'!ACD5+'Daily-Prod.'!ABU5+'Daily-Prod.'!ABL5+'Daily-Prod.'!ABC5+'Daily-Prod.'!AAT5+'Daily-Prod.'!AAK5+'Daily-Prod.'!AAB5+'Daily-Prod.'!ZS5+'Daily-Prod.'!ZJ5+'Daily-Prod.'!ZA5+'Daily-Prod.'!YR5+'Daily-Prod.'!YI5+'Daily-Prod.'!XZ5+'Daily-Prod.'!XQ5+'Daily-Prod.'!XH5+'Daily-Prod.'!WY5+'Daily-Prod.'!WP5+'Daily-Prod.'!WG5+'Daily-Prod.'!VX5+'Daily-Prod.'!VO5+'Daily-Prod.'!VF5+'Daily-Prod.'!UW5+'Daily-Prod.'!UN5+'Daily-Prod.'!UE5)/Y5,"") -> 0.55737705 | W5: =IFERROR(('Daily-Prod.'!ADO5+'Daily-Prod.'!ADF5+'Daily-Prod.'!ACW5+'Daily-Prod.'!ACN5+'Daily-Prod.'!ACE5+'Daily-Prod.'!ABV5+'Daily-Prod.'!ABM5+'Daily-Prod.'!ABD5+'Daily-Prod.'!AAU5+'Daily-Prod.'!AAL5+'Daily-Prod.'!AAC5+'Daily-Prod.'!ZT5+'Daily-Prod.'!ZK5+'Daily-Prod.'!ZB5+'Daily-Prod.'!YS5+'Daily-Prod.'!YJ5+'Daily-Prod.'!YA5+'Daily-Prod.'!XR5+'Daily-Prod.'!XI5+'Daily-Prod.'!WZ5+'Daily-Prod.'!WQ5+'Daily-Prod.'!WH5+'Daily-Prod.'!VY5+'Daily-Prod.'!VP5+'Daily-Prod.'!VG5+'Daily-Prod.'!UX5+'Daily-Prod.'!UO5+'Daily-Prod.'!UF5)/Y5,"") -> 0.073770492 | X5: =IFERROR(('Daily-Prod.'!ADR5+'Daily-Prod.'!ADI5+'Daily-Prod.'!ACZ5+'Daily-Prod.'!ACQ5+'Daily-Prod.'!ACH5+'Daily-Prod.'!ABY5+'Daily-Prod.'!ABP5+'Daily-Prod.'!ABG5+'Daily-Prod.'!AAX5+'Daily-Prod.'!AAO5+'Daily-Prod.'!AAF5+'Daily-Prod.'!ZW5+'Daily-Prod.'!ZN5+'Daily-Prod.'!ZE5+'Daily-Prod.'!YV5+'Daily-Prod.'!YM5+'Daily-Prod.'!YD5+'Daily-Prod.'!XU5+'Daily-Prod.'!XL5+'Daily-Prod.'!XC5+'Daily-Prod.'!WT5+'Daily-Prod.'!WK5+'Daily-Prod.'!WB5+'Daily-Prod.'!VS5+'Daily-Prod.'!VJ5+'Daily-Prod.'!VA5+'Daily-Prod.'!UR5+'Daily-Prod.'!UI5+'Daily-Prod.'!ADQ5+'Daily-Prod.'!ADH5+'Daily-Prod.'!ACY5+'Daily-Prod.'!ACP5+'Daily-Prod.'!ACG5+'Daily-Prod.'!ABX5+'Daily-Prod.'!ABO5+'Daily-Prod.'!ABF5+'Daily-Prod.'!AAW5+'Daily-Prod.'!AAN5+'Daily-Prod.'!AAE5+'Daily-Prod.'!ZV5+'Daily-Prod.'!ZM5+'Daily-Prod.'!ZD5+'Daily-Prod.'!YU5+'Daily-Prod.'!YL5+'Daily-Prod.'!YC5+'Daily-Prod.'!XT5+'Daily-Prod.'!XK5+'Daily-Prod.'!XB5+'Daily-Prod.'!WS5+'Daily-Prod.'!WJ5+'Daily-Prod.'!WA5+'Daily-Prod.'!VR5+'Daily-Prod.'!VI5+'Daily-Prod.'!UZ5+'Daily-Prod.'!UQ5+'Daily-Prod.'!UH5)/Y5,"") -> 0.36885246 | Y5: =IFERROR(('Daily-Prod.'!ADS5+'Daily-Prod.'!ADJ5+'Daily-Prod.'!ADA5+'Daily-Prod.'!ACR5+'Daily-Prod.'!ACI5+'Daily-Prod.'!ABZ5+'Daily-Prod.'!ABQ5+'Daily-Prod.'!ABH5+'Daily-Prod.'!AAY5+'Daily-Prod.'!AAP5+'Daily-Prod.'!AAG5+'Daily-Prod.'!ZX5+'Daily-Prod.'!ZO5+'Daily-Prod.'!ZF5+'Daily-Prod.'!YW5+'Daily-Prod.'!YN5+'Daily-Prod.'!YE5+'Daily-Prod.'!XV5+'Daily-Prod.'!XM5+'Daily-Prod.'!XD5+'Daily-Prod.'!WU5+'Daily-Prod.'!WL5+'Daily-Prod.'!WC5+'Daily-Prod.'!VT5+'Daily-Prod.'!VK5+'Daily-Prod.'!VB5+'Daily-Prod.'!US5+'Daily-Prod.'!UJ5),"") -> 244 | AA5: =IFERROR(('Daily-Prod.'!ADU5+'Daily-Prod.'!ADL5+'Daily-Prod.'!ADC5+'Daily-Prod.'!ACT5+'Daily-Prod.'!ACK5+'Daily-Prod.'!ACB5+'Daily-Prod.'!ABS5+'Daily-Prod.'!ABJ5+'Daily-Prod.'!ABA5+'Daily-Prod.'!AAR5+'Daily-Prod.'!AAI5+'Daily-Prod.'!ZZ5+'Daily-Prod.'!ZQ5+'Daily-Prod.'!ZH5+'Daily-Prod.'!YY5+'Daily-Prod.'!YP5+'Daily-Prod.'!YG5+'Daily-Prod.'!XX5+'Daily-Prod.'!XO5+'Daily-Prod.'!XF5+'Daily-Prod.'!WW5+'Daily-Prod.'!WN5+'Daily-Prod.'!WE5+'Daily-Prod.'!VV5+'Daily-Prod.'!VM5+'Daily-Prod.'!VD5+'Daily-Prod.'!UU5+'Daily-Prod.'!UL5),"") -> 28 | AB5: =IFERROR((AA5/Z5),"") | AC5: =IFERROR(AVERAGE('Daily-Prod.'!ADS5,'Daily-Prod.'!ADJ5,'Daily-Prod.'!ADA5,'Daily-Prod.'!ACR5,'Daily-Prod.'!ACI5,'Daily-Prod.'!ABZ5,'Daily-Prod.'!ABQ5,'Daily-Prod.'!ABH5,'Daily-Prod.'!AAY5,'Daily-Prod.'!AAP5,'Daily-Prod.'!AAG5,'Daily-Prod.'!ZX5,'Daily-Prod.'!ZO5,'Daily-Prod.'!ZF5,'Daily-Prod.'!YW5,'Daily-Prod.'!YN5,'Daily-Prod.'!YE5,'Daily-Prod.'!XV5,'Daily-Prod.'!XM5,'Daily-Prod.'!XD5,'Daily-Prod.'!WU5,'Daily-Prod.'!WL5,'Daily-Prod.'!WC5,'Daily-Prod.'!VT5,'Daily-Prod.'!VK5,'Daily-Prod.'!VB5,'Daily-Prod.'!US5,'Daily-Prod.'!UJ5),"") -> 12.842105 | AE5: =IFERROR(AVERAGE('Daily-Prod.'!ADU5,'Daily-Prod.'!ADL5,'Daily-Prod.'!ADC5,'Daily-Prod.'!ACT5,'Daily-Prod.'!ACK5,'Daily-Prod.'!ACB5,'Daily-Prod.'!ABS5,'Daily-Prod.'!ABJ5,'Daily-Prod.'!ABA5,'Daily-Prod.'!AAR5,'Daily-Prod.'!AAI5,'Daily-Prod.'!ZZ5,'Daily-Prod.'!ZQ5,'Daily-Prod.'!ZH5,'Daily-Prod.'!YY5,'Daily-Prod.'!YP5,'Daily-Prod.'!YG5,'Daily-Prod.'!XX5,'Daily-Prod.'!XO5,'Daily-Prod.'!XF5,'Daily-Prod.'!WW5,'Daily-Prod.'!WN5,'Daily-Prod.'!WE5,'Daily-Prod.'!VV5,'Daily-Prod.'!VM5,'Daily-Prod.'!VD5,'Daily-Prod.'!UU5,'Daily-Prod.'!UL5),"") -> 1.6470588 | AF5: =IFERROR(('Daily-Prod.'!AOG5+'Daily-Prod.'!ANX5+'Daily-Prod.'!ANO5+'Daily-Prod.'!ANF5+'Daily-Prod.'!AMW5+'Daily-Prod.'!AMN5+'Daily-Prod.'!AME5+'Daily-Prod.'!ALV5+'Daily-Prod.'!ALM5+'Daily-Prod.'!ALD5+'Daily-Prod.'!AKU5+'Daily-Prod.'!AKL5+'Daily-Prod.'!AKC5+'Daily-Prod.'!AJT5+'Daily-Prod.'!AJK5+'Daily-Prod.'!AJB5+'Daily-Prod.'!AIS5+'Daily-Prod.'!AIJ5+'Daily-Prod.'!AIA5+'Daily-Prod.'!AHR5+'Daily-Prod.'!AHI5+'Daily-Prod.'!AGZ5+'Daily-Prod.'!AGQ5+'Daily-Prod.'!AGH5+'Daily-Prod.'!AFY5+'Daily-Prod.'!AFP5+'Daily-Prod.'!AFG5+'Daily-Prod.'!AEX5+'Daily-Prod.'!AEO5+'Daily-Prod.'!AEF5+'Daily-Prod.'!ADW5)/AI5,"") -> 0.64258555 | AG5: =IFERROR(('Daily-Prod.'!AOH5+'Daily-Prod.'!ANY5+'Daily-Prod.'!ANP5+'Daily-Prod.'!ANG5+'Daily-Prod.'!AMX5+'Daily-Prod.'!AMO5+'Daily-Prod.'!AMF5+'Daily-Prod.'!ALW5+'Daily-Prod.'!ALN5+'Daily-Prod.'!ALE5+'Daily-Prod.'!AKV5+'Daily-Prod.'!AKM5+'Daily-Prod.'!AKD5+'Daily-Prod.'!AJU5+'Daily-Prod.'!AJL5+'Daily-Prod.'!AJC5+'Daily-Prod.'!AIT5+'Daily-Prod.'!AIK5+'Daily-Prod.'!AIB5+'Daily-Prod.'!AHS5+'Daily-Prod.'!AHJ5+'Daily-Prod.'!AHA5+'Daily-Prod.'!AGR5+'Daily-Prod.'!AGI5+'Daily-Prod.'!AFZ5+'Daily-Prod.'!AFQ5+'Daily-Prod.'!AFH5+'Daily-Prod.'!AEY5+'Daily-Prod.'!AEP5+'Daily-Prod.'!AEG5+'Daily-Prod.'!ADX5)/AI5,"") -> 0.049429658 | AH5: =IFERROR(('Daily-Prod.'!AOK5+'Daily-Prod.'!AOB5+'Daily-Prod.'!ANS5+'Daily-Prod.'!ANJ5+'Daily-Prod.'!ANA5+'Daily-Prod.'!AMR5+'Daily-Prod.'!AMI5+'Daily-Prod.'!ALZ5+'Daily-Prod.'!ALQ5+'Daily-Prod.'!ALH5+'Daily-Prod.'!AKY5+'Daily-Prod.'!AKP5+'Daily-Prod.'!AKG5+'Daily-Prod.'!AJX5+'Daily-Prod.'!AJO5+'Daily-Prod.'!AJF5+'Daily-Prod.'!AIW5+'Daily-Prod.'!AIN5+'Daily-Prod.'!AIE5+'Daily-Prod.'!AHV5+'Daily-Prod.'!AHM5+'Daily-Prod.'!AHD5+'Daily-Prod.'!AGU5+'Daily-Prod.'!AGL5+'Daily-Prod.'!AGC5+'Daily-Prod.'!AFT5+'Daily-Prod.'!AFK5+'Daily-Prod.'!AFB5+'Daily-Prod.'!AES5+'Daily-Prod.'!AEJ5+'Daily-Prod.'!AEA5+'Daily-Prod.'!AOJ5+'Daily-Prod.'!AOA5+'Daily-Prod.'!ANR5+'Daily-Prod.'!ANI5+'Daily-Prod.'!AMZ5+'Daily-Prod.'!AMQ5+'Daily-Prod.'!AMH5+'Daily-Prod.'!ALY5+'Daily-Prod.'!ALP5+'Daily-Prod.'!ALG5+'Daily-Prod.'!AKX5+'Daily-Prod.'!AKO5+'Daily-Prod.'!AKF5+'Daily-Prod.'!AJW5+'Daily-Prod.'!AJN5+'Daily-Prod.'!AJE5+'Daily-Prod.'!AIV5+'Daily-Prod.'!AIM5+'Daily-Prod.'!AID5+'Daily-Prod.'!AHU5+'Daily-Prod.'!AHL5+'Daily-Prod.'!AHC5+'Daily-Prod.'!AGT5+'Daily-Prod.'!AGK5+'Daily-Prod.'!AGB5+'Daily-Prod.'!AFS5+'Daily-Prod.'!AFJ5+'Daily-Prod.'!AFA5+'Daily-Prod.'!AER5+'Daily-Prod.'!AEI5+'Daily-Prod.'!ADZ5)/AI5,"") -> 0.30798479 | AI5: =IFERROR(('Daily-Prod.'!AOL5+'Daily-Prod.'!AOC5+'Daily-Prod.'!ANT5+'Daily-Prod.'!ANK5+'Daily-Prod.'!ANB5+'Daily-Prod.'!AMS5+'Daily-Prod.'!AMJ5+'Daily-Prod.'!AMA5+'Daily-Prod.'!ALR5+'Daily-Prod.'!ALI5+'Daily-Prod.'!AKZ5+'Daily-Prod.'!AKQ5+'Daily-Prod.'!AKH5+'Daily-Prod.'!AJY5+'Daily-Prod.'!AJP5+'Daily-Prod.'!AJG5+'Daily-Prod.'!AIX5+'Daily-Prod.'!AIO5+'Daily-Prod.'!AIF5+'Daily-Prod.'!AHW5+'Daily-Prod.'!AHN5+'Daily-Prod.'!AHE5+'Daily-Prod.'!AGV5+'Daily-Prod.'!AGM5+'Daily-Prod.'!AGD5+'Daily-Prod.'!AFU5+'Daily-Prod.'!AFL5+'Daily-Prod.'!AFC5+'Daily-Prod.'!AET5+'Daily-Prod.'!AEK5+'Daily-Prod.'!AEB5),"") -> 263 | AK5: =IFERROR(('Daily-Prod.'!AON5+'Daily-Prod.'!AOE5+'Daily-Prod.'!ANV5+'Daily-Prod.'!ANM5+'Daily-Prod.'!AND5+'Daily-Prod.'!AMU5+'Daily-Prod.'!AML5+'Daily-Prod.'!AMC5+'Daily-Prod.'!ALT5+'Daily-Prod.'!ALK5+'Daily-Prod.'!ALB5+'Daily-Prod.'!AKS5+'Daily-Prod.'!AKJ5+'Daily-Prod.'!AKA5+'Daily-Prod.'!AJR5+'Daily-Prod.'!AJI5+'Daily-Prod.'!AIZ5+'Daily-Prod.'!AIQ5+'Daily-Prod.'!AIH5+'Daily-Prod.'!AHY5+'Daily-Prod.'!AHP5+'Daily-Prod.'!AHG5+'Daily-Prod.'!AGX5+'Daily-Prod.'!AGO5+'Daily-Prod.'!AGF5+'Daily-Prod.'!AFW5+'Daily-Prod.'!AFN5+'Daily-Prod.'!AFE5+'Daily-Prod.'!AEV5+'Daily-Prod.'!AEM5+'Daily-Prod.'!AED5),"") -> 83 | AL5: =IFERROR((AK5/AJ5),"") | AM5: =IFERROR(AVERAGE('Daily-Prod.'!AOL5,'Daily-Prod.'!AOC5,'Daily-Prod.'!ANT5,'Daily-Prod.'!ANK5,'Daily-Prod.'!ANB5,'Daily-Prod.'!AMS5,'Daily-Prod.'!AMJ5,'Daily-Prod.'!AMA5,'Daily-Prod.'!ALR5,'Daily-Prod.'!ALI5,'Daily-Prod.'!AKZ5,'Daily-Prod.'!AKQ5,'Daily-Prod.'!AKH5,'Daily-Prod.'!AJY5,'Daily-Prod.'!AJP5,'Daily-Prod.'!AJG5,'Daily-Prod.'!AIX5,'Daily-Prod.'!AIO5,'Daily-Prod.'!AIF5,'Daily-Prod.'!AHW5,'Daily-Prod.'!AHN5,'Daily-Prod.'!AHE5,'Daily-Prod.'!AGV5,'Daily-Prod.'!AGM5,'Daily-Prod.'!AGD5,'Daily-Prod.'!AFU5,'Daily-Prod.'!AFL5,'Daily-Prod.'!AFC5,'Daily-Prod.'!AET5,'Daily-Prod.'!AEK5,'Daily-Prod.'!AEB5),"") -> 15.470588 | AO5: =IFERROR(AVERAGE('Daily-Prod.'!AON5,'Daily-Prod.'!AOE5,'Daily-Prod.'!ANV5,'Daily-Prod.'!ANM5,'Daily-Prod.'!AND5,'Daily-Prod.'!AMU5,'Daily-Prod.'!AML5,'Daily-Prod.'!AMC5,'Daily-Prod.'!ALT5,'Daily-Prod.'!ALK5,'Daily-Prod.'!ALB5,'Daily-Prod.'!AKS5,'Daily-Prod.'!AKJ5,'Daily-Prod.'!AKA5,'Daily-Prod.'!AJR5,'Daily-Prod.'!AJI5,'Daily-Prod.'!AIZ5,'Daily-Prod.'!AIQ5,'Daily-Prod.'!AIH5,'Daily-Prod.'!AHY5,'Daily-Prod.'!AHP5,'Daily-Prod.'!AHG5,'Daily-Prod.'!AGX5,'Daily-Prod.'!AGO5,'Daily-Prod.'!AGF5,'Daily-Prod.'!AFW5,'Daily-Prod.'!AFN5,'Daily-Prod.'!AFE5,'Daily-Prod.'!AEV5,'Daily-Prod.'!AEM5,'Daily-Prod.'!AED5),"") -> 4.3684211 | AP5: =IFERROR(('Daily-Prod.'!AYZ5+'Daily-Prod.'!AYQ5+'Daily-Prod.'!AYH5+'Daily-Prod.'!AXY5+'Daily-Prod.'!AXP5+'Daily-Prod.'!AXG5+'Daily-Prod.'!AWX5+'Daily-Prod.'!AWO5+'Daily-Prod.'!AWF5+'Daily-Prod.'!AVW5+'Daily-Prod.'!AVN5+'Daily-Prod.'!AVE5+'Daily-Prod.'!AUV5+'Daily-Prod.'!AUM5+'Daily-Prod.'!AUD5+'Daily-Prod.'!ATU5+'Daily-Prod.'!ATL5+'Daily-Prod.'!ATC5+'Daily-Prod.'!AST5+'Daily-Prod.'!ASK5+'Daily-Prod.'!ASB5+'Daily-Prod.'!ARS5+'Daily-Prod.'!ARJ5+'Daily-Prod.'!ARA5+'Daily-Prod.'!AQR5+'Daily-Prod.'!AQI5+'Daily-Prod.'!APZ5+'Daily-Prod.'!APQ5+'Daily-Prod.'!APH5+'Daily-Prod.'!AOY5+'Daily-Prod.'!AOP5)/AS5,"") -> 0.36267606 | AQ5: =IFERROR(('Daily-Prod.'!AZA5+'Daily-Prod.'!AYR5+'Daily-Prod.'!AYI5+'Daily-Prod.'!AXZ5+'Daily-Prod.'!AXQ5+'Daily-Prod.'!AXH5+'Daily-Prod.'!AWY5+'Daily-Prod.'!AWP5+'Daily-Prod.'!AWG5+'Daily-Prod.'!AVX5+'Daily-Prod.'!AVO5+'Daily-Prod.'!AVF5+'Daily-Prod.'!AUW5+'Daily-Prod.'!AUN5+'Daily-Prod.'!AUE5+'Daily-Prod.'!ATV5+'Daily-Prod.'!ATM5+'Daily-Prod.'!ATD5+'Daily-Prod.'!ASU5+'Daily-Prod.'!ASL5+'Daily-Prod.'!ASC5+'Daily-Prod.'!ART5+'Daily-Prod.'!ARK5+'Daily-Prod.'!ARB5+'Daily-Prod.'!AQS5+'Daily-Prod.'!AQJ5+'Daily-Prod.'!AQA5+'Daily-Prod.'!APR5+'Daily-Prod.'!API5+'Daily-Prod.'!AOZ5+'Daily-Prod.'!AOQ5)/AS5,"") -> 0.073943662 | AR5: =IFERROR(('Daily-Prod.'!AZC5+'Daily-Prod.'!AYT5+'Daily-Prod.'!AYK5+'Daily-Prod.'!AYB5+'Daily-Prod.'!AXS5+'Daily-Prod.'!AXJ5+'Daily-Prod.'!AXA5+'Daily-Prod.'!AWR5+'Daily-Prod.'!AWI5+'Daily-Prod.'!AVZ5+'Daily-Prod.'!AVQ5+'Daily-Prod.'!AVH5+'Daily-Prod.'!AUY5+'Daily-Prod.'!AUP5+'Daily-Prod.'!AUG5+'Daily-Prod.'!ATX5+'Daily-Prod.'!ATO5+'Daily-Prod.'!ATF5+'Daily-Prod.'!ASW5+'Daily-Prod.'!ASN5+'Daily-Prod.'!ASE5+'Daily-Prod.'!ARV5+'Daily-Prod.'!ARM5+'Daily-Prod.'!ARD5+'Daily-Prod.'!AQU5+'Daily-Prod.'!AQL5+'Daily-Prod.'!AQC5+'Daily-Prod.'!APT5+'Daily-Prod.'!APK5+'Daily-Prod.'!APB5+'Daily-Prod.'!AOS5+'Daily-Prod.'!AZD5+'Daily-Prod.'!AYU5+'Daily-Prod.'!AYL5+'Daily-Prod.'!AYC5+'Daily-Prod.'!AXT5+'Daily-Prod.'!AXK5+'Daily-Prod.'!AXB5+'Daily-Prod.'!AWS5+'Daily-Prod.'!AWJ5+'Daily-Prod.'!AWA5+'Daily-Prod.'!AVR5+'Daily-Prod.'!AVI5+'Daily-Prod.'!AUZ5+'Daily-Prod.'!AUQ5+'Daily-Prod.'!AUH5+'Daily-Prod.'!ATY5+'Daily-Prod.'!ATP5+'Daily-Prod.'!ATG5+'Daily-Prod.'!ASX5+'Daily-Prod.'!ASO5+'Daily-Prod.'!ASF5+'Daily-Prod.'!ARW5+'Daily-Prod.'!ARN5+'Daily-Prod.'!ARE5+'Daily-Prod.'!AQV5+'Daily-Prod.'!AQM5+'Daily-Prod.'!AQD5+'Daily-Prod.'!APU5+'Daily-Prod.'!APL5+'Daily-Prod.'!APC5+'Daily-Prod.'!AOT5)/AS5,"") -> 0.56338028 | AS5: =IFERROR(('Daily-Prod.'!AZE5+'Daily-Prod.'!AYV5+'Daily-Prod.'!AYM5+'Daily-Prod.'!AYD5+'Daily-Prod.'!AXU5+'Daily-Prod.'!AXL5+'Daily-Prod.'!AXC5+'Daily-Prod.'!AWT5+'Daily-Prod.'!AWK5+'Daily-Prod.'!AWB5+'Daily-Prod.'!AVS5+'Daily-Prod.'!AVJ5+'Daily-Prod.'!AVA5+'Daily-Prod.'!AUR5+'Daily-Prod.'!AUI5+'Daily-Prod.'!ATZ5+'Daily-Prod.'!ATQ5+'Daily-Prod.'!ATH5+'Daily-Prod.'!ASY5+'Daily-Prod.'!ASP5+'Daily-Prod.'!ASG5+'Daily-Prod.'!ARX5+'Daily-Prod.'!ARO5+'Daily-Prod.'!ARF5+'Daily-Prod.'!AQW5+'Daily-Prod.'!AQN5+'Daily-Prod.'!AQE5+'Daily-Prod.'!APV5+'Daily-Prod.'!APM5+'Daily-Prod.'!APD5+'Daily-Prod.'!AOU5),"") -> 284 | AU5: =IFERROR(('Daily-Prod.'!AZG5+'Daily-Prod.'!AYX5+'Daily-Prod.'!AYO5+'Daily-Prod.'!AYF5+'Daily-Prod.'!AXW5+'Daily-Prod.'!AXN5+'Daily-Prod.'!AXE5+'Daily-Prod.'!AWV5+'Daily-Prod.'!AWM5+'Daily-Prod.'!AWD5+'Daily-Prod.'!AVU5+'Daily-Prod.'!AVL5+'Daily-Prod.'!AVC5+'Daily-Prod.'!AUT5+'Daily-Prod.'!AUK5+'Daily-Prod.'!AUB5+'Daily-Prod.'!ATS5+'Daily-Prod.'!ATJ5+'Daily-Prod.'!ATA5+'Daily-Prod.'!ASR5+'Daily-Prod.'!ASI5+'Daily-Prod.'!ARZ5+'Daily-Prod.'!ARQ5+'Daily-Prod.'!ARH5+'Daily-Prod.'!AQY5+'Daily-Prod.'!AQP5+'Daily-Prod.'!AQG5+'Daily-Prod.'!APX5+'Daily-Prod.'!APO5+'Daily-Prod.'!APF5+'Daily-Prod.'!AOW5),"") -> 122 | AV5: =IFERROR((AU5/AT5),"") | AW5: =IFERROR(AVERAGE('Daily-Prod.'!AZE5,'Daily-Prod.'!AYV5,'Daily-Prod.'!AYM5,'Daily-Prod.'!AYD5,'Daily-Prod.'!AXU5,'Daily-Prod.'!AXL5,'Daily-Prod.'!AXC5,'Daily-Prod.'!AWT5,'Daily-Prod.'!AWK5,'Daily-Prod.'!AWB5,'Daily-Prod.'!AVS5,'Daily-Prod.'!AVJ5,'Daily-Prod.'!AVA5,'Daily-Prod.'!AUR5,'Daily-Prod.'!AUI5,'Daily-Prod.'!ATZ5,'Daily-Prod.'!ATQ5,'Daily-Prod.'!ATH5,'Daily-Prod.'!ASY5,'Daily-Prod.'!ASP5,'Daily-Prod.'!ASG5,'Daily-Prod.'!ARX5,'Daily-Prod.'!ARO5,'Daily-Prod.'!ARF5,'Daily-Prod.'!AQW5,'Daily-Prod.'!AQN5,'Daily-Prod.'!AQE5,'Daily-Prod.'!APV5,'Daily-Prod.'!APM5,'Daily-Prod.'!APD5,'Daily-Prod.'!AOU5),"") -> 16.705882 | AY5: =IFERROR(AVERAGE('Daily-Prod.'!AZG5,'Daily-Prod.'!AYX5,'Daily-Prod.'!AYO5,'Daily-Prod.'!AYF5,'Daily-Prod.'!AXW5,'Daily-Prod.'!AXN5,'Daily-Prod.'!AXE5,'Daily-Prod.'!AWV5,'Daily-Prod.'!AWM5,'Daily-Prod.'!AWD5,'Daily-Prod.'!AVU5,'Daily-Prod.'!AVL5,'Daily-Prod.'!AVC5,'Daily-Prod.'!AUT5,'Daily-Prod.'!AUK5,'Daily-Prod.'!AUB5,'Daily-Prod.'!ATS5,'Daily-Prod.'!ATJ5,'Daily-Prod.'!ATA5,'Daily-Prod.'!ASR5,'Daily-Prod.'!ASI5,'Daily-Prod.'!ARZ5,'Daily-Prod.'!ARQ5,'Daily-Prod.'!ARH5,'Daily-Prod.'!AQY5,'Daily-Prod.'!AQP5,'Daily-Prod.'!AQG5,'Daily-Prod.'!APX5,'Daily-Prod.'!APO5,'Daily-Prod.'!APF5,'Daily-Prod.'!AOW5),"") -> 4.88 | AZ5: =IFERROR(('Daily-Prod.'!BJJ5+'Daily-Prod.'!BJA5+'Daily-Prod.'!BIR5+'Daily-Prod.'!BII5+'Daily-Prod.'!BHZ5+'Daily-Prod.'!BHQ5+'Daily-Prod.'!BHH5+'Daily-Prod.'!BGY5+'Daily-Prod.'!BGP5+'Daily-Prod.'!BGG5+'Daily-Prod.'!BFX5+'Daily-Prod.'!BFO5+'Daily-Prod.'!BFF5+'Daily-Prod.'!BEW5+'Daily-Prod.'!BEN5+'Daily-Prod.'!BEE5+'Daily-Prod.'!BDV5+'Daily-Prod.'!BDM5+'Daily-Prod.'!BDD5+'Daily-Prod.'!BCU5+'Daily-Prod.'!BCL5+'Daily-Prod.'!BCC5+'Daily-Prod.'!BBT5+'Daily-Prod.'!BBK5+'Daily-Prod.'!BBB5+'Daily-Prod.'!BAS5+'Daily-Prod.'!BAJ5+'Daily-Prod.'!BAA5+'Daily-Prod.'!AZR5+'Daily-Prod.'!AZI5)/BC5,"") -> 0.44983819 | BA5: =IFERROR(('Daily-Prod.'!BJK5+'Daily-Prod.'!BJB5+'Daily-Prod.'!BIS5+'Daily-Prod.'!BIJ5+'Daily-Prod.'!BIA5+'Daily-Prod.'!BHR5+'Daily-Prod.'!BHI5+'Daily-Prod.'!BGZ5+'Daily-Prod.'!BGQ5+'Daily-Prod.'!BGH5+'Daily-Prod.'!BFY5+'Daily-Prod.'!BFP5+'Daily-Prod.'!BFG5+'Daily-Prod.'!BEX5+'Daily-Prod.'!BEO5+'Daily-Prod.'!BEF5+'Daily-Prod.'!BDW5+'Daily-Prod.'!BDN5+'Daily-Prod.'!BDE5+'Daily-Prod.'!BCV5+'Daily-Prod.'!BCM5+'Daily-Prod.'!BCD5+'Daily-Prod.'!BBU5+'Daily-Prod.'!BBL5+'Daily-Prod.'!BBC5+'Daily-Prod.'!BAT5+'Daily-Prod.'!BAK5+'Daily-Prod.'!BAB5+'Daily-Prod.'!AZS5+'Daily-Prod.'!AZJ5)/BC5,"") -> 0.10355987 | BB5: =IFERROR(('Daily-Prod.'!BJM5+'Daily-Prod.'!BJD5+'Daily-Prod.'!BIU5+'Daily-Prod.'!BIL5+'Daily-Prod.'!BIC5+'Daily-Prod.'!BHT5+'Daily-Prod.'!BHK5+'Daily-Prod.'!BHB5+'Daily-Prod.'!BGS5+'Daily-Prod.'!BGJ5+'Daily-Prod.'!BGA5+'Daily-Prod.'!BFR5+'Daily-Prod.'!BFI5+'Daily-Prod.'!BEZ5+'Daily-Prod.'!BEQ5+'Daily-Prod.'!BEH5+'Daily-Prod.'!BDY5+'Daily-Prod.'!BDP5+'Daily-Prod.'!BDG5+'Daily-Prod.'!BCX5+'Daily-Prod.'!BCO5+'Daily-Prod.'!BCF5+'Daily-Prod.'!BBW5+'Daily-Prod.'!BBN5+'Daily-Prod.'!BBE5+'Daily-Prod.'!BAV5+'Daily-Prod.'!BAM5+'Daily-Prod.'!BAD5+'Daily-Prod.'!AZU5+'Daily-Prod.'!AZL5+'Daily-Prod.'!BJN5+'Daily-Prod.'!BJE5+'Daily-Prod.'!BIV5+'Daily-Prod.'!BIM5+'Daily-Prod.'!BID5+'Daily-Prod.'!BHU5+'Daily-Prod.'!BHL5+'Daily-Prod.'!BHC5+'Daily-Prod.'!BGT5+'Daily-Prod.'!BGK5+'Daily-Prod.'!BGB5+'Daily-Prod.'!BFS5+'Daily-Prod.'!BFJ5+'Daily-Prod.'!BFA5+'Daily-Prod.'!BER5+'Daily-Prod.'!BEI5+'Daily-Prod.'!BDZ5+'Daily-Prod.'!BDQ5+'Daily-Prod.'!BDH5+'Daily-Prod.'!BCY5+'Daily-Prod.'!BCP5+'Daily-Prod.'!BCG5+'Daily-Prod.'!BBX5+'Daily-Prod.'!BBO5+'Daily-Prod.'!BBF5+'Daily-Prod.'!BAW5+'Daily-Prod.'!BAN5+'Daily-Prod.'!BAE5+'Daily-Prod.'!AZV5+'Daily-Prod.'!AZM5)/BC5,"") -> 0.44660194 | BC5: =IFERROR(('Daily-Prod.'!BJO5+'Daily-Prod.'!BJF5+'Daily-Prod.'!BIW5+'Daily-Prod.'!BIN5+'Daily-Prod.'!BIE5+'Daily-Prod.'!BHV5+'Daily-Prod.'!BHM5+'Daily-Prod.'!BHD5+'Daily-Prod.'!BGU5+'Daily-Prod.'!BGL5+'Daily-Prod.'!BGC5+'Daily-Prod.'!BFT5+'Daily-Prod.'!BFK5+'Daily-Prod.'!BFB5+'Daily-Prod.'!BES5+'Daily-Prod.'!BEJ5+'Daily-Prod.'!BEA5+'Daily-Prod.'!BDR5+'Daily-Prod.'!BDI5+'Daily-Prod.'!BCZ5+'Daily-Prod.'!BCQ5+'Daily-Prod.'!BCH5+'Daily-Prod.'!BBY5+'Daily-Prod.'!BBP5+'Daily-Prod.'!BBG5+'Daily-Prod.'!BAX5+'Daily-Prod.'!BAO5+'Daily-Prod.'!BAF5+'Daily-Prod.'!AZW5+'Daily-Prod.'!AZN5),"") -> 309 | BD5: =IFERROR(('Daily-Prod.'!BJP5+'Daily-Prod.'!BJG5+'Daily-Prod.'!BIX5+'Daily-Prod.'!BIO5+'Daily-Prod.'!BIF5+'Daily-Prod.'!BHW5+'Daily-Prod.'!BHN5+'Daily-Prod.'!BHE5+'Daily-Prod.'!BGV5+'Daily-Prod.'!BGM5+'Daily-Prod.'!BGD5+'Daily-Prod.'!BFU5+'Daily-Prod.'!BFL5+'Daily-Prod.'!BFC5+'Daily-Prod.'!BET5+'Daily-Prod.'!BEK5+'Daily-Prod.'!BEB5+'Daily-Prod.'!BDS5+'Daily-Prod.'!BDJ5+'Daily-Prod.'!BDA5+'Daily-Prod.'!BCR5+'Daily-Prod.'!BCI5+'Daily-Prod.'!BBZ5+'Daily-Prod.'!BBQ5+'Daily-Prod.'!BBH5+'Daily-Prod.'!BAY5+'Daily-Prod.'!BAP5+'Daily-Prod.'!BAG5+'Daily-Prod.'!AZX5+'Daily-Prod.'!AZO5),"") -> 108 | BE5: =IFERROR(('Daily-Prod.'!BJQ5+'Daily-Prod.'!BJH5+'Daily-Prod.'!BIY5+'Daily-Prod.'!BIP5+'Daily-Prod.'!BIG5+'Daily-Prod.'!BHX5+'Daily-Prod.'!BHO5+'Daily-Prod.'!BHF5+'Daily-Prod.'!BGW5+'Daily-Prod.'!BGN5+'Daily-Prod.'!BGE5+'Daily-Prod.'!BFV5+'Daily-Prod.'!BFM5+'Daily-Prod.'!BFD5+'Daily-Prod.'!BEU5+'Daily-Prod.'!BEL5+'Daily-Prod.'!BEC5+'Daily-Prod.'!BDT5+'Daily-Prod.'!BDK5+'Daily-Prod.'!BDB5+'Daily-Prod.'!BCS5+'Daily-Prod.'!BCJ5+'Daily-Prod.'!BCA5+'Daily-Prod.'!BBR5+'Daily-Prod.'!BBI5+'Daily-Prod.'!BAZ5+'Daily-Prod.'!BAQ5+'Daily-Prod.'!BAH5+'Daily-Prod.'!AZY5+'Daily-Prod.'!AZP5),"") -> 107 | BF5: =IFERROR((BE5/BD5),"") -> 0.99074074 | BG5: =IFERROR(AVERAGE('Daily-Prod.'!BJO5,'Daily-Prod.'!BJF5,'Daily-Prod.'!BIW5,'Daily-Prod.'!BIN5,'Daily-Prod.'!BIE5,'Daily-Prod.'!BHV5,'Daily-Prod.'!BHM5,'Daily-Prod.'!BHD5,'Daily-Prod.'!BGU5,'Daily-Prod.'!BGL5,'Daily-Prod.'!BGC5,'Daily-Prod.'!BFT5,'Daily-Prod.'!BFK5,'Daily-Prod.'!BFB5,'Daily-Prod.'!BES5,'Daily-Prod.'!BEJ5,'Daily-Prod.'!BEA5,'Daily-Prod.'!BDR5,'Daily-Prod.'!BDI5,'Daily-Prod.'!BCZ5,'Daily-Prod.'!BCQ5,'Daily-Prod.'!BCH5,'Daily-Prod.'!BBY5,'Daily-Prod.'!BBP5,'Daily-Prod.'!BBG5,'Daily-Prod.'!BAX5,'Daily-Prod.'!BAO5,'Daily-Prod.'!BAF5,'Daily-Prod.'!AZW5,'Daily-Prod.'!AZN5),"") -> 17.166667 | BH5: =IFERROR(AVERAGE('Daily-Prod.'!BJP5,'Daily-Prod.'!BJG5,'Daily-Prod.'!BIX5,'Daily-Prod.'!BIO5,'Daily-Prod.'!BIF5,'Daily-Prod.'!BHW5,'Daily-Prod.'!BHN5,'Daily-Prod.'!BHE5,'Daily-Prod.'!BGV5,'Daily-Prod.'!BGM5,'Daily-Prod.'!BGD5,'Daily-Prod.'!BFU5,'Daily-Prod.'!BFL5,'Daily-Prod.'!BFC5,'Daily-Prod.'!BET5,'Daily-Prod.'!BEK5,'Daily-Prod.'!BEB5,'Daily-Prod.'!BDS5,'Daily-Prod.'!BDJ5,'Daily-Prod.'!BDA5,'Daily-Prod.'!BCR5,'Daily-Prod.'!BCI5,'Daily-Prod.'!BBZ5,'Daily-Prod.'!BBQ5,'Daily-Prod.'!BBH5,'Daily-Prod.'!BAY5,'Daily-Prod.'!BAP5,'Daily-Prod.'!BAG5,'Daily-Prod.'!AZX5,'Daily-Prod.'!AZO5),"") -> 3.6 | BI5: =IFERROR(AVERAGE('Daily-Prod.'!BJQ5,'Daily-Prod.'!BJH5,'Daily-Prod.'!BIY5,'Daily-Prod.'!BIP5,'Daily-Prod.'!BIG5,'Daily-Prod.'!BHX5,'Daily-Prod.'!BHO5,'Daily-Prod.'!BHF5,'Daily-Prod.'!BGW5,'Daily-Prod.'!BGN5,'Daily-Prod.'!BGE5,'Daily-Prod.'!BFV5,'Daily-Prod.'!BFM5,'Daily-Prod.'!BFD5,'Daily-Prod.'!BEU5,'Daily-Prod.'!BEL5,'Daily-Prod.'!BEC5,'Daily-Prod.'!BDT5,'Daily-Prod.'!BDK5,'Daily-Prod.'!BDB5,'Daily-Prod.'!BCS5,'Daily-Prod.'!BCJ5,'Daily-Prod.'!BCA5,'Daily-Prod.'!BBR5,'Daily-Prod.'!BBI5,'Daily-Prod.'!BAZ5,'Daily-Prod.'!BAQ5,'Daily-Prod.'!BAH5,'Daily-Prod.'!AZY5,'Daily-Prod.'!AZP5),"") -> 3.5666667 | BJ5: =IFERROR((('Daily-Prod.'!BUC5+'Daily-Prod.'!BTT5+'Daily-Prod.'!BTK5+'Daily-Prod.'!BTB5+'Daily-Prod.'!BSS5+'Daily-Prod.'!BSJ5+'Daily-Prod.'!BSA5+'Daily-Prod.'!BRR5+'Daily-Prod.'!BRI5+'Daily-Prod.'!BQZ5+'Daily-Prod.'!BQQ5+'Daily-Prod.'!BQH5+'Daily-Prod.'!BPY5+'Daily-Prod.'!BPP5+'Daily-Prod.'!BPG5+'Daily-Prod.'!BOX5+'Daily-Prod.'!BOO5+'Daily-Prod.'!BOF5+'Daily-Prod.'!BNW5+'Daily-Prod.'!BNN5+'Daily-Prod.'!BNE5+'Daily-Prod.'!BMV5+'Daily-Prod.'!BMM5+'Daily-Prod.'!BMD5+'Daily-Prod.'!BLU5+'Daily-Prod.'!BLL5+'Daily-Prod.'!BLC5+'Daily-Prod.'!BKT5+'Daily-Prod.'!BKK5+'Daily-Prod.'!BKB5+'Daily-Prod.'!BJS5)/BM5),"") -> 0.55709343 | BK5: =IFERROR((('Daily-Prod.'!BUD5+'Daily-Prod.'!BTU5+'Daily-Prod.'!BTL5+'Daily-Prod.'!BTC5+'Daily-Prod.'!BST5+'Daily-Prod.'!BSK5+'Daily-Prod.'!BSB5+'Daily-Prod.'!BRS5+'Daily-Prod.'!BRJ5+'Daily-Prod.'!BRA5+'Daily-Prod.'!BQR5+'Daily-Prod.'!BQI5+'Daily-Prod.'!BPZ5+'Daily-Prod.'!BPQ5+'Daily-Prod.'!BPH5+'Daily-Prod.'!BOY5+'Daily-Prod.'!BOP5+'Daily-Prod.'!BOG5+'Daily-Prod.'!BNX5+'Daily-Prod.'!BNO5+'Daily-Prod.'!BNF5+'Daily-Prod.'!BMW5+'Daily-Prod.'!BMN5+'Daily-Prod.'!BME5+'Daily-Prod.'!BLV5+'Daily-Prod.'!BLM5+'Daily-Prod.'!BLD5+'Daily-Prod.'!BKU5+'Daily-Prod.'!BKL5+'Daily-Prod.'!BKC5+'Daily-Prod.'!BJT5)/BM5),"") -> 0.093425606 | BL5: =IFERROR((('Daily-Prod.'!BUG5+'Daily-Prod.'!BTX5+'Daily-Prod.'!BTO5+'Daily-Prod.'!BTF5+'Daily-Prod.'!BSW5+'Daily-Prod.'!BSN5+'Daily-Prod.'!BSE5+'Daily-Prod.'!BRV5+'Daily-Prod.'!BRM5+'Daily-Prod.'!BRD5+'Daily-Prod.'!BQU5+'Daily-Prod.'!BQL5+'Daily-Prod.'!BQC5+'Daily-Prod.'!BPT5+'Daily-Prod.'!BPK5+'Daily-Prod.'!BPB5+'Daily-Prod.'!BOS5+'Daily-Prod.'!BOJ5+'Daily-Prod.'!BOA5+'Daily-Prod.'!BNR5+'Daily-Prod.'!BNI5+'Daily-Prod.'!BMZ5+'Daily-Prod.'!BMQ5+'Daily-Prod.'!BMH5+'Daily-Prod.'!BLY5+'Daily-Prod.'!BLP5+'Daily-Prod.'!BLG5+'Daily-Prod.'!BKX5+'Daily-Prod.'!BKO5+'Daily-Prod.'!BKF5+'Daily-Prod.'!BJW5+'Daily-Prod.'!BUF5+'Daily-Prod.'!BTW5+'Daily-Prod.'!BTN5+'Daily-Prod.'!BTE5+'Daily-Prod.'!BSV5+'Daily-Prod.'!BSM5+'Daily-Prod.'!BSD5+'Daily-Prod.'!BRU5+'Daily-Prod.'!BRL5+'Daily-Prod.'!BRC5+'Daily-Prod.'!BQT5+'Daily-Prod.'!BQK5+'Daily-Prod.'!BQB5+'Daily-Prod.'!BPS5+'Daily-Prod.'!BPJ5+'Daily-Prod.'!BPA5+'Daily-Prod.'!BOR5+'Daily-Prod.'!BOI5+'Daily-Prod.'!BNZ5+'Daily-Prod.'!BNQ5+'Daily-Prod.'!BNH5+'Daily-Prod.'!BMY5+'Daily-Prod.'!BMP5+'Daily-Prod.'!BMG5+'Daily-Prod.'!BLX5+'Daily-Prod.'!BLO5+'Daily-Prod.'!BLF5+'Daily-Prod.'!BKW5+'Daily-Prod.'!BKN5+'Daily-Prod.'!BKE5+'Daily-Prod.'!BJV5)/BM5),"") -> 0.34948097 | BM5: =IFERROR(('Daily-Prod.'!BUH5+'Daily-Prod.'!BTY5+'Daily-Prod.'!BTP5+'Daily-Prod.'!BTG5+'Daily-Prod.'!BSX5+'Daily-Prod.'!BSO5+'Daily-Prod.'!BSF5+'Daily-Prod.'!BRW5+'Daily-Prod.'!BRN5+'Daily-Prod.'!BRE5+'Daily-Prod.'!BQV5+'Daily-Prod.'!BQM5+'Daily-Prod.'!BQD5+'Daily-Prod.'!BPU5+'Daily-Prod.'!BPL5+'Daily-Prod.'!BPC5+'Daily-Prod.'!BOT5+'Daily-Prod.'!BOK5+'Daily-Prod.'!BOB5+'Daily-Prod.'!BNS5+'Daily-Prod.'!BNJ5+'Daily-Prod.'!BNA5+'Daily-Prod.'!BMR5+'Daily-Prod.'!BMI5+'Daily-Prod.'!BLZ5+'Daily-Prod.'!BLQ5+'Daily-Prod.'!BLH5+'Daily-Prod.'!BKY5+'Daily-Prod.'!BKP5+'Daily-Prod.'!BKG5+'Daily-Prod.'!BJX5),"") -> 289 | BO5: =IFERROR(('Daily-Prod.'!BUJ5+'Daily-Prod.'!BUA5+'Daily-Prod.'!BTR5+'Daily-Prod.'!BTI5+'Daily-Prod.'!BSZ5+'Daily-Prod.'!BSQ5+'Daily-Prod.'!BSH5+'Daily-Prod.'!BRY5+'Daily-Prod.'!BRP5+'Daily-Prod.'!BRG5+'Daily-Prod.'!BQX5+'Daily-Prod.'!BQO5+'Daily-Prod.'!BQF5+'Daily-Prod.'!BPW5+'Daily-Prod.'!BPN5+'Daily-Prod.'!BPE5+'Daily-Prod.'!BOV5+'Daily-Prod.'!BOM5+'Daily-Prod.'!BOD5+'Daily-Prod.'!BNU5+'Daily-Prod.'!BNL5+'Daily-Prod.'!BNC5+'Daily-Prod.'!BMT5+'Daily-Prod.'!BMK5+'Daily-Prod.'!BMB5+'Daily-Prod.'!BLS5+'Daily-Prod.'!BLJ5+'Daily-Prod.'!BLA5+'Daily-Prod.'!BKR5+'Daily-Prod.'!BKI5+'Daily-Prod.'!BJZ5),"") -> 37 | BP5: =IFERROR((BO5/BN5),"") | BQ5: =IFERROR(AVERAGE(('Daily-Prod.'!BUH5,'Daily-Prod.'!BTY5,'Daily-Prod.'!BTP5,'Daily-Prod.'!BTG5,'Daily-Prod.'!BSX5,'Daily-Prod.'!BSO5,'Daily-Prod.'!BSF5,'Daily-Prod.'!BRW5,'Daily-Prod.'!BRN5,'Daily-Prod.'!BRE5,'Daily-Prod.'!BQV5,'Daily-Prod.'!BQM5,'Daily-Prod.'!BQD5,'Daily-Prod.'!BPU5,'Daily-Prod.'!BPL5,'Daily-Prod.'!BPC5,'Daily-Prod.'!BOT5,'Daily-Prod.'!BOK5,'Daily-Prod.'!BOB5,'Daily-Prod.'!BNS5,'Daily-Prod.'!BNJ5,'Daily-Prod.'!BNA5,'Daily-Prod.'!BMR5,'Daily-Prod.'!BMI5,'Daily-Prod.'!BLZ5,'Daily-Prod.'!BLQ5,'Daily-Prod.'!BLH5,'Daily-Prod.'!BKY5,'Daily-Prod.'!BKP5,'Daily-Prod.'!BKG5,'Daily-Prod.'!BJX5)),"") -> 14.45 | BS5: =IFERROR((AVERAGE('Daily-Prod.'!BUJ5,'Daily-Prod.'!BUA5,'Daily-Prod.'!BTR5,'Daily-Prod.'!BTI5,'Daily-Prod.'!BSZ5,'Daily-Prod.'!BSQ5,'Daily-Prod.'!BSH5,'Daily-Prod.'!BRY5,'Daily-Prod.'!BRP5,'Daily-Prod.'!BRG5,'Daily-Prod.'!BQX5,'Daily-Prod.'!BQO5,'Daily-Prod.'!BQF5,'Daily-Prod.'!BPW5,'Daily-Prod.'!BPN5,'Daily-Prod.'!BPE5,'Daily-Prod.'!BOV5,'Daily-Prod.'!BOM5,'Daily-Prod.'!BOD5,'Daily-Prod.'!BNU5,'Daily-Prod.'!BNL5,'Daily-Prod.'!BNC5,'Daily-Prod.'!BMT5,'Daily-Prod.'!BMK5,'Daily-Prod.'!BMB5,'Daily-Prod.'!BLS5,'Daily-Prod.'!BLJ5,'Daily-Prod.'!BLA5,'Daily-Prod.'!BKR5,'Daily-Prod.'!BKI5,'Daily-Prod.'!BJZ5)),"") -> 3.7
A6: Bassma BOUKHLAL | B6: =IFERROR(('Daily-Prod.'!JC6+'Daily-Prod.'!IT6+'Daily-Prod.'!IK6+'Daily-Prod.'!IB6+'Daily-Prod.'!HS6+'Daily-Prod.'!HJ6+'Daily-Prod.'!HA6+'Daily-Prod.'!GR6+'Daily-Prod.'!GI6+'Daily-Prod.'!FZ6+'Daily-Prod.'!FQ6+'Daily-Prod.'!FH6+'Daily-Prod.'!EY6+'Daily-Prod.'!EP6+'Daily-Prod.'!EG6+'Daily-Prod.'!DX6+'Daily-Prod.'!DO6+'Daily-Prod.'!DF6+'Daily-Prod.'!CW6+'Daily-Prod.'!CN6+'Daily-Prod.'!CE6+'Daily-Prod.'!BV6+'Daily-Prod.'!BM6+'Daily-Prod.'!BD6+'Daily-Prod.'!AU6+'Daily-Prod.'!AL6+'Daily-Prod.'!AC6+'Daily-Prod.'!T6+'Daily-Prod.'!K6+'Daily-Prod.'!B6)/E6,"") -> 0.40397351 | C6: =IFERROR(('Daily-Prod.'!JD6+'Daily-Prod.'!IU6+'Daily-Prod.'!IL6+'Daily-Prod.'!IC6+'Daily-Prod.'!HT6+'Daily-Prod.'!HK6+'Daily-Prod.'!HB6+'Daily-Prod.'!GS6+'Daily-Prod.'!GJ6+'Daily-Prod.'!GA6+'Daily-Prod.'!FR6+'Daily-Prod.'!FI6+'Daily-Prod.'!EZ6+'Daily-Prod.'!EQ6+'Daily-Prod.'!EH6+'Daily-Prod.'!DY6+'Daily-Prod.'!DP6+'Daily-Prod.'!DG6+'Daily-Prod.'!CX6+'Daily-Prod.'!CO6+'Daily-Prod.'!CF6+'Daily-Prod.'!BW6+'Daily-Prod.'!BN6+'Daily-Prod.'!BE6+'Daily-Prod.'!AV6+'Daily-Prod.'!AM6+'Daily-Prod.'!AD6+'Daily-Prod.'!U6+'Daily-Prod.'!L6+'Daily-Prod.'!C6)/E6,"") -> 0.081677704 | D6: =IFERROR(('Daily-Prod.'!JF6+'Daily-Prod.'!IW6+'Daily-Prod.'!IN6+'Daily-Prod.'!IE6+'Daily-Prod.'!HV6+'Daily-Prod.'!HM6+'Daily-Prod.'!HD6+'Daily-Prod.'!GU6+'Daily-Prod.'!GL6+'Daily-Prod.'!GC6+'Daily-Prod.'!FT6+'Daily-Prod.'!FK6+'Daily-Prod.'!FB6+'Daily-Prod.'!ES6+'Daily-Prod.'!EJ6+'Daily-Prod.'!EA6+'Daily-Prod.'!DR6+'Daily-Prod.'!DI6+'Daily-Prod.'!CZ6+'Daily-Prod.'!CQ6+'Daily-Prod.'!CH6+'Daily-Prod.'!BY6+'Daily-Prod.'!BP6+'Daily-Prod.'!BG6+'Daily-Prod.'!AX6+'Daily-Prod.'!AO6+'Daily-Prod.'!AF6+'Daily-Prod.'!W6+'Daily-Prod.'!N6+'Daily-Prod.'!E6+'Daily-Prod.'!JG6+'Daily-Prod.'!IX6+'Daily-Prod.'!IO6+'Daily-Prod.'!IF6+'Daily-Prod.'!HW6+'Daily-Prod.'!HN6+'Daily-Prod.'!HE6+'Daily-Prod.'!GV6+'Daily-Prod.'!GM6+'Daily-Prod.'!GD6+'Daily-Prod.'!FU6+'Daily-Prod.'!FL6+'Daily-Prod.'!FC6+'Daily-Prod.'!ET6+'Daily-Prod.'!EK6+'Daily-Prod.'!EB6+'Daily-Prod.'!DS6+'Daily-Prod.'!DJ6+'Daily-Prod.'!DA6+'Daily-Prod.'!CR6+'Daily-Prod.'!CI6+'Daily-Prod.'!BZ6+'Daily-Prod.'!BQ6+'Daily-Prod.'!BH6+'Daily-Prod.'!AY6+'Daily-Prod.'!AP6+'Daily-Prod.'!AG6+'Daily-Prod.'!X6+'Daily-Prod.'!O6+'Daily-Prod.'!F6)/E6,"") -> 0.51434879 | E6: =IFERROR(('Daily-Prod.'!JH6+'Daily-Prod.'!IY6+'Daily-Prod.'!IP6+'Daily-Prod.'!IG6+'Daily-Prod.'!HX6+'Daily-Prod.'!HO6+'Daily-Prod.'!HF6+'Daily-Prod.'!GW6+'Daily-Prod.'!GN6+'Daily-Prod.'!GE6+'Daily-Prod.'!FV6+'Daily-Prod.'!FM6+'Daily-Prod.'!FD6+'Daily-Prod.'!EU6+'Daily-Prod.'!EL6+'Daily-Prod.'!EC6+'Daily-Prod.'!DT6+'Daily-Prod.'!DK6+'Daily-Prod.'!DB6+'Daily-Prod.'!CS6+'Daily-Prod.'!CJ6+'Daily-Prod.'!CA6+'Daily-Prod.'!BR6+'Daily-Prod.'!BI6+'Daily-Prod.'!AZ6+'Daily-Prod.'!AQ6+'Daily-Prod.'!AH6+'Daily-Prod.'!Y6+'Daily-Prod.'!P6+'Daily-Prod.'!G6),"") -> 453 | G6: =IFERROR(('Daily-Prod.'!JJ6+'Daily-Prod.'!JA6+'Daily-Prod.'!IR6+'Daily-Prod.'!II6+'Daily-Prod.'!HZ6+'Daily-Prod.'!HQ6+'Daily-Prod.'!HH6+'Daily-Prod.'!GY6+'Daily-Prod.'!GP6+'Daily-Prod.'!GG6+'Daily-Prod.'!FX6+'Daily-Prod.'!FO6+'Daily-Prod.'!FF6+'Daily-Prod.'!EW6+'Daily-Prod.'!EN6+'Daily-Prod.'!EE6+'Daily-Prod.'!DV6+'Daily-Prod.'!DM6+'Daily-Prod.'!DD6+'Daily-Prod.'!CU6+'Daily-Prod.'!CL6+'Daily-Prod.'!CC6+'Daily-Prod.'!BT6+'Daily-Prod.'!BK6+'Daily-Prod.'!BB6+'Daily-Prod.'!AS6+'Daily-Prod.'!AJ6+'Daily-Prod.'!AA6+'Daily-Prod.'!R6+'Daily-Prod.'!I6),"") -> 152 | H6: =IFERROR((G6/F6),"") | I6: =IFERROR(AVERAGE('Daily-Prod.'!JH6,'Daily-Prod.'!IY6,'Daily-Prod.'!IP6,'Daily-Prod.'!IG6,'Daily-Prod.'!HX6,'Daily-Prod.'!HO6,'Daily-Prod.'!HF6,'Daily-Prod.'!GW6,'Daily-Prod.'!GN6,'Daily-Prod.'!GE6,'Daily-Prod.'!FV6,'Daily-Prod.'!FM6,'Daily-Prod.'!FD6,'Daily-Prod.'!EU6,'Daily-Prod.'!EL6,'Daily-Prod.'!EC6,'Daily-Prod.'!DT6,'Daily-Prod.'!DK6,'Daily-Prod.'!DB6,'Daily-Prod.'!CS6,'Daily-Prod.'!CJ6,'Daily-Prod.'!CA6,'Daily-Prod.'!BR6,'Daily-Prod.'!BI6,'Daily-Prod.'!AZ6,'Daily-Prod.'!AQ6,'Daily-Prod.'!AH6,'Daily-Prod.'!Y6,'Daily-Prod.'!P6,'Daily-Prod.'!G6),"") -> 20.590909 | J6: =IFERROR(AVERAGE('Daily-Prod.'!JI6,'Daily-Prod.'!IZ6,'Daily-Prod.'!IQ6,'Daily-Prod.'!IH6,'Daily-Prod.'!HY6,'Daily-Prod.'!HP6,'Daily-Prod.'!HG6,'Daily-Prod.'!GX6,'Daily-Prod.'!GO6,'Daily-Prod.'!GF6,'Daily-Prod.'!FW6,'Daily-Prod.'!FN6,'Daily-Prod.'!FE6,'Daily-Prod.'!EV6,'Daily-Prod.'!EM6,'Daily-Prod.'!ED6,'Daily-Prod.'!DU6,'Daily-Prod.'!DL6,'Daily-Prod.'!DC6,'Daily-Prod.'!CT6,'Daily-Prod.'!CK6,'Daily-Prod.'!CB6,'Daily-Prod.'!BS6,'Daily-Prod.'!BJ6,'Daily-Prod.'!BA6,'Daily-Prod.'!AR6,'Daily-Prod.'!AI6,'Daily-Prod.'!Z6,'Daily-Prod.'!Q6,'Daily-Prod.'!H6),"") | K6: =IFERROR(AVERAGE('Daily-Prod.'!JJ6,'Daily-Prod.'!JA6,'Daily-Prod.'!IR6,'Daily-Prod.'!II6,'Daily-Prod.'!HZ6,'Daily-Prod.'!HQ6,'Daily-Prod.'!HH6,'Daily-Prod.'!GY6,'Daily-Prod.'!GP6,'Daily-Prod.'!GG6,'Daily-Prod.'!FX6,'Daily-Prod.'!FO6,'Daily-Prod.'!FF6,'Daily-Prod.'!EW6,'Daily-Prod.'!EN6,'Daily-Prod.'!EE6,'Daily-Prod.'!DV6,'Daily-Prod.'!DM6,'Daily-Prod.'!DD6,'Daily-Prod.'!CU6,'Daily-Prod.'!CL6,'Daily-Prod.'!CC6,'Daily-Prod.'!BT6,'Daily-Prod.'!BK6,'Daily-Prod.'!BB6,'Daily-Prod.'!AS6,'Daily-Prod.'!AJ6,'Daily-Prod.'!AA6,'Daily-Prod.'!R6,'Daily-Prod.'!I6),"") -> 10.857143 | L6: =IFERROR(('Daily-Prod.'!TV6+'Daily-Prod.'!TM6+'Daily-Prod.'!TD6+'Daily-Prod.'!SU6+'Daily-Prod.'!SL6+'Daily-Prod.'!SC6+'Daily-Prod.'!RT6+'Daily-Prod.'!RK6+'Daily-Prod.'!RB6+'Daily-Prod.'!QS6+'Daily-Prod.'!QJ6+'Daily-Prod.'!QA6+'Daily-Prod.'!PR6+'Daily-Prod.'!PI6+'Daily-Prod.'!OZ6+'Daily-Prod.'!OQ6+'Daily-Prod.'!OH6+'Daily-Prod.'!NY6+'Daily-Prod.'!NP6+'Daily-Prod.'!NG6+'Daily-Prod.'!MX6+'Daily-Prod.'!MO6+'Daily-Prod.'!MF6+'Daily-Prod.'!LW6+'Daily-Prod.'!LN6+'Daily-Prod.'!LE6+'Daily-Prod.'!KV6+'Daily-Prod.'!KM6+'Daily-Prod.'!KD6+'Daily-Prod.'!JU6+'Daily-Prod.'!JL6)/O6,"") -> 0.34265734 | M6: =IFERROR(('Daily-Prod.'!TW6+'Daily-Prod.'!TN6+'Daily-Prod.'!TE6+'Daily-Prod.'!SV6+'Daily-Prod.'!SM6+'Daily-Prod.'!SD6+'Daily-Prod.'!RU6+'Daily-Prod.'!RL6+'Daily-Prod.'!RC6+'Daily-Prod.'!QT6+'Daily-Prod.'!QK6+'Daily-Prod.'!QB6+'Daily-Prod.'!PS6+'Daily-Prod.'!PJ6+'Daily-Prod.'!PA6+'Daily-Prod.'!OR6+'Daily-Prod.'!OI6+'Daily-Prod.'!NZ6+'Daily-Prod.'!NQ6+'Daily-Prod.'!NH6+'Daily-Prod.'!MY6+'Daily-Prod.'!MP6+'Daily-Prod.'!MG6+'Daily-Prod.'!LX6+'Daily-Prod.'!LO6+'Daily-Prod.'!LF6+'Daily-Prod.'!KW6+'Daily-Prod.'!KN6+'Daily-Prod.'!KE6+'Daily-Prod.'!JV6+'Daily-Prod.'!JM6)/O6,"") -> 0.073426573 | N6: =IFERROR(('Daily-Prod.'!TY6+'Daily-Prod.'!TP6+'Daily-Prod.'!TG6+'Daily-Prod.'!SX6+'Daily-Prod.'!SO6+'Daily-Prod.'!SF6+'Daily-Prod.'!RW6+'Daily-Prod.'!RN6+'Daily-Prod.'!RE6+'Daily-Prod.'!QV6+'Daily-Prod.'!QM6+'Daily-Prod.'!QD6+'Daily-Prod.'!PU6+'Daily-Prod.'!PL6+'Daily-Prod.'!PC6+'Daily-Prod.'!OT6+'Daily-Prod.'!OK6+'Daily-Prod.'!OB6+'Daily-Prod.'!NS6+'Daily-Prod.'!NJ6+'Daily-Prod.'!NA6+'Daily-Prod.'!MR6+'Daily-Prod.'!MI6+'Daily-Prod.'!LZ6+'Daily-Prod.'!LQ6+'Daily-Prod.'!LH6+'Daily-Prod.'!KY6+'Daily-Prod.'!KP6+'Daily-Prod.'!KG6+'Daily-Prod.'!JX6+'Daily-Prod.'!JO6+'Daily-Prod.'!TZ6+'Daily-Prod.'!TQ6+'Daily-Prod.'!TH6+'Daily-Prod.'!SY6+'Daily-Prod.'!SP6+'Daily-Prod.'!SG6+'Daily-Prod.'!RX6+'Daily-Prod.'!RO6+'Daily-Prod.'!RF6+'Daily-Prod.'!QW6+'Daily-Prod.'!QN6+'Daily-Prod.'!QE6+'Daily-Prod.'!PV6+'Daily-Prod.'!PM6+'Daily-Prod.'!PD6+'Daily-Prod.'!OU6+'Daily-Prod.'!OL6+'Daily-Prod.'!OC6+'Daily-Prod.'!NT6+'Daily-Prod.'!NK6+'Daily-Prod.'!NB6+'Daily-Prod.'!MS6+'Daily-Prod.'!MJ6+'Daily-Prod.'!MA6+'Daily-Prod.'!LR6+'Daily-Prod.'!LI6+'Daily-Prod.'!KZ6+'Daily-Prod.'!KQ6+'Daily-Prod.'!KH6+'Daily-Prod.'!JY6+'Daily-Prod.'!JP6)/O6,"") -> 0.58391608 | O6: =IFERROR(('Daily-Prod.'!UA6+'Daily-Prod.'!TR6+'Daily-Prod.'!TI6+'Daily-Prod.'!SZ6+'Daily-Prod.'!SQ6+'Daily-Prod.'!SH6+'Daily-Prod.'!RY6+'Daily-Prod.'!RP6+'Daily-Prod.'!RG6+'Daily-Prod.'!QX6+'Daily-Prod.'!QO6+'Daily-Prod.'!QF6+'Daily-Prod.'!PW6+'Daily-Prod.'!PN6+'Daily-Prod.'!PE6+'Daily-Prod.'!OV6+'Daily-Prod.'!OM6+'Daily-Prod.'!OD6+'Daily-Prod.'!NU6+'Daily-Prod.'!NL6+'Daily-Prod.'!NC6+'Daily-Prod.'!MT6+'Daily-Prod.'!MK6+'Daily-Prod.'!MB6+'Daily-Prod.'!LS6+'Daily-Prod.'!LJ6+'Daily-Prod.'!LA6+'Daily-Prod.'!KR6+'Daily-Prod.'!KI6+'Daily-Prod.'!JZ6+'Daily-Prod.'!JQ6),"") -> 286 | Q6: =IFERROR(('Daily-Prod.'!UC6+'Daily-Prod.'!TT6+'Daily-Prod.'!TK6+'Daily-Prod.'!TB6+'Daily-Prod.'!SS6+'Daily-Prod.'!SJ6+'Daily-Prod.'!SA6+'Daily-Prod.'!RR6+'Daily-Prod.'!RI6+'Daily-Prod.'!QZ6+'Daily-Prod.'!QQ6+'Daily-Prod.'!QH6+'Daily-Prod.'!PY6+'Daily-Prod.'!PP6+'Daily-Prod.'!PG6+'Daily-Prod.'!OX6+'Daily-Prod.'!OO6+'Daily-Prod.'!OF6+'Daily-Prod.'!NW6+'Daily-Prod.'!NN6+'Daily-Prod.'!NE6+'Daily-Prod.'!MV6+'Daily-Prod.'!MM6+'Daily-Prod.'!MD6+'Daily-Prod.'!LU6+'Daily-Prod.'!LL6+'Daily-Prod.'!LC6+'Daily-Prod.'!KT6+'Daily-Prod.'!KK6+'Daily-Prod.'!KB6+'Daily-Prod.'!JS6),"") -> 202 | R6: =IFERROR((Q6/P6),"") | S6: =IFERROR(AVERAGE('Daily-Prod.'!TR6,'Daily-Prod.'!UA6,'Daily-Prod.'!TI6,'Daily-Prod.'!SZ6,'Daily-Prod.'!SQ6,'Daily-Prod.'!SH6,'Daily-Prod.'!RY6,'Daily-Prod.'!RP6,'Daily-Prod.'!RG6,'Daily-Prod.'!QX6,'Daily-Prod.'!QO6,'Daily-Prod.'!QF6,'Daily-Prod.'!PW6,'Daily-Prod.'!PN6,'Daily-Prod.'!PE6,'Daily-Prod.'!OV6,'Daily-Prod.'!OM6,'Daily-Prod.'!OD6,'Daily-Prod.'!NU6,'Daily-Prod.'!NL6,'Daily-Prod.'!NC6,'Daily-Prod.'!MT6,'Daily-Prod.'!MK6,'Daily-Prod.'!MB6,'Daily-Prod.'!LS6,'Daily-Prod.'!LJ6,'Daily-Prod.'!LA6,'Daily-Prod.'!KR6,'Daily-Prod.'!KI6,'Daily-Prod.'!JZ6),"") -> 17.533333 | T6: =IFERROR(AVERAGE('Daily-Prod.'!TS6,'Daily-Prod.'!UB6,'Daily-Prod.'!TJ6,'Daily-Prod.'!TA6,'Daily-Prod.'!SR6,'Daily-Prod.'!SI6,'Daily-Prod.'!RZ6,'Daily-Prod.'!RQ6,'Daily-Prod.'!RH6,'Daily-Prod.'!QY6,'Daily-Prod.'!QP6,'Daily-Prod.'!QG6,'Daily-Prod.'!PX6,'Daily-Prod.'!PO6,'Daily-Prod.'!PF6,'Daily-Prod.'!OW6,'Daily-Prod.'!ON6,'Daily-Prod.'!OE6,'Daily-Prod.'!NV6,'Daily-Prod.'!NM6,'Daily-Prod.'!ND6,'Daily-Prod.'!MU6,'Daily-Prod.'!ML6,'Daily-Prod.'!MC6,'Daily-Prod.'!LT6,'Daily-Prod.'!LK6,'Daily-Prod.'!LB6,'Daily-Prod.'!KS6,'Daily-Prod.'!KJ6,'Daily-Prod.'!KA6),"") | U6: =IFERROR(AVERAGE('Daily-Prod.'!TT6,'Daily-Prod.'!UC6,'Daily-Prod.'!TK6,'Daily-Prod.'!TB6,'Daily-Prod.'!SS6,'Daily-Prod.'!SJ6,'Daily-Prod.'!SA6,'Daily-Prod.'!RR6,'Daily-Prod.'!RI6,'Daily-Prod.'!QZ6,'Daily-Prod.'!QQ6,'Daily-Prod.'!QH6,'Daily-Prod.'!PY6,'Daily-Prod.'!PP6,'Daily-Prod.'!PG6,'Daily-Prod.'!OX6,'Daily-Prod.'!OO6,'Daily-Prod.'!OF6,'Daily-Prod.'!NW6,'Daily-Prod.'!NN6,'Daily-Prod.'!NE6,'Daily-Prod.'!MV6,'Daily-Prod.'!MM6,'Daily-Prod.'!MD6,'Daily-Prod.'!LU6,'Daily-Prod.'!LL6,'Daily-Prod.'!LC6,'Daily-Prod.'!KT6,'Daily-Prod.'!KK6,'Daily-Prod.'!KB6),"") -> 11.647059 | V6: =IFERROR(('Daily-Prod.'!ADN6+'Daily-Prod.'!ADE6+'Daily-Prod.'!ACV6+'Daily-Prod.'!ACM6+'Daily-Prod.'!ACD6+'Daily-Prod.'!ABU6+'Daily-Prod.'!ABL6+'Daily-Prod.'!ABC6+'Daily-Prod.'!AAT6+'Daily-Prod.'!AAK6+'Daily-Prod.'!AAB6+'Daily-Prod.'!ZS6+'Daily-Prod.'!ZJ6+'Daily-Prod.'!ZA6+'Daily-Prod.'!YR6+'Daily-Prod.'!YI6+'Daily-Prod.'!XZ6+'Daily-Prod.'!XQ6+'Daily-Prod.'!XH6+'Daily-Prod.'!WY6+'Daily-Prod.'!WP6+'Daily-Prod.'!WG6+'Daily-Prod.'!VX6+'Daily-Prod.'!VO6+'Daily-Prod.'!VF6+'Daily-Prod.'!UW6+'Daily-Prod.'!UN6+'Daily-Prod.'!UE6)/Y6,"") -> 0.42359249 | W6: =IFERROR(('Daily-Prod.'!ADO6+'Daily-Prod.'!ADF6+'Daily-Prod.'!ACW6+'Daily-Prod.'!ACN6+'Daily-Prod.'!ACE6+'Daily-Prod.'!ABV6+'Daily-Prod.'!ABM6+'Daily-Prod.'!ABD6+'Daily-Prod.'!AAU6+'Daily-Prod.'!AAL6+'Daily-Prod.'!AAC6+'Daily-Prod.'!ZT6+'Daily-Prod.'!ZK6+'Daily-Prod.'!ZB6+'Daily-Prod.'!YS6+'Daily-Prod.'!YJ6+'Daily-Prod.'!YA6+'Daily-Prod.'!XR6+'Daily-Prod.'!XI6+'Daily-Prod.'!WZ6+'Daily-Prod.'!WQ6+'Daily-Prod.'!WH6+'Daily-Prod.'!VY6+'Daily-Prod.'!VP6+'Daily-Prod.'!VG6+'Daily-Prod.'!UX6+'Daily-Prod.'!UO6+'Daily-Prod.'!UF6)/Y6,"") -> 0.091152815 | X6: =IFERROR(('Daily-Prod.'!ADR6+'Daily-Prod.'!ADI6+'Daily-Prod.'!ACZ6+'Daily-Prod.'!ACQ6+'Daily-Prod.'!ACH6+'Daily-Prod.'!ABY6+'Daily-Prod.'!ABP6+'Daily-Prod.'!ABG6+'Daily-Prod.'!AAX6+'Daily-Prod.'!AAO6+'Daily-Prod.'!AAF6+'Daily-Prod.'!ZW6+'Daily-Prod.'!ZN6+'Daily-Prod.'!ZE6+'Daily-Prod.'!YV6+'Daily-Prod.'!YM6+'Daily-Prod.'!YD6+'Daily-Prod.'!XU6+'Daily-Prod.'!XL6+'Daily-Prod.'!XC6+'Daily-Prod.'!WT6+'Daily-Prod.'!WK6+'Daily-Prod.'!WB6+'Daily-Prod.'!VS6+'Daily-Prod.'!VJ6+'Daily-Prod.'!VA6+'Daily-Prod.'!UR6+'Daily-Prod.'!UI6+'Daily-Prod.'!ADQ6+'Daily-Prod.'!ADH6+'Daily-Prod.'!ACY6+'Daily-Prod.'!ACP6+'Daily-Prod.'!ACG6+'Daily-Prod.'!ABX6+'Daily-Prod.'!ABO6+'Daily-Prod.'!ABF6+'Daily-Prod.'!AAW6+'Daily-Prod.'!AAN6+'Daily-Prod.'!AAE6+'Daily-Prod.'!ZV6+'Daily-Prod.'!ZM6+'Daily-Prod.'!ZD6+'Daily-Prod.'!YU6+'Daily-Prod.'!YL6+'Daily-Prod.'!YC6+'Daily-Prod.'!XT6+'Daily-Prod.'!XK6+'Daily-Prod.'!XB6+'Daily-Prod.'!WS6+'Daily-Prod.'!WJ6+'Daily-Prod.'!WA6+'Daily-Prod.'!VR6+'Daily-Prod.'!VI6+'Daily-Prod.'!UZ6+'Daily-Prod.'!UQ6+'Daily-Prod.'!UH6)/Y6,"") -> 0.48525469 | Y6: =IFERROR(('Daily-Prod.'!ADS6+'Daily-Prod.'!ADJ6+'Daily-Prod.'!ADA6+'Daily-Prod.'!ACR6+'Daily-Prod.'!ACI6+'Daily-Prod.'!ABZ6+'Daily-Prod.'!ABQ6+'Daily-Prod.'!ABH6+'Daily-Prod.'!AAY6+'Daily-Prod.'!AAP6+'Daily-Prod.'!AAG6+'Daily-Prod.'!ZX6+'Daily-Prod.'!ZO6+'Daily-Prod.'!ZF6+'Daily-Prod.'!YW6+'Daily-Prod.'!YN6+'Daily-Prod.'!YE6+'Daily-Prod.'!XV6+'Daily-Prod.'!XM6+'Daily-Prod.'!XD6+'Daily-Prod.'!WU6+'Daily-Prod.'!WL6+'Daily-Prod.'!WC6+'Daily-Prod.'!VT6+'Daily-Prod.'!VK6+'Daily-Prod.'!VB6+'Daily-Prod.'!US6+'Daily-Prod.'!UJ6),"") -> 373 | AA6: =IFERROR(('Daily-Prod.'!ADU6+'Daily-Prod.'!ADL6+'Daily-Prod.'!ADC6+'Daily-Prod.'!ACT6+'Daily-Prod.'!ACK6+'Daily-Prod.'!ACB6+'Daily-Prod.'!ABS6+'Daily-Prod.'!ABJ6+'Daily-Prod.'!ABA6+'Daily-Prod.'!AAR6+'Daily-Prod.'!AAI6+'Daily-Prod.'!ZZ6+'Daily-Prod.'!ZQ6+'Daily-Prod.'!ZH6+'Daily-Prod.'!YY6+'Daily-Prod.'!YP6+'Daily-Prod.'!YG6+'Daily-Prod.'!XX6+'Daily-Prod.'!XO6+'Daily-Prod.'!XF6+'Daily-Prod.'!WW6+'Daily-Prod.'!WN6+'Daily-Prod.'!WE6+'Daily-Prod.'!VV6+'Daily-Prod.'!VM6+'Daily-Prod.'!VD6+'Daily-Prod.'!UU6+'Daily-Prod.'!UL6),"") -> 210 | AB6: =IFERROR((AA6/Z6),"") | AC6: =IFERROR(AVERAGE('Daily-Prod.'!ADS6,'Daily-Prod.'!ADJ6,'Daily-Prod.'!ADA6,'Daily-Prod.'!ACR6,'Daily-Prod.'!ACI6,'Daily-Prod.'!ABZ6,'Daily-Prod.'!ABQ6,'Daily-Prod.'!ABH6,'Daily-Prod.'!AAY6,'Daily-Prod.'!AAP6,'Daily-Prod.'!AAG6,'Daily-Prod.'!ZX6,'Daily-Prod.'!ZO6,'Daily-Prod.'!ZF6,'Daily-Prod.'!YW6,'Daily-Prod.'!YN6,'Daily-Prod.'!YE6,'Daily-Prod.'!XV6,'Daily-Prod.'!XM6,'Daily-Prod.'!XD6,'Daily-Prod.'!WU6,'Daily-Prod.'!WL6,'Daily-Prod.'!WC6,'Daily-Prod.'!VT6,'Daily-Prod.'!VK6,'Daily-Prod.'!VB6,'Daily-Prod.'!US6,'Daily-Prod.'!UJ6),"") -> 19.631579 | AE6: =IFERROR(AVERAGE('Daily-Prod.'!ADU6,'Daily-Prod.'!ADL6,'Daily-Prod.'!ADC6,'Daily-Prod.'!ACT6,'Daily-Prod.'!ACK6,'Daily-Prod.'!ACB6,'Daily-Prod.'!ABS6,'Daily-Prod.'!ABJ6,'Daily-Prod.'!ABA6,'Daily-Prod.'!AAR6,'Daily-Prod.'!AAI6,'Daily-Prod.'!ZZ6,'Daily-Prod.'!ZQ6,'Daily-Prod.'!ZH6,'Daily-Prod.'!YY6,'Daily-Prod.'!YP6,'Daily-Prod.'!YG6,'Daily-Prod.'!XX6,'Daily-Prod.'!XO6,'Daily-Prod.'!XF6,'Daily-Prod.'!WW6,'Daily-Prod.'!WN6,'Daily-Prod.'!WE6,'Daily-Prod.'!VV6,'Daily-Prod.'!VM6,'Daily-Prod.'!VD6,'Daily-Prod.'!UU6,'Daily-Prod.'!UL6),"") -> 11.666667 | AF6: =IFERROR(('Daily-Prod.'!AOG6+'Daily-Prod.'!ANX6+'Daily-Prod.'!ANO6+'Daily-Prod.'!ANF6+'Daily-Prod.'!AMW6+'Daily-Prod.'!AMN6+'Daily-Prod.'!AME6+'Daily-Prod.'!ALV6+'Daily-Prod.'!ALM6+'Daily-Prod.'!ALD6+'Daily-Prod.'!AKU6+'Daily-Prod.'!AKL6+'Daily-Prod.'!AKC6+'Daily-Prod.'!AJT6+'Daily-Prod.'!AJK6+'Daily-Prod.'!AJB6+'Daily-Prod.'!AIS6+'Daily-Prod.'!AIJ6+'Daily-Prod.'!AIA6+'Daily-Prod.'!AHR6+'Daily-Prod.'!AHI6+'Daily-Prod.'!AGZ6+'Daily-Prod.'!AGQ6+'Daily-Prod.'!AGH6+'Daily-Prod.'!AFY6+'Daily-Prod.'!AFP6+'Daily-Prod.'!AFG6+'Daily-Prod.'!AEX6+'Daily-Prod.'!AEO6+'Daily-Prod.'!AEF6+'Daily-Prod.'!ADW6)/AI6,"") -> 0.30357143 | AG6: =IFERROR(('Daily-Prod.'!AOH6+'Daily-Prod.'!ANY6+'Daily-Prod.'!ANP6+'Daily-Prod.'!ANG6+'Daily-Prod.'!AMX6+'Daily-Prod.'!AMO6+'Daily-Prod.'!AMF6+'Daily-Prod.'!ALW6+'Daily-Prod.'!ALN6+'Daily-Prod.'!ALE6+'Daily-Prod.'!AKV6+'Daily-Prod.'!AKM6+'Daily-Prod.'!AKD6+'Daily-Prod.'!AJU6+'Daily-Prod.'!AJL6+'Daily-Prod.'!AJC6+'Daily-Prod.'!AIT6+'Daily-Prod.'!AIK6+'Daily-Prod.'!AIB6+'Daily-Prod.'!AHS6+'Daily-Prod.'!AHJ6+'Daily-Prod.'!AHA6+'Daily-Prod.'!AGR6+'Daily-Prod.'!AGI6+'Daily-Prod.'!AFZ6+'Daily-Prod.'!AFQ6+'Daily-Prod.'!AFH6+'Daily-Prod.'!AEY6+'Daily-Prod.'!AEP6+'Daily-Prod.'!AEG6+'Daily-Prod.'!ADX6)/AI6,"") -> 0.10714286 | AH6: =IFERROR(('Daily-Prod.'!AOK6+'Daily-Prod.'!AOB6+'Daily-Prod.'!ANS6+'Daily-Prod.'!ANJ6+'Daily-Prod.'!ANA6+'Daily-Prod.'!AMR6+'Daily-Prod.'!AMI6+'Daily-Prod.'!ALZ6+'Daily-Prod.'!ALQ6+'Daily-Prod.'!ALH6+'Daily-Prod.'!AKY6+'Daily-Prod.'!AKP6+'Daily-Prod.'!AKG6+'Daily-Prod.'!AJX6+'Daily-Prod.'!AJO6+'Daily-Prod.'!AJF6+'Daily-Prod.'!AIW6+'Daily-Prod.'!AIN6+'Daily-Prod.'!AIE6+'Daily-Prod.'!AHV6+'Daily-Prod.'!AHM6+'Daily-Prod.'!AHD6+'Daily-Prod.'!AGU6+'Daily-Prod.'!AGL6+'Daily-Prod.'!AGC6+'Daily-Prod.'!AFT6+'Daily-Prod.'!AFK6+'Daily-Prod.'!AFB6+'Daily-Prod.'!AES6+'Daily-Prod.'!AEJ6+'Daily-Prod.'!AEA6+'Daily-Prod.'!AOJ6+'Daily-Prod.'!AOA6+'Daily-Prod.'!ANR6+'Daily-Prod.'!ANI6+'Daily-Prod.'!AMZ6+'Daily-Prod.'!AMQ6+'Daily-Prod.'!AMH6+'Daily-Prod.'!ALY6+'Daily-Prod.'!ALP6+'Daily-Prod.'!ALG6+'Daily-Prod.'!AKX6+'Daily-Prod.'!AKO6+'Daily-Prod.'!AKF6+'Daily-Prod.'!AJW6+'Daily-Prod.'!AJN6+'Daily-Prod.'!AJE6+'Daily-Prod.'!AIV6+'Daily-Prod.'!AIM6+'Daily-Prod.'!AID6+'Daily-Prod.'!AHU6+'Daily-Prod.'!AHL6+'Daily-Prod.'!AHC6+'Daily-Prod.'!AGT6+'Daily-Prod.'!AGK6+'Daily-Prod.'!AGB6+'Daily-Prod.'!AFS6+'Daily-Prod.'!AFJ6+'Daily-Prod.'!AFA6+'Daily-Prod.'!AER6+'Daily-Prod.'!AEI6+'Daily-Prod.'!ADZ6)/AI6,"") -> 0.58928571 | AI6: =IFERROR(('Daily-Prod.'!AOL6+'Daily-Prod.'!AOC6+'Daily-Prod.'!ANT6+'Daily-Prod.'!ANK6+'Daily-Prod.'!ANB6+'Daily-Prod.'!AMS6+'Daily-Prod.'!AMJ6+'Daily-Prod.'!AMA6+'Daily-Prod.'!ALR6+'Daily-Prod.'!ALI6+'Daily-Prod.'!AKZ6+'Daily-Prod.'!AKQ6+'Daily-Prod.'!AKH6+'Daily-Prod.'!AJY6+'Daily-Prod.'!AJP6+'Daily-Prod.'!AJG6+'Daily-Prod.'!AIX6+'Daily-Prod.'!AIO6+'Daily-Prod.'!AIF6+'Daily-Prod.'!AHW6+'Daily-Prod.'!AHN6+'Daily-Prod.'!AHE6+'Daily-Prod.'!AGV6+'Daily-Prod.'!AGM6+'Daily-Prod.'!AGD6+'Daily-Prod.'!AFU6+'Daily-Prod.'!AFL6+'Daily-Prod.'!AFC6+'Daily-Prod.'!AET6+'Daily-Prod.'!AEK6+'Daily-Prod.'!AEB6),"") -> 336 | AK6: =IFERROR(('Daily-Prod.'!AON6+'Daily-Prod.'!AOE6+'Daily-Prod.'!ANV6+'Daily-Prod.'!ANM6+'Daily-Prod.'!AND6+'Daily-Prod.'!AMU6+'Daily-Prod.'!AML6+'Daily-Prod.'!AMC6+'Daily-Prod.'!ALT6+'Daily-Prod.'!ALK6+'Daily-Prod.'!ALB6+'Daily-Prod.'!AKS6+'Daily-Prod.'!AKJ6+'Daily-Prod.'!AKA6+'Daily-Prod.'!AJR6+'Daily-Prod.'!AJI6+'Daily-Prod.'!AIZ6+'Daily-Prod.'!AIQ6+'Daily-Prod.'!AIH6+'Daily-Prod.'!AHY6+'Daily-Prod.'!AHP6+'Daily-Prod.'!AHG6+'Daily-Prod.'!AGX6+'Daily-Prod.'!AGO6+'Daily-Prod.'!AGF6+'Daily-Prod.'!AFW6+'Daily-Prod.'!AFN6+'Daily-Prod.'!AFE6+'Daily-Prod.'!AEV6+'Daily-Prod.'!AEM6+'Daily-Prod.'!AED6),"") -> 287 | AL6: =IFERROR((AK6/AJ6),"") | AM6: =IFERROR(AVERAGE('Daily-Prod.'!AOL6,'Daily-Prod.'!AOC6,'Daily-Prod.'!ANT6,'Daily-Prod.'!ANK6,'Daily-Prod.'!ANB6,'Daily-Prod.'!AMS6,'Daily-Prod.'!AMJ6,'Daily-Prod.'!AMA6,'Daily-Prod.'!ALR6,'Daily-Prod.'!ALI6,'Daily-Prod.'!AKZ6,'Daily-Prod.'!AKQ6,'Daily-Prod.'!AKH6,'Daily-Prod.'!AJY6,'Daily-Prod.'!AJP6,'Daily-Prod.'!AJG6,'Daily-Prod.'!AIX6,'Daily-Prod.'!AIO6,'Daily-Prod.'!AIF6,'Daily-Prod.'!AHW6,'Daily-Prod.'!AHN6,'Daily-Prod.'!AHE6,'Daily-Prod.'!AGV6,'Daily-Prod.'!AGM6,'Daily-Prod.'!AGD6,'Daily-Prod.'!AFU6,'Daily-Prod.'!AFL6,'Daily-Prod.'!AFC6,'Daily-Prod.'!AET6,'Daily-Prod.'!AEK6,'Daily-Prod.'!AEB6),"") -> 16 | AO6: =IFERROR(AVERAGE('Daily-Prod.'!AON6,'Daily-Prod.'!AOE6,'Daily-Prod.'!ANV6,'Daily-Prod.'!ANM6,'Daily-Prod.'!AND6,'Daily-Prod.'!AMU6,'Daily-Prod.'!AML6,'Daily-Prod.'!AMC6,'Daily-Prod.'!ALT6,'Daily-Prod.'!ALK6,'Daily-Prod.'!ALB6,'Daily-Prod.'!AKS6,'Daily-Prod.'!AKJ6,'Daily-Prod.'!AKA6,'Daily-Prod.'!AJR6,'Daily-Prod.'!AJI6,'Daily-Prod.'!AIZ6,'Daily-Prod.'!AIQ6,'Daily-Prod.'!AIH6,'Daily-Prod.'!AHY6,'Daily-Prod.'!AHP6,'Daily-Prod.'!AHG6,'Daily-Prod.'!AGX6,'Daily-Prod.'!AGO6,'Daily-Prod.'!AGF6,'Daily-Prod.'!AFW6,'Daily-Prod.'!AFN6,'Daily-Prod.'!AFE6,'Daily-Prod.'!AEV6,'Daily-Prod.'!AEM6,'Daily-Prod.'!AED6),"") -> 13.666667 | AP6: =IFERROR(('Daily-Prod.'!AYZ6+'Daily-Prod.'!AYQ6+'Daily-Prod.'!AYH6+'Daily-Prod.'!AXY6+'Daily-Prod.'!AXP6+'Daily-Prod.'!AXG6+'Daily-Prod.'!AWX6+'Daily-Prod.'!AWO6+'Daily-Prod.'!AWF6+'Daily-Prod.'!AVW6+'Daily-Prod.'!AVN6+'Daily-Prod.'!AVE6+'Daily-Prod.'!AUV6+'Daily-Prod.'!AUM6+'Daily-Prod.'!AUD6+'Daily-Prod.'!ATU6+'Daily-Prod.'!ATL6+'Daily-Prod.'!ATC6+'Daily-Prod.'!AST6+'Daily-Prod.'!ASK6+'Daily-Prod.'!ASB6+'Daily-Prod.'!ARS6+'Daily-Prod.'!ARJ6+'Daily-Prod.'!ARA6+'Daily-Prod.'!AQR6+'Daily-Prod.'!AQI6+'Daily-Prod.'!APZ6+'Daily-Prod.'!APQ6+'Daily-Prod.'!APH6+'Daily-Prod.'!AOY6+'Daily-Prod.'!AOP6)/AS6,"") -> 0.32458234 | AQ6: =IFERROR(('Daily-Prod.'!AZA6+'Daily-Prod.'!AYR6+'Daily-Prod.'!AYI6+'Daily-Prod.'!AXZ6+'Daily-Prod.'!AXQ6+'Daily-Prod.'!AXH6+'Daily-Prod.'!AWY6+'Daily-Prod.'!AWP6+'Daily-Prod.'!AWG6+'Daily-Prod.'!AVX6+'Daily-Prod.'!AVO6+'Daily-Prod.'!AVF6+'Daily-Prod.'!AUW6+'Daily-Prod.'!AUN6+'Daily-Prod.'!AUE6+'Daily-Prod.'!ATV6+'Daily-Prod.'!ATM6+'Daily-Prod.'!ATD6+'Daily-Prod.'!ASU6+'Daily-Prod.'!ASL6+'Daily-Prod.'!ASC6+'Daily-Prod.'!ART6+'Daily-Prod.'!ARK6+'Daily-Prod.'!ARB6+'Daily-Prod.'!AQS6+'Daily-Prod.'!AQJ6+'Daily-Prod.'!AQA6+'Daily-Prod.'!APR6+'Daily-Prod.'!API6+'Daily-Prod.'!AOZ6+'Daily-Prod.'!AOQ6)/AS6,"") -> 0.07398568 | AR6: =IFERROR(('Daily-Prod.'!AZC6+'Daily-Prod.'!AYT6+'Daily-Prod.'!AYK6+'Daily-Prod.'!AYB6+'Daily-Prod.'!AXS6+'Daily-Prod.'!AXJ6+'Daily-Prod.'!AXA6+'Daily-Prod.'!AWR6+'Daily-Prod.'!AWI6+'Daily-Prod.'!AVZ6+'Daily-Prod.'!AVQ6+'Daily-Prod.'!AVH6+'Daily-Prod.'!AUY6+'Daily-Prod.'!AUP6+'Daily-Prod.'!AUG6+'Daily-Prod.'!ATX6+'Daily-Prod.'!ATO6+'Daily-Prod.'!ATF6+'Daily-Prod.'!ASW6+'Daily-Prod.'!ASN6+'Daily-Prod.'!ASE6+'Daily-Prod.'!ARV6+'Daily-Prod.'!ARM6+'Daily-Prod.'!ARD6+'Daily-Prod.'!AQU6+'Daily-Prod.'!AQL6+'Daily-Prod.'!AQC6+'Daily-Prod.'!APT6+'Daily-Prod.'!APK6+'Daily-Prod.'!APB6+'Daily-Prod.'!AOS6+'Daily-Prod.'!AZD6+'Daily-Prod.'!AYU6+'Daily-Prod.'!AYL6+'Daily-Prod.'!AYC6+'Daily-Prod.'!AXT6+'Daily-Prod.'!AXK6+'Daily-Prod.'!AXB6+'Daily-Prod.'!AWS6+'Daily-Prod.'!AWJ6+'Daily-Prod.'!AWA6+'Daily-Prod.'!AVR6+'Daily-Prod.'!AVI6+'Daily-Prod.'!AUZ6+'Daily-Prod.'!AUQ6+'Daily-Prod.'!AUH6+'Daily-Prod.'!ATY6+'Daily-Prod.'!ATP6+'Daily-Prod.'!ATG6+'Daily-Prod.'!ASX6+'Daily-Prod.'!ASO6+'Daily-Prod.'!ASF6+'Daily-Prod.'!ARW6+'Daily-Prod.'!ARN6+'Daily-Prod.'!ARE6+'Daily-Prod.'!AQV6+'Daily-Prod.'!AQM6+'Daily-Prod.'!AQD6+'Daily-Prod.'!APU6+'Daily-Prod.'!APL6+'Daily-Prod.'!APC6+'Daily-Prod.'!AOT6)/AS6,"") -> 0.60143198 | AS6: =IFERROR(('Daily-Prod.'!AZE6+'Daily-Prod.'!AYV6+'Daily-Prod.'!AYM6+'Daily-Prod.'!AYD6+'Daily-Prod.'!AXU6+'Daily-Prod.'!AXL6+'Daily-Prod.'!AXC6+'Daily-Prod.'!AWT6+'Daily-Prod.'!AWK6+'Daily-Prod.'!AWB6+'Daily-Prod.'!AVS6+'Daily-Prod.'!AVJ6+'Daily-Prod.'!AVA6+'Daily-Prod.'!AUR6+'Daily-Prod.'!AUI6+'Daily-Prod.'!ATZ6+'Daily-Prod.'!ATQ6+'Daily-Prod.'!ATH6+'Daily-Prod.'!ASY6+'Daily-Prod.'!ASP6+'Daily-Prod.'!ASG6+'Daily-Prod.'!ARX6+'Daily-Prod.'!ARO6+'Daily-Prod.'!ARF6+'Daily-Prod.'!AQW6+'Daily-Prod.'!AQN6+'Daily-Prod.'!AQE6+'Daily-Prod.'!APV6+'Daily-Prod.'!APM6+'Daily-Prod.'!APD6+'Daily-Prod.'!AOU6),"") -> 419 | AU6: =IFERROR(('Daily-Prod.'!AZG6+'Daily-Prod.'!AYX6+'Daily-Prod.'!AYO6+'Daily-Prod.'!AYF6+'Daily-Prod.'!AXW6+'Daily-Prod.'!AXN6+'Daily-Prod.'!AXE6+'Daily-Prod.'!AWV6+'Daily-Prod.'!AWM6+'Daily-Prod.'!AWD6+'Daily-Prod.'!AVU6+'Daily-Prod.'!AVL6+'Daily-Prod.'!AVC6+'Daily-Prod.'!AUT6+'Daily-Prod.'!AUK6+'Daily-Prod.'!AUB6+'Daily-Prod.'!ATS6+'Daily-Prod.'!ATJ6+'Daily-Prod.'!ATA6+'Daily-Prod.'!ASR6+'Daily-Prod.'!ASI6+'Daily-Prod.'!ARZ6+'Daily-Prod.'!ARQ6+'Daily-Prod.'!ARH6+'Daily-Prod.'!AQY6+'Daily-Prod.'!AQP6+'Daily-Prod.'!AQG6+'Daily-Prod.'!APX6+'Daily-Prod.'!APO6+'Daily-Prod.'!APF6+'Daily-Prod.'!AOW6),"") -> 248 | AV6: =IFERROR((AU6/AT6),"") | AW6: =IFERROR(AVERAGE('Daily-Prod.'!AZE6,'Daily-Prod.'!AYV6,'Daily-Prod.'!AYM6,'Daily-Prod.'!AYD6,'Daily-Prod.'!AXU6,'Daily-Prod.'!AXL6,'Daily-Prod.'!AXC6,'Daily-Prod.'!AWT6,'Daily-Prod.'!AWK6,'Daily-Prod.'!AWB6,'Daily-Prod.'!AVS6,'Daily-Prod.'!AVJ6,'Daily-Prod.'!AVA6,'Daily-Prod.'!AUR6,'Daily-Prod.'!AUI6,'Daily-Prod.'!ATZ6,'Daily-Prod.'!ATQ6,'Daily-Prod.'!ATH6,'Daily-Prod.'!ASY6,'Daily-Prod.'!ASP6,'Daily-Prod.'!ASG6,'Daily-Prod.'!ARX6,'Daily-Prod.'!ARO6,'Daily-Prod.'!ARF6,'Daily-Prod.'!AQW6,'Daily-Prod.'!AQN6,'Daily-Prod.'!AQE6,'Daily-Prod.'!APV6,'Daily-Prod.'!APM6,'Daily-Prod.'!APD6,'Daily-Prod.'!AOU6),"") -> 19.952381 | AY6: =IFERROR(AVERAGE('Daily-Prod.'!AZG6,'Daily-Prod.'!AYX6,'Daily-Prod.'!AYO6,'Daily-Prod.'!AYF6,'Daily-Prod.'!AXW6,'Daily-Prod.'!AXN6,'Daily-Prod.'!AXE6,'Daily-Prod.'!AWV6,'Daily-Prod.'!AWM6,'Daily-Prod.'!AWD6,'Daily-Prod.'!AVU6,'Daily-Prod.'!AVL6,'Daily-Prod.'!AVC6,'Daily-Prod.'!AUT6,'Daily-Prod.'!AUK6,'Daily-Prod.'!AUB6,'Daily-Prod.'!ATS6,'Daily-Prod.'!ATJ6,'Daily-Prod.'!ATA6,'Daily-Prod.'!ASR6,'Daily-Prod.'!ASI6,'Daily-Prod.'!ARZ6,'Daily-Prod.'!ARQ6,'Daily-Prod.'!ARH6,'Daily-Prod.'!AQY6,'Daily-Prod.'!AQP6,'Daily-Prod.'!AQG6,'Daily-Prod.'!APX6,'Daily-Prod.'!APO6,'Daily-Prod.'!APF6,'Daily-Prod.'!AOW6),"") -> 10.782609 | AZ6: =IFERROR(('Daily-Prod.'!BJJ6+'Daily-Prod.'!BJA6+'Daily-Prod.'!BIR6+'Daily-Prod.'!BII6+'Daily-Prod.'!BHZ6+'Daily-Prod.'!BHQ6+'Daily-Prod.'!BHH6+'Daily-Prod.'!BGY6+'Daily-Prod.'!BGP6+'Daily-Prod.'!BGG6+'Daily-Prod.'!BFX6+'Daily-Prod.'!BFO6+'Daily-Prod.'!BFF6+'Daily-Prod.'!BEW6+'Daily-Prod.'!BEN6+'Daily-Prod.'!BEE6+'Daily-Prod.'!BDV6+'Daily-Prod.'!BDM6+'Daily-Prod.'!BDD6+'Daily-Prod.'!BCU6+'Daily-Prod.'!BCL6+'Daily-Prod.'!BCC6+'Daily-Prod.'!BBT6+'Daily-Prod.'!BBK6+'Daily-Prod.'!BBB6+'Daily-Prod.'!BAS6+'Daily-Prod.'!BAJ6+'Daily-Prod.'!BAA6+'Daily-Prod.'!AZR6+'Daily-Prod.'!AZI6)/BC6,"") -> 0.40045767 | BA6: =IFERROR(('Daily-Prod.'!BJK6+'Daily-Prod.'!BJB6+'Daily-Prod.'!BIS6+'Daily-Prod.'!BIJ6+'Daily-Prod.'!BIA6+'Daily-Prod.'!BHR6+'Daily-Prod.'!BHI6+'Daily-Prod.'!BGZ6+'Daily-Prod.'!BGQ6+'Daily-Prod.'!BGH6+'Daily-Prod.'!BFY6+'Daily-Prod.'!BFP6+'Daily-Prod.'!BFG6+'Daily-Prod.'!BEX6+'Daily-Prod.'!BEO6+'Daily-Prod.'!BEF6+'Daily-Prod.'!BDW6+'Daily-Prod.'!BDN6+'Daily-Prod.'!BDE6+'Daily-Prod.'!BCV6+'Daily-Prod.'!BCM6+'Daily-Prod.'!BCD6+'Daily-Prod.'!BBU6+'Daily-Prod.'!BBL6+'Daily-Prod.'!BBC6+'Daily-Prod.'!BAT6+'Daily-Prod.'!BAK6+'Daily-Prod.'!BAB6+'Daily-Prod.'!AZS6+'Daily-Prod.'!AZJ6)/BC6,"") -> 0.082379863 | BB6: =IFERROR(('Daily-Prod.'!BJM6+'Daily-Prod.'!BJD6+'Daily-Prod.'!BIU6+'Daily-Prod.'!BIL6+'Daily-Prod.'!BIC6+'Daily-Prod.'!BHT6+'Daily-Prod.'!BHK6+'Daily-Prod.'!BHB6+'Daily-Prod.'!BGS6+'Daily-Prod.'!BGJ6+'Daily-Prod.'!BGA6+'Daily-Prod.'!BFR6+'Daily-Prod.'!BFI6+'Daily-Prod.'!BEZ6+'Daily-Prod.'!BEQ6+'Daily-Prod.'!BEH6+'Daily-Prod.'!BDY6+'Daily-Prod.'!BDP6+'Daily-Prod.'!BDG6+'Daily-Prod.'!BCX6+'Daily-Prod.'!BCO6+'Daily-Prod.'!BCF6+'Daily-Prod.'!BBW6+'Daily-Prod.'!BBN6+'Daily-Prod.'!BBE6+'Daily-Prod.'!BAV6+'Daily-Prod.'!BAM6+'Daily-Prod.'!BAD6+'Daily-Prod.'!AZU6+'Daily-Prod.'!AZL6+'Daily-Prod.'!BJN6+'Daily-Prod.'!BJE6+'Daily-Prod.'!BIV6+'Daily-Prod.'!BIM6+'Daily-Prod.'!BID6+'Daily-Prod.'!BHU6+'Daily-Prod.'!BHL6+'Daily-Prod.'!BHC6+'Daily-Prod.'!BGT6+'Daily-Prod.'!BGK6+'Daily-Prod.'!BGB6+'Daily-Prod.'!BFS6+'Daily-Prod.'!BFJ6+'Daily-Prod.'!BFA6+'Daily-Prod.'!BER6+'Daily-Prod.'!BEI6+'Daily-Prod.'!BDZ6+'Daily-Prod.'!BDQ6+'Daily-Prod.'!BDH6+'Daily-Prod.'!BCY6+'Daily-Prod.'!BCP6+'Daily-Prod.'!BCG6+'Daily-Prod.'!BBX6+'Daily-Prod.'!BBO6+'Daily-Prod.'!BBF6+'Daily-Prod.'!BAW6+'Daily-Prod.'!BAN6+'Daily-Prod.'!BAE6+'Daily-Prod.'!AZV6+'Daily-Prod.'!AZM6)/BC6,"") -> 0.51716247 | BC6: =IFERROR(('Daily-Prod.'!BJO6+'Daily-Prod.'!BJF6+'Daily-Prod.'!BIW6+'Daily-Prod.'!BIN6+'Daily-Prod.'!BIE6+'Daily-Prod.'!BHV6+'Daily-Prod.'!BHM6+'Daily-Prod.'!BHD6+'Daily-Prod.'!BGU6+'Daily-Prod.'!BGL6+'Daily-Prod.'!BGC6+'Daily-Prod.'!BFT6+'Daily-Prod.'!BFK6+'Daily-Prod.'!BFB6+'Daily-Prod.'!BES6+'Daily-Prod.'!BEJ6+'Daily-Prod.'!BEA6+'Daily-Prod.'!BDR6+'Daily-Prod.'!BDI6+'Daily-Prod.'!BCZ6+'Daily-Prod.'!BCQ6+'Daily-Prod.'!BCH6+'Daily-Prod.'!BBY6+'Daily-Prod.'!BBP6+'Daily-Prod.'!BBG6+'Daily-Prod.'!BAX6+'Daily-Prod.'!BAO6+'Daily-Prod.'!BAF6+'Daily-Prod.'!AZW6+'Daily-Prod.'!AZN6),"") -> 437 | BD6: =IFERROR(('Daily-Prod.'!BJP6+'Daily-Prod.'!BJG6+'Daily-Prod.'!BIX6+'Daily-Prod.'!BIO6+'Daily-Prod.'!BIF6+'Daily-Prod.'!BHW6+'Daily-Prod.'!BHN6+'Daily-Prod.'!BHE6+'Daily-Prod.'!BGV6+'Daily-Prod.'!BGM6+'Daily-Prod.'!BGD6+'Daily-Prod.'!BFU6+'Daily-Prod.'!BFL6+'Daily-Prod.'!BFC6+'Daily-Prod.'!BET6+'Daily-Prod.'!BEK6+'Daily-Prod.'!BEB6+'Daily-Prod.'!BDS6+'Daily-Prod.'!BDJ6+'Daily-Prod.'!BDA6+'Daily-Prod.'!BCR6+'Daily-Prod.'!BCI6+'Daily-Prod.'!BBZ6+'Daily-Prod.'!BBQ6+'Daily-Prod.'!BBH6+'Daily-Prod.'!BAY6+'Daily-Prod.'!BAP6+'Daily-Prod.'!BAG6+'Daily-Prod.'!AZX6+'Daily-Prod.'!AZO6),"") -> 320 | BE6: =IFERROR(('Daily-Prod.'!BJQ6+'Daily-Prod.'!BJH6+'Daily-Prod.'!BIY6+'Daily-Prod.'!BIP6+'Daily-Prod.'!BIG6+'Daily-Prod.'!BHX6+'Daily-Prod.'!BHO6+'Daily-Prod.'!BHF6+'Daily-Prod.'!BGW6+'Daily-Prod.'!BGN6+'Daily-Prod.'!BGE6+'Daily-Prod.'!BFV6+'Daily-Prod.'!BFM6+'Daily-Prod.'!BFD6+'Daily-Prod.'!BEU6+'Daily-Prod.'!BEL6+'Daily-Prod.'!BEC6+'Daily-Prod.'!BDT6+'Daily-Prod.'!BDK6+'Daily-Prod.'!BDB6+'Daily-Prod.'!BCS6+'Daily-Prod.'!BCJ6+'Daily-Prod.'!BCA6+'Daily-Prod.'!BBR6+'Daily-Prod.'!BBI6+'Daily-Prod.'!BAZ6+'Daily-Prod.'!BAQ6+'Daily-Prod.'!BAH6+'Daily-Prod.'!AZY6+'Daily-Prod.'!AZP6),"") -> 319 | BF6: =IFERROR((BE6/BD6),"") -> 0.996875 | BG6: =IFERROR(AVERAGE('Daily-Prod.'!BJO6,'Daily-Prod.'!BJF6,'Daily-Prod.'!BIW6,'Daily-Prod.'!BIN6,'Daily-Prod.'!BIE6,'Daily-Prod.'!BHV6,'Daily-Prod.'!BHM6,'Daily-Prod.'!BHD6,'Daily-Prod.'!BGU6,'Daily-Prod.'!BGL6,'Daily-Prod.'!BGC6,'Daily-Prod.'!BFT6,'Daily-Prod.'!BFK6,'Daily-Prod.'!BFB6,'Daily-Prod.'!BES6,'Daily-Prod.'!BEJ6,'Daily-Prod.'!BEA6,'Daily-Prod.'!BDR6,'Daily-Prod.'!BDI6,'Daily-Prod.'!BCZ6,'Daily-Prod.'!BCQ6,'Daily-Prod.'!BCH6,'Daily-Prod.'!BBY6,'Daily-Prod.'!BBP6,'Daily-Prod.'!BBG6,'Daily-Prod.'!BAX6,'Daily-Prod.'!BAO6,'Daily-Prod.'!BAF6,'Daily-Prod.'!AZW6,'Daily-Prod.'!AZN6),"") -> 20.809524 | BH6: =IFERROR(AVERAGE('Daily-Prod.'!BJP6,'Daily-Prod.'!BJG6,'Daily-Prod.'!BIX6,'Daily-Prod.'!BIO6,'Daily-Prod.'!BIF6,'Daily-Prod.'!BHW6,'Daily-Prod.'!BHN6,'Daily-Prod.'!BHE6,'Daily-Prod.'!BGV6,'Daily-Prod.'!BGM6,'Daily-Prod.'!BGD6,'Daily-Prod.'!BFU6,'Daily-Prod.'!BFL6,'Daily-Prod.'!BFC6,'Daily-Prod.'!BET6,'Daily-Prod.'!BEK6,'Daily-Prod.'!BEB6,'Daily-Prod.'!BDS6,'Daily-Prod.'!BDJ6,'Daily-Prod.'!BDA6,'Daily-Prod.'!BCR6,'Daily-Prod.'!BCI6,'Daily-Prod.'!BBZ6,'Daily-Prod.'!BBQ6,'Daily-Prod.'!BBH6,'Daily-Prod.'!BAY6,'Daily-Prod.'!BAP6,'Daily-Prod.'!BAG6,'Daily-Prod.'!AZX6,'Daily-Prod.'!AZO6),"") -> 10.666667 | BI6: =IFERROR(AVERAGE('Daily-Prod.'!BJQ6,'Daily-Prod.'!BJH6,'Daily-Prod.'!BIY6,'Daily-Prod.'!BIP6,'Daily-Prod.'!BIG6,'Daily-Prod.'!BHX6,'Daily-Prod.'!BHO6,'Daily-Prod.'!BHF6,'Daily-Prod.'!BGW6,'Daily-Prod.'!BGN6,'Daily-Prod.'!BGE6,'Daily-Prod.'!BFV6,'Daily-Prod.'!BFM6,'Daily-Prod.'!BFD6,'Daily-Prod.'!BEU6,'Daily-Prod.'!BEL6,'Daily-Prod.'!BEC6,'Daily-Prod.'!BDT6,'Daily-Prod.'!BDK6,'Daily-Prod.'!BDB6,'Daily-Prod.'!BCS6,'Daily-Prod.'!BCJ6,'Daily-Prod.'!BCA6,'Daily-Prod.'!BBR6,'Daily-Prod.'!BBI6,'Daily-Prod.'!BAZ6,'Daily-Prod.'!BAQ6,'Daily-Prod.'!BAH6,'Daily-Prod.'!AZY6,'Daily-Prod.'!AZP6),"") -> 10.633333 | BJ6: =IFERROR((('Daily-Prod.'!BUC6+'Daily-Prod.'!BTT6+'Daily-Prod.'!BTK6+'Daily-Prod.'!BTB6+'Daily-Prod.'!BSS6+'Daily-Prod.'!BSJ6+'Daily-Prod.'!BSA6+'Daily-Prod.'!BRR6+'Daily-Prod.'!BRI6+'Daily-Prod.'!BQZ6+'Daily-Prod.'!BQQ6+'Daily-Prod.'!BQH6+'Daily-Prod.'!BPY6+'Daily-Prod.'!BPP6+'Daily-Prod.'!BPG6+'Daily-Prod.'!BOX6+'Daily-Prod.'!BOO6+'Daily-Prod.'!BOF6+'Daily-Prod.'!BNW6+'Daily-Prod.'!BNN6+'Daily-Prod.'!BNE6+'Daily-Prod.'!BMV6+'Daily-Prod.'!BMM6+'Daily-Prod.'!BMD6+'Daily-Prod.'!BLU6+'Daily-Prod.'!BLL6+'Daily-Prod.'!BLC6+'Daily-Prod.'!BKT6+'Daily-Prod.'!BKK6+'Daily-Prod.'!BKB6+'Daily-Prod.'!BJS6)/BM6),"") -> 0.45392491 | BK6: =IFERROR((('Daily-Prod.'!BUD6+'Daily-Prod.'!BTU6+'Daily-Prod.'!BTL6+'Daily-Prod.'!BTC6+'Daily-Prod.'!BST6+'Daily-Prod.'!BSK6+'Daily-Prod.'!BSB6+'Daily-Prod.'!BRS6+'Daily-Prod.'!BRJ6+'Daily-Prod.'!BRA6+'Daily-Prod.'!BQR6+'Daily-Prod.'!BQI6+'Daily-Prod.'!BPZ6+'Daily-Prod.'!BPQ6+'Daily-Prod.'!BPH6+'Daily-Prod.'!BOY6+'Daily-Prod.'!BOP6+'Daily-Prod.'!BOG6+'Daily-Prod.'!BNX6+'Daily-Prod.'!BNO6+'Daily-Prod.'!BNF6+'Daily-Prod.'!BMW6+'Daily-Prod.'!BMN6+'Daily-Prod.'!BME6+'Daily-Prod.'!BLV6+'Daily-Prod.'!BLM6+'Daily-Prod.'!BLD6+'Daily-Prod.'!BKU6+'Daily-Prod.'!BKL6+'Daily-Prod.'!BKC6+'Daily-Prod.'!BJT6)/BM6),"") -> 0.064846416 | BL6: =IFERROR((('Daily-Prod.'!BUG6+'Daily-Prod.'!BTX6+'Daily-Prod.'!BTO6+'Daily-Prod.'!BTF6+'Daily-Prod.'!BSW6+'Daily-Prod.'!BSN6+'Daily-Prod.'!BSE6+'Daily-Prod.'!BRV6+'Daily-Prod.'!BRM6+'Daily-Prod.'!BRD6+'Daily-Prod.'!BQU6+'Daily-Prod.'!BQL6+'Daily-Prod.'!BQC6+'Daily-Prod.'!BPT6+'Daily-Prod.'!BPK6+'Daily-Prod.'!BPB6+'Daily-Prod.'!BOS6+'Daily-Prod.'!BOJ6+'Daily-Prod.'!BOA6+'Daily-Prod.'!BNR6+'Daily-Prod.'!BNI6+'Daily-Prod.'!BMZ6+'Daily-Prod.'!BMQ6+'Daily-Prod.'!BMH6+'Daily-Prod.'!BLY6+'Daily-Prod.'!BLP6+'Daily-Prod.'!BLG6+'Daily-Prod.'!BKX6+'Daily-Prod.'!BKO6+'Daily-Prod.'!BKF6+'Daily-Prod.'!BJW6+'Daily-Prod.'!BUF6+'Daily-Prod.'!BTW6+'Daily-Prod.'!BTN6+'Daily-Prod.'!BTE6+'Daily-Prod.'!BSV6+'Daily-Prod.'!BSM6+'Daily-Prod.'!BSD6+'Daily-Prod.'!BRU6+'Daily-Prod.'!BRL6+'Daily-Prod.'!BRC6+'Daily-Prod.'!BQT6+'Daily-Prod.'!BQK6+'Daily-Prod.'!BQB6+'Daily-Prod.'!BPS6+'Daily-Prod.'!BPJ6+'Daily-Prod.'!BPA6+'Daily-Prod.'!BOR6+'Daily-Prod.'!BOI6+'Daily-Prod.'!BNZ6+'Daily-Prod.'!BNQ6+'Daily-Prod.'!BNH6+'Daily-Prod.'!BMY6+'Daily-Prod.'!BMP6+'Daily-Prod.'!BMG6+'Daily-Prod.'!BLX6+'Daily-Prod.'!BLO6+'Daily-Prod.'!BLF6+'Daily-Prod.'!BKW6+'Daily-Prod.'!BKN6+'Daily-Prod.'!BKE6+'Daily-Prod.'!BJV6)/BM6),"") -> 0.48122867 | BM6: =IFERROR(('Daily-Prod.'!BUH6+'Daily-Prod.'!BTY6+'Daily-Prod.'!BTP6+'Daily-Prod.'!BTG6+'Daily-Prod.'!BSX6+'Daily-Prod.'!BSO6+'Daily-Prod.'!BSF6+'Daily-Prod.'!BRW6+'Daily-Prod.'!BRN6+'Daily-Prod.'!BRE6+'Daily-Prod.'!BQV6+'Daily-Prod.'!BQM6+'Daily-Prod.'!BQD6+'Daily-Prod.'!BPU6+'Daily-Prod.'!BPL6+'Daily-Prod.'!BPC6+'Daily-Prod.'!BOT6+'Daily-Prod.'!BOK6+'Daily-Prod.'!BOB6+'Daily-Prod.'!BNS6+'Daily-Prod.'!BNJ6+'Daily-Prod.'!BNA6+'Daily-Prod.'!BMR6+'Daily-Prod.'!BMI6+'Daily-Prod.'!BLZ6+'Daily-Prod.'!BLQ6+'Daily-Prod.'!BLH6+'Daily-Prod.'!BKY6+'Daily-Prod.'!BKP6+'Daily-Prod.'!BKG6+'Daily-Prod.'!BJX6),"") -> 293 | BO6: =IFERROR(('Daily-Prod.'!BUJ6+'Daily-Prod.'!BUA6+'Daily-Prod.'!BTR6+'Daily-Prod.'!BTI6+'Daily-Prod.'!BSZ6+'Daily-Prod.'!BSQ6+'Daily-Prod.'!BSH6+'Daily-Prod.'!BRY6+'Daily-Prod.'!BRP6+'Daily-Prod.'!BRG6+'Daily-Prod.'!BQX6+'Daily-Prod.'!BQO6+'Daily-Prod.'!BQF6+'Daily-Prod.'!BPW6+'Daily-Prod.'!BPN6+'Daily-Prod.'!BPE6+'Daily-Prod.'!BOV6+'Daily-Prod.'!BOM6+'Daily-Prod.'!BOD6+'Daily-Prod.'!BNU6+'Daily-Prod.'!BNL6+'Daily-Prod.'!BNC6+'Daily-Prod.'!BMT6+'Daily-Prod.'!BMK6+'Daily-Prod.'!BMB6+'Daily-Prod.'!BLS6+'Daily-Prod.'!BLJ6+'Daily-Prod.'!BLA6+'Daily-Prod.'!BKR6+'Daily-Prod.'!BKI6+'Daily-Prod.'!BJZ6),"") -> 140 | BP6: =IFERROR((BO6/BN6),"") | BQ6: =IFERROR(AVERAGE(('Daily-Prod.'!BUH6,'Daily-Prod.'!BTY6,'Daily-Prod.'!BTP6,'Daily-Prod.'!BTG6,'Daily-Prod.'!BSX6,'Daily-Prod.'!BSO6,'Daily-Prod.'!BSF6,'Daily-Prod.'!BRW6,'Daily-Prod.'!BRN6,'Daily-Prod.'!BRE6,'Daily-Prod.'!BQV6,'Daily-Prod.'!BQM6,'Daily-Prod.'!BQD6,'Daily-Prod.'!BPU6,'Daily-Prod.'!BPL6,'Daily-Prod.'!BPC6,'Daily-Prod.'!BOT6,'Daily-Prod.'!BOK6,'Daily-Prod.'!BOB6,'Daily-Prod.'!BNS6,'Daily-Prod.'!BNJ6,'Daily-Prod.'!BNA6,'Daily-Prod.'!BMR6,'Daily-Prod.'!BMI6,'Daily-Prod.'!BLZ6,'Daily-Prod.'!BLQ6,'Daily-Prod.'!BLH6,'Daily-Prod.'!BKY6,'Daily-Prod.'!BKP6,'Daily-Prod.'!BKG6,'Daily-Prod.'!BJX6)),"") -> 13.952381 | BS6: =IFERROR((AVERAGE('Daily-Prod.'!BUJ6,'Daily-Prod.'!BUA6,'Daily-Prod.'!BTR6,'Daily-Prod.'!BTI6,'Daily-Prod.'!BSZ6,'Daily-Prod.'!BSQ6,'Daily-Prod.'!BSH6,'Daily-Prod.'!BRY6,'Daily-Prod.'!BRP6,'Daily-Prod.'!BRG6,'Daily-Prod.'!BQX6,'Daily-Prod.'!BQO6,'Daily-Prod.'!BQF6,'Daily-Prod.'!BPW6,'Daily-Prod.'!BPN6,'Daily-Prod.'!BPE6,'Daily-Prod.'!BOV6,'Daily-Prod.'!BOM6,'Daily-Prod.'!BOD6,'Daily-Prod.'!BNU6,'Daily-Prod.'!BNL6,'Daily-Prod.'!BNC6,'Daily-Prod.'!BMT6,'Daily-Prod.'!BMK6,'Daily-Prod.'!BMB6,'Daily-Prod.'!BLS6,'Daily-Prod.'!BLJ6,'Daily-Prod.'!BLA6,'Daily-Prod.'!BKR6,'Daily-Prod.'!BKI6,'Daily-Prod.'!BJZ6)),"") -> 12.727273
