Workbook

Sheet Synthèse
B1: Daily | I1: Weekly | P1: Monthly
B2: 46035 | D2: Trame de résolution | F2: Type de résolution | I2: S19 | K2: Trame de résolution | M2: Type de résolution | P2: 5 | R2: Trame de résolution | T2: Type de résolution
B3: Bannettes | C3: Nr ticket | D3: OK | E3: KO | F3: OK | G3: KO | I3: Bannettes | J3: Nr ticket | K3: OK | L3: KO | M3: OK | N3: KO | P3: Bannettes | Q3: Nr ticket | R3: OK | S3: KO | T3: OK | U3: KO
B4: FO | C4: =COUNTIFS(Picking!A:A,$B$2,Picking!E:E,B4) -> 0 | D4: =IFERROR((COUNTIFS(Picking!A:A,$B$2,Picking!E:E,B4,Picking!O:O,1)/C4),"") | E4: =IFERROR((COUNTIFS(Picking!A:A,$B$2,Picking!E:E,B4,Picking!O:O,0)/C4),"") | F4: =IFERROR((COUNTIFS(Picking!A:A,$B$2,Picking!E:E,B4,Picking!P:P,1)/C4),"") | G4: =IFERROR((COUNTIFS(Picking!A:A,$B$2,Picking!E:E,B4,Picking!P:P,0)/C4),"") | I4: FO | J4: =COUNTIFS(Picking!B:B,$I$2,Picking!E:E,I4) -> 0 | K4: =IFERROR((COUNTIFS(Picking!B:B,$I$2,Picking!E:E,I4,Picking!O:O,1)/J4),"") | L4: =IFERROR((COUNTIFS(Picking!B:B,$I$2,Picking!E:E,I4,Picking!O:O,0)/J4),"") | M4: =IFERROR((COUNTIFS(Picking!B:B,$I$2,Picking!E:E,I4,Picking!P:P,1)/J4),"") | N4: =IFERROR((COUNTIFS(Picking!B:B,$I$2,Picking!E:E,I4,Picking!P:P,0)/J4),"") | P4: FO | Q4: =COUNTIFS(Picking!C:C,$P$2,Picking!E:E,P4) -> 0 | R4: =IFERROR((COUNTIFS(Picking!C:C,$P$2,Picking!E:E,P4,Picking!O:O,1)/Q4),"") | S4: =IFERROR((COUNTIFS(Picking!C:C,$P$2,Picking!E:E,P4,Picking!O:O,0)/Q4),"") | T4: =IFERROR((COUNTIFS(Picking!C:C,$P$2,Picking!E:E,P4,Picking!P:P,1)/Q4),"") | U4: =IFERROR((COUNTIFS(Picking!C:C,$P$2,Picking!E:E,P4,Picking!P:P,0)/Q4),"")
B5: BO | C5: =COUNTIFS(Picking!A:A,$B$2,Picking!E:E,B5) -> 0 | D5: =IFERROR((COUNTIFS(Picking!A:A,$B$2,Picking!E:E,B5,Picking!O:O,1)/C5),"") | E5: =IFERROR((COUNTIFS(Picking!A:A,$B$2,Picking!E:E,B5,Picking!O:O,0)/C5),"") | F5: =IFERROR((COUNTIFS(Picking!A:A,$B$2,Picking!E:E,B5,Picking!P:P,1)/C5),"") | G5: =IFERROR((COUNTIFS(Picking!A:A,$B$2,Picking!E:E,B5,Picking!P:P,0)/C5),"") | I5: BO | J5: =COUNTIFS(Picking!B:B,$I$2,Picking!E:E,I5) -> 0 | K5: =IFERROR((COUNTIFS(Picking!B:B,$I$2,Picking!E:E,I5,Picking!O:O,1)/J5),"") | L5: =IFERROR((COUNTIFS(Picking!B:B,$I$2,Picking!E:E,I5,Picking!O:O,0)/J5),"") | M5: =IFERROR((COUNTIFS(Picking!B:B,$I$2,Picking!E:E,I5,Picking!P:P,1)/J5),"") | N5: =IFERROR((COUNTIFS(Picking!B:B,$I$2,Picking!E:E,I5,Picking!P:P,0)/J5),"") | P5: BO | Q5: =COUNTIFS(Picking!C:C,$P$2,Picking!E:E,P5) -> 0 | R5: =IFERROR((COUNTIFS(Picking!C:C,$P$2,Picking!E:E,P5,Picking!O:O,1)/Q5),"") | S5: =IFERROR((COUNTIFS(Picking!C:C,$P$2,Picking!E:E,P5,Picking!O:O,0)/Q5),"") | T5: =IFERROR((COUNTIFS(Picking!C:C,$P$2,Picking!E:E,P5,Picking!P:P,1)/Q5),"") | U5: =IFERROR((COUNTIFS(Picking!C:C,$P$2,Picking!E:E,P5,Picking!P:P,0)/Q5),"")
B6: PROXI-PMC | C6: =COUNTIFS(Picking!A:A,$B$2,Picking!E:E,B6) -> 0 | D6: =IFERROR((COUNTIFS(Picking!A:A,$B$2,Picking!E:E,B6,Picking!O:O,1)/C6),"") | E6: =IFERROR((COUNTIFS(Picking!A:A,$B$2,Picking!E:E,B6,Picking!O:O,0)/C6),"") | F6: =IFERROR((COUNTIFS(Picking!A:A,$B$2,Picking!E:E,B6,Picking!P:P,1)/C6),"") | G6: =IFERROR((COUNTIFS(Picking!A:A,$B$2,Picking!E:E,B6,Picking!P:P,0)/C6),"") | I6: PROXI-PMC | J6: =COUNTIFS(Picking!B:B,$I$2,Picking!E:E,I6) -> 0 | K6: =IFERROR((COUNTIFS(Picking!B:B,$I$2,Picking!E:E,I6,Picking!O:O,1)/J6),"") | L6: =IFERROR((COUNTIFS(Picking!B:B,$I$2,Picking!E:E,I6,Picking!O:O,0)/J6),"") | M6: =IFERROR((COUNTIFS(Picking!B:B,$I$2,Picking!E:E,I6,Picking!P:P,1)/J6),"") | N6: =IFERROR((COUNTIFS(Picking!B:B,$I$2,Picking!E:E,I6,Picking!P:P,0)/J6),"") | P6: PROXI-PMC | Q6: =COUNTIFS(Picking!C:C,$P$2,Picking!E:E,P6) -> 0 | R6: =IFERROR((COUNTIFS(Picking!C:C,$P$2,Picking!E:E,P6,Picking!O:O,1)/Q6),"") | S6: =IFERROR((COUNTIFS(Picking!C:C,$P$2,Picking!E:E,P6,Picking!O:O,0)/Q6),"") | T6: =IFERROR((COUNTIFS(Picking!C:C,$P$2,Picking!E:E,P6,Picking!P:P,1)/Q6),"") | U6: =IFERROR((COUNTIFS(Picking!C:C,$P$2,Picking!E:E,P6,Picking!P:P,0)/Q6),"")
B7: Partenaire | C7: =COUNTIFS(Picking!A:A,$B$2,Picking!E:E,B7) -> 0 | D7: =IFERROR((COUNTIFS(Picking!A:A,$B$2,Picking!E:E,B7,Picking!O:O,1)/C7),"") | E7: =IFERROR((COUNTIFS(Picking!A:A,$B$2,Picking!E:E,B7,Picking!O:O,0)/C7),"") | F7: =IFERROR((COUNTIFS(Picking!A:A,$B$2,Picking!E:E,B7,Picking!P:P,1)/C7),"") | G7: =IFERROR((COUNTIFS(Picking!A:A,$B$2,Picking!E:E,B7,Picking!P:P,0)/C7),"") | I7: Partenaire | J7: =COUNTIFS(Picking!B:B,$I$2,Picking!E:E,I7) -> 0 | K7: =IFERROR((COUNTIFS(Picking!B:B,$I$2,Picking!E:E,I7,Picking!O:O,1)/J7),"") | L7: =IFERROR((COUNTIFS(Picking!B:B,$I$2,Picking!E:E,I7,Picking!O:O,0)/J7),"") | M7: =IFERROR((COUNTIFS(Picking!B:B,$I$2,Picking!E:E,I7,Picking!P:P,1)/J7),"") | N7: =IFERROR((COUNTIFS(Picking!B:B,$I$2,Picking!E:E,I7,Picking!P:P,0)/J7),"") | P7: Partenaire | Q7: =COUNTIFS(Picking!C:C,$P$2,Picking!E:E,P7) -> 0 | R7: =IFERROR((COUNTIFS(Picking!C:C,$P$2,Picking!E:E,P7,Picking!O:O,1)/Q7),"") | S7: =IFERROR((COUNTIFS(Picking!C:C,$P$2,Picking!E:E,P7,Picking!O:O,0)/Q7),"") | T7: =IFERROR((COUNTIFS(Picking!C:C,$P$2,Picking!E:E,P7,Picking!P:P,1)/Q7),"") | U7: =IFERROR((COUNTIFS(Picking!C:C,$P$2,Picking!E:E,P7,Picking!P:P,0)/Q7),"")
B8: Supply | C8: =COUNTIFS(Picking!A:A,$B$2,Picking!E:E,B8) -> 0 | D8: =IFERROR((COUNTIFS(Picking!A:A,$B$2,Picking!E:E,B8,Picking!O:O,1)/C8),"") | E8: =IFERROR((COUNTIFS(Picking!A:A,$B$2,Picking!E:E,B8,Picking!O:O,0)/C8),"") | F8: =IFERROR((COUNTIFS(Picking!A:A,$B$2,Picking!E:E,B8,Picking!P:P,1)/C8),"") | G8: =IFERROR((COUNTIFS(Picking!A:A,$B$2,Picking!E:E,B8,Picking!P:P,0)/C8),"") | I8: Supply | J8: =COUNTIFS(Picking!B:B,$I$2,Picking!E:E,I8) -> 0 | K8: =IFERROR((COUNTIFS(Picking!B:B,$I$2,Picking!E:E,I8,Picking!O:O,1)/J8),"") | L8: =IFERROR((COUNTIFS(Picking!B:B,$I$2,Picking!E:E,I8,Picking!O:O,0)/J8),"") | M8: =IFERROR((COUNTIFS(Picking!B:B,$I$2,Picking!E:E,I8,Picking!P:P,1)/J8),"") | N8: =IFERROR((COUNTIFS(Picking!B:B,$I$2,Picking!E:E,I8,Picking!P:P,0)/J8),"") | P8: Supply | Q8: =COUNTIFS(Picking!C:C,$P$2,Picking!E:E,P8) -> 0 | R8: =IFERROR((COUNTIFS(Picking!C:C,$P$2,Picking!E:E,P8,Picking!O:O,1)/Q8),"") | S8: =IFERROR((COUNTIFS(Picking!C:C,$P$2,Picking!E:E,P8,Picking!O:O,0)/Q8),"") | T8: =IFERROR((COUNTIFS(Picking!C:C,$P$2,Picking!E:E,P8,Picking!P:P,1)/Q8),"") | U8: =IFERROR((COUNTIFS(Picking!C:C,$P$2,Picking!E:E,P8,Picking!P:P,0)/Q8),"")
B9: DS-Magasin | C9: =SUM(C4:C8) -> 0 | D9: =IFERROR((COUNTIFS(Picking!A:A,$B$2,Picking!O:O,1)/C9),"") | E9: =IFERROR((COUNTIFS(Picking!A:A,$B$2,Picking!O:O,0)/C9),"") | F9: =IFERROR((COUNTIFS(Picking!A:A,$B$2,Picking!P:P,1)/C9),"") | G9: =IFERROR((COUNTIFS(Picking!A:A,$B$2,Picking!P:P,0)/C9),"") | I9: DS-Magasin | J9: =SUM(J4:J8) -> 0 | K9: =IFERROR((COUNTIFS(Picking!B:B,$I$2,Picking!O:O,1)/J9),"") | L9: =IFERROR((COUNTIFS(Picking!B:B,$I$2,Picking!O:O,0)/J9),"") | M9: =IFERROR((COUNTIFS(Picking!B:B,$I$2,Picking!P:P,1)/J9),"") | N9: =IFERROR((COUNTIFS(Picking!B:B,$I$2,Picking!P:P,0)/J9),"") | P9: DS-Magasin | Q9: =SUM(Q4:Q8) -> 0 | R9: =IFERROR((COUNTIFS(Picking!C:C,$P$2,Picking!O:O,1)/Q9),"") | S9: =IFERROR((COUNTIFS(Picking!C:C,$P$2,Picking!O:O,0)/Q9),"") | T9: =IFERROR((COUNTIFS(Picking!C:C,$P$2,Picking!P:P,1)/Q9),"") | U9: =IFERROR((COUNTIFS(Picking!C:C,$P$2,Picking!P:P,0)/Q9),"")

Sheet Picking
A1: ID Ticket | B1: Titre | C1: Description | D1: Solution | E1: Type de résolution | F1: Synthèse de la demande | G1: Actions / Résultat | H1: Formule de politesse | I1: Conformité Solution | J1: Conformité Type de Résolution | K1: Correction Type de résolution | L1: Actions Sup | M1: Commentaire Sup
A2: 101906873 | F2: 1 | G2: 1 | H2: 1 | I2: =IF(COUNTA(F2:H2)<3,"",IF(AND(F2=1,G2=1,H2=1),1,0)) -> 1 | J2: 1 | K2: Conforme
A3: 101960296 | F3: 1 | G3: 1 | H3: 1 | I3: =IF(COUNTA(F3:H3)<3,"",IF(AND(F3=1,G3=1,H3=1),1,0)) -> 1 | J3: 1 | K3: Conforme
A4: 102028083 | F4: 1 | G4: 0 | H4: 1 | I4: =IF(COUNTA(F4:H4)<3,"",IF(AND(F4=1,G4=1,H4=1),1,0)) -> 0 | J4: 1 | K4: Conforme
A5: 101936765 | F5: 1 | G5: 1 | H5: 1 | I5: =IF(COUNTA(F5:H5)<3,"",IF(AND(F5=1,G5=1,H5=1),1,0)) -> 1 | J5: 1 | K5: Conforme
A6: 101938802 | F6: 1 | G6: 1 | H6: 1 | I6: =IF(COUNTA(F6:H6)<3,"",IF(AND(F6=1,G6=1,H6=1),1,0)) -> 1 | J6: 0 | K6: 01 - Aide à l’utilisation
A7: 101362015 | F7: 1 | G7: 1 | H7: 1 | I7: =IF(COUNTA(F7:H7)<3,"",IF(AND(F7=1,G7=1,H7=1),1,0)) -> 1 | J7: 1 | K7: Conforme
A8: 101860991 | F8: 1 | G8: 1 | H8: 1 | I8: =IF(COUNTA(F8:H8)<3,"",IF(AND(F8=1,G8=1,H8=1),1,0)) -> 1 | J8: 1 | K8: 04 - Aucune action nécessaire ou possible
A9: 101923390 | F9: 1 | G9: 1 | H9: 1 | I9: =IF(COUNTA(F9:H9)<3,"",IF(AND(F9=1,G9=1,H9=1),1,0)) -> 1 | J9: 1 | K9: Conforme
A10: 102011417 | F10: 1 | G10: 1 | H10: 1 | I10: =IF(COUNTA(F10:H10)<3,"",IF(AND(F10=1,G10=1,H10=1),1,0)) -> 1 | J10: 0 | K10: 03 - Script, fix ou contournement
A11: 101972013 | F11: 1 | G11: 1 | H11: 1 | I11: =IF(COUNTA(F11:H11)<3,"",IF(AND(F11=1,G11=1,H11=1),1,0)) -> 1 | J11: 1 | K11: Conforme
A12: 101961756 | F12: 1 | G12: 1 | H12: 1 | I12: =IF(COUNTA(F12:H12)<3,"",IF(AND(F12=1,G12=1,H12=1),1,0)) -> 1 | J12: 0 | K12: 01 - Aide à l’utilisation
A13: 101820880 | F13: 1 | G13: 1 | H13: 1 | I13: =IF(COUNTA(F13:H13)<3,"",IF(AND(F13=1,G13=1,H13=1),1,0)) -> 1 | J13: 1 | K13: Conforme
... A28: 101902986 | F28: 1 | G28: 1 | H28: 1 | I28: =IF(COUNTA(F28:H28)<3,"",IF(AND(F28=1,G28=1,H28=1),1,0)) -> 1 | J28: 1 | K28: Conforme
A29: 101436098 | F29: 1 | G29: 1 | H29: 1 | I29: =IF(COUNTA(F29:H29)<3,"",IF(AND(F29=1,G29=1,H29=1),1,0)) -> 1 | J29: 0 | K29: 05 - Hors périmètre support | M29: L'attribution des droits d'accès sont hors périmètre support.
A30: 101960078 | F30: 1 | G30: 1 | H30: 1 | I30: =IF(COUNTA(F30:H30)<3,"",IF(AND(F30=1,G30=1,H30=1),1,0)) -> 1 | J30: 0 | K30: 01 - Aide à l’utilisation
A31: 102027025 | F31: 1 | G31: 1 | H31: 1 | I31: =IF(COUNTA(F31:H31)<3,"",IF(AND(F31=1,G31=1,H31=1),1,0)) -> 1 | J31: 0 | K31: 03 - Script, fix ou contournement
A32: 101904715 | F32: 1 | G32: 1 | H32: 1 | I32: =IF(COUNTA(F32:H32)<3,"",IF(AND(F32=1,G32=1,H32=1),1,0)) -> 1 | J32: 1 | K32: Conforme
A33: 102010905 | F33: 1 | G33: 1 | H33: 1 | I33: =IF(COUNTA(F33:H33)<3,"",IF(AND(F33=1,G33=1,H33=1),1,0)) -> 1 | J33: 1 | K33: Conforme
A34: 101977407 | F34: 1 | G34: 1 | H34: 1 | I34: =IF(COUNTA(F34:H34)<3,"",IF(AND(F34=1,G34=1,H34=1),1,0)) -> 1 | J34: 0 | K34: 03 - Script, fix ou contournement
A35: 101997967 | F35: 1 | G35: 1 | H35: 1 | I35: =IF(COUNTA(F35:H35)<3,"",IF(AND(F35=1,G35=1,H35=1),1,0)) -> 1 | J35: 0 | K35: 01 - Aide à l’utilisation
A36: 102037863 | F36: 1 | G36: 0 | H36: 1 | I36: =IF(COUNTA(F36:H36)<3,"",IF(AND(F36=1,G36=1,H36=1),1,0)) -> 0 | J36: 1 | K36: Conforme | M36: Action non mentionnée.
A37: 101661869 | F37: 1 | G37: 1 | H37: 1 | I37: =IF(COUNTA(F37:H37)<3,"",IF(AND(F37=1,G37=1,H37=1),1,0)) -> 1 | J37: 1 | K37: Conforme
A38: 101893115 | F38: 1 | G38: 1 | H38: 1 | I38: =IF(COUNTA(F38:H38)<3,"",IF(AND(F38=1,G38=1,H38=1),1,0)) -> 1 | J38: 0 | K38: 02 - Correction donnée ou modification de paramétrage
A39: 101893164 | F39: 1 | G39: 1 | H39: 1 | I39: =IF(COUNTA(F39:H39)<3,"",IF(AND(F39=1,G39=1,H39=1),1,0)) -> 1 | J39: 1 | K39: 01 - Aide à l’utilisation
A40: 101920245 | F40: 1 | G40: 1 | H40: 1 | I40: =IF(COUNTA(F40:H40)<3,"",IF(AND(F40=1,G40=1,H40=1),1,0)) -> 1 | J40: 1 | K40: 01 - Aide à l’utilisation
A41: 101929135 | F41: 1 | G41: 1 | H41: 1 | I41: =IF(COUNTA(F41:H41)<3,"",IF(AND(F41=1,G41=1,H41=1),1,0)) -> 1 | J41: 1 | K41: Conforme
A42: 101903687 | F42: 1 | G42: 1 | H42: 1 | I42: =IF(COUNTA(F42:H42)<3,"",IF(AND(F42=1,G42=1,H42=1),1,0)) -> 1 | J42: 1 | K42: Conforme
A43: 101979421 | F43: 1 | G43: 1 | H43: 0 | I43: =IF(COUNTA(F43:H43)<3,"",IF(AND(F43=1,G43=1,H43=1),1,0)) -> 0 | J43: 1 | K43: Conforme
A44: 101945076 | F44: 1 | G44: 1 | H44: 1 | I44: =IF(COUNTA(F44:H44)<3,"",IF(AND(F44=1,G44=1,H44=1),1,0)) -> 1 | J44: 1 | K44: 01 - Aide à l’utilisation
A45: 102029208 | F45: 1 | G45: 1 | H45: 1 | I45: =IF(COUNTA(F45:H45)<3,"",IF(AND(F45=1,G45=1,H45=1),1,0)) -> 1 | J45: 1 | K45: Conforme
A46: 102094681 | F46: 1 | G46: 1 | H46: 1 | I46: =IF(COUNTA(F46:H46)<3,"",IF(AND(F46=1,G46=1,H46=1),1,0)) -> 1 | J46: 1 | K46: Conforme
A47: 102020926 | F47: 1 | G47: 1 | H47: 1 | I47: =IF(COUNTA(F47:H47)<3,"",IF(AND(F47=1,G47=1,H47=1),1,0)) -> 1 | J47: 1 | K47: Conforme
A48: 101553287 | F48: 1 | G48: 1 | H48: 1 | I48: =IF(COUNTA(F48:H48)<3,"",IF(AND(F48=1,G48=1,H48=1),1,0)) -> 1 | J48: 1 | K48: Conforme
... A56: 101820338 | F56: 1 | G56: 1 | H56: 1 | I56: =IF(COUNTA(F56:H56)<3,"",IF(AND(F56=1,G56=1,H56=1),1,0)) -> 1 | J56: 1 | K56: Conforme
A57: 101972013 | F57: 1 | G57: 1 | H57: 1 | I57: =IF(COUNTA(F57:H57)<3,"",IF(AND(F57=1,G57=1,H57=1),1,0)) -> 1 | J57: 0 | K57: 03 - Script, fix ou contournement | M57: Type de résolution incohérent
A58: 102052236 | F58: 1 | G58: 1 | H58: 1 | I58: =IF(COUNTA(F58:H58)<3,"",IF(AND(F58=1,G58=1,H58=1),1,0)) -> 1 | J58: 1 | K58: Conforme
A59: 102047416 | F59: 1 | G59: 1 | H59: 1 | I59: =IF(COUNTA(F59:H59)<3,"",IF(AND(F59=1,G59=1,H59=1),1,0)) -> 1 | J59: 1 | K59: Conforme
A60: 101421291 | F60: 1 | G60: 1 | H60: 1 | I60: =IF(COUNTA(F60:H60)<3,"",IF(AND(F60=1,G60=1,H60=1),1,0)) -> 1 | J60: 1 | K60: Conforme
A61: 102123134 | F61: 1 | G61: 1 | H61: 1 | I61: =IF(COUNTA(F61:H61)<3,"",IF(AND(F61=1,G61=1,H61=1),1,0)) -> 1 | J61: 1 | K61: Conforme
A62: 102172937 | F62: 1 | G62: 1 | H62: 1 | I62: =IF(COUNTA(F62:H62)<3,"",IF(AND(F62=1,G62=1,H62=1),1,0)) -> 1 | J62: 1 | K62: Conforme
A63: 102224276 | F63: 1 | G63: 1 | H63: 1 | I63: =IF(COUNTA(F63:H63)<3,"",IF(AND(F63=1,G63=1,H63=1),1,0)) -> 1 | J63: 1 | K63: Conforme
A64: 101261686 | F64: 1 | G64: 1 | H64: 1 | I64: =IF(COUNTA(F64:H64)<3,"",IF(AND(F64=1,G64=1,H64=1),1,0)) -> 1 | J64: 1 | K64: Conforme
A65: 102133212 | F65: 1 | G65: 1 | H65: 1 | I65: =IF(COUNTA(F65:H65)<3,"",IF(AND(F65=1,G65=1,H65=1),1,0)) -> 1 | J65: 1 | K65: Conforme
A66: 102047205 | F66: 1 | G66: 1 | H66: 1 | I66: =IF(COUNTA(F66:H66)<3,"",IF(AND(F66=1,G66=1,H66=1),1,0)) -> 1 | J66: 1 | K66: Conforme
A67: 102083898 | F67: 1 | G67: 1 | H67: 1 | I67: =IF(COUNTA(F67:H67)<3,"",IF(AND(F67=1,G67=1,H67=1),1,0)) -> 1 | J67: 1 | K67: Conforme
A68: 102160630 | F68: 1 | G68: 1 | H68: 1 | I68: =IF(COUNTA(F68:H68)<3,"",IF(AND(F68=1,G68=1,H68=1),1,0)) -> 1 | J68: 1 | K68: Conforme
A69: 102075540 | F69: 1 | G69: 1 | H69: 1 | I69: =IF(COUNTA(F69:H69)<3,"",IF(AND(F69=1,G69=1,H69=1),1,0)) -> 1 | J69: 1 | K69: Conforme
... A79: 102121027 | F79: 1 | G79: 1 | H79: 1 | I79: =IF(COUNTA(F79:H79)<3,"",IF(AND(F79=1,G79=1,H79=1),1,0)) -> 1 | J79: 1 | K79: Conforme
A80: 101864209 | F80: 1 | G80: 0 | H80: 1 | I80: =IF(COUNTA(F80:H80)<3,"",IF(AND(F80=1,G80=1,H80=1),1,0)) -> 0 | J80: 1 | K80: Conforme | M80: Actions non mentionnées;
A81: 102204661 | F81: 1 | G81: 1 | H81: 1 | I81: =IF(COUNTA(F81:H81)<3,"",IF(AND(F81=1,G81=1,H81=1),1,0)) -> 1 | J81: 1 | K81: Conforme
A82: 101944573 | F82: 1 | G82: 1 | H82: 1 | I82: =IF(COUNTA(F82:H82)<3,"",IF(AND(F82=1,G82=1,H82=1),1,0)) -> 1 | J82: 1 | K82: Conforme
A83: 102093673 | F83: 1 | G83: 1 | H83: 1 | I83: =IF(COUNTA(F83:H83)<3,"",IF(AND(F83=1,G83=1,H83=1),1,0)) -> 1 | J83: 1 | K83: Conforme
A84: 102139396 | F84: 0 | G84: 1 | H84: 1 | I84: =IF(COUNTA(F84:H84)<3,"",IF(AND(F84=1,G84=1,H84=1),1,0)) -> 0 | J84: 1 | K84: Conforme
A85: 101824887 | F85: 0 | G85: 1 | H85: 1 | I85: =IF(COUNTA(F85:H85)<3,"",IF(AND(F85=1,G85=1,H85=1),1,0)) -> 0 | J85: 1 | K85: Conforme
A86: 102040604 | F86: 1 | G86: 1 | H86: 1 | I86: =IF(COUNTA(F86:H86)<3,"",IF(AND(F86=1,G86=1,H86=1),1,0)) -> 1 | J86: 1 | K86: Conforme
A87: 101864507 | F87: 1 | G87: 1 | H87: 1 | I87: =IF(COUNTA(F87:H87)<3,"",IF(AND(F87=1,G87=1,H87=1),1,0)) -> 1 | J87: 1 | K87: Conforme
A88: 101898981 | F88: 1 | G88: 1 | H88: 1 | I88: =IF(COUNTA(F88:H88)<3,"",IF(AND(F88=1,G88=1,H88=1),1,0)) -> 1 | J88: 1 | K88: Conforme
A89: 101854900 | F89: 1 | G89: 1 | H89: 1 | I89: =IF(COUNTA(F89:H89)<3,"",IF(AND(F89=1,G89=1,H89=1),1,0)) -> 1 | J89: 1 | K89: Conforme
A90: 102219849 | F90: 1 | G90: 1 | H90: 1 | I90: =IF(COUNTA(F90:H90)<3,"",IF(AND(F90=1,G90=1,H90=1),1,0)) -> 1 | J90: 1 | K90: Conforme
A91: 102202881 | F91: 1 | G91: 1 | H91: 1 | I91: =IF(COUNTA(F91:H91)<3,"",IF(AND(F91=1,G91=1,H91=1),1,0)) -> 1 | J91: 1 | K91: Conforme
A92: 102310612 | F92: 1 | G92: 0 | H92: 1 | I92: =IF(COUNTA(F92:H92)<3,"",IF(AND(F92=1,G92=1,H92=1),1,0)) -> 0 | J92: 1 | K92: Conforme
... A205: 102601224 | F205: 1 | G205: 1 | H205: 1 | I205: =IF(COUNTA(F205:H205)<3,"",IF(AND(F205=1,G205=1,H205=1),1,0)) -> 1 | J205: 1 | K205: Conforme
A206: 102855298 | F206: 1 | G206: 1 | H206: 1 | I206: =IF(COUNTA(F206:H206)<3,"",IF(AND(F206=1,G206=1,H206=1),1,0)) -> 1 | J206: 1 | K206: Conforme | M206: Preciser qu'aucune action n'est appliqué
A207: 103183845 | F207: 1 | G207: 1 | H207: 1 | I207: =IF(COUNTA(F207:H207)<3,"",IF(AND(F207=1,G207=1,H207=1),1,0)) -> 1 | J207: 1 | K207: Conforme
A208: 103099621 | F208: 1 | G208: 1 | H208: 1 | I208: =IF(COUNTA(F208:H208)<3,"",IF(AND(F208=1,G208=1,H208=1),1,0)) -> 1 | J208: 1 | K208: Conforme
A209: 103295337 | F209: 1 | G209: 1 | H209: 1 | I209: =IF(COUNTA(F209:H209)<3,"",IF(AND(F209=1,G209=1,H209=1),1,0)) -> 1 | J209: 1 | K209: Conforme
A210: 102894494 | F210: 1 | G210: 0 | H210: 0 | I210: =IF(COUNTA(F210:H210)<3,"",IF(AND(F210=1,G210=1,H210=1),1,0)) -> 0 | J210: 1 | K210: Conforme | M210: Pas de trame
A211: 102651157 | F211: 1 | G211: 0 | H211: 0 | I211: =IF(COUNTA(F211:H211)<3,"",IF(AND(F211=1,G211=1,H211=1),1,0)) -> 0 | J211: 1 | K211: Conforme | M211: Pas de trame
A212: 103284057 | F212: 1 | G212: 1 | H212: 1 | I212: =IF(COUNTA(F212:H212)<3,"",IF(AND(F212=1,G212=1,H212=1),1,0)) -> 1 | J212: 1 | K212: Conforme
A213: 102844453 | F213: 1 | G213: 1 | H213: 1 | I213: =IF(COUNTA(F213:H213)<3,"",IF(AND(F213=1,G213=1,H213=1),1,0)) -> 1 | J213: 1 | K213: Conforme
A214: 102646141 | F214: 1 | G214: 1 | H214: 1 | I214: =IF(COUNTA(F214:H214)<3,"",IF(AND(F214=1,G214=1,H214=1),1,0)) -> 1 | J214: 1 | K214: Conforme
A215: 103116613 | F215: 1 | G215: 1 | H215: 1 | I215: =IF(COUNTA(F215:H215)<3,"",IF(AND(F215=1,G215=1,H215=1),1,0)) -> 1 | J215: 1 | K215: Conforme
A216: 103001492 | F216: 1 | G216: 1 | H216: 1 | I216: =IF(COUNTA(F216:H216)<3,"",IF(AND(F216=1,G216=1,H216=1),1,0)) -> 1 | J216: 1 | K216: Conforme
A217: 102832468 | F217: 1 | G217: 1 | H217: 1 | I217: =IF(COUNTA(F217:H217)<3,"",IF(AND(F217=1,G217=1,H217=1),1,0)) -> 1 | J217: 1 | K217: Conforme
A218: 102888341 | F218: 1 | G218: 1 | H218: 1 | I218: =IF(COUNTA(F218:H218)<3,"",IF(AND(F218=1,G218=1,H218=1),1,0)) -> 1 | J218: 1 | K218: Conforme
A219: 102595898 | F219: 1 | G219: 1 | H219: 1 | I219: =IF(COUNTA(F219:H219)<3,"",IF(AND(F219=1,G219=1,H219=1),1,0)) -> 1 | J219: 1 | K219: Conforme
A220: 102930262 | F220: 1 | G220: 1 | H220: 1 | I220: =IF(COUNTA(F220:H220)<3,"",IF(AND(F220=1,G220=1,H220=1),1,0)) -> 1 | J220: 1 | K220: Conforme
A221: 102529618 | F221: 1 | G221: 1 | H221: 1 | I221: =IF(COUNTA(F221:H221)<3,"",IF(AND(F221=1,G221=1,H221=1),1,0)) -> 1 | J221: 1 | K221: Conforme
A222: 103108105 | F222: 1 | G222: 1 | H222: 1 | I222: =IF(COUNTA(F222:H222)<3,"",IF(AND(F222=1,G222=1,H222=1),1,0)) -> 1 | J222: 1 | K222: Conforme
A223: 103100700 | F223: 1 | G223: 1 | H223: 1 | I223: =IF(COUNTA(F223:H223)<3,"",IF(AND(F223=1,G223=1,H223=1),1,0)) -> 1 | J223: 1 | K223: Conforme
... A227: 103123143 | F227: 1 | G227: 1 | H227: 1 | I227: =IF(COUNTA(F227:H227)<3,"",IF(AND(F227=1,G227=1,H227=1),1,0)) -> 1 | J227: 1 | K227: Conforme
A228: 103140371 | F228: 1 | G228: 1 | H228: 1 | I228: =IF(COUNTA(F228:H228)<3,"",IF(AND(F228=1,G228=1,H228=1),1,0)) -> 1 | J228: 1 | K228: Conforme | M228: Plus de precision d'actions
A229: 103162287 | F229: 1 | G229: 1 | H229: 1 | I229: =IF(COUNTA(F229:H229)<3,"",IF(AND(F229=1,G229=1,H229=1),1,0)) -> 1 | J229: 1 | K229: Conforme | M229: Plus de precision d'actions
A230: 103107636 | F230: 1 | G230: 1 | H230: 1 | I230: =IF(COUNTA(F230:H230)<3,"",IF(AND(F230=1,G230=1,H230=1),1,0)) -> 1 | J230: 1 | K230: Conforme
A231: 103287789 | F231: 1 | G231: 1 | H231: 1 | I231: =IF(COUNTA(F231:H231)<3,"",IF(AND(F231=1,G231=1,H231=1),1,0)) -> 1 | J231: 1 | K231: Conforme
A232: 103329863 | F232: 1 | G232: 1 | H232: 1 | I232: =IF(COUNTA(F232:H232)<3,"",IF(AND(F232=1,G232=1,H232=1),1,0)) -> 1 | J232: 1 | K232: Conforme
A233: 103001821 | F233: 1 | G233: 1 | H233: 1 | I233: =IF(COUNTA(F233:H233)<3,"",IF(AND(F233=1,G233=1,H233=1),1,0)) -> 1 | J233: 1 | K233: Conforme
A234: 103370361 | F234: 1 | G234: 0 | H234: 1 | I234: =IF(COUNTA(F234:H234)<3,"",IF(AND(F234=1,G234=1,H234=1),1,0)) -> 0 | J234: 0 | K234: 01 - Aide à l’utilisation
A235: 102850580 | F235: 1 | G235: 1 | H235: 1 | I235: =IF(COUNTA(F235:H235)<3,"",IF(AND(F235=1,G235=1,H235=1),1,0)) -> 1 | J235: 1 | K235: Conforme
A236: 102860501 | F236: 1 | G236: 1 | H236: 1 | I236: =IF(COUNTA(F236:H236)<3,"",IF(AND(F236=1,G236=1,H236=1),1,0)) -> 1 | J236: 1 | K236: Conforme
A237: 103100458 | F237: 1 | G237: 1 | H237: 1 | I237: =IF(COUNTA(F237:H237)<3,"",IF(AND(F237=1,G237=1,H237=1),1,0)) -> 1 | J237: 1 | K237: Conforme
A238: 101402874 | F238: 1 | G238: 1 | H238: 1 | I238: =IF(COUNTA(F238:H238)<3,"",IF(AND(F238=1,G238=1,H238=1),1,0)) -> 1 | J238: 1 | K238: Conforme
A239: 103321355 | F239: 1 | G239: 1 | H239: 1 | I239: =IF(COUNTA(F239:H239)<3,"",IF(AND(F239=1,G239=1,H239=1),1,0)) -> 1 | J239: 1 | K239: 03 - Script, fix ou contournement
A240: 103390867 | F240: 1 | G240: 1 | H240: 1 | I240: =IF(COUNTA(F240:H240)<3,"",IF(AND(F240=1,G240=1,H240=1),1,0)) -> 1 | J240: 1 | K240: Conforme
A241: 103284208 | F241: 1 | G241: 1 | H241: 1 | I241: =IF(COUNTA(F241:H241)<3,"",IF(AND(F241=1,G241=1,H241=1),1,0)) -> 1 | J241: 0 | K241: 03 - Script, fix ou contournement
... A299: 103287641 | F299: 1 | G299: 1 | H299: 1 | I299: =IF(COUNTA(F299:H299)<3,"",IF(AND(F299=1,G299=1,H299=1),1,0)) -> 1 | J299: 1 | K299: 02 - Correction donnée ou modification de paramétrage
A300: 103825354 | F300: 0 | G300: 1 | H300: 1 | I300: =IF(COUNTA(F300:H300)<3,"",IF(AND(F300=1,G300=1,H300=1),1,0)) -> 0 | J300: 0 | K300: 06 - Intervention sur matériel | M300: pas de Synthèse
A301: 103614929 | F301: 1 | G301: 1 | H301: 1 | I301: =IF(COUNTA(F301:H301)<3,"",IF(AND(F301=1,G301=1,H301=1),1,0)) -> 1 | J301: 1 | K301: 04 - Aucune action nécessaire ou possible
A302: 103821549 | F302: 0 | G302: 1 | H302: 0 | I302: =IF(COUNTA(F302:H302)<3,"",IF(AND(F302=1,G302=1,H302=1),1,0)) -> 0 | J302: 1 | K302: 02 - Correction donnée ou modification de paramétrage | M302: pas de trame
...

Sheet Rejets
A1: Résponsable | B1: Bannette | C1: Motif du rejet | D1: Action | E1: ID TICKET | F1: TYPE | G1: TITRE | H1: SERVICE IMPACTANT | I1: SERVICE IMPACTE | J1: DIGITAL SUPPORT | K1: CATEGORISATION | L1: DATE CREATION | M1: PRIORITE INITIALE | N1: PRIORITE | O1: BANNETTE RESOLUTION | P1: DOMAINE | Q1: EMPLACEMENT | R1: BU EMPLACEMENT | S1: STATUT | T1: TYPE CIBLE | U1: ETAT CIBLE | V1: DATE RESOLUTION | W1: DUREE TTR (H) | X1: CIBLE (H) | Y1: ETAT TTR | Z1: REAFFECTATIONS | AA1: RELANCES | AB1: REOUVERTURES | AC1: HO HNO | AD1: INCIDENT LIE | AE1: ID ODM
A2: =VLOOKUP(O2,Dictionnaire!A:B,2,0) -> Mouad Bounouar | B2: =O2 -> FR IT SIC N1_N2 PROMOCASH BACK OFFICE | E2: 118396606 | F2: DS | G2: Activer imprimante sur Aquilon | H2: AQUILON-FR | I2: AQUILON-FR | J2: DS Magasin | K2: Back Office Promocash \ Commande \ Commande automatique | L2: ########## | M2: P4 | N2: P4 | O2: FR IT SIC N1_N2 PROMOCASH BACK OFFICE | P2: IT | Q2: ALES - PROMOCASH | R2: PROMOCASH | S2: FranchisÃ© | T2: ExÃ©cution | U2: Atteint | V2: ########## | W2: 155.81 | X2: 180 | Y2: OK | Z2: 5 | AA2: 0 | AB2: 4 | AC2: HO
A3: =VLOOKUP(O3,Dictionnaire!A:B,2,0) -> Mouad Bounouar | B3: =O3 -> FR IT SIC N1_N2 PROMOCASH BACK OFFICE | E3: 121470954 | F3: DA | G3: information sur aquilon Windows | H3: PROMOCASH MARKETING CLOUD-FR | I3: PROMOCASH MARKETING CLOUD-FR | J3: DS Magasin | K3: Back Office Promocash | L3: ########## | M3: P4 | N3: P4 | O3: FR IT SIC N1_N2 PROMOCASH BACK OFFICE | P3: IT | Q3: MACON -VARENNES LES - PROMOCASH | R3: PROMOCASH | S3: FranchisÃ© | T3: RÃ©solution | U3: Echec | V3: ########## | W3: 70.64 | X3: 45 | Y3: KO | Z3: 4 | AA3: 0 | AB3: 1 | AC3: HO
A4: =VLOOKUP(O4,Dictionnaire!A:B,2,0) -> Mouad Bounouar | B4: =O4 -> FR IT SIC N1_N2 PROMOCASH BACK OFFICE | E4: 122479425 | F4: DA | G4: Document bloquÃ© sur la file d'impression | H4: AQUILON-FR | I4: AQUILON-FR | J4: DS Magasin | K4: Back Office Promocash \ Impression | L4: ########## | M4: P4 | N4: P4 | O4: FR IT SIC N1_N2 PROMOCASH BACK OFFICE | P4: IT | Q4: BORDEAUX - PROMOCASH | R4: PROMOCASH | S4: FranchisÃ© | T4: RÃ©solution | U4: Atteint | V4: ########## | W4: 2.27 | X4: 45 | Y4: OK | Z4: 0 | AA4: 0 | AB4: 1 | AC4: HO
A5: =VLOOKUP(O5,Dictionnaire!A:B,2,0) -> Mouad Bounouar | B5: =O5 -> FR IT SIC N1_N2 PROMOCASH BACK OFFICE | E5: 123201848 | F5: DA | G5: Aquilon | H5: AQUILON-FR | I5: AQUILON-FR | J5: DS Magasin | K5: Acces \ Application \ Application KO | L5: ########## | M5: P2 | N5: P2 | O5: FR IT SIC N1_N2 PROMOCASH BACK OFFICE | P5: IT | Q5: LE PUY EN VELAY -CHA - PROMOCASH | R5: PROMOCASH | S5: FranchisÃ© | T5: RÃ©solution | U5: Atteint | V5: ########## | W5: 0.06 | X5: 18 | Y5: OK | Z5: 0 | AA5: 0 | AB5: 1 | AC5: HO
A6: =VLOOKUP(O6,Dictionnaire!A:B,2,0) -> Mouad Bounouar | B6: =O6 -> FR IT SIC N1_N2 PROMOCASH BACK OFFICE | E6: 123385451 | F6: DS | G6: dÃ©blocage client | H6: AQUILON-FR | I6: AQUILON-FR | J6: DS Magasin | K6: Back Office Promocash \ Client | L6: ########## | M6: P4 | N6: P4 | O6: FR IT SIC N1_N2 PROMOCASH BACK OFFICE | P6: IT | Q6: CARCASSONNE - PROMOCASH | R6: PROMOCASH | S6: FranchisÃ© | T6: ExÃ©cution | U6: Atteint | V6: ########## | W6: 12.46 | X6: 180 | Y6: OK | Z6: 6 | AA6: 0 | AB6: 1 | AC6: HO
A7: =VLOOKUP(O7,Dictionnaire!A:B,2,0) -> Mouad Bounouar | B7: =O7 -> FR IT SIC N1_N2 PROMOCASH BACK OFFICE | E7: 123452881 | F7: DA | G7: AUCUNE DESCENTE DE MODEM DE LIVRAISON | H7: AQUILON-FR | I7: AQUILON-FR | J7: DS Magasin | K7: Back Office Promocash \ Reception \ Modem | L7: ########## | M7: P2 | N7: P2 | O7: FR IT SIC N1_N2 PROMOCASH BACK OFFICE | P7: IT | Q7: ANGERS - PROMOCASH | R7: PROMOCASH | S7: FranchisÃ© | T7: RÃ©solution | U7: Atteint | V7: ########## | W7: 9.90 | X7: 18 | Y7: OK | Z7: 1 | AA7: 0 | AB7: 1 | AC7: HO | AD7: 123918877
A8: =VLOOKUP(O8,Dictionnaire!A:B,2,0) -> Mouad Bounouar | B8: =O8 -> FR IT SIC N1_N2 PROMOCASH BACK OFFICE | E8: 123850744 | F8: DA | G8: MODEMS | H8: AQUILON-FR | I8: AQUILON-FR | J8: DS Magasin | K8: Back Office Promocash | L8: ########## | M8: P2 | N8: P2 | O8: FR IT SIC N1_N2 PROMOCASH BACK OFFICE | P8: IT | Q8: GAP - PROMOCASH | R8: PROMOCASH | S8: FranchisÃ© | T8: RÃ©solution | U8: Atteint | V8: ########## | W8: 3.41 | X8: 18 | Y8: OK | Z8: 6 | AA8: 0 | AB8: 2 | AC8: HNO
A9: =VLOOKUP(O9,Dictionnaire!A:B,2,0) -> Mouad Bounouar | B9: =O9 -> FR IT SIC N1_N2 PROXIMITE | E9: 122270764 | F9: DA | G9: UG des produits qui disparait | H9: METI STORE-FR | I9: METI STORE-FR | J9: DS Magasin | K9: Back Office Proximite | L9: ########## | M9: P2 | N9: P2 | O9: FR IT SIC N1_N2 PROXIMITE | P9: IT | Q9: HUSSIGNY -HOPITAL - PROXIMITE | R9: PROXIMITE | S9: FranchisÃ© | T9: RÃ©solution | U9: Echec | V9: ########## | W9: 32.13 | X9: 18 | Y9: KO | Z9: 2 | AA9: 0 | AB9: 1 | AC9: HNO
A10: =VLOOKUP(O10,Dictionnaire!A:B,2,0) -> Mouad Bounouar | B10: =O10 -> FR IT SIC N1_N2 PROXIMITE | E10: 122395503 | F10: DA | G10: non Ã©dition des recapitulatif des mouvements de rÃ©gularisation | H10: REEVA-FR | I10: REEVA-FR | J10: DS Magasin | K10: Back Office Multi format \ Mobilite \ Controle facture | L10: ########## | M10: P4 | N10: P4 | O10: FR IT SIC N1_N2 PROXIMITE | P10: IT | Q10: TOULOUSE -PUJOL 68 - PROXIMITE | R10: PROXIMITE | S10: LG | T10: RÃ©solution | U10: Atteint | V10: ########## | W10: 24.48 | X10: 45 | Y10: OK | Z10: 3 | AA10: 0 | AB10: 1 | AC10: HO
A11: =VLOOKUP(O11,Dictionnaire!A:B,2,0) -> Mouad Bounouar | B11: =O11 -> FR IT SIC N1_N2 PROXIMITE | E11: 122677453 | F11: DA | G11: souci sortie musique | H11: LOGICIEL | I11: MUSIQUE MOODMEDIA-FR | J11: DS Magasin | K11: Back Office Proximite \ Parametrage | L11: ########## | M11: P4 | N11: P4 | O11: FR IT SIC N1_N2 PROXIMITE | P11: IT | Q11: PERIGUEUX -REPUBLIQ - PROXIMITE | R11: PROXIMITE | S11: LG | T11: RÃ©solution | U11: Atteint | V11: ########## | W11: 14.23 | X11: 45 | Y11: OK | Z11: 2 | AA11: 0 | AB11: 3 | AC11: HO
A12: =VLOOKUP(O12,Dictionnaire!A:B,2,0) -> Mouad Bounouar | B12: =O12 -> FR IT SIC N1_N2 PROXIMITE | E12: 122947548 | F12: DA | G12: METI : N A PAS EU LA REMONTEE METI | H12: METI STORE-FR | I12: METI STORE-FR | J12: DS Magasin | K12: Back Office Proximite \ Chiffre d affaire \ Ecart CA | L12: ########## | M12: P4 | N12: P4 | O12: FR IT SIC N1_N2 PROXIMITE | P12: IT | Q12: COMBS LA VIL -QUINCY - PROXIMITE | R12: PROXIMITE | S12: LG | T12: RÃ©solution | U12: Atteint | V12: ########## | W12: 0.00 | X12: 45 | Y12: OK | Z12: 1 | AA12: 0 | AB12: 1 | AC12: HNO
A13: =VLOOKUP(O13,Dictionnaire!A:B,2,0) -> Mouad Bounouar | B13: =O13 -> FR IT SIC N1_N2 PROXIMITE | E13: 122957037 | F13: DA | G13: Refresh | H13: METI STORE-FR | I13: METI STORE-FR | J13: DS Magasin | K13: Back Office Proximite \ Article \ Referentiel | L13: ########## | M13: P2 | N13: P2 | O13: FR IT SIC N1_N2 PROXIMITE | P13: IT | Q13: ST-MARTIN-BELLEVUE - PROXIMITE | R13: PROXIMITE | S13: FranchisÃ© | T13: RÃ©solution | U13: Atteint | V13: ########## | W13: 13.76 | X13: 18 | Y13: OK | Z13: 2 | AA13: 0 | AB13: 3 | AC13: HNO
A14: =VLOOKUP(O14,Dictionnaire!A:B,2,0) -> Mouad Bounouar | B14: =O14 -> FR IT SIC N1_N2 PROXIMITE | E14: 122992712 | F14: DA | G14: METI : N A PAS EU LA REMONTEE METI | H14: METI STORE-FR | I14: METI STORE-FR | J14: DS Magasin | K14: Back Office Proximite | L14: ########## | M14: P4 | N14: P4 | O14: FR IT SIC N1_N2 PROXIMITE | P14: IT | Q14: PARIS -ND DE LORETTE - PROXIMITE | R14: PROXIMITE | S14: FranchisÃ© | T14: RÃ©solution | U14: Atteint | V14: ########## | W14: 36.19 | X14: 60 | Y14: OK | Z14: 11 | AA14: 0 | AB14: 1 | AC14: HNO
A15: =VLOOKUP(O15,Dictionnaire!A:B,2,0) -> Mouad Bounouar | B15: =O15 -> FR IT SIC N1_N2 PROXIMITE | E15: 123002323 | F15: DA | G15: Envoie en caisse | H15: METI STORE-FR | I15: METI STORE-FR | J15: DS Magasin | K15: Back Office Proximite \ Livre de caisse | L15: ########## | M15: P4 | N15: P4 | O15: FR IT SIC N1_N2 PROXIMITE | P15: IT | Q15: BOURGOIN JALLIEU - SUPECO | R15: DISCOUNT SUPERMARCHES | S15: FranchisÃ© | T15: RÃ©solution | U15: Atteint | V15: ########## | W15: 9.44 | X15: 45 | Y15: OK | Z15: 2 | AA15: 0 | AB15: 2 | AC15: HNO
A16: =VLOOKUP(O16,Dictionnaire!A:B,2,0) -> Mouad Bounouar | B16: =O16 -> FR IT SIC N1_N2 PROXIMITE | E16: 123167199 | F16: DA | G16: Doublon - Envoie en caisse | H16: METI STORE-FR | I16: METI STORE-FR | J16: DS Magasin | K16: Back Office Proximite \ Livre de caisse | L16: ########## | M16: P4 | N16: P4 | O16: FR IT SIC N1_N2 PROXIMITE | P16: IT | Q16: BOURGOIN JALLIEU - SUPECO | R16: DISCOUNT SUPERMARCHES | S16: FranchisÃ© | T16: RÃ©solution | U16: Atteint | V16: ########## | W16: 0.20 | X16: 45 | Y16: OK | Z16: 0 | AA16: 0 | AB16: 1 | AC16: HO
A17: =VLOOKUP(O17,Dictionnaire!A:B,2,0) -> Mouad Bounouar | B17: =O17 -> FR IT SIC N1_N2 PROXIMITE | E17: 123667863 | F17: DA | G17: Soufflenheim - Suppression inventaire nÃ©120 | H17: METI STORE-FR | I17: METI STORE-FR | J17: DS Magasin | K17: Back Office Proximite \ Inventaire \ Suppression inventaire | L17: ########## | M17: P2 | N17: P2 | O17: FR IT SIC N1_N2 PROXIMITE | P17: IT | Q17: SOUFFLENHEIM -GR.RUE - PROXIMITE | R17: PROXIMITE | S17: LG | T17: RÃ©solution | U17: Atteint | V17: ########## | W17: 7.71 | X17: 18 | Y17: OK | Z17: 2 | AA17: 0 | AB17: 1 | AC17: HO
A18: =VLOOKUP(O18,Dictionnaire!A:B,2,0) -> Mouad Bounouar | B18: =O18 -> FR IT SIC N1_N2 PROXIMITE | E18: 123706844 | F18: DA | G18: MAJ stock / TEST / RICARD | H18: METIMOBILE (PROXI)-FR | I18: METIMOBILE (PROXI)-FR | J18: DS Magasin | K18: Back Office Proximite \ Stock \ Mouvement | L18: ########## | M18: P5 | N18: P5 | O18: FR IT SIC N1_N2 PROXIMITE | P18: IT | Q18: SAINT-GREGOIRE -FORG - PROXIMITE | R18: PROXIMITE | S18: LG | T18: RÃ©solution | U18: Atteint | V18: ########## | W18: 46186 | X18: 45 | Y18: OK | Z18: 0 | AA18: 0 | AB18: 1 | AC18: HO
A19: =VLOOKUP(O19,Dictionnaire!A:B,2,0) -> Mouad Bounouar | B19: =O19 -> FR IT SIC N1_N2 PROXIMITE | E19: 124264750 | F19: DA | G19: AUCUN MODEM | H19: PROLOG-FR | I19: AQUILON-FR | J19: DS Magasin | K19: Back Office Promocash \ Reception \ Modem | L19: ########## | M19: P4 | N19: P4 | O19: FR IT SIC N1_N2 PROXIMITE | P19: IT | Q19: BOURG EN BRESSE - PROMOCASH | R19: PROMOCASH | S19: FranchisÃ© | T19: RÃ©solution | U19: Atteint | V19: ########## | W19: 4.95 | X19: 45 | Y19: OK | Z19: 6 | AA19: 0 | AB19: 1 | AC19: HNO
A20: =VLOOKUP(O20,Dictionnaire!A:B,2,0) -> Mohamed BENSAID | B20: =O20 -> FR IT SIC N1_N2 SUPER-HYPER BACK OFFICE | E20: 121813044 | F20: DA | G20: Erreur Nomencature SM | H20: CAROLINE HYPER-FR | I20: CAROLINE HYPER-FR | J20: DS Magasin | K20: Back Office Hyper \ Referentiel \ Modification donnee article | L20: ########## | M20: P2 | N20: P2 | O20: FR IT SIC N1_N2 SUPER-HYPER BACK OFFICE | P20: IT | Q20: DIR COMMERCIALE FR (DIR COMMERCIALE FR) | R20: DIR MARCHANDISES | S20: SiÃ¨ge | T20: RÃ©solution | U20: Echec | V20: ########## | W20: 26.74 | X20: 18 | Y20: KO | Z20: 5 | AA20: 0 | AB20: 1 | AC20: HO
A21: =VLOOKUP(O21,Dictionnaire!A:B,2,0) -> Mohamed BENSAID | B21: =O21 -> FR IT SIC N1_N2 SUPER-HYPER BACK OFFICE | E21: 121948632 | F21: DA | G21: etiquette | H21: CAROMOBILE-FR | I21: CAROLINE SUPER-FR | J21: DS Magasin | K21: Back Office Super \ Referentiel | L21: ########## | M21: P1 | N21: P4 | O21: FR IT SIC N1_N2 SUPER-HYPER BACK OFFICE | P21: IT | Q21: NEUILLY EN THELLE - SUPERMARCHES | R21: SUPERMARCHES FRANCE | S21: LG | T21: RÃ©solution | U21: Atteint | V21: ########## | W21: 5.67 | X21: 45 | Y21: OK | Z21: 0 | AA21: 0 | AB21: 1 | AC21: HNO
A22: =VLOOKUP(O22,Dictionnaire!A:B,2,0) -> Mohamed BENSAID | B22: =O22 -> FR IT SIC N1_N2 SUPER-HYPER BACK OFFICE | E22: 122003791 | F22: DA | G22: problÃ©me de produit rayon | H22: CAROLINE HYPER-FR | I22: CAROLINE HYPER-FR | J22: DS Magasin | K22: Back Office Hyper \ Referentiel \ Modification donnee article | L22: ########## | M22: P1 | N22: P3 | O22: FR IT SIC N1_N2 SUPER-HYPER BACK OFFICE | P22: IT | Q22: PORT DE BOUC - HYPERMARCHES | R22: HYPERMARCHES FRANCE | S22: LG | T22: RÃ©solution | U22: Atteint | V22: ########## | W22: 11.34 | X22: 27 | Y22: OK | Z22: 4 | AA22: 0 | AB22: 2 | AC22: HNO
A23: =VLOOKUP(O23,Dictionnaire!A:B,2,0) -> Mohamed BENSAID | B23: =O23 -> FR IT SIC N1_N2 SUPER-HYPER BACK OFFICE | E23: 122242280 | F23: DS | G23: Changement IFLS pour le EAN 3492500066001 sur Caroline | H23: BCP-FR | I23: CAROLINE HYPER-FR | J23: DS Magasin | K23: Back Office Hyper \ Gestion des retours | L23: ########## | M23: P3 | N23: P3 | O23: FR IT SIC N1_N2 SUPER-HYPER BACK OFFICE | P23: IT | Q23: WITTENHEIM - HYPERMARCHES | R23: HYPERMARCHES FRANCE | S23: IntÃ©grÃ© | T23: ExÃ©cution | U23: Atteint | V23: ########## | W23: 46.35 | X23: 66 | Y23: OK | Z23: 6 | AA23: 0 | AB23: 1 | AC23: HO
A24: =VLOOKUP(O24,Dictionnaire!A:B,2,0) -> Mohamed BENSAID | B24: =O24 -> FR IT SIC N1_N2 SUPER-HYPER BACK OFFICE | E24: 122302633 | F24: DA | G24: ProcÃ©dure terminÃ©e confirmÃ© par le magasin | H24: CAROLINE HYPER-FR | I24: CAROLINE HYPER-FR | J24: DS Magasin | K24: Back Office Hyper \ Gestion des retours \ Bon de retour | L24: ########## | M24: P4 | N24: P3 | O24: FR IT SIC N1_N2 SUPER-HYPER BACK OFFICE | P24: IT | Q24: VENETTE - HYPERMARCHES | R24: HYPERMARCHES FRANCE | S24: IntÃ©grÃ© | T24: RÃ©solution | U24: Atteint | V24: ########## | W24: 16.71 | X24: 27 | Y24: OK | Z24: 0 | AA24: 0 | AB24: 1 | AC24: HNO
A25: =VLOOKUP(O25,Dictionnaire!A:B,2,0) -> Mohamed BENSAID | B25: =O25 -> FR IT SIC N1_N2 SUPER-HYPER BACK OFFICE | E25: 122328683 | F25: DA | G25: CA | H25: SMARTPOS-FR | I25: CAROLINE SUPER-FR | J25: DS Magasin | K25: Data BI \ Donnee \ Qualite | L25: ########## | M25: P3 | N25: P3 | O25: FR IT SIC N1_N2 SUPER-HYPER BACK OFFICE | P25: IT | Q25: VILLEVIEILLE - SUPERMARCHES | R25: SUPERMARCHES FRANCE | S25: IntÃ©grÃ© | T25: RÃ©solution | U25: Atteint | V25: ########## | W25: 25.91 | X25: 27 | Y25: OK | Z25: 3 | AA25: 0 | AB25: 1 | AC25: HO
A26: =VLOOKUP(O26,Dictionnaire!A:B,2,0) -> Mohamed BENSAID | B26: =O26 -> FR IT SIC N1_N2 SUPER-HYPER BACK OFFICE | E26: 122354503 | F26: DA | G26: TONDEUSE GARDENA | H26: CAROLINE SUPER-FR | I26: CAROLINE SUPER-FR | J26: DS Magasin | K26: Back Office Super \ Tarification \ Prix de vente | L26: ########## | M26: P3 | N26: P3 | O26: FR IT SIC N1_N2 SUPER-HYPER BACK OFFICE | P26: IT | Q26: BADEN - SUPERMARCHES | R26: SUPERMARCHES FRANCE | S26: FranchisÃ© | T26: RÃ©solution | U26: Atteint | V26: ########## | W26: 1.63 | X26: 27 | Y26: OK | Z26: 0 | AA26: 0 | AB26: 1 | AC26: HO
A27: =VLOOKUP(O27,Dictionnaire!A:B,2,0) -> Mohamed BENSAID | B27: =O27 -> FR IT SIC N1_N2 SUPER-HYPER BACK OFFICE | E27: 122521409 | F27: DA | G27: ProblÃ©me connexion Caroline et lenteur sur TR | H27: CAROLINE SUPER-FR | I27: CAROLINE SUPER-FR | J27: DS Magasin | K27: Acces \ Application \ Application KO | L27: ########## | M27: P3 | N27: P3 | O27: FR IT SIC N1_N2 SUPER-HYPER BACK OFFICE | P27: IT | Q27: LILLERS -DEKEISER - SUPERMARCHES | R27: SUPERMARCHES FRANCE | S27: IntÃ©grÃ© | T27: RÃ©solution | U27: Atteint | V27: ########## | W27: 9.00 | X27: 27 | Y27: OK | Z27: 0 | AA27: 0 | AB27: 1 | AC27: HNO
A28: =VLOOKUP(O28,Dictionnaire!A:B,2,0) -> Mohamed BENSAID | B28: =O28 -> FR IT SIC N1_N2 SUPER-HYPER BACK OFFICE | E28: 122527244 | F28: DA | G28: modifier 5 PV bloquer par enveloppe promo | H28: CAROLINE SUPER-FR | I28: CAROLINE SUPER-FR | J28: DS Magasin | K28: Back Office Super \ Tarification \ Prix de vente | L28: ########## | M28: P1 | N28: P2 | O28: FR IT SIC N1_N2 SUPER-HYPER BACK OFFICE | P28: IT | Q28: BRAM - SUPERMARCHES | R28: SUPERMARCHES FRANCE | S28: FranchisÃ© | T28: RÃ©solution | U28: Atteint | V28: ########## | W28: 5.56 | X28: 18 | Y28: OK | Z28: 0 | AA28: 0 | AB28: 2 | AC28: HNO
A29: =VLOOKUP(O29,Dictionnaire!A:B,2,0) -> Mohamed BENSAID | B29: =O29 -> FR IT SIC N1_N2 SUPER-HYPER BACK OFFICE | E29: 122570579 | F29: DA | G29: z- Autre | H29: CAROLINE HYPER-FR | I29: CAROLINE HYPER-FR | J29: DS Magasin | K29: Back Office Hyper \ Tarification \ Prix d achat | L29: ########## | M29: P2 | N29: P2 | O29: FR IT SIC N1_N2 SUPER-HYPER BACK OFFICE | P29: IT | Q29: ST JOUAN DES GUERETS - HYPERMARCHES | R29: HYPERMARCHES FRANCE | S29: IntÃ©grÃ© | T29: RÃ©solution | U29: Atteint | V29: ########## | W29: 4.18 | X29: 18 | Y29: OK | Z29: 0 | AA29: 0 | AB29: 1 | AC29: HO
A30: =VLOOKUP(O30,Dictionnaire!A:B,2,0) -> Mohamed BENSAID | B30: =O30 -> FR IT SIC N1_N2 SUPER-HYPER BACK OFFICE | E30: 122573647 | F30: DA | G30: PVB/PVC | H30: CAROLINE HYPER-FR | I30: CAROLINE HYPER-FR | J30: DS Magasin | K30: Back Office Hyper \ Tarification \ Prix d achat | L30: ########## | M30: P1 | N30: P4 | O30: FR IT SIC N1_N2 SUPER-HYPER BACK OFFICE | P30: IT | Q30: PORT DE BOUC - HYPERMARCHES | R30: HYPERMARCHES FRANCE | S30: LG | T30: RÃ©solution | U30: Atteint | V30: ########## | W30: 1.90 | X30: 45 | Y30: OK | Z30: 0 | AA30: 0 | AB30: 1 | AC30: HO
... A40: =VLOOKUP(O40,Dictionnaire!A:B,2,0) -> Mohamed BENSAID | B40: =O40 -> FR IT SIC N1_N2 SUPER-HYPER BACK OFFICE | E40: 123210960 | F40: DA | G40: Ecart proforma et financier | H40: CAROLINE SUPER-FR | I40: VLP SUPER-FR | J40: DS Magasin | K40: Encaissement \ Chiffre d affaire \ Ecart de CA | L40: ########## | M40: P3 | N40: P4 | O40: FR IT SIC N1_N2 SUPER-HYPER BACK OFFICE | P40: IT | Q40: OULLINS - SUPERMARCHES | R40: SUPERMARCHES FRANCE | S40: FranchisÃ© | T40: RÃ©solution | U40: Atteint | V40: ########## | W40: 5.20 | X40: 60 | Y40: OK | Z40: 1 | AA40: 0 | AB40: 1 | AC40: HO
A41: =VLOOKUP(O41,Dictionnaire!A:B,2,0) -> Mohamed BENSAID | B41: =O41 -> FR IT SIC N1_N2 SUPER-HYPER BACK OFFICE | E41: 123214288 | F41: DA | G41: Ã©cart sur le chiffre d'affaire 14 avril | H41: CAROLINE SUPER-FR | I41: CAROLINE SUPER-FR | J41: DS Magasin | K41: Back Office Super \ Chiffre d affaire | L41: ########## | M41: P3 | N41: P3 | O41: FR IT SIC N1_N2 SUPER-HYPER BACK OFFICE | P41: IT | Q41: CAZOULS LES BEZIERS - SUPERMARCHES | R41: SUPERMARCHES FRANCE | S41: FranchisÃ© | T41: RÃ©solution | U41: Atteint | V41: ########## | W41: 46154 | X41: 27 | Y41: OK | Z41: 2 | AA41: 0 | AB41: 1 | AC41: HO
A42: =VLOOKUP(O42,Dictionnaire!A:B,2,0) -> Mohamed BENSAID | B42: =O42 -> FR IT SIC N1_N2 SUPER-HYPER BACK OFFICE | E42: 123266939 | F42: DA | G42: ARTICLE INEXISTANT MAIS IMPOSSIBLE DE LE CREER | H42: CAROLINE HYPER-FR | I42: CAROLINE HYPER-FR | J42: DS Magasin | K42: Back Office Hyper \ Referentiel \ Article inconnu | L42: ########## | M42: P3 | N42: P3 | O42: FR IT SIC N1_N2 SUPER-HYPER BACK OFFICE | P42: IT | Q42: MONTAUBAN - HYPERMARCHES | R42: HYPERMARCHES FRANCE | S42: FranchisÃ© | T42: RÃ©solution | U42: Atteint | V42: ########## | W42: 17.22 | X42: 27 | Y42: OK | Z42: 0 | AA42: 0 | AB42: 1 | AC42: HO
A43: =VLOOKUP(O43,Dictionnaire!A:B,2,0) -> Mohamed BENSAID | B43: =O43 -> FR IT SIC N1_N2 SUPER-HYPER BACK OFFICE | E43: 123320167 | F43: DA | G43: Suppression urgente EAN 8423230000305 vente Ã© perte | H43: CAROLINE HYPER-FR | I43: CAROLINE HYPER-FR | J43: DS Magasin | K43: Back Office Hyper \ Inventaire \ Annulation / suppression | L43: ########## | M43: P2 | N43: P1 | O43: FR IT SIC N1_N2 SUPER-HYPER BACK OFFICE | P43: IT | Q43: MONACO - HYPERMARCHES | R43: HYPERMARCHES FRANCE | S43: IntÃ©grÃ© | T43: RÃ©solution | U43: Atteint | V43: ########## | W43: 6.44 | X43: 9 | Y43: OK | Z43: 1 | AA43: 0 | AB43: 1 | AC43: HNO
A44: =VLOOKUP(O44,Dictionnaire!A:B,2,0) -> Mohamed BENSAID | B44: =O44 -> FR IT SIC N1_N2 SUPER-HYPER BACK OFFICE | E44: 123371536 | F44: DA | G44: CREME | H44: CAROLINE HYPER-FR | I44: CAROLINE HYPER-FR | J44: DS Magasin | K44: Back Office Hyper \ Referentiel \ Modification donnee article | L44: ########## | M44: P1 | N44: P3 | O44: FR IT SIC N1_N2 SUPER-HYPER BACK OFFICE | P44: IT | Q44: VILLEFRANCHE DE ROUE - HYPERMARCHES | R44: HYPERMARCHES FRANCE | S44: LG | T44: RÃ©solution | U44: Atteint | V44: ########## | W44: 5.39 | X44: 27 | Y44: OK | Z44: 0 | AA44: 0 | AB44: 2 | AC44: HO
A45: =VLOOKUP(O45,Dictionnaire!A:B,2,0) -> Mohamed BENSAID | B45: =O45 -> FR IT SIC N1_N2 SUPER-HYPER BACK OFFICE | E45: 123399176 | F45: DA | G45: ACCES IMPOSSIBLE AU MENU INVENTAIRE POUR UNE MANAGER | H45: CAROLINE HYPER-FR | I45: CAROLINE HYPER-FR | J45: DS Magasin | K45: Acces \ Application \ Droit GDI | L45: ########## | M45: P2 | N45: P2 | O45: FR IT SIC N1_N2 SUPER-HYPER BACK OFFICE | P45: IT | Q45: FERNEY VOLTAIRE - HYPERMARCHES | R45: HYPERMARCHES FRANCE | S45: FranchisÃ© | T45: RÃ©solution | U45: Atteint | V45: ########## | W45: 12.55 | X45: 18 | Y45: OK | Z45: 0 | AA45: 0 | AB45: 1 | AC45: HO
A46: =VLOOKUP(O46,Dictionnaire!A:B,2,0) -> Mohamed BENSAID | B46: =O46 -> FR IT SIC N1_N2 SUPER-HYPER BACK OFFICE | E46: 123454896 | F46: DA | G46: Demande de facture fournisseur | H46: CAROLINE HYPER-FR | I46: CAROLINE HYPER-FR | J46: DS Magasin | K46: Back Office Hyper \ Commande | L46: ########## | M46: P3 | N46: P3 | O46: FR IT SIC N1_N2 SUPER-HYPER BACK OFFICE | P46: IT | Q46: EVREUX -SAINT TAURIN - HYPERMARCHES | R46: HYPERMARCHES FRANCE | S46: IntÃ©grÃ© | T46: RÃ©solution | U46: Atteint | V46: ########## | W46: 1.00 | X46: 27 | Y46: OK | Z46: 0 | AA46: 0 | AB46: 1 | AC46: HO
A47: =VLOOKUP(O47,Dictionnaire!A:B,2,0) -> Mohamed BENSAID | B47: =O47 -> FR IT SIC N1_N2 SUPER-HYPER BACK OFFICE | E47: 123641447 | F47: DA | G47: Impossible de crÃ©er des zones d?inventaire sur Caroline | H47: CAROLINE HYPER-FR | I47: CAROLINE HYPER-FR | J47: DS Magasin | K47: Back Office Hyper \ Inventaire \ Chiffrage box | L47: ########## | M47: P3 | N47: P3 | O47: FR IT SIC N1_N2 SUPER-HYPER BACK OFFICE | P47: IT | Q47: METZ -TECHNOPOLE - HYPERMARCHES | R47: HYPERMARCHES FRANCE | S47: IntÃ©grÃ© | T47: RÃ©solution | U47: Atteint | V47: ########## | W47: 10.75 | X47: 27 | Y47: OK | Z47: 0 | AA47: 0 | AB47: 1 | AC47: HO | AD47: 123904947
A48: =VLOOKUP(O48,Dictionnaire!A:B,2,0) -> Mohamed BENSAID | B48: =O48 -> FR IT SIC N1_N2 SUPER-HYPER BACK OFFICE | E48: 123658710 | F48: DA | G48: Validation | H48: CAROLINE HYPER-FR | I48: CAROLINE HYPER-FR | J48: DS Magasin | K48: Back Office Hyper \ Inventaire \ Chiffrage box | L48: ########## | M48: P2 | N48: P2 | O48: FR IT SIC N1_N2 SUPER-HYPER BACK OFFICE | P48: IT | Q48: DORLISHEIM -MOLSHEIM - HYPERMARCHES | R48: HYPERMARCHES FRANCE | S48: IntÃ©grÃ© | T48: RÃ©solution | U48: Atteint | V48: ########## | W48: 12.33 | X48: 18 | Y48: OK | Z48: 0 | AA48: 0 | AB48: 1 | AC48: HO | AD48: 123904947
A49: =VLOOKUP(O49,Dictionnaire!A:B,2,0) -> Mohamed BENSAID | B49: =O49 -> FR IT SIC N1_N2 SUPER-HYPER BACK OFFICE | E49: 123691576 | F49: DS | G49: Demande d'integration de SMP dans Caroline sur le SMP Magasin et sur le SMP prÃ©conisÃ© HYPER TEXTILE | H49: CAROLINE HYPER-FR | I49: CAROLINE HYPER-FR | J49: DS Magasin | K49: Back Office Hyper \ Referentiel | L49: ########## | M49: P3 | N49: P3 | O49: FR IT SIC N1_N2 SUPER-HYPER BACK OFFICE | P49: IT | Q49: FRANCE | R49: NON DEFINIE | S49: Non affectÃ© | T49: ExÃ©cution | U49: Atteint | V49: ########## | W49: 0.23 | X49: 66 | Y49: OK | Z49: 0 | AA49: 0 | AB49: 1 | AC49: HO
A50: =VLOOKUP(O50,Dictionnaire!A:B,2,0) -> Mohamed BENSAID | B50: =O50 -> FR IT SIC N1_N2 SUPER-HYPER BACK OFFICE | E50: 123889352 | F50: DA | G50: CA | H50: CAROLINE SUPER-FR | I50: VLP SUPER-FR | J50: DS Magasin | K50: Encaissement \ Chiffre d affaire \ Ecart de CA | L50: ########## | M50: P3 | N50: P3 | O50: FR IT SIC N1_N2 SUPER-HYPER BACK OFFICE | P50: IT | Q50: COSNE COURS S/L -RN7 - SUPERMARCHES | R50: SUPERMARCHES FRANCE | S50: LG | T50: RÃ©solution | U50: Atteint | V50: ########## | W50: 10.39 | X50: 36 | Y50: OK | Z50: 3 | AA50: 0 | AB50: 1 | AC50: HO
A51: =VLOOKUP(O51,Dictionnaire!A:B,2,0) -> Mohamed BENSAID | B51: =O51 -> FR IT SIC N1_N2 SUPER-HYPER BACK OFFICE | E51: 123943031 | F51: DA | G51: chiffre livre de caisse prÃ©lÃ©vement | H51: CAROLINE SUPER-FR | I51: CAROLINE SUPER-FR | J51: DS Magasin | K51: Back Office Super \ Livre de caisse \ Prelevement | L51: ########## | M51: P2 | N51: P3 | O51: FR IT SIC N1_N2 SUPER-HYPER BACK OFFICE | P51: IT | Q51: SANCERRE - SUPERMARCHES | R51: SUPERMARCHES FRANCE | S51: LG | T51: RÃ©solution | U51: Atteint | V51: ########## | W51: 5.88 | X51: 27 | Y51: OK | Z51: 2 | AA51: 0 | AB51: 1 | AC51: HO
A52: =VLOOKUP(O52,Dictionnaire!A:B,2,0) -> Mohamed BENSAID | B52: =O52 -> FR IT SIC N1_N2 SUPER-HYPER BACK OFFICE | E52: 124095534 | F52: DA | G52: Tarification | H52: CAROLINE HYPER-FR | I52: CAROLINE HYPER-FR | J52: DS Magasin | K52: Back Office Hyper \ Tarification | L52: ########## | M52: P3 | N52: P3 | O52: FR IT SIC N1_N2 SUPER-HYPER BACK OFFICE | P52: IT | Q52: VALENCIENNES - HYPERMARCHES | R52: HYPERMARCHES FRANCE | S52: IntÃ©grÃ© | T52: RÃ©solution | U52: Atteint | V52: ########## | W52: 0.00 | X52: 27 | Y52: OK | Z52: 0 | AA52: 0 | AB52: 1 | AC52: HNO
A53: =VLOOKUP(O53,Dictionnaire!A:B,2,0) -> Yassine RABBAI | B53: =O53 -> FR IT SIC N1_N2 SUPER-HYPER FRONT OFFICE | E53: 121034136 | F53: DA | G53: Doublon - Caisse (douchette, Ã©cran, imprimante, scanner, TPE, UC...) | H53: E-PORTAL-FR | I53: CARINE (SA V2 HYPER)-FR | J53: DS Magasin | K53: Encaissement \ Serveur caisse | L53: ########## | M53: P4 | N53: P4 | O53: FR IT SIC N1_N2 SUPER-HYPER FRONT OFFICE | P53: IT | Q53: VENETTE - HYPERMARCHES | R53: HYPERMARCHES FRANCE | S53: IntÃ©grÃ© | T53: RÃ©solution | U53: Atteint | V53: ########## | W53: 7.49 | X53: 45 | Y53: OK | Z53: 1 | AA53: 0 | AB53: 3 | AC53: HO
A54: =VLOOKUP(O54,Dictionnaire!A:B,2,0) -> Yassine RABBAI | B54: =O54 -> FR IT SIC N1_N2 SUPER-HYPER FRONT OFFICE | E54: 121429661 | F54: DA | G54: Doublon - Double paiement | H54: SCO NCR-FR | I54: SCO NCR-FR | J54: DS Magasin | K54: Caisse libre service \ Parametrage | L54: ########## | M54: P4 | N54: P4 | O54: FR IT SIC N1_N2 SUPER-HYPER FRONT OFFICE | P54: IT | Q54: NOISY LE SEC - SUPERMARCHES | R54: SUPERMARCHES FRANCE | S54: FranchisÃ© | T54: RÃ©solution | U54: Atteint | V54: ########## | W54: 44.37 | X54: 60 | Y54: OK | Z54: 0 | AA54: 0 | AB54: 1 | AC54: HO
A55: =VLOOKUP(O55,Dictionnaire!A:B,2,0) -> Yassine RABBAI | B55: =O55 -> FR IT SIC N1_N2 SUPER-HYPER FRONT OFFICE | E55: 121816520 | F55: DA | G55: SCANETTE | H55: SCANEO-FR | I55: SCANEO-FR | J55: DS Magasin | K55: Encaissement \ Scaneo \ Utilisation scanette | L55: ########## | M55: P3 | N55: P3 | O55: FR IT SIC N1_N2 SUPER-HYPER FRONT OFFICE | P55: IT | Q55: BEAUCAIRE - HYPERMARCHES | R55: HYPERMARCHES FRANCE | S55: IntÃ©grÃ© | T55: RÃ©solution | U55: Atteint | V55: ########## | W55: 17.14 | X55: 36 | Y55: OK | Z55: 0 | AA55: 0 | AB55: 2 | AC55: HO
A56: =VLOOKUP(O56,Dictionnaire!A:B,2,0) -> Yassine RABBAI | B56: =O56 -> FR IT SIC N1_N2 SUPER-HYPER FRONT OFFICE | E56: 121985211 | F56: DA | G56: Doublon - SCO 31 erreur imprimante ticket malgrÃ© bloc neuf | H56: SCO NCR-FR | I56: SCO NCR-FR | J56: DS Magasin | K56: Caisse libre service \ Caisse deconnecte | L56: ########## | M56: P3 | N56: P4 | O56: FR IT SIC N1_N2 SUPER-HYPER FRONT OFFICE | P56: IT | Q56: LEON - SUPERMARCHES | R56: SUPERMARCHES FRANCE | S56: IntÃ©grÃ© | T56: RÃ©solution | U56: Atteint | V56: ########## | W56: 55.96 | X56: 60 | Y56: OK | Z56: 4 | AA56: 0 | AB56: 2 | AC56: HNO | AE56: 121991045, 122227550, 123316787
A57: =VLOOKUP(O57,Dictionnaire!A:B,2,0) -> Yassine RABBAI | B57: =O57 -> FR IT SIC N1_N2 SUPER-HYPER FRONT OFFICE | E57: 122581766 | F57: DA | G57: Orientation des cartes Pluxee vers rÃ©seau Visa et Conecs | H57: VLP SUPER-FR | I57: VLP SUPER-FR | J57: DS Magasin | K57: Encaissement \ Article | L57: ########## | M57: P2 | N57: P2 | O57: FR IT SIC N1_N2 SUPER-HYPER FRONT OFFICE | P57: IT | Q57: TOURNAN EN BRIE - SUPERMARCHES | R57: SUPERMARCHES FRANCE | S57: LG | T57: RÃ©solution | U57: Echec | V57: ########## | W57: 51.57 | X57: 24 | Y57: KO | Z57: 0 | AA57: 0 | AB57: 1 | AC57: HO
A58: =VLOOKUP(O58,Dictionnaire!A:B,2,0) -> Yassine RABBAI | B58: =O58 -> FR IT SIC N1_N2 SUPER-HYPER FRONT OFFICE | E58: 122721720 | F58: DA | G58: Paiement amex vlp | H58: VLP SUPER-FR | I58: VLP SUPER-FR | J58: DS Magasin | K58: Encaissement \ Chiffre d affaire | L58: ########## | M58: P2 | N58: P2 | O58: FR IT SIC N1_N2 SUPER-HYPER FRONT OFFICE | P58: IT | Q58: PALAVAS LES FLOTS - SUPERMARCHES | R58: SUPERMARCHES FRANCE | S58: FranchisÃ© | T58: RÃ©solution | U58: Atteint | V58: ########## | W58: 12.91 | X58: 24 | Y58: OK | Z58: 0 | AA58: 0 | AB58: 2 | AC58: HO
A59: =VLOOKUP(O59,Dictionnaire!A:B,2,0) -> Yassine RABBAI | B59: =O59 -> FR IT SIC N1_N2 SUPER-HYPER FRONT OFFICE | E59: 122732234 | F59: DA | G59: Absence de paiement sans contact sur TPE Accueil DÃ©diÃ© au carburant, demande de fonctionnement en sans contact et apple pay! | H59: AXIS-FR | I59: AXIS-FR | J59: DS Magasin | K59: Monetique \ TPE | L59: ########## | M59: P4 | N59: P4 | O59: FR IT SIC N1_N2 SUPER-HYPER FRONT OFFICE | P59: IT | Q59: BLANCS CO -VERTUS - SUPERMARCHES | R59: SUPERMARCHES FRANCE | S59: FranchisÃ© | T59: RÃ©solution | U59: Atteint | V59: ########## | W59: 11.41 | X59: 60 | Y59: OK | Z59: 0 | AA59: 0 | AB59: 1 | AC59: HO
A60: =VLOOKUP(O60,Dictionnaire!A:B,2,0) -> Yassine RABBAI | B60: =O60 -> FR IT SIC N1_N2 SUPER-HYPER FRONT OFFICE | E60: 122802877 | F60: DA | G60: BESOIN D'AIDE SUR ECART DE CA | H60: VLP SUPER-FR | I60: VLP SUPER-FR | J60: DS Magasin | K60: Encaissement \ Chiffre d affaire \ Ecart de CA | L60: ########## | M60: P1 | N60: P3 | O60: FR IT SIC N1_N2 SUPER-HYPER FRONT OFFICE | P60: IT | Q60: LA CRAU - SUPERMARCHES | R60: SUPERMARCHES FRANCE | S60: LG | T60: RÃ©solution | U60: Atteint | V60: ########## | W60: 27.98 | X60: 36 | Y60: OK | Z60: 0 | AA60: 0 | AB60: 1 | AC60: HO
A61: =VLOOKUP(O61,Dictionnaire!A:B,2,0) -> Yassine RABBAI | B61: =O61 -> FR IT SIC N1_N2 SUPER-HYPER FRONT OFFICE | E61: 122879669 | F61: DA | G61: Les cartes cadeaux ne s'activent pas lors du passage en caisse | H61: VLP SUPER-FR | I61: VLP SUPER-FR | J61: DS Magasin | K61: Acces \ Application \ Anomalie compte | L61: ########## | M61: P2 | N61: P2 | O61: FR IT SIC N1_N2 SUPER-HYPER FRONT OFFICE | P61: IT | Q61: REVEL - SUPERMARCHES | R61: SUPERMARCHES FRANCE | S61: FranchisÃ© | T61: RÃ©solution | U61: Atteint | V61: ########## | W61: 46086 | X61: 24 | Y61: OK | Z61: 2 | AA61: 0 | AB61: 1 | AC61: HO
A62: =VLOOKUP(O62,Dictionnaire!A:B,2,0) -> Yassine RABBAI | B62: =O62 -> FR IT SIC N1_N2 SUPER-HYPER FRONT OFFICE | E62: 122963211 | F62: DA | G62: Caisse SCO NCR 29- 31 bloquÃ©e Ã© la fermeture POS | H62: SCO NCR-FR | I62: SCO NCR-FR | J62: DS Magasin | K62: Caisse libre service \ Fermeture \ Caissier bloque | L62: ########## | M62: P4 | N62: P4 | O62: FR IT SIC N1_N2 SUPER-HYPER FRONT OFFICE | P62: IT | Q62: LEON - SUPERMARCHES | R62: SUPERMARCHES FRANCE | S62: IntÃ©grÃ© | T62: RÃ©solution | U62: Atteint | V62: ########## | W62: 46182 | X62: 60 | Y62: OK | Z62: 0 | AA62: 0 | AB62: 3 | AC62: HNO
A63: =VLOOKUP(O63,Dictionnaire!A:B,2,0) -> Yassine RABBAI | B63: =O63 -> FR IT SIC N1_N2 SUPER-HYPER FRONT OFFICE | E63: 122977774 | F63: DA | G63: caisse 6 | H63: VLP SUPER-FR | I63: VLP SUPER-FR | J63: DS Magasin | K63: Encaissement \ Chiffre d affaire \ Ecart de CA | L63: ########## | M63: P2 | N63: P4 | O63: FR IT SIC N1_N2 SUPER-HYPER FRONT OFFICE | P63: IT | Q63: STE MAXIME -MERMOZ - SUPERMARCHES | R63: SUPERMARCHES FRANCE | S63: FranchisÃ© | T63: RÃ©solution | U63: Atteint | V63: ########## | W63: 0.82 | X63: 60 | Y63: OK | Z63: 0 | AA63: 0 | AB63: 1 | AC63: HNO
A64: =VLOOKUP(O64,Dictionnaire!A:B,2,0) -> Yassine RABBAI | B64: =O64 -> FR IT SIC N1_N2 SUPER-HYPER FRONT OFFICE | E64: 123097783 | F64: DA | G64: Caisse acceuil | H64: VLP SUPER-FR | I64: VLP SUPER-FR | J64: DS Magasin | K64: Encaissement \ Caisse deconnecte \ En chargement avec erreur | L64: ########## | M64: P3 | N64: P3 | O64: FR IT SIC N1_N2 SUPER-HYPER FRONT OFFICE | P64: IT | Q64: ORBEC -VESPIERE - SUPERMARCHES | R64: SUPERMARCHES FRANCE | S64: FranchisÃ© | T64: RÃ©solution | U64: Atteint | V64: ########## | W64: 1.17 | X64: 36 | Y64: OK | Z64: 2 | AA64: 0 | AB64: 1 | AC64: HO
A65: =VLOOKUP(O65,Dictionnaire!A:B,2,0) -> Yassine RABBAI | B65: =O65 -> FR IT SIC N1_N2 SUPER-HYPER FRONT OFFICE | E65: 123228748 | F65: DA | G65: reinitialisation des adj | H65: VLP SUPER-FR | I65: VLP SUPER-FR | J65: DS Magasin | K65: Encaissement \ Parametrage peripherique caisse | L65: ########## | M65: P5 | N65: P4 | O65: FR IT SIC N1_N2 SUPER-HYPER FRONT OFFICE | P65: IT | Q65: ST DENIS EN VAL - SUPERMARCHES | R65: SUPERMARCHES FRANCE | S65: FranchisÃ© | T65: RÃ©solution | U65: Atteint | V65: ########## | W65: 1.31 | X65: 60 | Y65: OK | Z65: 0 | AA65: 0 | AB65: 1 | AC65: HO
A66: =VLOOKUP(O66,Dictionnaire!A:B,2,0) -> Yassine RABBAI | B66: =O66 -> FR IT SIC N1_N2 SUPER-HYPER FRONT OFFICE | E66: 123249378 | F66: DA | G66: recherche ticket de caisse | H66: COCASE-FR | I66: COCASE-FR | J66: DS Magasin | K66: Encaissement \ Serveur caisse \ Ticket de caisse | L66: ########## | M66: P4 | N66: P4 | O66: FR IT SIC N1_N2 SUPER-HYPER FRONT OFFICE | P66: IT | Q66: SARREBOURG - HYPERMARCHES | R66: HYPERMARCHES FRANCE | S66: IntÃ©grÃ© | T66: RÃ©solution | U66: Atteint | V66: ########## | W66: 11.66 | X66: 60 | Y66: OK | Z66: 0 | AA66: 0 | AB66: 1 | AC66: HO
A67: =VLOOKUP(O67,Dictionnaire!A:B,2,0) -> Yassine RABBAI | B67: =O67 -> FR IT SIC N1_N2 SUPER-HYPER FRONT OFFICE | E67: 123249819 | F67: DA | G67: Touche grise sur Ã©quipement magasin | H67: SCO NCR-FR | I67: SCO NCR-FR | J67: DS Magasin | K67: Caisse libre service \ Caisse deconnecte | L67: ########## | M67: P3 | N67: P4 | O67: FR IT SIC N1_N2 SUPER-HYPER FRONT OFFICE | P67: IT | Q67: PARIS -AUTEUIL - HYPERMARCHES | R67: HYPERMARCHES FRANCE | S67: IntÃ©grÃ© | T67: RÃ©solution | U67: Atteint | V67: ########## | W67: 0.82 | X67: 60 | Y67: OK | Z67: 1 | AA67: 0 | AB67: 1 | AC67: HO
A68: =VLOOKUP(O68,Dictionnaire!A:B,2,0) -> Yassine RABBAI | B68: =O68 -> FR IT SIC N1_N2 SUPER-HYPER FRONT OFFICE | E68: 123327703 | F68: DA | G68: Doublon - Panne borne SCA 166 | H68: CARINE (SA V2 HYPER)-FR | I68: SCO NCR-FR | J68: DS Magasin | K68: Caisse libre service \ Borne kodak \ Parametrage borne | L68: ########## | M68: P4 | N68: P4 | O68: FR IT SIC N1_N2 SUPER-HYPER FRONT OFFICE | P68: IT | Q68: ORMESSON - HYPERMARCHES | R68: HYPERMARCHES FRANCE | S68: IntÃ©grÃ© | T68: RÃ©solution | U68: Atteint | V68: ########## | W68: 0.23 | X68: 60 | Y68: OK | Z68: 0 | AA68: 0 | AB68: 1 | AC68: HO
A69: =VLOOKUP(O69,Dictionnaire!A:B,2,0) -> Yassine RABBAI | B69: =O69 -> FR IT SIC N1_N2 SUPER-HYPER FRONT OFFICE | E69: 123464412 | F69: DA | G69: Double dÃ©bit client malgrÃ© une transaction refusÃ©e | H69: E-PORTAL-FR | I69: E-PORTAL-FR | J69: DS Magasin | K69: Monetique \ E-portal \ Ecart de CA | L69: ########## | M69: P3 | N69: P4 | O69: FR IT SIC N1_N2 SUPER-HYPER FRONT OFFICE | P69: IT | Q69: JASSANS RIOTTIER - SUPERMARCHES | R69: SUPERMARCHES FRANCE | S69: IntÃ©grÃ© | T69: RÃ©solution | U69: Atteint | V69: ########## | W69: 0.29 | X69: 60 | Y69: OK | Z69: 0 | AA69: 0 | AB69: 1 | AC69: HO
A70: =VLOOKUP(O70,Dictionnaire!A:B,2,0) -> Yassine RABBAI | B70: =O70 -> FR IT SIC N1_N2 SUPER-HYPER FRONT OFFICE | E70: 123656892 | F70: DA | G70: Doublon - Caisse CARINE bloquÃ©e lors du paiement par chÃ©que | H70: AXIS-FR | I70: AXIS-FR | J70: DS Magasin | K70: Monetique \ E-portal \ Financement | L70: ########## | M70: P3 | N70: P3 | O70: FR IT SIC N1_N2 SUPER-HYPER FRONT OFFICE | P70: IT | Q70: BEAUCAIRE - HYPERMARCHES | R70: HYPERMARCHES FRANCE | S70: IntÃ©grÃ© | T70: RÃ©solution | U70: Atteint | V70: ########## | W70: 4.76 | X70: 36 | Y70: OK | Z70: 0 | AA70: 1 | AB70: 1 | AC70: HO
A71: =VLOOKUP(O71,Dictionnaire!A:B,2,0) -> Yassine RABBAI | B71: =O71 -> FR IT SIC N1_N2 SUPER-HYPER FRONT OFFICE | E71: 123748097 | F71: DA | G71: Ã©cart de caisse du 27/04/2026 | H71: VLP SUPER-FR | I71: VLP SUPER-FR | J71: DS Magasin | K71: Encaissement \ Chiffre d affaire \ Ecart de CA station | L71: ########## | M71: P1 | N71: P3 | O71: FR IT SIC N1_N2 SUPER-HYPER FRONT OFFICE | P71: IT | Q71: PARIS -ITALIE 2 - SUPERMARCHES | R71: SUPERMARCHES FRANCE | S71: LG | T71: RÃ©solution | U71: Atteint | V71: ########## | W71: 21.41 | X71: 36 | Y71: OK | Z71: 0 | AA71: 0 | AB71: 2 | AC71: HO
A72: =VLOOKUP(O72,Dictionnaire!A:B,2,0) -> Yassine RABBAI | B72: =O72 -> FR IT SIC N1_N2 SUPER-HYPER FRONT OFFICE | E72: 123800368 | F72: DA | G72: carte bancaire | H72: VLP SUPER-FR | I72: VLP SUPER-FR | J72: DS Magasin | K72: Encaissement \ Chiffre d affaire | L72: ########## | M72: P3 | N72: P3 | O72: FR IT SIC N1_N2 SUPER-HYPER FRONT OFFICE | P72: IT | Q72: ROMILLY S/S -MARAIS - SUPERMARCHES | R72: SUPERMARCHES FRANCE | S72: LG | T72: RÃ©solution | U72: Atteint | V72: ########## | W72: 0.23 | X72: 36 | Y72: OK | Z72: 0 | AA72: 0 | AB72: 1 | AC72: HO
A73: =VLOOKUP(O73,Dictionnaire!A:B,2,0) -> Yassine RABBAI | B73: =O73 -> FR IT SIC N1_N2 SUPER-HYPER FRONT OFFICE | E73: 123942904 | F73: DS | G73: ProblÃ©me de dÃ©calage horaire dans les Ã©ditions de retours | H73: CARINE (SA V2 HYPER)-FR | I73: CARINE (SA V2 HYPER)-FR | J73: DS Magasin | K73: Encaissement \ Serveur caisse \ Edition | L73: ########## | M73: P3 | N73: P3 | O73: FR IT SIC N1_N2 SUPER-HYPER FRONT OFFICE | P73: IT | Q73: ST CLEMENT DE RIVIER - HYPERMARCHES | R73: HYPERMARCHES FRANCE | S73: IntÃ©grÃ© | T73: ExÃ©cution | U73: Atteint | V73: ########## | W73: 3.74 | X73: 120 | Y73: OK | Z73: 0 | AA73: 0 | AB73: 2 | AC73: HO
A74: =VLOOKUP(O74,Dictionnaire!A:B,2,0) -> Yassine RABBAI | B74: =O74 -> FR IT SIC N1_N2 SUPER-HYPER FRONT OFFICE | E74: 124088506 | F74: DA | G74: Demande de duplicata ticket caisse achat janvier 2025 | H74: VLP SUPER-FR | I74: VLP SUPER-FR | J74: DS Magasin | K74: Encaissement \ Gravage \ Journal de caisse | L74: ########## | M74: P3 | N74: P3 | O74: FR IT SIC N1_N2 SUPER-HYPER FRONT OFFICE | P74: IT | Q74: ERGUE GABERIC - SUPERMARCHES | R74: SUPERMARCHES FRANCE | S74: IntÃ©grÃ© | T74: RÃ©solution | U74: Atteint | V74: ########## | W74: 1.83 | X74: 36 | Y74: OK | Z74: 0 | AA74: 0 | AB74: 1 | AC74: HNO
... A80: =VLOOKUP(O80,Dictionnaire!A:B,2,0) -> Amine BABA | B80: =O80 -> FR IT UMA N1 N2 PARTENAIRE MAGASIN | E80: 122228982 | F80: DA | G80: ASSISTANCE: BALANCE - Balance Mettler Toledo FW-T 15D D - S/N:C147036970 BIO VRAC EPICERIE Carrefour | H80: BALANCE METTLER TOLEDO HYPER-FR | I80: BALANCE METTLER TOLEDO HYPER-FR | J80: DS Magasin | K80: Materiel Balance \ Mettler Toledo | L80: ########## | M80: P3 | N80: P3 | O80: FR IT UMA N1 N2 PARTENAIRE MAGASIN | P80: IT | Q80: LONGEVILLE ST AVOLD - HYPERMARCHES | R80: HYPERMARCHES FRANCE | S80: IntÃ©grÃ© | T80: RÃ©solution | U80: Atteint | V80: ########## | W80: 4.53 | X80: 27 | Y80: OK | Z80: 0 | AA80: 0 | AB80: 1 | AC80: HO
A81: =VLOOKUP(O81,Dictionnaire!A:B,2,0) -> Amine BABA | B81: =O81 -> FR IT UMA N1 N2 PARTENAIRE MAGASIN | E81: 122519128 | F81: DA | G81: ASSISTANCE: MAGALI - CombinÃ© Balance / Etiqueteuse / Emballeuse DIGI AW 4600 CP - S/N:16176308 BOUCHERIE UVCM | H81: DIGI-FR | I81: DIGI-FR | J81: DS Magasin | K81: Back Office Multi format \ Balance \ Donnee erronee | L81: ########## | M81: P4 | N81: P4 | O81: FR IT UMA N1 N2 PARTENAIRE MAGASIN | P81: IT | Q81: CLAYE SOUILLY - HYPERMARCHES | R81: HYPERMARCHES FRANCE | S81: IntÃ©grÃ© | T81: RÃ©solution | U81: Atteint | V81: ########## | W81: 46194 | X81: 45 | Y81: OK | Z81: 0 | AA81: 0 | AB81: 1 | AC81: HNO
A82: =VLOOKUP(O82,Dictionnaire!A:B,2,0) -> Amine BABA | B82: =O82 -> FR IT UMA N1 N2 PARTENAIRE MAGASIN | E82: 122730508 | F82: DA | G82: Autre problÃ©me Magali | H82: MAGALI-FR | I82: MAGALI-FR | J82: DS Magasin | K82: Back Office Multi format \ Balance \ Relance service | L82: ########## | M82: P4 | N82: P4 | O82: FR IT UMA N1 N2 PARTENAIRE MAGASIN | P82: IT | Q82: COLMAR -HOUSSEN - HYPERMARCHES | R82: HYPERMARCHES FRANCE | S82: IntÃ©grÃ© | T82: RÃ©solution | U82: Atteint | V82: ########## | W82: 34.03 | X82: 45 | Y82: OK | Z82: 2 | AA82: 0 | AB82: 1 | AC82: HNO
A83: =VLOOKUP(O83,Dictionnaire!A:B,2,0) -> Amine BABA | B83: =O83 -> FR IT UMA N1 N2 PARTENAIRE MAGASIN | E83: 123050620 | F83: DA | G83: balance ls paramÃ©trÃ© en Ã©tiquette Trade | H83: MAGALI-FR | I83: MAGALI-FR | J83: DS Magasin | K83: Back Office Multi format \ Balance \ Donnee erronee | L83: ########## | M83: P2 | N83: P2 | O83: FR IT UMA N1 N2 PARTENAIRE MAGASIN | P83: IT | Q83: RUY - SUPERMARCHES | R83: SUPERMARCHES FRANCE | S83: LG | T83: RÃ©solution | U83: Atteint | V83: ########## | W83: 8.62 | X83: 18 | Y83: OK | Z83: 0 | AA83: 0 | AB83: 1 | AC83: HNO
A84: =VLOOKUP(O84,Dictionnaire!A:B,2,0) -> Amine BABA | B84: =O84 -> FR IT UMA N1 N2 PARTENAIRE MAGASIN | E84: 123073831 | F84: DA | G84: ASSISTANCE: BALANCE - Balance Avery Berkel XT 300 - S/N:14480377 FRUITS & LEGUMES | H84: BERKEL-FR | I84: BERKEL-FR | J84: DS Magasin | K84: Back Office Multi format \ Balance \ Connectivite | L84: ########## | M84: P4 | N84: P4 | O84: FR IT UMA N1 N2 PARTENAIRE MAGASIN | P84: IT | Q84: PLOEMEUR -BRETAGNE - SUPERMARCHES | R84: SUPERMARCHES FRANCE | S84: IntÃ©grÃ© | T84: RÃ©solution | U84: Atteint | V84: ########## | W84: 0.41 | X84: 45 | Y84: OK | Z84: 0 | AA84: 0 | AB84: 1 | AC84: HNO
A85: =VLOOKUP(O85,Dictionnaire!A:B,2,0) -> Amine BABA | B85: =O85 -> FR IT UMA N1 N2 PARTENAIRE MAGASIN | E85: 123461823 | F85: DA | G85: accÃ©s VLINK | H85: EEG SES-FR | I85: EEG SES-FR | J85: DS Magasin | K85: Back Office Multi format \ Balisage \ Balisage electronique | L85: ########## | M85: P2 | N85: P2 | O85: FR IT UMA N1 N2 PARTENAIRE MAGASIN | P85: IT | Q85: PARIS -ROCHECHOUART - SUPERMARCHES | R85: SUPERMARCHES FRANCE | S85: IntÃ©grÃ© | T85: RÃ©solution | U85: Atteint | V85: ########## | W85: 2.58 | X85: 18 | Y85: OK | Z85: 2 | AA85: 0 | AB85: 1 | AC85: HO
A86: =VLOOKUP(O86,Dictionnaire!A:B,2,0) -> Amine BABA | B86: =O86 -> FR IT UMA N1 N2 PARTENAIRE MAGASIN | E86: 123714874 | F86: DA | G86: Ã©tiquettes en attente de mises Ã© jour | H86: EEG HANSHOW-FR | I86: EEG PRICER-FR | J86: DS Magasin | K86: Back Office Multi format \ Balisage \ Balisage electronique | L86: ########## | M86: P4 | N86: P4 | O86: FR IT UMA N1 N2 PARTENAIRE MAGASIN | P86: IT | Q86: NANCY -HOUDEMONT - HYPERMARCHES | R86: HYPERMARCHES FRANCE | S86: IntÃ©grÃ© | T86: RÃ©solution | U86: Atteint | V86: ########## | W86: 11.99 | X86: 45 | Y86: OK | Z86: 0 | AA86: 0 | AB86: 1 | AC86: HO
A87: =VLOOKUP(O87,Dictionnaire!A:B,2,0) -> Mohamed BENSAID | B87: =O87 -> FR IT UMA N3 BACK OFFICE MAGASIN | E87: 121058967 | F87: DA | G87: problÃ©me ventilation article | H87: CAROLINE SUPER-FR | I87: CAROLINE SUPER-FR | J87: DS Magasin | K87: Back Office Super \ Referentiel \ Fournisseur | L87: ########## | M87: P3 | N87: P3 | O87: FR IT UMA N3 BACK OFFICE MAGASIN | P87: IT | Q87: VOIRON -COLOMBIER - SUPERMARCHES | R87: SUPERMARCHES FRANCE | S87: LG | T87: RÃ©solution | U87: Echec | V87: ########## | W87: 46.25 | X87: 27 | Y87: KO | Z87: 1 | AA87: 0 | AB87: 5 | AC87: HO
A88: =VLOOKUP(O88,Dictionnaire!A:B,2,0) -> Mohamed BENSAID | B88: =O88 -> FR IT UMA N3 BACK OFFICE MAGASIN | E88: 121269526 | F88: DA | G88: Pb remontÃ©e CA caroline et VLP | H88: CAROLINE SUPER-FR | I88: VLP SUPER-FR | J88: DS Magasin | K88: Encaissement \ Chiffre d affaire \ Ecart de CA | L88: ########## | M88: P3 | N88: P4 | O88: FR IT UMA N3 BACK OFFICE MAGASIN | P88: IT | Q88: QUEVERT DINAN - SUPERMARCHES | R88: SUPERMARCHES FRANCE | S88: LG | T88: RÃ©solution | U88: Atteint | V88: ########## | W88: 39.26 | X88: 60 | Y88: OK | Z88: 6 | AA88: 0 | AB88: 2 | AC88: HO
A89: =VLOOKUP(O89,Dictionnaire!A:B,2,0) -> Mohamed BENSAID | B89: =O89 -> FR IT UMA N3 BACK OFFICE MAGASIN | E89: 121981077 | F89: DA | G89: manque de CA sur caroline | H89: CAROLINE SUPER-FR | I89: CAROLINE SUPER-FR | J89: DS Magasin | K89: Back Office Super | L89: ########## | M89: P3 | N89: P3 | O89: FR IT UMA N3 BACK OFFICE MAGASIN | P89: IT | Q89: MARQUISE - SUPERMARCHES | R89: SUPERMARCHES FRANCE | S89: LG | T89: RÃ©solution | U89: Echec | V89: ########## | W89: 88.65 | X89: 36 | Y89: KO | Z89: 7 | AA89: 0 | AB89: 1 | AC89: HNO
A90: =VLOOKUP(O90,Dictionnaire!A:B,2,0) -> Mohamed BENSAID | B90: =O90 -> FR IT UMA N3 BACK OFFICE MAGASIN | E90: 122110188 | F90: DA | G90: problÃ©me prix d'achat prix de vente | H90: CAROLINE SUPER-FR | I90: CAROLINE SUPER-FR | J90: DS Magasin | K90: Back Office Super \ Tarification | L90: ########## | M90: P3 | N90: P3 | O90: FR IT UMA N3 BACK OFFICE MAGASIN | P90: IT | Q90: SIN-LE-NOBLE - SUPERMARCHES | R90: SUPERMARCHES FRANCE | S90: LG | T90: RÃ©solution | U90: Echec | V90: ########## | W90: 69.11 | X90: 27 | Y90: KO | Z90: 1 | AA90: 0 | AB90: 1 | AC90: HO
A91: =VLOOKUP(O91,Dictionnaire!A:B,2,0) -> Mohamed BENSAID | B91: =O91 -> FR IT UMA N3 BACK OFFICE MAGASIN | E91: 122265779 | F91: DA | G91: Stocks articles | H91: CAROLINE HYPER-FR | I91: CAROLINE HYPER-FR | J91: DS Magasin | K91: Back Office Hyper \ Referentiel \ Fournisseur | L91: ########## | M91: P2 | N91: P2 | O91: FR IT UMA N3 BACK OFFICE MAGASIN | P91: IT | Q91: SAINT RENAN - HYPERMARCHES | R91: HYPERMARCHES FRANCE | S91: FranchisÃ© | T91: RÃ©solution | U91: Echec | V91: ########## | W91: 62.29 | X91: 18 | Y91: KO | Z91: 1 | AA91: 0 | AB91: 1 | AC91: HNO
A92: =VLOOKUP(O92,Dictionnaire!A:B,2,0) -> Mohamed BENSAID | B92: =O92 -> FR IT UMA N3 BACK OFFICE MAGASIN | E92: 122368084 | F92: DA | G92: DEMANDE DE REMISE A DISPOSITION DE BLI | H92: CAROLINE HYPER-FR | I92: CAROLINE HYPER-FR | J92: DS Magasin | K92: Back Office Hyper \ Stock \ BLI entrepot | L92: ########## | M92: P4 | N92: P4 | O92: FR IT UMA N3 BACK OFFICE MAGASIN | P92: IT | Q92: LOMME - HYPERMARCHES | R92: HYPERMARCHES FRANCE | S92: LG | T92: RÃ©solution | U92: Atteint | V92: ########## | W92: 15.70 | X92: 45 | Y92: OK | Z92: 3 | AA92: 0 | AB92: 1 | AC92: HO
A93: =VLOOKUP(O93,Dictionnaire!A:B,2,0) -> Mohamed BENSAID | B93: =O93 -> FR IT UMA N3 BACK OFFICE MAGASIN | E93: 122374595 | F93: DA | G93: Ecart sur le chiffre d'affaire entre CAROline et Carine(j2art-gravix) sur la journÃ©e du Lundi 27/07/2026 | H93: CAROLINE HYPER-FR | I93: CAROLINE HYPER-FR | J93: DS Magasin | K93: Back Office Hyper \ Chiffre d affaire | L93: ########## | M93: P4 | N93: P4 | O93: FR IT UMA N3 BACK OFFICE MAGASIN | P93: IT | Q93: LE CRES - HYPERMARCHES | R93: HYPERMARCHES FRANCE | S93: FranchisÃ© | T93: RÃ©solution | U93: Atteint | V93: ########## | W93: 27.97 | X93: 45 | Y93: OK | Z93: 1 | AA93: 0 | AB93: 1 | AC93: HO
... A98: =VLOOKUP(O98,Dictionnaire!A:B,2,0) -> Mohamed BENSAID | B98: =O98 -> FR IT UMA N3 BACK OFFICE MAGASIN | E98: 122945064 | F98: DA | G98: Taux de marge erronÃ© sur le bon de livraison | H98: CAROLINE HYPER-FR | I98: CAROLINE HYPER-FR | J98: DS Magasin | K98: Back Office Hyper \ Commande \ Commande manuelle | L98: ########## | M98: P3 | N98: P3 | O98: FR IT UMA N3 BACK OFFICE MAGASIN | P98: IT | Q98: MARSEILLE -BONNEVEIN - HYPERMARCHES | R98: HYPERMARCHES FRANCE | S98: LG | T98: RÃ©solution | U98: Atteint | V98: ########## | W98: 21.89 | X98: 27 | Y98: OK | Z98: 1 | AA98: 0 | AB98: 2 | AC98: HNO
A99: =VLOOKUP(O99,Dictionnaire!A:B,2,0) -> Mohamed BENSAID | B99: =O99 -> FR IT UMA N3 BACK OFFICE MAGASIN | E99: 122960875 | F99: DA | G99: Articles non intÃ©grÃ© aprÃ©s arrivage | H99: CAROLINE HYPER-FR | I99: CAROLINE HYPER-FR | J99: DS Magasin | K99: Back Office Hyper \ Stock \ BLI entrepot | L99: ########## | M99: P3 | N99: P3 | O99: FR IT UMA N3 BACK OFFICE MAGASIN | P99: IT | Q99: GRENOBLE -GD PLACE - HYPERMARCHES | R99: HYPERMARCHES FRANCE | S99: LG | T99: RÃ©solution | U99: Atteint | V99: ########## | W99: 46349 | X99: 27 | Y99: OK | Z99: 1 | AA99: 0 | AB99: 1 | AC99: HNO
A100: =VLOOKUP(O100,Dictionnaire!A:B,2,0) -> Mohamed BENSAID | B100: =O100 -> FR IT UMA N3 BACK OFFICE MAGASIN | E100: 123231424 | F100: DA | G100: ecart entre VLP et Proformat CAROLINE journÃ©e du 15/04/2026 | H100: CAROLINE SUPER-FR | I100: VLP SUPER-FR | J100: DS Magasin | K100: Encaissement \ Chiffre d affaire | L100: ########## | M100: P1 | N100: P3 | O100: FR IT UMA N3 BACK OFFICE MAGASIN | P100: IT | Q100: PALAVAS LES FLOTS - SUPERMARCHES | R100: SUPERMARCHES FRANCE | S100: FranchisÃ© | T100: RÃ©solution | U100: Atteint | V100: ########## | W100: 14.24 | X100: 36 | Y100: OK | Z100: 2 | AA100: 0 | AB100: 1 | AC100: HO
A101: =VLOOKUP(O101,Dictionnaire!A:B,2,0) -> Mohamed BENSAID | B101: =O101 -> FR IT UMA N3 BACK OFFICE MAGASIN | E101: 123306450 | F101: DA | G101: Erreur de liaison d'un ean sur un article deja existant | H101: CAROLINE HYPER-FR | I101: CAROLINE HYPER-FR | J101: DS Magasin | K101: Back Office Hyper \ Referentiel \ Modification donnee article | L101: ########## | M101: P1 | N101: P4 | O101: FR IT UMA N3 BACK OFFICE MAGASIN | P101: IT | Q101: AJACCIO - HYPERMARCHES | R101: HYPERMARCHES FRANCE | S101: LG | T101: RÃ©solution | U101: Atteint | V101: ########## | W101: 46202 | X101: 45 | Y101: OK | Z101: 1 | AA101: 0 | AB101: 1 | AC101: HNO
A102: =VLOOKUP(O102,Dictionnaire!A:B,2,0) -> Mohamed BENSAID | B102: =O102 -> FR IT UMA N3 BACK OFFICE MAGASIN | E102: 123331606 | F102: DA | G102: UG DESACTIVEE | H102: CAROLINE SUPER-FR | I102: CAROLINE SUPER-FR | J102: DS Magasin | K102: Back Office Super \ Commande | L102: ########## | M102: P3 | N102: P3 | O102: FR IT UMA N3 BACK OFFICE MAGASIN | P102: IT | Q102: ASNIERES -GRESILLONS - SUPERMARCHES | R102: SUPERMARCHES FRANCE | S102: LG | T102: RÃ©solution | U102: Atteint | V102: ########## | W102: 25.18 | X102: 27 | Y102: OK | Z102: 4 | AA102: 0 | AB102: 1 | AC102: HO
A103: =VLOOKUP(O103,Dictionnaire!A:B,2,0) -> Mohamed BENSAID | B103: =O103 -> FR IT UMA N3 BACK OFFICE MAGASIN | E103: 123523100 | F103: DS | G103: SMP HYBRIDE MONTESSON | H103: CAROLINE HYPER-FR | I103: CAROLINE HYPER-FR | J103: DS Magasin | K103: Back Office Hyper \ Referentiel \ Modification donnee article | L103: ########## | M103: P1 | N103: P2 | O103: FR IT UMA N3 BACK OFFICE MAGASIN | P103: IT | Q103: SGE ET APPRO SCH (SIEGE ENTREPRISE) | R103: LOGISTIQUE FRANCE | S103: SiÃ¨ge | T103: ExÃ©cution | U103: Atteint | V103: ########## | W103: 9.00 | X103: 45 | Y103: OK | Z103: 1 | AA103: 0 | AB103: 1 | AC103: HNO
A104: =VLOOKUP(O104,Dictionnaire!A:B,2,0) -> Mohamed BENSAID | B104: =O104 -> FR IT UMA N3 BACK OFFICE MAGASIN | E104: 123741844 | F104: DA | G104: RAPPORT DES CHANGEMENTS DE PRIX | H104: CAROLINE HYPER-FR | I104: CAROLINE HYPER-FR | J104: DS Magasin | K104: Acces \ Application \ Anomalie compte | L104: ########## | M104: P2 | N104: P2 | O104: FR IT UMA N3 BACK OFFICE MAGASIN | P104: IT | Q104: FERNEY VOLTAIRE - HYPERMARCHES | R104: HYPERMARCHES FRANCE | S104: FranchisÃ© | T104: RÃ©solution | U104: Atteint | V104: ########## | W104: 15.42 | X104: 18 | Y104: OK | Z104: 1 | AA104: 0 | AB104: 1 | AC104: HO
A105: =VLOOKUP(O105,Dictionnaire!A:B,2,0) -> Yassine RABBAI | B105: =O105 -> FR IT UMA N3 ENCAISSEMENT HYPER | E105: 118182803 | F105: DA | G105: Doublon - Plantage de caisse traditionnelle lors de la fin de transaction | H105: CARINE (SA V2 HYPER)-FR | I105: CARINE (SA V2 HYPER)-FR | J105: DS Magasin | K105: Encaissement \ Caisse deconnecte \ En chargement avec erreur | L105: ########## | M105: P3 | N105: P3 | O105: FR IT UMA N3 ENCAISSEMENT HYPER | P105: IT | Q105: VENETTE - HYPERMARCHES | R105: HYPERMARCHES FRANCE | S105: IntÃ©grÃ© | T105: RÃ©solution | U105: Echec | V105: ########## | W105: 37.58 | X105: 36 | Y105: KO | Z105: 5 | AA105: 0 | AB105: 6 | AC105: HO | AD105: 124322387
A106: =VLOOKUP(O106,Dictionnaire!A:B,2,0) -> Yassine RABBAI | B106: =O106 -> FR IT UMA N3 ENCAISSEMENT HYPER | E106: 119885799 | F106: DA | G106: 403 | H106: SCO NCR-FR | I106: SCO NCR-FR | J106: DS Magasin | K106: Caisse libre service \ Fermeture \ Caissier bloque | L106: ########## | M106: P4 | N106: P4 | O106: FR IT UMA N3 ENCAISSEMENT HYPER | P106: IT | Q106: ORMESSON - HYPERMARCHES | R106: HYPERMARCHES FRANCE | S106: IntÃ©grÃ© | T106: RÃ©solution | U106: Echec | V106: ########## | W106: 167.21 | X106: 60 | Y106: KO | Z106: 6 | AA106: 0 | AB106: 1 | AC106: HO | AD106: 120750553 | AE106: 120250831, 120725749
A107: =VLOOKUP(O107,Dictionnaire!A:B,2,0) -> Yassine RABBAI | B107: =O107 -> FR IT UMA N3 ENCAISSEMENT HYPER | E107: 121479069 | F107: DA | G107: CA ne remonte pas | H107: SCO NCR-FR | I107: SCO NCR-FR | J107: DS Magasin | K107: Caisse libre service \ Caisse deconnecte | L107: ########## | M107: P3 | N107: P4 | O107: FR IT UMA N3 ENCAISSEMENT HYPER | P107: IT | Q107: ST EGREVE - HYPERMARCHES | R107: HYPERMARCHES FRANCE | S107: IntÃ©grÃ© | T107: RÃ©solution | U107: Echec | V107: ########## | W107: 71.12 | X107: 60 | Y107: KO | Z107: 10 | AA107: 0 | AB107: 1 | AC107: HO
A108: =VLOOKUP(O108,Dictionnaire!A:B,2,0) -> Yassine RABBAI | B108: =O108 -> FR IT UMA N3 ENCAISSEMENT HYPER | E108: 122153236 | F108: DA | G108: Probleme de remontÃ©e prÃ©lÃ©vement espÃ©ce sur carine | H108: CARINE (SA V2 HYPER)-FR | I108: CARINE (SA V2 HYPER)-FR | J108: DS Magasin | K108: Encaissement \ Chiffre d affaire \ Ecart de CA | L108: ########## | M108: P2 | N108: P2 | O108: FR IT UMA N3 ENCAISSEMENT HYPER | P108: IT | Q108: ECULLY - HYPERMARCHES | R108: HYPERMARCHES FRANCE | S108: IntÃ©grÃ© | T108: RÃ©solution | U108: Echec | V108: ########## | W108: 32.70 | X108: 24 | Y108: KO | Z108: 1 | AA108: 0 | AB108: 1 | AC108: HO
A109: =VLOOKUP(O109,Dictionnaire!A:B,2,0) -> Yassine RABBAI | B109: =O109 -> FR IT UMA N3 ENCAISSEMENT HYPER | E109: 124083865 | F109: DA | G109: ProblÃ©me balance caisse en libre-service | H109: SCO NCR-FR | I109: SCO NCR-FR | J109: DS Magasin | K109: Caisse libre service \ Parametrage \ Balance | L109: ########## | M109: P4 | N109: P4 | O109: FR IT UMA N3 ENCAISSEMENT HYPER | P109: IT | Q109: ORMESSON - HYPERMARCHES | R109: HYPERMARCHES FRANCE | S109: IntÃ©grÃ© | T109: RÃ©solution | U109: Atteint | V109: ########## | W109: 6.52 | X109: 60 | Y109: OK | Z109: 1 | AA109: 0 | AB109: 1 | AC109: HNO
A110: =VLOOKUP(O110,Dictionnaire!A:B,2,0) -> #N/A | B110: =O110 -> 0
A111: =VLOOKUP(O111,Dictionnaire!A:B,2,0) -> #N/A | B111: =O111 -> 0
A112: =VLOOKUP(O112,Dictionnaire!A:B,2,0) -> #N/A | B112: =O112 -> 0
A113: =VLOOKUP(O113,Dictionnaire!A:B,2,0) -> #N/A | B113: =O113 -> 0 | AE113: 121179766, 122820330
A114: =VLOOKUP(O114,Dictionnaire!A:B,2,0) -> #N/A | B114: =O114 -> 0
A115: =VLOOKUP(O115,Dictionnaire!A:B,2,0) -> #N/A | B115: =O115 -> 0
A116: =VLOOKUP(O116,Dictionnaire!A:B,2,0) -> #N/A | B116: =O116 -> 0
A117: =VLOOKUP(O117,Dictionnaire!A:B,2,0) -> #N/A | B117: =O117 -> 0
A118: =VLOOKUP(O118,Dictionnaire!A:B,2,0) -> #N/A | B118: =O118 -> 0
...

Sheet Publipostage
A1: Date Publi | B1: Semaine | C1: Bannette | D1: Résponsable action | E1: N° Ticket | F1: Adresse mail | G1: Note NPS
A2: 46013 | B2: S52 | C2: Proximité/Promocash | D2: BOUNOUAR Mouad | E2: 101809705 | F2: fabien_durand@carrefour.com
A3: 46013 | B3: S52 | C3: Proximité/Promocash | D3: BOUNOUAR Mouad | E3: 101837157 | F3: damien_declercq@franchise.carrefour.com
A4: 46013 | B4: S52 | C4: Proximité/Promocash | D4: BOUNOUAR Mouad | E4: 101737488 | F4: corine_benardon@franchise.carrefour.com
A5: 46013 | B5: S52 | C5: Proximité/Promocash | D5: BOUNOUAR Mouad | E5: 101805660 | F5: hichem_abdelli@franchise.carrefour.com
A6: 46013 | B6: S52 | C6: Proximité/Promocash | D6: BOUNOUAR Mouad | E6: 101814092 | F6: m_hamed_mellouki@franchise.carrefour.com
A7: 46013 | B7: S52 | C7: Proximité/Promocash | D7: BOUNOUAR Mouad | E7: 101559519 | F7: bertrand_guignard@promocash.com
A8: 46013 | B8: S52 | C8: Proximité/Promocash | D8: BOUNOUAR Mouad | E8: 101611584 | F8: remi_henri_sanchez@franchise.carrefour.com
A9: 46013 | B9: S52 | C9: Proximité/Promocash | D9: BOUNOUAR Mouad | E9: 101821177 | F9: nicolas_peyras@franchise.carrefour.com | G9: 9
A10: 46013 | B10: S52 | C10: Proximité/Promocash | D10: BOUNOUAR Mouad | E10: 101834405 | F10: aude_benedet@franchise.carrefour.com
A11: 46013 | B11: S52 | C11: Proximité/Promocash | D11: BOUNOUAR Mouad | E11: 101786001 | F11: aurore_capron@franchise.carrefour.com
A12: 46013 | B12: S52 | C12: Proximité/Promocash | D12: BOUNOUAR Mouad | E12: 101847244 | F12: francois_bouthemy_1@franchise.carrefour.com
A13: 46013 | B13: S52 | C13: Proximité/Promocash | D13: BOUNOUAR Mouad | E13: 101811661 | F13: yolaine_paris@franchise.carrefour.com | G13: 10
A14: 46013 | B14: S52 | C14: Proximité/Promocash | D14: BOUNOUAR Mouad | E14: 101770801 | F14: maryline_guilbaud@franchise.carrefour.com | G14: 10
A15: 46013 | B15: S52 | C15: Proximité/Promocash | D15: BOUNOUAR Mouad | E15: 101820109 | F15: marine_perre_1@franchise.carrefour.com
A16: 46013 | B16: S52 | C16: Proximité/Promocash | D16: BOUNOUAR Mouad | E16: 101810988 | F16: pierre_yves_reuzeau@franchise.carrefour.com
A17: 46013 | B17: S52 | C17: Proximité/Promocash | D17: BOUNOUAR Mouad | E17: 101812647 | F17: bruno_hay@franchise.carrefour.com
A18: 46013 | B18: S52 | C18: Proximité/Promocash | D18: BOUNOUAR Mouad | E18: 101827588 | F18: sebastien_thillerot_1@franchise.carrefour.com | G18: 10
A19: 46013 | B19: S52 | C19: Proximité/Promocash | D19: BOUNOUAR Mouad | E19: 101680538 | F19: theo_ceze@franchise.carrefour.com
A20: 46013 | B20: S52 | C20: Proximité/Promocash | D20: BOUNOUAR Mouad | E20: 101824975 | F20: jean_jacques_vieilly@carrefour.com
A21: 46013 | B21: S52 | C21: Proximité/Promocash | D21: BOUNOUAR Mouad | E21: 101847118 | F21: francois_bouthemy_1@franchise.carrefour.com
A22: 46014 | B22: S52 | C22: Proximité/Promocash | D22: BOUNOUAR Mouad | E22: 101995278 | F22: morgan_roche_2@franchise.carrefour.com
A23: 46014 | B23: S52 | C23: Proximité/Promocash | D23: BOUNOUAR Mouad | E23: 102116078 | F23: odette_brocheton@franchise.carrefour.com
A24: 46014 | B24: S52 | C24: Proximité/Promocash | D24: BOUNOUAR Mouad | E24: 102116745 | F24: julien_le_scolan@promocash.com
A25: 46014 | B25: S52 | C25: Proximité/Promocash | D25: BOUNOUAR Mouad | E25: 102118052 | F25: tarek_asri_1@franchise.carrefour.com
A26: 46014 | B26: S52 | C26: Proximité/Promocash | D26: BOUNOUAR Mouad | E26: 102047545 | F26: emilien_letourneux@franchise.carrefour.com
A27: 46014 | B27: S52 | C27: Proximité/Promocash | D27: BOUNOUAR Mouad | E27: 101913324 | F27: bernadette_noury@franchise.carrefour.com
A28: 46014 | B28: S52 | C28: Proximité/Promocash | D28: BOUNOUAR Mouad | E28: 101910016 | F28: amar_nemraoui_1@franchise.carrefour.com
A29: 46014 | B29: S52 | C29: Proximité/Promocash | D29: BOUNOUAR Mouad | E29: 101918304 | F29: morandeau_guillaume@franchise.carrefour.com
A30: 46014 | B30: S52 | C30: Proximité/Promocash | D30: BOUNOUAR Mouad | E30: 102056528 | F30: sebastien_duffau_1@franchise.carrefour.com
A31: 46014 | B31: S52 | C31: Proximité/Promocash | D31: BOUNOUAR Mouad | E31: 101923147 | F31: foad_el_imami@franchise.carrefour.com
A32: 46014 | B32: S52 | C32: Proximité/Promocash | D32: BOUNOUAR Mouad | E32: 101923018 | F32: laura_dewasmes@promocash.com
A33: 46014 | B33: S52 | C33: Proximité/Promocash | D33: BOUNOUAR Mouad | E33: 101926890 | F33: martin_carpentier@franchise.carrefour.com
A34: 46014 | B34: S52 | C34: Proximité/Promocash | D34: BOUNOUAR Mouad | E34: 102061037 | F34: elodie_duchenne@promocash.com | G34: 10
A35: 46014 | B35: S52 | C35: Proximité/Promocash | D35: BOUNOUAR Mouad | E35: 102073775 | F35: david_duamelle@franchise.carrefour.com
A36: 46014 | B36: S52 | C36: Proximité/Promocash | D36: BOUNOUAR Mouad | E36: 102078973 | F36: sidy_sow@franchise.carrefour.com
A37: 46014 | B37: S52 | C37: Proximité/Promocash | D37: BOUNOUAR Mouad | E37: 102075277 | F37: sidy_sow@franchise.carrefour.com
A38: 46014 | B38: S52 | C38: Proximité/Promocash | D38: BOUNOUAR Mouad | E38: 101957802 | F38: paul_garcia@franchise.carrefour.com
A39: 46014 | B39: S52 | C39: Proximité/Promocash | D39: BOUNOUAR Mouad | E39: 102087751 | F39: yohann_marguerite@promocash.com
A40: 46014 | B40: S52 | C40: Proximité/Promocash | D40: BOUNOUAR Mouad | E40: 102082128 | F40: sebastien_gleize@franchise.carrefour.com
A41: 46014 | B41: S52 | C41: Proximité/Promocash | D41: BOUNOUAR Mouad | E41: 102089478 | F41: julien_bouley_1@franchise.carrefour.com
A42: 46014 | B42: S52 | C42: Proximité/Promocash | D42: BOUNOUAR Mouad | E42: 102029208 | F42: philippe_richard_1@franchise.carrefour.com
A43: 46014 | B43: S52 | C43: Proximité/Promocash | D43: BOUNOUAR Mouad | E43: 101960631 | F43: blerta_zyberaj@franchise.carrefour.com
A44: 46014 | B44: S52 | C44: Proximité/Promocash | D44: BOUNOUAR Mouad | E44: 101966568 | F44: thierry_planchais@franchise.carrefour.com
A45: 46014 | B45: S52 | C45: Proximité/Promocash | D45: BOUNOUAR Mouad | E45: 101967755 | F45: stephane_clozel@franchise.carrefour.com
A46: 46014 | B46: S52 | C46: Proximité/Promocash | D46: BOUNOUAR Mouad | E46: 102043177 | F46: olivier_courbard@franchise.carrefour.com
... A144: 46043 | B144: S4 | C144: Proximité/Promocash | D144: BOUNOUAR Mouad | E144: 105291345 | F144: sophie_fournie@promocash.com
A145: 46043 | B145: S4 | C145: Proximité/Promocash | D145: BOUNOUAR Mouad | E145: 105275904 | F145: jonathan_derosier@franchise.carrefour.com
A146: 46043 | B146: S4 | C146: Proximité/Promocash | D146: BOUNOUAR Mouad | E146: 105344295 | F146: melanie_fontaine@franchise.carrefour.com
A147: 46043 | B147: S4 | C147: Proximité/Promocash | D147: BOUNOUAR Mouad | E147: 105070846 | F147: patrick_kremer@franchise.carrefour.com
A148: 46043 | B148: S4 | C148: Proximité/Promocash | D148: BOUNOUAR Mouad | E148: 105259699 | F148: philippe_thomas@franchise.carrefour.com
A149: 46043 | B149: S4 | C149: Proximité/Promocash | D149: BOUNOUAR Mouad | E149: 105253346 | F149: philippe_thomas@franchise.carrefour.com
A150: 46043 | B150: S4 | C150: Proximité/Promocash | D150: BOUNOUAR Mouad | E150: 105230531 | F150: aziz_ennabihe@franchise.carrefour.com
A151: 46043 | B151: S4 | C151: Proximité/Promocash | D151: BOUNOUAR Mouad | E151: 105330185 | F151: nicolas_locatelli@franchise.carrefour.com
A152: 46043 | B152: S4 | C152: Proximité/Promocash | D152: BOUNOUAR Mouad | E152: 105287747 | F152: ludovic_belo_1@franchise.carrefour.com
A153: 46043 | B153: S4 | C153: Proximité/Promocash | D153: BOUNOUAR Mouad | E153: 105219610 | F153: lilia_andriatsiory@franchise.carrefour.com
A154: 46043 | B154: S4 | C154: Proximité/Promocash | D154: BOUNOUAR Mouad | E154: 105192747 | F154: pharana_phaton@promocash.com
A155: 46043 | B155: S4 | C155: Proximité/Promocash | D155: BOUNOUAR Mouad | E155: 105357788 | F155: mohamed_taha_himmich@franchise.carrefour.com
A156: 46043 | B156: S4 | C156: Proximité/Promocash | D156: BOUNOUAR Mouad | E156: 105256838 | F156: julio_harilanto@franchise.carrefour.com
... A174: 46043 | B174: S4 | C174: Proximité/Promocash | D174: BOUNOUAR Mouad | E174: 105406139 | F174: mickael_ribeiro_1@carrefour.com
A175: 46044 | B175: S4 | C175: Proximité/Promocash | D175: BOUNOUAR Mouad | E175: 105469757 | F175: swan_dauvergne@franchise.carrefour.com
A176: 46044 | B176: S4 | C176: Proximité/Promocash | D176: BOUNOUAR Mouad | E176: 105486509 | F176: lise_geraldes@franchise.carrefour.com
A177: 46044 | B177: S4 | C177: Proximité/Promocash | D177: BOUNOUAR Mouad | E177: 105550728 | F177: lisa_wille1@franchise.carrefour.com
A178: 46044 | B178: S4 | C178: Proximité/Promocash | D178: BOUNOUAR Mouad | E178: 105278578 | F178: christian_pedat_1@franchise.carrefour.com
A179: 46044 | B179: S4 | C179: Proximité/Promocash | D179: BOUNOUAR Mouad | E179: 105360830 | F179: elise_fouligny@franchise.carrefour.com
A180: 46044 | B180: S4 | C180: Proximité/Promocash | D180: BOUNOUAR Mouad | E180: 105582683 | F180: corinne_urvoy@promocash.com
A181: 46044 | B181: S4 | C181: Proximité/Promocash | D181: BOUNOUAR Mouad | E181: 105464140 | F181: melissa_pujalte@promocash.com
A182: 46044 | B182: S4 | C182: Proximité/Promocash | D182: BOUNOUAR Mouad | E182: 105435098 | F182: celine_guillemin_2@franchise.carrefour.com
A183: 46044 | B183: S4 | C183: Proximité/Promocash | D183: BOUNOUAR Mouad | E183: 105433921 | F183: damien_mazies@franchise.carrefour.com
A184: 46044 | B184: S4 | C184: Proximité/Promocash | D184: BOUNOUAR Mouad | E184: 105434551 | F184: sevrine_camard@promocash.com
A185: 46044 | B185: S4 | C185: Proximité/Promocash | D185: BOUNOUAR Mouad | E185: 105564452 | F185: luc_forma@promocash.com
A186: 46044 | B186: S4 | C186: Proximité/Promocash | D186: BOUNOUAR Mouad | E186: 105435412 | F186: maeva_lombard@carrefour.com
... A198: 46044 | B198: S4 | C198: Proximité/Promocash | D198: BOUNOUAR Mouad | E198: 105434788 | F198: veronique_moura@promocash.com
A199: 46045 | B199: S4 | C199: Proximité/Promocash | D199: BOUNOUAR Mouad | E199: 105587126 | F199: demba_camara@franchise.carrefour.com
A200: 46045 | B200: S4 | C200: Proximité/Promocash | D200: BOUNOUAR Mouad | E200: 105599848 | F200: florence_renollet@promocash.com
A201: 46045 | B201: S4 | C201: Proximité/Promocash | D201: BOUNOUAR Mouad | E201: 105284593 | F201: julien_morandeau@franchise.carrefour.com
A202: 46045 | B202: S4 | C202: Proximité/Promocash | D202: BOUNOUAR Mouad | E202: 105475661 | F202: sebastien_benoist_2@promocash.com
A203: 46045 | B203: S4 | C203: Proximité/Promocash | D203: BOUNOUAR Mouad | E203: 105638536 | F203: bastien_perreal@franchise.carrefour.com
A204: 46045 | B204: S4 | C204: Proximité/Promocash | D204: BOUNOUAR Mouad | E204: 105652437 | F204: corinne_liope_delaunay@carrefour.com
A205: 46045 | B205: S4 | C205: Proximité/Promocash | D205: BOUNOUAR Mouad | E205: 105741993 | F205: bastien1_devigne@franchise.carrefour.com
A206: 46045 | B206: S4 | C206: Proximité/Promocash | D206: BOUNOUAR Mouad | E206: 105648800 | F206: margaux_kermoal@carrefour.com
A207: 46045 | B207: S4 | C207: Proximité/Promocash | D207: BOUNOUAR Mouad | E207: 105673960 | F207: olivier_gaultier@franchise.carrefour.com
A208: 46045 | B208: S4 | C208: Proximité/Promocash | D208: BOUNOUAR Mouad | E208: 105487621 | F208: luc_masselot@franchise.carrefour.com
A209: 46045 | B209: S4 | C209: Proximité/Promocash | D209: BOUNOUAR Mouad | E209: 105346640 | F209: mickael_bucher@franchise.carrefour.com
A210: 46045 | B210: S4 | C210: Proximité/Promocash | D210: BOUNOUAR Mouad | E210: 105628016 | F210: mickey_wassmann@franchise.carrefour.com
... A282: 46051 | B282: S5 | C282: Proximité/Promocash | D282: BOUNOUAR Mouad | E282: 106652094 | F282: cedric_chenevier_1@franchise.carrefour.com
A283: 46056 | B283: S5 | C283: Proximité/Promocash | D283: BOUNOUAR Mouad | E283: 107143045 | F283: nathalie_gueno@promocash.com
A284: 46056 | B284: S5 | C284: Proximité/Promocash | D284: BOUNOUAR Mouad | E284: 107023457 | F284: julia_freycon_1@franchise.carrefour.com
A285: 46056 | B285: S5 | C285: Proximité/Promocash | D285: BOUNOUAR Mouad | E285: 106988921 | F285: laure_bedalow@franchise.carrefour.com
A286: 46056 | B286: S5 | C286: Proximité/Promocash | D286: BOUNOUAR Mouad | E286: 107051295 | F286: melissa_pujalte@promocash.com
A287: 46056 | B287: S5 | C287: Proximité/Promocash | D287: BOUNOUAR Mouad | E287: 107026170 | F287: vincent_guest@promocash.com
A288: 46056 | B288: S5 | C288: Proximité/Promocash | D288: BOUNOUAR Mouad | E288: 106995892 | F288: maryline_guilbaud@franchise.carrefour.com
A289: 46056 | B289: S5 | C289: Proximité/Promocash | D289: BOUNOUAR Mouad | E289: 107115095 | F289: carla_yondo_dipanda@carrefour.com
A290: 46056 | B290: S5 | C290: Proximité/Promocash | D290: BOUNOUAR Mouad | E290: 106946159 | F290: tony_ganadu@franchise.carrefour.com
A291: 46056 | B291: S5 | C291: Proximité/Promocash | D291: BOUNOUAR Mouad | E291: 107143308 | F291: denis_messan_1@promocash.com
A292: 46056 | B292: S5 | C292: Proximité/Promocash | D292: BOUNOUAR Mouad | E292: 106991123 | F292: bocar_sow_1@franchise.carrefour.com
A293: 46056 | B293: S5 | C293: Proximité/Promocash | D293: BOUNOUAR Mouad | E293: 107057870 | F293: florent_friedrich@promocash.com
A294: 46056 | B294: S5 | C294: Proximité/Promocash | D294: BOUNOUAR Mouad | E294: 106994696 | F294: stella_feo@carrefour.com
... A372: 46057 | B372: S5 | C372: Proximité/Promocash | D372: BOUNOUAR Mouad | E372: 107308368 | F372: mamadou_barry_10@franchise.carrefour.com
A373: 46058 | B373: S5 | C373: Proximité/Promocash | D373: BOUNOUAR Mouad | E373: 107540642 | F373: thomas_bigiarini@carrefour.com
...

Sheet Détail Agent
A1: Date | B1: (Multiple Items)
A3: Résolu par | B3: Bannette | C3: COUNTA of Type de résolution
A4: Abdelilah SAOUDI | B4: FO | C4: 17
A5: Abdelmoughit ARRABIH | B5: FO | C5: 18
A6: Achraf Bouabdelli | B6: BO | C6: 15
A7: Ahmed EL MESSAOUDI | B7: Partenaire | C7: 12
A8: Alan Nowak | B8: FO
A9: Amina AATATI | B9: BO | C9: 20
A10: Anas FAID | B10: FO | C10: 2
A11: Aya BOURMAILA | B11: Supply
A12: Aymane DOUCHI IDRISSI | B12: BO
A13: Ayoub ABDELLAH | B13: BO | C13: 14
A14: Azzeddine BOUHLAL | B14: FO | C14: 14
A15: Baba mohammed amine | B15: Partenaire | C15: 36
A16: Badr EL MOUAHHID | B16: Supply | C16: 16
A17: Bassma BOUKHLAL | B17: FO | C17: 15
A18: Chaimaa JIRANI | B18: BO | C18: 22
A19: Chaimae EL KADIRI | B19: FO | C19: 22
A20: El Mehdi EL MANSOURI | B20: PROXI-PMC | C20: 13
A21: Fatima Ezzahra AMANNE | B21: FO | C21: 17
A22: fatima Zahra | B22: FO
A23: Hajar ESSABIR | B23: FO | C23: 18
A24: Hamza ABBA | B24: Supply | C24: 23
A25: Hamza MESSAOUDI | B25: Partenaire | C25: 47
B26: PROXI-PMC | C26: 17
B27: Supply
A28: Hassnae HASSIB | B28: FO | C28: 18
A29: Hiba BARICH | B29: PROXI-PMC | C29: 14
A30: Karam ZNIDIGA | B30: FO | C30: 14
A31: Khalid BEKKALI | B31: PROXI-PMC | C31: 1
A32: Majdouline HRAR | B32: FO | C32: 19
A33: Marwane BENHAYMAD | B33: BO | C33: 15
A34: Moad TINOUISSI | B34: Partenaire | C34: 51
A35: Mohamed ARRAJ | B35: BO | C35: 7
A36: Mohamed Sedik MASTARI | B36: PROXI-PMC | C36: 14
A37: Mohammed Amine CHETOUI | B37: BO | C37: 19
A38: Nabil ATIF | B38: PROXI-PMC | C38: 15
A39: Nabil JEBILOU | B39: BO | C39: 12
... A54: Zidane MOUASSINE | B54: PROXI-PMC | C54: 12
A55: (blank) | B55: (blank)
A56: Grand Total | C56: 807

Sheet Dictionnaire
A1: Bannete | B1: Résponsable
A2: FR IT SIC N1_N2 PROMOCASH BACK OFFICE | B2: Mouad Bounouar
A3: FR IT SIC N1_N2 PROXIMITE | B3: Mouad Bounouar
A4: FR IT SIC N1_N2 SUPER-HYPER FRONT OFFICE | B4: Yassine RABBAI
A5: FR IT SIC N1_N2 SUPER-HYPER BACK OFFICE | B5: Mohamed BENSAID
A6: FR IT UMA N3 BACK OFFICE MAGASIN | B6: Mohamed BENSAID
A7: FR IT UMA N1 N2 PARTENAIRE MAGASIN | B7: Amine BABA
A8: FR IT SIC N1_N2 SUPPLY | B8: Khalil HABRRMAN
A9: FR IT UMA N3 ENCAISSEMENT HYPER | B9: Yassine RABBAI
